Workbook

Sheet VAT Schedule
A2: Shirefolk, Inc
A3: YEAR 2025
B4: Taz-Exempt Sales | C4: Vatable-Sales | D4: Vat on Sales (Output Tax) | E4: Input Tax Carried Over | F4: VAT on Purchases (Goods Not Qual for Input Tax) | G4: VAT on Purchases (Services Not Qualified for Input Tax) | H4: Purchases Capital Goods | I4: Purchases of Goods Other than Capital Goods | J4: Purchases of Services | K4: Vat on Purchases of Capital Goods (Input Tax) | L4: Allowable Vat on Purchases of Capital Goods More Than 1M (Input Tax) | M4: Vat on Purchases of Goods other than Capital Goods & Services (Input Tax) | N4: Total Vat on Purchases (Input Tax) | O4: VAT Payable | P4: in eBIR Form | Q4: difference | S4: Amount Filed | T4: Date Filed | U4: Date Paid | V4: SLSP
A6: Beg. Bal. | O6: 0
A7: Q1 2025 | B7: 0 | C7: 5011457.3 | D7: =C7*0.12 -> 601374.87 | E7: 0 | F7: 33374.37 | G7: =SUM('Xero Purchases S'!H13) -> 0 | H7: 7714.29 | I7: 225614.24 | J7: 1751892.4 | K7: =H7*0.12 -> 925.7148 | L7: =401500.9-355637.67 -> 45863.23 | M7: =SUM(I7:J7)*0.12 -> 237300.8 | N7: =SUM(K7:M7) -> 284089.74 | O7: =$D7+$E7-$N7 -> 317285.13
A8: `1st Quarter | B8: =SUM(B7) -> 0 | C8: =SUM(C7) -> 5011457.3 | D8: =C8*0.12 -> 601374.87 | E8: =O6 -> 0 | F8: =SUM(F7) -> 33374.37 | G8: =SUM(G7) -> 0 | H8: =SUM(H7) -> 7714.29 | I8: =SUM(I7) -> 225614.24 | J8: =SUM(J7) -> 1751892.4 | K8: =SUM(K7) -> 925.7148 | L8: =SUM(L7) -> 45863.23 | M8: =SUM(M7) -> 237300.8 | N8: =SUM(N7) -> 284089.74 | O8: =$D8+$E8-$N8 -> 317285.13
A11: Beg. Bal. | O11: 0
A12: January | C12: =SUM('Xero Sales'!G18:G292,'Xero Sales'!G828,'Xero Sales'!G834,'Xero Sales'!G855) -> 2474960.2 | D12: =C12*0.12 -> 296995.22 | E12: 0 | F12: =SUM('Xero Purchases G'!H11:H14) -> 630 | G12: =SUM('Xero Purchases S'!H15:H17) -> 580 | H12: =SUM(0) -> 0 | I12: =SUM('Xero Purchases G'!H40:H56) -> 23768.89 | J12: =SUM('Xero Purchases S'!H11,'Xero Purchases S'!H29:H51) -> 450457.51 | K12: =H12*0.12 -> 0 | L12: ='Schedule of CG Input Tax'!R15 -> 7643.8703 | M12: =SUM(I12:J12)*0.12 -> 56907.168 | N12: =SUM(K12:M12) -> 64551.038 | O12: =$D12+$E12-$N12 -> 232444.19
A13: February | B13: 0 | C13: =SUM('Xero Sales'!G294:G536)-SUM('Xero Sales'!G809,'Xero Sales'!G823) -> 1080016.4 | D13: =C13*0.12 -> 129601.97 | E13: 0 | F13: =SUM('Xero Purchases G'!H16:H18) -> 436.07 | G13: =SUM('Xero Purchases S'!H19:H20) -> 10400 | H13: =SUM(0) -> 0 | I13: =SUM('Xero Purchases G'!H58:H77) -> 44442.85 | J13: =SUM('Xero Purchases S'!H53:H70) -> 458377.52 | K13: =H13*0.12 -> 0 | L13: ='Schedule of CG Input Tax'!S15 -> 7643.8703 | M13: =SUM(I13:J13)*0.12 -> 60338.444 | N13: =SUM(K13:M13) -> 67982.315 | O13: =$D13+$E13-$N13 -> 61619.654
A14: March | B14: 0 | C14: =SUM('Xero Sales'!G538:G796)-'Xero Sales'!G798 -> 1366349.4 | D14: =C14*0.12 -> 163961.93 | E14: 0 | F14: =SUM('Xero Purchases G'!H20:H36) -> 3178.3 | G14: =SUM('Xero Purchases S'!H22:H25) -> 18300 | H14: =SUM(0) -> 0 | I14: =SUM('Xero Purchases G'!H79:H116) -> 157402.49 | J14: =SUM('Xero Purchases S'!H72:H109) -> 843057.39 | K14: =H14*0.12 -> 0 | L14: ='Schedule of CG Input Tax'!T15 -> 7643.8703 | M14: =SUM(I14:J14)*0.12 -> 120055.19 | N14: =SUM(K14:M14) -> 127699.06 | O14: =$D14+$E14-$N14 -> 36262.877
A15: `1st Quarter Amended | B15: =SUM(B12:B14) -> 0 | C15: =SUM(C12:C14) -> 4921326 | D15: =C15*0.12 -> 590559.12 | E15: =O11 -> 0 | F15: =SUM(F12:F14) -> 4244.37 | G15: =SUM(G12:G14) -> 29280 | H15: =SUM(H12:H14) -> 0 | I15: =SUM(I12:I14) -> 225614.23 | J15: =SUM(J12:J14) -> 1751892.4 | K15: =SUM(K12:K14) -> 0 | L15: =SUM(L12:L14) -> 22931.611 | M15: =SUM(M12:M14) -> 237300.8 | N15: =SUM(N12:N14) -> 260232.41 | O15: =$D15+$E15-$N15 -> 330326.72 | P15: =O15/SUM(B15:C15) -> 0.067121486
C16: =C15-'Xero Sales'!M844 -> 0.64714287 | I16: =I15-'Xero Purchases G'!H117 -> 0 | J16: =J15-'Xero Purchases S'!H110-'Xero Purchases S'!H12 -> -1.0244605e-10
A18: April | B18: ='Xero Sales'!G13 -> 37500 | C18: 1548215.6 | D18: =C18*12% -> 185785.88 | E18: 0 | F18: =SUM('Xero Purchases G'!H133:H156) -> 19678.8 | G18: =SUM('Xero Purchases S'!H126) -> 1921.32 | H18: 0 | I18: =SUM('Xero Purchases G'!H184:H193) -> 13107.64 | J18: =SUM('Xero Purchases S'!H133:H159) -> 523840.2 | K18: =H18*0.12 -> 0 | L18: ='Schedule of CG Input Tax'!U15 -> 7643.8703 | M18: =(SUM(I18:J18)*0.12) -> 64433.741 | N18: =SUM(K18:M18) -> 72077.611 | O18: =$D18+$E18-$N18 -> 113708.27
A19: May | B19: 0 | C19: =SUM('Xero Sales'!G1174:G1448,'Xero Sales'!G1722) -> 1339480.4 | D19: =C19*12% -> 160737.65 | E19: 0 | F19: =SUM('Xero Purchases G'!H158:H175) -> 2466 | G19: =SUM('Xero Purchases S'!J128:J129) -> 0 | H19: 0 | I19: =SUM('Xero Purchases G'!H195:H209) -> 21831.75 | J19: =SUM('Xero Purchases S'!H161:H184) -> 468577.49 | K19: =H19*0.12 -> 0 | L19: ='Schedule of CG Input Tax'!V15 -> 7643.8703 | M19: =(SUM(I19:J19)*0.12) -> 58849.109 | N19: =SUM(K19:M19) -> 66492.979 | O19: =$D19+$E19-$N19 -> 94244.673
A20: June | B20: 0 | C20: =SUM('Xero Sales'!G1450:G1713) -> 1098895.4 | D20: =C20*12% -> 131867.45 | E20: 0 | F20: =SUM('Xero Purchases G'!H177:H180) -> 755.4 | G20: 0 | H20: 0 | I20: =SUM('Xero Purchases G'!H211:H228) -> 23033.48 | J20: =SUM('Xero Purchases S'!H186:H197) -> 350529.27 | K20: =H20*0.12 -> 0 | L20: ='Schedule of CG Input Tax'!W15 -> 7643.8703 | M20: =(SUM(I20:J20)*0.12) -> 44827.53 | N20: =SUM(K20:M20) -> 52471.4 | O20: =$D20+$E20-$N20 -> 79396.053
A21: 2nd Quarter | B21: =SUM(B18:B20) -> 37500 | C21: =SUM(C18:C20) -> 3986591.5 | D21: =C21*0.12 -> 478390.98 | E21: =E18 -> 0 | F21: =SUM(F18:F20) -> 22900.2 | G21: =SUM(G18:G20) -> 1921.32 | H21: =SUM(H18:H20) -> 0 | I21: =SUM(I18:I20) -> 57972.87 | J21: =SUM(J18:J20) -> 1342947 | K21: =SUM(K18:K20) -> 0 | L21: =SUM(L18:L20) -> 22931.611 | M21: =SUM(M18:M20) -> 168110.38 | N21: =SUM(K21:M21) -> 191041.99 | O21: =D21+E21-N21 -> 287348.99 | P21: =O21/SUM(B21:C21) -> 0.071407171
C22: =C21-SI!G2741 -> 0.67071429 | D22: =D21-SI!H2741 -> 0.080485715
A23: July | B23: 0 | C23: =SUM('Xero Sales'!G1757:G2039)-SUM('Xero Sales'!G2046:G2051) -> 1525930.2 | D23: =C23*12% -> 183111.63 | E23: 0 | F23: =SUM('Xero Purchases G'!G454:G465) -> 0 | G23: =SUM('Xero Purchases S'!H213) -> 800 | H23: =SUM('Xero Purchases G'!H245:H249) -> 1820.53 | I23: =SUM('Xero Purchases G'!H253:H267) -> 10331.11 | J23: =SUM('Xero Purchases S'!H217:H230) -> 381222.43 | K23: =H23*0.12 -> 218.4636 | L23: ='Schedule of CG Input Tax'!X15 -> 7643.8703 | M23: =(SUM(I23:J23)*0.12) -> 46986.425 | N23: =SUM(K23:M23) -> 54848.759 | O23: =$D23+$E23-$N23 -> 128262.87
A24: August | B24: 0 | C24: =SI!G2743 -> 1316048.3 | D24: =C24*12% -> 157925.8 | E24: 0 | F24: =SUM('Xero Purchases G'!G467:G482) -> 0 | G24: =SUM('Xero Purchases S'!G237:G241) -> 0 | H24: 0 | I24: ='Xero Purchases G'!H282 -> 7200 | J24: =SUM('Xero Purchases S'!H245:H263) -> 539658.21 | K24: =H24*0.12 -> 0 | L24: ='Schedule of CG Input Tax'!Y15 -> 7643.8703 | M24: =(SUM(I24:J24)*0.12) -> 65622.985 | N24: =SUM(K24:M24) -> 73266.855 | O24: =$D24+$E24-$N24 -> 84658.946
A25: September | D25: =C25*12% -> 0 | E25: 0 | F25: =SUM('Xero Purchases G'!G484:G494) -> 0 | G25: =SUM('Xero Purchases S'!G243:G244) -> 0 | H25: 0 | I25: =SUM('Xero Purchases G'!H537:H551) -> 0 | J25: =SUM('Xero Purchases S'!H302:H332) -> 0 | K25: =H25*0.12 -> 0 | L25: 0 | M25: =(SUM(I25:J25)*0.12) -> 0 | N25: =SUM(K25:M25) -> 0 | O25: =$D25+$E25-$N25 -> 0
A26: 3rd Quarter | B26: =SUM(B23:B25) -> 0 | C26: =SUM(C23:C25) -> 2841978.6 | D26: =C26*0.12 -> 341037.43 | E26: =E23 -> 0 | F26: =SUM(F23:F25) -> 0 | G26: =SUM(G23:G25) -> 800 | H26: =SUM(H23:H25) -> 1820.53 | I26: =SUM(I23:I25) -> 17531.11 | J26: =SUM(J23:J25) -> 920880.64 | K26: =SUM(K23:K25) -> 218.4636 | L26: =SUM(L23:L25) -> 15287.741 | M26: =SUM(M23:M25) -> 112609.41 | N26: =SUM(K26:M26) -> 128115.61 | O26: =D26+E26-N26 -> 212921.81
A28: Oct | D28: =C28*12% -> 0 | K28: =H28*0.12 -> 0 | M28: =(SUM(I28:J28)*0.12) -> 0 | N28: =SUM(K28:M28) -> 0 | O28: =$D28+$E28-$N28 -> 0
A29: Nov | D29: =C29*12% -> 0 | E29: =IF($P28<0,$P28,"") | G29: 0 | H29: 0 | K29: =H29*0.12 -> 0 | M29: =(SUM(I29:J29)*0.12) -> 0 | N29: =SUM(K29:M29) -> 0 | O29: =$D29+$E29-$N29 -> 0
A30: Dec | D30: =C30*12% -> 0 | E30: =IF($P29<0,$P29,"") | K30: =H30*0.12 -> 0 | M30: =(SUM(I30:J30)*0.12) -> 0 | N30: =SUM(K30:M30) -> 0 | O30: =$D30+$E30-$N30 -> 0
A31: 4th Quarter | B31: =SUM(B28:B30) -> 0 | C31: =SUM(C28:C30) -> 0 | D31: =C31*0.12 -> 0 | E31: =E28 | F31: =SUM(F28:F30) -> 0 | G31: =SUM(G28:G30) -> 0 | H31: =SUM(H28:H30) -> 0 | I31: =SUM(I28:I30) -> 0 | J31: =SUM(J28:J30) -> 0 | K31: =SUM(K28:K30) -> 0 | L31: =SUM(L28:L30) -> 0 | M31: =SUM(M28:M30) -> 0 | N31: =SUM(N28:N30) -> 0 | O31: =D31+E31-N31 -> 0
A33: Year Total | B33: =B8+B21+B26+B31 -> 37500 | C33: =C8+C21+C26+C31 -> 11840027 | D33: =D8+D21+D26+D31 -> 1420803.3 | E33: =E8+E21+E26+E31 -> 0 | F33: =F8+F21+F26+F31 -> 56274.57 | G33: =G8+G21+G26+G31 -> 2721.32 | H33: =H8+H21+H26+H31 -> 9534.82 | I33: =I8+I21+I26+I31 -> 301118.22 | ... N33: =N8+N21+N26+N31 -> 603247.35 | O33: =O31 -> 0

Sheet SI
B1: Date | C1: Xero Inv. No. | D1: Client Name | E1: OR Amount | F1: Description | G1: Mode of Payment | H1: Cash / Check Deposit | I1: Remarks | J1: Type of Service | K1: GROSS | L1: CWT | M1: TOTAL | N1: Checking | O1: EWT | P1: CC Fee | Q1: Net Amount | R1: Checking | U1: NATURE | X1: GROSS AMOUNT | Y1: NET AMOUNT | Z1: VAT AMOUNT | AB1: GROSS AMOUNT | AC1: NET AMOUNT | AD1: VAT AMOUNT
A2: 1201 | B2: 45659 | C2: INV-10151 | D2: Gabby Ortega (Gabriela Ortega) | E2: 550 | F2: Whole Day Flypass | G2: Gcash QR Standee | H2: UBP | J2: Walk-Ins | K2: =E2 -> 550 | L2: 0 | M2: =K2-L2 -> 550 | N2: =E2-M2 -> 0 | P2: 13.4 | Q2: =E2-P2 -> 536.6 | X2: =E2 -> 550 | Y2: =X2/1.12 -> 491.07143 | Z2: =Y2*0.12 -> 58.928571 | AB2: 550 | AC2: 491.07143 | AD2: 58.928571 | AF2: =AC2-Y2 -> 0
A3: 1202 | B3: 45659 | C3: INV-10146 | D3: Aguilar IT Solutions | E3: 3000 | F3: Virtual Office,Dec 24, 2024 - Jan 23, 2025 | G3: Check | H3: UBP | I3: Eastwest Bank 0001545556 | J3: Virtual Office | K3: =E3 -> 3000 | L3: 0 | M3: =K3-L3 -> 3000 | N3: =E3-M3 -> 0 | X3: =E3 -> 3000 | Y3: =X3/1.12 -> 2678.5714 | Z3: =Y3*0.12 -> 321.42857 | AB3: 3000 | AC3: 2678.5714 | AD3: 321.42857 | AF3: =AC3-Y3 -> 0
A4: 1203 | B4: 45659 | C4: INV-10152 | D4: Paulwil Martin | E4: 400 | F4: 3 hour Flypass and 1 hour extension | G4: Gcash QR Standee | H4: UBP | J4: Walk-Ins | K4: =E4 -> 400 | L4: 0 | M4: =K4-L4 -> 400 | N4: =E4-M4 -> 0 | P4: 9.75 | Q4: =E4-P4 -> 390.25 | X4: =E4 -> 400 | Y4: =X4/1.12 -> 357.14286 | Z4: =Y4*0.12 -> 42.857143 | AB4: 400 | AC4: 357.14286 | AD4: 42.857143 | AF4: =AC4-Y4 -> 0
A5: 1204 | B5: 45659 | C5: INV-10147 | D5: CP-DC Development Corporation | E5: 3000 | F5: Virtual Office,Dec 24, 2024 - Jan 23, 2025 | G5: Check | H5: UBP | I5: Chinabank 0001902944 | J5: Virtual Office | K5: =E5 -> 3000 | L5: 0 | M5: =K5-L5 -> 3000 | N5: =E5-M5 -> 0 | X5: =E5 -> 3000 | Y5: =X5/1.12 -> 2678.5714 | Z5: =Y5*0.12 -> 321.42857 | AB5: 3000 | AC5: 2678.5714 | AD5: 321.42857 | AE5: 2024 SALES | AF5: =AC5-Y5 -> 0
A6: 1205 | D6: CANCELLED | K6: =E6 | L6: 0 | M6: =K6-L6 -> 0 | N6: =E6-M6 -> 0 | AF6: =AC6-Y6 -> 0
A7: 1206 | B7: 45659 | C7: INV-10166 | D7: Vipre Security Group Philippines Inc. | E7: 86650.89 | F7: Voyager 3 rent, January 2025 rent | G7: Check | H7: UBP | J7: Virtual Office | K7: 90700 | L7: =K7/1.12*0.05 -> 4049.1071 | M7: =K7-L7 -> 86650.893 | N7: =E7-M7 -> -0.0028571429 | X7: =E7 -> 86650.89 | Y7: =X7/1.12 -> 77366.866 | Z7: =Y7*0.12 -> 9284.0239 | AB7: 90700 | AC7: 80982.143 | AD7: 9717.8571 | AF7: =AC7-Y7 -> 3615.2768
A8: 1207 | B8: 45659 | C8: INV-10009 | D8: Bon Conseil Realty OPC | E8: 2866.07 | F8: Virtual Office, Dec 24, 2024 to Jan 23, 2025 | G8: Bank Transfer | H8: UBP | I8: UB3673112 | J8: Virtual Office | K8: 3000 | L8: =K8/1.12*0.05 -> 133.92857 | M8: =K8-L8 -> 2866.0714 | N8: =E8-M8 -> -0.0014285714 | X8: =E8 -> 2866.07 | Y8: =X8/1.12 -> 2558.9911 | Z8: =Y8*0.12 -> 307.07893 | AB8: 3000 | AC8: =AB8/1.12 -> 2678.5714 | AD8: =AC8*12% -> 321.42857 | AE8: 45627 | AF8: =AC8-Y8 -> 119.58036
A9: 1208 | B9: 45659 | C9: INV-10181 | D9: Tristan San Buenaventura | E9: 1544 | F9: Astra 1, 3:30pm to 5:30pm and Printing 36xP4 | G9: Gcash QR Standee | H9: UBP | J9: Meeting Rooms | K9: =E9 -> 1544 | L9: 0 | M9: =K9-L9 -> 1544 | N9: =E9-M9 -> 0 | P9: 37.62 | Q9: =E9-P9 -> 1506.38 | X9: =E9 -> 1544 | Y9: =X9/1.12 -> 1378.5714 | Z9: =Y9*0.12 -> 165.42857 | AB9: 1544 | AC9: 1378.5714 | AD9: 165.42857 | AF9: =AC9-Y9 -> 0
A10: 1209 | B10: 45659 | C10: INV-10153 | D10: AF Vista City Inc | E10: 8980.36 | F10: Astra 1, Dec 26-27, 2024, 10 am to 5pm | G10: Check | H10: UBP | I10: BDO 0000174186 | J10: Meeting Rooms | K10: 9400 | L10: =K10/1.12*0.05 -> 419.64286 | M10: =K10-L10 -> 8980.3571 | N10: =E10-M10 -> 0.0028571429 | X10: =K10 -> 9400 | Y10: =X10/1.12 -> 8392.8571 | Z10: =Y10*0.12 -> 1007.1429 | AB10: 9400 | AC10: 8392.8571 | AD10: 1007.1429 | AF10: =AC10-Y10 -> 0
A11: 1210 | B11: 45660 | C11: INV-10171 | D11: Mylene Padua | E11: 300 | F11: 3 hour Flypass | G11: Cash | K11: =E11 -> 300 | L11: 0 | M11: =K11-L11 -> 300 | N11: =E11-M11 -> 0 | X11: =E11 -> 300 | Y11: =X11/1.12 -> 267.85714 | Z11: =Y11*0.12 -> 32.142857 | AB11: 300 | AC11: 267.85714 | AD11: 32.142857 | AF11: =AC11-Y11 -> 0
A12: 1211 | B12: 45660 | C12: INV-10185 | D12: Plebeian B Medina | E12: 2100 | F12: Rocket Room, 9 am to 12pm | G12: Maya Card | H12: UBP | J12: Meeting Rooms | K12: =E12 -> 2100 | L12: 0 | M12: =K12-L12 -> 2100 | N12: =E12-M12 -> 0 | P12: 68.96 | Q12: =E12-P12 -> 2031.04 | X12: =E12 -> 2100 | Y12: =X12/1.12 -> 1875 | Z12: =Y12*0.12 -> 225 | AB12: 2100 | AC12: 1875 | AD12: 225 | AF12: =AC12-Y12 -> 0
A13: 1212 | B13: 45660 | C13: INV-9977 | D13: Bon Conseil Realty OPC | E13: 2200.45 | F13: Locker rental, Dec 3, 2024 to Jul 23, 2025 | G13: Bank Transfer | H13: UBP | J13: Add Ons | K13: 2303.28 | L13: =K13/1.12*0.05 -> 102.825 | M13: =K13-L13 -> 2200.455 | N13: =E13-M13 -> -0.005 | X13: =K13 -> 2303.28 | Y13: =X13/1.12 -> 2056.5 | Z13: =Y13*0.12 -> 246.78 | AB13: 2303.28 | AC13: 2056.5 | AD13: 246.78 | AE13: 45627 | AF13: =AC13-Y13 -> 0
A14: 1213 | B14: 45660 | C14: INV-10173 | D14: Christina Paruli | E14: 1400 | F14: Rocket Room Jan 3, 2025, 1pm to 3pm | G14: AR 795 Bank Transfer BPI (1400) Cash (700) | H14: MBTC | J14: Meeting Rooms | K14: =E14 -> 1400 | L14: 0 | M14: =K14-L14 -> 1400 | N14: =E14-M14 -> 0 | X14: =E14 -> 1400 | Y14: =X14/1.12 -> 1250 | Z14: =Y14*0.12 -> 150 | AB14: 1400 | AC14: 1250 | AD14: 150 | AF14: =AC14-Y14 -> 0
A15: 1214 | B15: 45660 | C15: INV-10174/INV-10176/INV-10177/INV-10178 | D15: Nix - N.T.B. Hair and Make up Services | E15: 34200 | F15: Event Space, Mar 1, May 24, Aug 30, Nov 22, 2025 - 9 am to 5pm | G15: Bank Transfer | H15: BPI | I15: 4348 | J15: Events | K15: =E15 -> 34200 | L15: 0 | M15: =K15-L15 -> 34200 | N15: =E15-M15 -> 0 | X15: =E15 -> 34200 | Y15: =X15/1.12 -> 30535.714 | Z15: =Y15*0.12 -> 3664.2857 | AB15: 34200 | AC15: 30535.714 | AD15: 3664.2857 | AE15: 8550 Xero | AF15: =AC15-Y15 -> 0
A16: 1215 | B16: 45660 | D16: Altech Vialab Inc. | E16: 25680 | F16: Office Suite 2 rent, Jan 1 - 31, 2025 (w/ 20% disc) | G16: Check | H16: UBP | I16: UBP 2002750714 | J16: Private Office | K16: 26880 | L16: =K16/1.12*0.05 -> 1200 | M16: =K16-L16 -> 25680 | N16: =E16-M16 -> 0 | X16: =K16 -> 26880 | Y16: =X16/1.12 -> 24000 | Z16: =Y16*0.12 -> 2880 | AE16: CANCELLED SI | AF16: =AC16-Y16 -> -24000
A17: 1216 | B17: 45660 | D17: Primera Biosolutions, Inc. | E17: 25680 | F17: Office Suite 2 rent, Jan 1 - 31, 2025 (w/ 20% disc) | G17: Check | H17: UBP | I17: UBP 2002918897 | J17: Private Office | K17: 26880 | L17: =K17/1.12*0.05 -> 1200 | M17: =K17-L17 -> 25680 | N17: =E17-M17 -> 0 | X17: =K17 -> 26880 | Y17: =X17/1.12 -> 24000 | Z17: =Y17*0.12 -> 2880 | AE17: CANCELLED SI | AF17: =AC17-Y17 -> -24000
A18: 1217 | B18: 45660 | C18: INV-10154 | D18: Marketing Master IO OPC | E18: 42000 | F18: Virtual Office, Jan 1, 2025 to December 31, 2025 | G18: Bank Transfer | H18: UBP | I18: UB422332 | J18: Virtual Office | K18: =E18 -> 42000 | L18: 0 | M18: =K18-L18 -> 42000 | N18: =E18-M18 -> 0 | X18: =E18 -> 42000 | Y18: =X18/1.12 -> 37500 | Z18: =Y18*0.12 -> 4500 | AB18: 42000 | AC18: 37500 | AD18: 4500 | AF18: =AC18-Y18 -> 0
A19: 1218 | B19: 45660 | C19: INV-10162 | D19: Megaluck Prime Solutions Inc | E19: 15000 | F19: Use Of Address, Jan 1, 2025 to December 31, 2025 | G19: Check | H19: UBP | I19: BDO 40620 | J19: Virtual Office | K19: =E19 -> 15000 | L19: 0 | M19: =K19-L19 -> 15000 | N19: =E19-M19 -> 0 | X19: =E19 -> 15000 | Y19: =X19/1.12 -> 13392.857 | Z19: =Y19*0.12 -> 1607.1429 | AB19: 15000 | AC19: 13392.857 | AD19: 1607.1429 | AF19: =AC19-Y19 -> 0
A20: 1219 | B20: 45660 | C20: INV-10167 | D20: Blue Point Properties Inc | E20: 1375 | F20: Use Of Address, Dec 29, 2024 to January 28, 2025 | G20: Check | H20: UBP | I20: Maybank 5022 | J20: Virtual Office | K20: =E20 -> 1375 | L20: 0 | M20: =K20-L20 -> 1375 | N20: =E20-M20 -> 0 | X20: =E20 -> 1375 | Y20: =X20/1.12 -> 1227.6786 | Z20: =Y20*0.12 -> 147.32143 | AB20: 1375 | AC20: 1227.6786 | AD20: 147.32143 | AE20: Dec sales | AF20: =AC20-Y20 -> 0
A21: 1220 | B21: 45660 | C21: INV-10168 | D21: Birch Registries Inc | E21: 1250 | F21: Use Of Address, Jan 2, 2025 to February 1, 2025 | G21: Check | H21: UBP | I21: BPI 1000162435 | J21: Virtual Office | K21: =E21 -> 1250 | L21: 0 | M21: =K21-L21 -> 1250 | N21: =E21-M21 -> 0 | X21: =E21 -> 1250 | Y21: =X21/1.12 -> 1116.0714 | Z21: =Y21*0.12 -> 133.92857 | AB21: 1250 | AC21: 1116.0714 | AD21: 133.92857 | AF21: =AC21-Y21 -> 0
A22: 1221 | B22: 45660 | C22: INV-10169 | D22: JFAQ Enterprise | E22: 1250 | F22: Use Of Address, Jan 1 - 31, 2025 | G22: Check | H22: UBP | I22: Eastwest Bank 0001567802 | J22: Virtual Office | K22: =E22 -> 1250 | L22: 0 | M22: =K22-L22 -> 1250 | N22: =E22-M22 -> 0 | X22: =E22 -> 1250 | Y22: =X22/1.12 -> 1116.0714 | Z22: =Y22*0.12 -> 133.92857 | AB22: 1250 | AC22: 1116.0714 | AD22: 133.92857 | AF22: =AC22-Y22 -> 0
A23: 1222 | B23: 45660 | C23: INV-10170 | D23: Prime Accounting and Consultancy Inc | E23: 955.36 | F23: Use Of Address, Jan 2, 2025 to February 1, 2025 | G23: Check | H23: UBP | I23: Chinabank 0000057687 | J23: Walk-Ins | K23: 1000 | L23: =K23/1.12*0.05 -> 44.642857 | M23: =K23-L23 -> 955.35714 | N23: =E23-M23 -> 0.0028571429 | X23: =E23 -> 955.36 | Y23: =X23/1.12 -> 853 | Z23: =Y23*0.12 -> 102.36 | AB23: 1000 | AC23: =AB23/1.12 -> 892.85714 | AD23: =AC23*12% -> 107.14286 | AF23: =AC23-Y23 -> 39.857143
A24: 1223 | B24: 45660 | C24: INV-10179 | D24: Jejo Fish Farm | E24: 2600 | F24: Meeting room (Suite 6), 1pm to 5pm | G24: Cash | H24: MBTC | J24: Meeting Rooms | K24: =E24 -> 2600 | L24: 0 | M24: =K24-L24 -> 2600 | N24: =E24-M24 -> 0 | X24: =E24 -> 2600 | Y24: =X24/1.12 -> 2321.4286 | Z24: =Y24*0.12 -> 278.57143 | AB24: 2600 | AC24: 2321.4286 | AD24: 278.57143 | AF24: =AC24-Y24 -> 0
A25: 1224 | D25: CANCELLED | K25: =E25 | L25: 0 | M25: =K25-L25 -> 0 | N25: =E25-M25 -> 0 | AF25: =AC25-Y25 -> 0
A26: 1225 | B26: 45661 | C26: INV-10180 | D26: RLTY Property Corp | E26: 4000 | F26: Astra 1, 10 am to 3:30 pm | G26: Cash | H26: MBTC | J26: Meeting Rooms | K26: =E26 -> 4000 | L26: 0 | M26: =K26-L26 -> 4000 | N26: =E26-M26 -> 0 | X26: =E26 -> 4000 | Y26: =X26/1.12 -> 3571.4286 | Z26: =Y26*0.12 -> 428.57143 | AB26: 4000 | AC26: 3571.4286 | AD26: 428.57143 | AF26: =AC26-Y26 -> 0
A27: 1226 | B27: 45661 | C27: INV-10182 | D27: Zoi's Meat Town | E27: 2600 | F27: Astra 2, 11:30 am to 3:30 pm | G27: Maya Card | H27: UBP | J27: Meeting Rooms | K27: =E27 -> 2600 | L27: 0 | M27: =K27-L27 -> 2600 | N27: =E27-M27 -> 0 | P27: 85.38 | Q27: =E27-P27 -> 2514.62 | X27: =E27 -> 2600 | Y27: =X27/1.12 -> 2321.4286 | Z27: =Y27*0.12 -> 278.57143 | AB27: 2600 | AC27: 2321.4286 | AD27: 278.57143 | AF27: =AC27-Y27 -> 0
A28: 1227 | B28: 45661 | C28: INV-10183 | D28: Limuel Libres | E28: 300 | F28: Whole day Flypass (Student Discount) | G28: Cash | H28: MBTC | J28: Walk-Ins | K28: =E28 -> 300 | L28: 0 | M28: =K28-L28 -> 300 | N28: =E28-M28 -> 0 | X28: =E28 -> 300 | Y28: =X28/1.12 -> 267.85714 | Z28: =Y28*0.12 -> 32.142857 | AB28: 300 | AC28: 267.85714 | AD28: 32.142857 | AF28: =AC28-Y28 -> 0
A29: 1228 | B29: 45661 | C29: INV-10184 | D29: Fyre Talent Academy | E29: 2100 | F29: Rocket Room, 2pm to 5pm | G29: Bank Transfer | H29: BPI | J29: Meeting Rooms | K29: =E29 -> 2100 | L29: 0 | M29: =K29-L29 -> 2100 | N29: =E29-M29 -> 0 | X29: =E29 -> 2100 | Y29: =X29/1.12 -> 1875 | Z29: =Y29*0.12 -> 225 | AB29: 2100 | AC29: 1875 | AD29: 225 | AF29: =AC29-Y29 -> 0
A30: 1229 | B30: 45663 | C30: INV-10186 | D30: Therese Navales | E30: 550 | F30: Whole day Flypass | G30: Maya Card | H30: UBP | J30: Walk-Ins | K30: =E30 -> 550 | L30: 0 | M30: =K30-L30 -> 550 | N30: =E30-M30 -> 0 | P30: 18.06 | Q30: =E30-P30 -> 531.94 | X30: =E30 -> 550 | Y30: =X30/1.12 -> 491.07143 | Z30: =Y30*0.12 -> 58.928571 | AB30: 550 | AC30: 491.07143 | AD30: 58.928571 | AF30: =AC30-Y30 -> 0
A31: 1230 | B31: 45663 | C31: INV-10187 | D31: AB Mauri Philippines Inc | E31: 5000 | F31: Rocket Room, Jan 8, 2025, 8 am to 5 pm | G31: Cash | H31: MBTC | J31: Meeting Rooms | K31: =E31 -> 5000 | L31: 0 | M31: =K31-L31 -> 5000 | N31: =E31-M31 -> 0 | X31: =E31 -> 5000 | Y31: =X31/1.12 -> 4464.2857 | Z31: =Y31*0.12 -> 535.71429 | AB31: 5000 | AC31: 4464.2857 | AD31: 535.71429 | AF31: =AC31-Y31 -> 0
A32: 1231 | B32: 45663 | C32: INV-10188 | D32: Altech Vialab Inc. | E32: 25680 | F32: Office Suite 2 rent, Jan 1 - 31, 2025 (w/ 20% disc) | G32: Check | H32: UBP | I32: UBP 2002750714 | J32: Private Office | K32: 26880 | L32: =K32/1.12*0.05 -> 1200 | M32: =K32-L32 -> 25680 | N32: =E32-M32 -> 0 | X32: =K32 -> 26880 | Y32: =X32/1.12 -> 24000 | Z32: =Y32*0.12 -> 2880 | AB32: 26880 | AC32: 24000 | AD32: 2880 | AF32: =AC32-Y32 -> 0
A33: 1232 | B33: 45663 | C33: INV-10189 | D33: Primera Biosolutions, Inc. | E33: 25680 | F33: Office Suite 2 rent, Jan 1 - 31, 2025 (w/ 20% disc) | G33: Check | H33: UBP | I33: UBP 2002918897 | J33: Private Office | K33: 26880 | L33: =K33/1.12*0.05 -> 1200 | M33: =K33-L33 -> 25680 | N33: =E33-M33 -> 0 | X33: =K33 -> 26880 | Y33: =X33/1.12 -> 24000 | Z33: =Y33*0.12 -> 2880 | AB33: 26880 | AC33: 24000 | AD33: 2880 | AF33: =AC33-Y33 -> 0
A34: 1233 | B34: 45663 | C34: INV-10190 | D34: Werner Access Products Philippines Inc | E34: 18000 | F34: Apollo 4&5, Jan 6&20,2025, 8am to 4pm | G34: Maya Card | H34: UBP | J34: Meeting Rooms | K34: =E34 -> 18000 | L34: 0 | M34: =K34-L34 -> 18000 | N34: =E34-M34 -> 0 | P34: 591.07 | Q34: =E34-P34 -> 17408.93 | X34: =E34 -> 18000 | Y34: =X34/1.12 -> 16071.429 | Z34: =Y34*0.12 -> 1928.5714 | AB34: 18000 | AC34: 16071.429 | AD34: 1928.5714 | AF34: =AC34-Y34 -> 0
A35: 1234 | B35: 45663 | C35: INV-10161 | D35: Aguilar IT Solutions | E35: 14072.56 | F35: Use of Address, Jan 24, 2025 to December 31, 2025 | G35: Maya Card | H35: UBP | J35: Virtual Office | K35: =E35 -> 14072.56 | L35: 0 | M35: =K35-L35 -> 14072.56 | N35: =E35-M35 -> 0 | P35: 462.1 | Q35: =E35-P35 -> 13610.46 | X35: =E35 -> 14072.56 | Y35: =X35/1.12 -> 12564.786 | Z35: =Y35*0.12 -> 1507.7743 | AB35: 14072.56 | AC35: 12564.786 | AD35: 1507.7743 | AF35: =AC35-Y35 -> 0
A36: 1235 | B36: 45663 | C36: INV-10191 | D36: JP Aclan | E36: 4700 | F36: Astra 1, Jan 3, 2025, 9:30 am to 4:30 pm | G36: Bank Transfer | H36: UBP | I36: UB723905 | J36: Meeting Rooms | K36: =E36 -> 4700 | L36: 0 | M36: =K36-L36 -> 4700 | N36: =E36-M36 -> 0 | X36: =E36 -> 4700 | Y36: =X36/1.12 -> 4196.4286 | Z36: =Y36*0.12 -> 503.57143 | AB36: 4700 | AC36: 4196.4286 | AD36: 503.57143 | AF36: =AC36-Y36 -> 0
A37: 1236 | B37: 45663 | C37: INV-10192 | D37: Feast Bellevue PM | E37: 5000 | F37: Rocket room, Jan 18, 2025, 8:00 am to 5:00 pm | G37: Bank Transfer | H37: UBP | I37: UB422188 - for tranfer SVI to SI | J37: Meeting Rooms | K37: =E37 -> 5000 | L37: 0 | M37: =K37-L37 -> 5000 | N37: =E37-M37 -> 0 | X37: =E37 -> 5000 | Y37: =X37/1.12 -> 4464.2857 | Z37: =Y37*0.12 -> 535.71429 | AB37: 5000 | AC37: 4464.2857 | AD37: 535.71429 | AF37: =AC37-Y37 -> 0
A38: 1237 | B38: 45663 | C38: INV-10071 | D38: Maso Fit Out Finishing Services | E38: 700 | F38: Rocket room, Dec 12, 2024, 1:00 pm to 2:00 pm | G38: Bank Transfer | H38: UBP | I38: UB1137273 | J38: Meeting Rooms | K38: =E38 -> 700 | L38: 0 | M38: =K38-L38 -> 700 | N38: =E38-M38 -> 0 | X38: =E38 -> 700 | Y38: =X38/1.12 -> 625 | Z38: =Y38*0.12 -> 75 | AB38: 700 | AC38: 625 | AD38: 75 | AE38: 2024 sales | AF38: =AC38-Y38 -> 0
A39: 1238 | B39: 45663 | C39: INV-10195 | D39: Vincent Carbajal | E39: 2371 | F39: Call room (Office Suite 9) , 12:30 pm to 7:30 pm | G39: Maya Card | H39: UBP | J39: Meeting Rooms | K39: =E39 -> 2371 | L39: 0 | M39: =K39-L39 -> 2371 | N39: =E39-M39 -> 0 | P39: 77.86 | Q39: =E39-P39 -> 2293.14 | X39: =E39 -> 2371 | Y39: =X39/1.12 -> 2116.9643 | Z39: =Y39*0.12 -> 254.03571 | AB39: 2371 | AC39: 2116.9643 | AD39: 254.03571 | AF39: =AC39-Y39 -> 0
A40: 1239 | B40: 45663 | C40: INV-10196 | D40: WonderPark Orbis Amusement, Inc. | E40: 2600 | F40: Astra 2, 12:00 pm to 4:00 pm - Jan 6, 2025 | G40: Maya Card | H40: UBP | J40: Meeting Rooms | K40: =E40 -> 2600 | L40: 0 | M40: =K40-L40 -> 2600 | N40: =E40-M40 -> 0 | P40: 85.38 | Q40: =E40-P40 -> 2514.62 | R40: =SUM(Q30:Q40) -> 36359.09 | X40: =E40 -> 2600 | Y40: =X40/1.12 -> 2321.4286 | Z40: =Y40*0.12 -> 278.57143 | AB40: 2600 | AC40: 2321.4286 | AD40: 278.57143 | AF40: =AC40-Y40 -> 0
A41: 1240 | B41: 45664 | C41: INV-10164 | D41: Arwin Cortez | E41: 3000 | F41: 10 days Flypass, Jan 7 - Feb 6, 2025 | G41: Maya Card | H41: UBP | J41: Walk-Ins | K41: =E41 -> 3000 | L41: 0 | M41: =K41-L41 -> 3000 | N41: =E41-M41 -> 0 | P41: 98.51 | Q41: =E41-P41 -> 2901.49 | X41: =E41 -> 3000 | Y41: =X41/1.12 -> 2678.5714 | Z41: =Y41*0.12 -> 321.42857 | AB41: 3000 | AC41: 2678.5714 | AD41: 321.42857 | AF41: =AC41-Y41 -> 0
A42: 1241 | B42: 45664 | C42: INV-10172 | D42: Aristo Marco | E42: 600 | F42: 3 hour flypass for 2 seats | G42: Gcash QR Standee | H42: UBP | J42: Walk-Ins | K42: =E42 -> 600 | L42: 0 | M42: =K42-L42 -> 600 | N42: =E42-M42 -> 0 | P42: 14.62 | Q42: =E42-P42 -> 585.38 | X42: =E42 -> 600 | Y42: =X42/1.12 -> 535.71429 | Z42: =Y42*0.12 -> 64.285714 | AB42: 600 | AC42: 535.71429 | AD42: 64.285714 | AF42: =AC42-Y42 -> 0
A43: 1242 | B43: 45664 | C43: INV-10175 | D43: Prime Institute | E43: 2100 | F43: Rocket Room, 12pm to 3 pm | G43: Bank Transfer | H43: UBP | I43: UB1466206 | J43: Meeting Rooms | K43: =E43 -> 2100 | L43: 0 | M43: =K43-L43 -> 2100 | N43: =E43-M43 -> 0 | X43: =E43 -> 2100 | Y43: =X43/1.12 -> 1875 | Z43: =Y43*0.12 -> 225 | AB43: 2100 | AC43: 1875 | AD43: 225 | AF43: =AC43-Y43 -> 0
A44: 1243 | B44: 45664 | C44: INV-10199 | D44: Enspire Global Inc | E44: 13945.08 | F44: Use of Address, Jan 11, 2025 to Dec 31, 2025 | G44: Maya Card | H44: UBP | J44: Virtual Office | K44: 14596.72 | L44: =K44/1.12*0.05 -> 651.63929 | M44: =K44-L44 -> 13945.081 | N44: =E44-M44 -> -0.00071428571 | P44: 457.92 | Q44: =E44-P44 -> 13487.16 | X44: =K44 -> 14596.72 | Y44: =X44/1.12 -> 13032.786 | Z44: =Y44*0.12 -> 1563.9343 | AB44: 14596.72 | AC44: 13032.786 | AD44: 1563.9343 | AF44: =AC44-Y44 -> 0
A45: 1244 | B45: 45664 | C45: INV-10200 | D45: Pat Balete | E45: 5000 | F45: Monthly flypass, Jan 7 - Feb 6, 2025 | G45: Maya Card | H45: UBP | J45: Monthly Membership | K45: =E45 -> 5000 | L45: 0 | M45: =K45-L45 -> 5000 | N45: =E45-M45 -> 0 | P45: 164.19 | Q45: =E45-P45 -> 4835.81 | R45: =Q41+Q44+Q45 -> 21224.46 | X45: =E45 -> 5000 | Y45: =X45/1.12 -> 4464.2857 | Z45: =Y45*0.12 -> 535.71429 | AB45: 5000 | AC45: 4464.2857 | AD45: 535.71429 | AF45: =AC45-Y45 -> 0
A46: 1245 | B46: 45665 | C46: INV-10128 | D46: Metals Focus Data Ltd. (Donadee Allene Francisco) | E46: 11200 | F46: Office Suite 1, Jan 2025 rent | G46: Bank Transfer | H46: UBP | I46: UB534203 | J46: Private Office | K46: =E46 -> 11200 | L46: 0 | M46: =K46-L46 -> 11200 | N46: =E46-M46 -> 0 | X46: =E46 -> 11200 | Y46: =X46/1.12 -> 10000 | Z46: =Y46*0.12 -> 1200 | AB46: 11200 | AC46: 10000 | AD46: 1200 | AF46: =AC46-Y46 -> 0
A47: 1246 | B47: 45665 | C47: INV-10111 | D47: Paysera Ltd | E47: 58850 | F47: Office Suite 11, January 2025 rent (w/50% Discount) | G47: Bank Transfer | H47: UBP | I47: UB248314 | J47: Private Office | K47: 61600 | L47: =K47/1.12*0.05 -> 2750 | M47: =K47-L47 -> 58850 | N47: =E47-M47 -> 0 | X47: =K47 -> 61600 | Y47: =X47/1.12 -> 55000 | Z47: =Y47*0.12 -> 6600 | AB47: 61600 | AC47: 55000 | AD47: 6600 | AF47: =AC47-Y47 -> 0
A48: 1247 | B48: 45665 | C48: INV-10128 | D48: Mary Joy Celine Zarate-Panol (Metals Focus Data Ltd.) | E48: 11200 | F48: Office Suite 1, Jan 2025 rent | G48: Maya Card | H48: UBP | J48: Private Office | K48: =E48 -> 11200 | L48: 0 | M48: =K48-L48 -> 11200 | N48: =E48-M48 -> 0 | P48: 367.49 | Q48: =E48-P48 -> 10832.51 | X48: =E48 -> 11200 | Y48: =X48/1.12 -> 10000 | Z48: =Y48*0.12 -> 1200 | AB48: 11200 | AC48: 10000 | AD48: 1200 | AF48: =AC48-Y48 -> 0
A49: 1248 | B49: 45665 | C49: INV-10201 | D49: Ed Libao | E49: 300 | F49: 3 hour flyass | G49: Gcash QR Standee | H49: UBP | J49: Walk-Ins | K49: =E49 -> 300 | L49: 0 | M49: =K49-L49 -> 300 | N49: =E49-M49 -> 0 | P49: 7.31 | Q49: =E49-P49 -> 292.69 | X49: =E49 -> 300 | Y49: =X49/1.12 -> 267.85714 | Z49: =Y49*0.12 -> 32.142857 | AB49: 300 | AC49: 267.85714 | AD49: 32.142857 | AF49: =AC49-Y49 -> 0
A50: 1249 | B50: 45665 | C50: INV-10202 | D50: Catherine Yambao | E50: 300 | F50: 3 hour flyass | G50: Gcash QR Standee | H50: UBP | J50: Walk-Ins | K50: =E50 -> 300 | L50: 0 | M50: =K50-L50 -> 300 | N50: =E50-M50 -> 0 | P50: 7.31 | Q50: =E50-P50 -> 292.69 | X50: =E50 -> 300 | Y50: =X50/1.12 -> 267.85714 | Z50: =Y50*0.12 -> 32.142857 | AB50: 300 | AC50: 267.85714 | AD50: 32.142857 | AF50: =AC50-Y50 -> 0
A51: 1250 | B51: 45665 | C51: INV-10203 | D51: JP Aclan | E51: 132 | F51: Printing (P4x33pages) | G51: Cash | H51: MBTC | J51: Add Ons | K51: =E51 -> 132 | L51: 0 | M51: =K51-L51 -> 132 | N51: =E51-M51 -> 0 | X51: =E51 -> 132 | Y51: =X51/1.12 -> 117.85714 | Z51: =Y51*0.12 -> 14.142857 | AB51: 132 | AC51: 117.85714 | AD51: 14.142857 | AF51: =AC51-Y51 -> 0
A52: 1251 | B52: 45665 | C52: INV-10194 | D52: Aquaspace Inc | E52: 16189.4 | F52: Use Of Address, Jan 8, 2025 to Dec 31, 2025 | G52: Maya Card | H52: UBP | J52: Virtual Office | K52: =E52 -> 16189.4 | L52: 0 | M52: =K52-L52 -> 16189.4 | N52: =E52-M52 -> 0 | P52: 531.2 | Q52: =E52-P52 -> 15658.2 | X52: =E52 -> 16189.4 | Y52: =X52/1.12 -> 14454.821 | Z52: =Y52*0.12 -> 1734.5786 | AB52: 16189.4 | AC52: 14454.821 | AD52: 1734.5786 | AF52: =AC52-Y52 -> 0
A53: 1252 | D53: CANCELLED | K53: =E53 | L53: 0 | M53: =K53-L53 -> 0 | N53: =E53-M53 -> 0 | AF53: =AC53-Y53 -> 0
A54: 1253 | B54: 45665 | C54: INV-10204 | D54: AB Mauri Philippines Inc | E54: 5000 | F54: Rocket room, Jan 14, 2025, 8 am to 5pm | G54: Maya Card | H54: UBP | J54: Meeting Rooms | K54: =E54 -> 5000 | L54: 0 | M54: =K54-L54 -> 5000 | N54: =E54-M54 -> 0 | P54: 164.06 | Q54: =E54-P54 -> 4835.94 | X54: =E54 -> 5000 | Y54: =X54/1.12 -> 4464.2857 | Z54: =Y54*0.12 -> 535.71429 | AB54: 5000 | AC54: 4464.2857 | AD54: 535.71429 | AF54: =AC54-Y54 -> 0
A55: 1254 | B55: 45665 | C55: INV-10205 | D55: Gavin Adam Centerno | E55: 240 | F55: 3 hour flypass (Parent Discount) | G55: Gcash QR Standee | H55: UBP | J55: Walk-Ins | K55: =E55 -> 240 | L55: 0 | M55: =K55-L55 -> 240 | N55: =E55-M55 -> 0 | P55: 5.85 | Q55: =E55-P55 -> 234.15 | X55: =E55 -> 240 | Y55: =X55/1.12 -> 214.28571 | Z55: =Y55*0.12 -> 25.714286 | AB55: 240 | AC55: 214.28571 | AD55: 25.714286 | AF55: =AC55-Y55 -> 0
A56: 1255 | B56: 45665 | C56: INV-10212 | D56: Bianca Larranaga | E56: 5415 | F56: Astra 1 rent, 9 am to 6 pm (w/ 5% discount) | G56: Maya Card | H56: UBP | J56: Meeting Rooms | K56: =E56 -> 5415 | L56: 0 | M56: =K56-L56 -> 5415 | N56: =E56-M56 -> 0 | P56: 178.64 | Q56: =E56-P56 -> 5236.36 | R56: =Q48+Q52+Q54+Q56 -> 36563.01 | X56: =E56 -> 5415 | Y56: =X56/1.12 -> 4834.8214 | Z56: =Y56*0.12 -> 580.17857 | AB56: 5415 | AC56: 4834.8214 | AD56: 580.17857 | AF56: =AC56-Y56 -> 0
A57: 1256 | B57: 45666 | C57: INV-10215 | D57: Coliconstruct Engineering Services | E57: 300 | F57: 3 hour flyass | G57: Gcash QR Standee | H57: UBP | J57: Walk-Ins | K57: =E57 -> 300 | L57: 0 | M57: =K57-L57 -> 300 | N57: =E57-M57 -> 0 | P57: 7.31 | Q57: =E57-P57 -> 292.69 | X57: =E57 -> 300 | Y57: =X57/1.12 -> 267.85714 | Z57: =Y57*0.12 -> 32.142857 | AB57: 300 | AC57: 267.85714 | AD57: 32.142857 | AF57: =AC57-Y57 -> 0
A58: 1257 | B58: 45666 | C58: INV-10129 | D58: Visit and Experience Travel Services Inc (VETS INC) | E58: 21400 | F58: Suites Office 8, Jan 4, 2025 - Feb 3, 2025 | G58: Check | H58: UBP | I58: Unionbank 0000987908 | J58: Private Office | K58: 22400 | L58: =K58/1.12*0.05 -> 1000 | M58: =K58-L58 -> 21400 | N58: =E58-M58 -> 0 | X58: =K58 -> 22400 | Y58: =X58/1.12 -> 20000 | Z58: =Y58*0.12 -> 2400 | AB58: 22400 | AC58: 20000 | AD58: 2400 | AF58: =AC58-Y58 -> 0
A59: 1258 | B59: 45666 | C59: INV-10128 | D59: Ruby Tagoon (Metals Focus Data Ltd.) | E59: 11200 | F59: Office Suite 1, Jan 2025 rent | G59: Maya Card | H59: UBP | J59: Private Office | K59: =E59 -> 11200 | L59: 0 | M59: =K59-L59 -> 11200 | N59: =E59-M59 -> 0 | P59: 367.78 | Q59: =E59-P59 -> 10832.22 | X59: =E59 -> 11200 | Y59: =X59/1.12 -> 10000 | Z59: =Y59*0.12 -> 1200 | AB59: 11200 | AC59: 10000 | AD59: 1200 | AF59: =AC59-Y59 -> 0
A60: 1259 | B60: 45666 | C60: INV-10216 | D60: Acasales Technologies Inc. | E60: 2100 | F60: Astra 2, 9:00 am to 12:00 pm, Jan 9, 2025 | G60: Cash (100) Gcash QR Standee (2000) | H60: MBTC | J60: Meeting Rooms | K60: =E60 -> 2100 | L60: 0 | M60: =K60-L60 -> 2100 | N60: =E60-M60 -> 0 | P60: 48.73 | Q60: =2000-P60 -> 1951.27 | X60: =E60 -> 2100 | Y60: =X60/1.12 -> 1875 | Z60: =Y60*0.12 -> 225 | AB60: 2100 | AC60: 1875 | AD60: 225 | AF60: =AC60-Y60 -> 0
A61: 1260 | B61: 45666 | C61: INV-10217 | D61: Acasales Technologies Inc. | E61: 2100 | F61: Astra 2, 9:00 am to 12:00 pm, Jan 28, 2025 | G61: Cash | H61: MBTC | J61: Meeting Rooms | K61: =E61 -> 2100 | L61: 0 | M61: =K61-L61 -> 2100 | N61: =E61-M61 -> 0 | X61: =E61 -> 2100 | Y61: =X61/1.12 -> 1875 | Z61: =Y61*0.12 -> 225 | AB61: 2100 | AC61: 1875 | AD61: 225 | AF61: =AC61-Y61 -> 0
A62: 1261 | B62: 45666 | C62: INV-10218 | D62: Awon | E62: 218 | F62: Printing (Bk/wh and colored) | G62: Cash | H62: MBTC | J62: Add Ons | K62: =E62 -> 218 | L62: 0 | M62: =K62-L62 -> 218 | N62: =E62-M62 -> 0 | X62: =E62 -> 218 | Y62: =X62/1.12 -> 194.64286 | Z62: =Y62*0.12 -> 23.357143 | AB62: 218 | AC62: 194.64286 | AD62: 23.357143 | AF62: =AC62-Y62 -> 0
A63: 1262 | B63: 45666 | C63: INV-10219 | D63: Renee Filio | E63: 300 | F63: 3 hour flyass | G63: Cash | H63: MBTC | J63: Walk-Ins | K63: =E63 -> 300 | L63: 0 | M63: =K63-L63 -> 300 | N63: =E63-M63 -> 0 | X63: =E63 -> 300 | Y63: =X63/1.12 -> 267.85714 | Z63: =Y63*0.12 -> 32.142857 | AB63: 300 | AC63: 267.85714 | AD63: 32.142857 | AF63: =AC63-Y63 -> 0
A64: 1263 | B64: 45666 | C64: INV-10220 | D64: Russell Yao | E64: 300 | F64: 3 hour flyass | G64: Gcash QR Standee | H64: UBP | J64: Walk-Ins | K64: =E64 -> 300 | L64: 0 | M64: =K64-L64 -> 300 | N64: =E64-M64 -> 0 | P64: 7.31 | Q64: =E64-P64 -> 292.69 | X64: =E64 -> 300 | Y64: =X64/1.12 -> 267.85714 | Z64: =Y64*0.12 -> 32.142857 | AB64: 300 | AC64: 267.85714 | AD64: 32.142857 | AF64: =AC64-Y64 -> 0
A65: 1264 | B65: 45666 | C65: INV-10221 | D65: Te-Anne Robles | E65: 550 | F65: Whole day Flypass | G65: Cash | H65: MBTC | J65: Walk-Ins | K65: =E65 -> 550 | L65: 0 | M65: =K65-L65 -> 550 | N65: =E65-M65 -> 0 | X65: =E65 -> 550 | Y65: =X65/1.12 -> 491.07143 | Z65: =Y65*0.12 -> 58.928571 | AB65: 550 | AC65: 491.07143 | AD65: 58.928571 | AF65: =AC65-Y65 -> 0
A66: 1265 | B66: 45666 | C66: INV-10222 | D66: Pauline Tanedo | E66: 550 | F66: Whole day Flypass | G66: Gcash QR Standee | H66: UBP | J66: Walk-Ins | K66: =E66 -> 550 | L66: 0 | M66: =K66-L66 -> 550 | N66: =E66-M66 -> 0 | P66: 13.4 | Q66: =E66-P66 -> 536.6 | X66: =E66 -> 550 | Y66: =X66/1.12 -> 491.07143 | Z66: =Y66*0.12 -> 58.928571 | AB66: 550 | AC66: 491.07143 | AD66: 58.928571 | AF66: =AC66-Y66 -> 0
A67: 1266 | B67: 45666 | C67: INV-10008 | D67: Switch Automation Philippines Inc. | E67: 1194.2 | F67: Use of Address, Dec 18, 2024 - Jan 17, 2025 | G67: Bank Transfer | H67: UBP | I67: UB176830 | J67: Virtual Office | K67: 1250 | L67: =K67/1.12*0.05 -> 55.803571 | M67: =K67-L67 -> 1194.1964 | N67: =E67-M67 -> 0.0035714286 | X67: =K67 -> 1250 | Y67: =X67/1.12 -> 1116.0714 | Z67: =Y67*0.12 -> 133.92857 | AB67: 1250 | AC67: 1116.0714 | AD67: 133.92857 | AF67: =AC67-Y67 -> 0
A68: 1267 | B68: 45666 | C68: INV-10231 | D68: P.A. Alvarez Properties and Development Corp | E68: 15000 | F68: Use of Address, Jan 1, 2025 - Dec 31, 2025 | G68: Check | H68: BPI | I68: 0331 | J68: Virtual Office | K68: =E68 -> 15000 | L68: 0 | M68: =K68-L68 -> 15000 | N68: =E68-M68 -> 0 | X68: =E68 -> 15000 | Y68: =X68/1.12 -> 13392.857 | Z68: =Y68*0.12 -> 1607.1429 | AB68: 15000 | AC68: 13392.857 | AD68: 1607.1429 | AF68: =AC68-Y68 -> 0
A69: 1268 | B69: 45666 | C69: INV-10232 | D69: Digibeacon BPO Inc. | E69: 14677.36 | F69: Use of Address, Jan 9, 2024 to Dec 31, 2025 | G69: Bank Transfer | H69: UBP | I69: UB624842 | J69: Virtual Office | K69: =E69 -> 14677.36 | L69: 0 | M69: =K69-L69 -> 14677.36 | N69: =E69-M69 -> 0 | X69: =E69 -> 14677.36 | Y69: =X69/1.12 -> 13104.786 | Z69: =Y69*0.12 -> 1572.5743 | AB69: 14677.36 | AC69: 13104.786 | AD69: 1572.5743 | AF69: =AC69-Y69 -> 0
A70: 1269 | B70: 45666 | C70: INV-10233 | D70: Prime Boucherie OPC | E70: 2600 | F70: Astra 1, 8:00 am to 12:00 pm - Jan 11, 2025 | G70: Bank Transfer | H70: BPI | I70: 0331 | J70: Meeting Rooms | K70: =E70 -> 2600 | L70: 0 | M70: =K70-L70 -> 2600 | N70: =E70-M70 -> 0 | X70: =E70 -> 2600 | Y70: =X70/1.12 -> 2321.4286 | Z70: =Y70*0.12 -> 278.57143 | AB70: 2600 | AC70: 2321.4286 | AD70: 278.57143 | AF70: =AC70-Y70 -> 0
A71: 1270 | B71: 45666 | C71: INV-10197 | D71: Ronin Business Ideas Management Solutions Inc | E71: 40125 | F71: Virtual Office, Jan 1, 2025 to December 31, 2025 | G71: Check | H71: UBP | I71: Security Bank 0000987277 | J71: Virtual Office | K71: 42000 | L71: =K71/1.12*0.05 -> 1875 | M71: =K71-L71 -> 40125 | N71: =E71-M71 -> 0 | X71: =K71 -> 42000 | Y71: =X71/1.12 -> 37500 | Z71: =Y71*0.12 -> 4500 | AB71: 42000 | AC71: 37500 | AD71: 4500 | AF71: =AC71-Y71 -> 0
A72: 1271 | B72: 45666 | C72: INV-10198 | D72: RLTY Property Corp | E72: 1250 | F72: Use of Address, Jan 1 - 31, 2025 | G72: Check | H72: UBP | I72: Chinabank 0000601462 | J72: Virtual Office | K72: =E72 -> 1250 | L72: 0 | M72: =K72-L72 -> 1250 | N72: =E72-M72 -> 0 | X72: =E72 -> 1250 | Y72: =X72/1.12 -> 1116.0714 | Z72: =Y72*0.12 -> 133.92857 | AB72: 1250 | AC72: 1116.0714 | AD72: 133.92857 | AF72: =AC72-Y72 -> 0
A73: 1272 | B73: 45666 | C73: INV-10226 | D73: Bianca Larrañaga | E73: 5415 | F73: Astra 1, 9:00 am to 6:00 pm | G73: Maya Card | H73: UBP | J73: Meeting Rooms | K73: =E73 -> 5415 | L73: 0 | M73: =K73-L73 -> 5415 | N73: =E73-M73 -> 0 | P73: 177.82 | Q73: =E73-P73 -> 5237.18 | X73: =E73 -> 5415 | Y73: =X73/1.12 -> 4834.8214 | Z73: =Y73*0.12 -> 580.17857 | AB73: 5415 | AC73: 4834.8214 | AD73: 580.17857 | AF73: =AC73-Y73 -> 0
A74: 1273 | D74: CANCELLED | K74: =E74 | L74: 0 | M74: =K74-L74 -> 0 | N74: =E74-M74 -> 0 | AF74: =AC74-Y74 -> 0
A75: 1274 | B75: 45666 | C75: INV-10247 | D75: Compare Club Australia | E75: 16200 | F75: Apollo 4 and Rocket Room, 9 am to 6 pm | G75: AR 802 Bank Transfer (8100) Maya Card (8100) | H75: UBP | J75: Meeting Rooms | K75: =E75 -> 16200 | L75: 0 | M75: =K75-L75 -> 16200 | N75: =E75-M75 -> 0 | P75: 265.98 | Q75: =8100-P75 -> 7834.02 | R75: =Q59+Q73+7834.02 -> 23903.42 | X75: =E75 -> 16200 | Y75: =X75/1.12 -> 14464.286 | Z75: =Y75*0.12 -> 1735.7143 | AB75: 16200 | AC75: 14464.286 | AD75: 1735.7143 | AF75: =AC75-Y75 -> 0
A76: 1275 | B76: 45667 | C76: INV-10234 | D76: Bianca Larrañaga | E76: 4000 | F76: Astra 1, 9:00 am to 3:00 pm | G76: Maya Card | H76: UBP | J76: Meeting Rooms | K76: =E76 -> 4000 | L76: 0 | M76: =K76-L76 -> 4000 | N76: =E76-M76 -> 0 | P76: 131.35 | Q76: =E76-P76 -> 3868.65 | R76: =Q76 -> 3868.65 | X76: =E76 -> 4000 | Y76: =X76/1.12 -> 3571.4286 | Z76: =Y76*0.12 -> 428.57143 | AB76: 4000 | AC76: 3571.4286 | AD76: 428.57143 | AF76: =AC76-Y76 -> 0
A77: 1276 | B77: 45667 | C77: INV-10235 | D77: Diane Krupasa | E77: 550 | F77: Whole day Flypass | G77: Gcash QR Standee | H77: UBP | J77: Walk-Ins | K77: =E77 -> 550 | L77: 0 | M77: =K77-L77 -> 550 | N77: =E77-M77 -> 0 | P77: 13.4 | Q77: =E77-P77 -> 536.6 | X77: =E77 -> 550 | Y77: =X77/1.12 -> 491.07143 | Z77: =Y77*0.12 -> 58.928571 | AB77: 550 | AC77: 491.07143 | AD77: 58.928571 | AF77: =AC77-Y77 -> 0
A78: 1277 | B78: 45667 | C78: INV-10236 | D78: QE 360 OPC | E78: 14314.48 | F78: Use of Address, Jan 18, 2025 to December 31, 2025 | G78: Bank Transfer | H78: UBP | I78: UB551396 | J78: Virtual Office | K78: =E78 -> 14314.48 | L78: 0 | M78: =K78-L78 -> 14314.48 | N78: =E78-M78 -> 0 | X78: =E78 -> 14314.48 | Y78: =X78/1.12 -> 12780.786 | Z78: =Y78*0.12 -> 1533.6943 | AB78: 14314.48 | AC78: 12780.786 | AD78: 1533.6943 | AF78: =AC78-Y78 -> 0
A79: 1278 | B79: 45667 | C79: INV-10237 | D79: Mamapina Enterprises OPC | E79: 16500 | F79: Use of Address, Jan 1, 2025 - Dec 31, 2025 | G79: Bank Transfer | H79: UBP | I79: UB342560 | J79: Virtual Office | K79: =E79 -> 16500 | L79: 0 | M79: =K79-L79 -> 16500 | N79: =E79-M79 -> 0 | X79: =E79 -> 16500 | Y79: =X79/1.12 -> 14732.143 | Z79: =Y79*0.12 -> 1767.8571 | AB79: 16500 | AC79: 14732.143 | AD79: 1767.8571 | AF79: =AC79-Y79 -> 0
A80: 1279 | B80: 45667 | C80: INV-10238 | D80: Ella Simon-Sarsoza | E80: 3300 | F80: Astra 2, 12:00 nn to 5:00 pm - Jan 10, 2025 | G80: AR 806 Bank Transfer (1650) Cash (1600) | H80: MBTC | I80: 3345 | J80: Meeting Rooms | K80: =E80 -> 3300 | L80: 0 | M80: =K80-L80 -> 3300 | N80: =E80-M80 -> 0 | X80: =E80 -> 3300 | Y80: =X80/1.12 -> 2946.4286 | Z80: =Y80*0.12 -> 353.57143 | AB80: 3300 | AC80: 2946.4286 | AD80: 353.57143 | AF80: =AC80-Y80 -> 0
A81: 1280 | B81: 45667 | C81: INV-10264 | D81: Onergy Safety Traning Center | E81: 13427.36 | F81: Use of Address, Feb 9, 2025 to Dec 31, 2025 | G81: Bank Transfer | H81: UBP | I81: UB383207 | J81: Virtual Office | K81: =E81 -> 13427.36 | L81: 0 | M81: =K81-L81 -> 13427.36 | N81: =E81-M81 -> 0 | X81: =E81 -> 13427.36 | Y81: =X81/1.12 -> 11988.714 | Z81: =Y81*0.12 -> 1438.6457 | AB81: 13427.36 | AC81: 11988.714 | AD81: 1438.6457 | AF81: =AC81-Y81 -> 0
A82: 1281 | D82: CANCELLED | K82: =E82 | L82: 0 | M82: =K82-L82 -> 0 | N82: =E82-M82 -> 0 | AF82: =AC82-Y82 -> 0
A83: 1282 | B83: 45667 | C83: INV-10239 | D83: Arkiya Francine Orosco | E83: 1400 | F83: Astra 1, 11:30 am to 1:30 pm | G83: Cash | H83: MBTC | J83: Meeting Rooms | K83: =E83 -> 1400 | L83: 0 | M83: =K83-L83 -> 1400 | N83: =E83-M83 -> 0 | X83: =E83 -> 1400 | Y83: =X83/1.12 -> 1250 | Z83: =Y83*0.12 -> 150 | AB83: 1400 | AC83: 1250 | AD83: 150 | AF83: =AC83-Y83 -> 0
A84: 1283 | B84: 45668 | C84: INV-10240 | D84: GP Capuchino | E84: 400 | F84: 3 hour flyass AND 1 hour extension | G84: Maya Card | H84: UBP | J84: Walk-Ins | K84: =E84 -> 400 | L84: 0 | M84: =K84-L84 -> 400 | N84: =E84-M84 -> 0 | P84: 13.13 | Q84: =E84-P84 -> 386.87 | R84: =Q84 -> 386.87 | X84: =E84 -> 400 | Y84: =X84/1.12 -> 357.14286 | Z84: =Y84*0.12 -> 42.857143 | AB84: 400 | AC84: 357.14286 | AD84: 42.857143 | AF84: =AC84-Y84 -> 0
A85: 1284 | B85: 45668 | C85: INV-10241 | D85: Jayvee Allen Malolos | E85: 1400 | F85: Astra 1, 2:00 pm to 4:00 pm | G85: Gcash QR Standee | H85: UBP | J85: Meeting Rooms | K85: =E85 -> 1400 | L85: 0 | M85: =K85-L85 -> 1400 | N85: =E85-M85 -> 0 | P85: 34.11 | Q85: =E85-P85 -> 1365.89 | X85: =E85 -> 1400 | Y85: =X85/1.12 -> 1250 | Z85: =Y85*0.12 -> 150 | AB85: 1400 | AC85: 1250 | AD85: 150 | AF85: =AC85-Y85 -> 0
A86: 1285 | B86: 45668 | C86: INV-10242 | D86: Fyre Talent Academy | E86: 5940 | F86: Event Space 1, 12:00 pm to 3:00 pm & Rocket Room, 12pm-1pm ; 3pm-5pm | G86: Cash | H86: MBTC | J86: Events | K86: =E86 -> 5940 | L86: 0 | M86: =K86-L86 -> 5940 | N86: =E86-M86 -> 0 | X86: =E86 -> 5940 | Y86: =X86/1.12 -> 5303.5714 | Z86: =Y86*0.12 -> 636.42857 | AB86: 5940 | AC86: 5303.5714 | AD86: 636.42857 | AF86: =AC86-Y86 -> 0
A87: 1286 | B87: 45669 | C87: INV-10243 | D87: Philippine Stakeholders For Nutrition and Dietetics Inc. (PSND) | E87: 9500 | F87: Event Space 1,12pm to 5pm | G87: AR 758 (4000) Cash (5500) | H87: MBTC | J87: Events | K87: =E87 -> 9500 | L87: 0 | M87: =K87-L87 -> 9500 | N87: =E87-M87 -> 0 | X87: =E87 -> 9500 | Y87: =X87/1.12 -> 8482.1429 | Z87: =Y87*0.12 -> 1017.8571 | AB87: 9500 | AC87: 8482.1429 | AD87: 1017.8571 | AF87: =AC87-Y87 -> 0
A88: 1287 | B88: 45670 | C88: INV-10244 | D88: Daiho Phils, Inc. | E88: 300 | F88: 3 hour flyass | G88: Cash | H88: MBTC | J88: Walk-Ins | K88: =E88 -> 300 | L88: 0 | M88: =K88-L88 -> 300 | N88: =E88-M88 -> 0 | X88: =E88 -> 300 | Y88: =X88/1.12 -> 267.85714 | Z88: =Y88*0.12 -> 32.142857 | AB88: 300 | AC88: 267.85714 | AD88: 32.142857 | AF88: =AC88-Y88 -> 0
A89: 1288 | B89: 45670 | C89: INV-10245 | D89: Prall Corporation | E89: 300 | F89: 3 hour flyass | G89: Gcash QR Standee | H89: UBP | J89: Walk-Ins | K89: =E89 -> 300 | L89: 0 | M89: =K89-L89 -> 300 | N89: =E89-M89 -> 0 | P89: 7.31 | Q89: =E89-P89 -> 292.69 | X89: =E89 -> 300 | Y89: =X89/1.12 -> 267.85714 | Z89: =Y89*0.12 -> 32.142857 | AB89: 300 | AC89: 267.85714 | AD89: 32.142857 | AF89: =AC89-Y89 -> 0
A90: 1289 | B90: 45670 | C90: INV-10246 | D90: Renee Filio | E90: 300 | F90: 3 hour flyass | G90: Gcash QR Standee | H90: UBP | J90: Walk-Ins | K90: =E90 -> 300 | L90: 0 | M90: =K90-L90 -> 300 | N90: =E90-M90 -> 0 | P90: 7.31 | Q90: =E90-P90 -> 292.69 | X90: =E90 -> 300 | Y90: =X90/1.12 -> 267.85714 | Z90: =Y90*0.12 -> 32.142857 | AB90: 300 | AC90: 267.85714 | AD90: 32.142857 | AF90: =AC90-Y90 -> 0
A91: 1290 | B91: 45670 | C91: INV-10248 | D91: KYDS, Inc. | E91: 7980 | F91: Rocket Room. 9:30 am to 12:30 pm, Jan 6,13,20 and 27, 2025 | G91: Bank Transfer | H91: BPI | I91: 3345 | J91: Meeting Rooms | K91: =E91 -> 7980 | L91: 0 | M91: =K91-L91 -> 7980 | N91: =E91-M91 -> 0 | X91: =E91 -> 7980 | Y91: =X91/1.12 -> 7125 | Z91: =Y91*0.12 -> 855 | AB91: 7980 | AC91: 7125 | AD91: 855 | AF91: =AC91-Y91 -> 0
A92: 1291 | B92: 45670 | C92: INV-10249 | D92: Gabriel Leonco | E92: 3000 | F92: 10-Day Fly Pass (Jan 13, 2025 - Feb 12, 2025) | G92: Maya Card | H92: UBP | J92: Walk-Ins | K92: =E92 -> 3000 | L92: 0 | M92: =K92-L92 -> 3000 | N92: =E92-M92 -> 0 | P92: 98.51 | Q92: =E92-P92 -> 2901.49 | R92: =Q92 -> 2901.49 | X92: =E92 -> 3000 | Y92: =X92/1.12 -> 2678.5714 | Z92: =Y92*0.12 -> 321.42857 | AB92: 3000 | AC92: 2678.5714 | AD92: 321.42857 | AF92: =AC92-Y92 -> 0
A93: 1292 | B93: 45671 | C93: INV-10250 | D93: Jason Alpuerto | E93: 300 | F93: 3 hour flyass | G93: Cash | H93: MBTC | K93: =E93 -> 300 | L93: 0 | M93: =K93-L93 -> 300 | N93: =E93-M93 -> 0 | X93: =E93 -> 300 | Y93: =X93/1.12 -> 267.85714 | Z93: =Y93*0.12 -> 32.142857 | AB93: 300 | AC93: 267.85714 | AD93: 32.142857 | AF93: =AC93-Y93 -> 0
A94: 1293 | D94: CANCELLED | K94: =E94 | L94: 0 | M94: =K94-L94 -> 0 | N94: =E94-M94 -> 0 | AF94: =AC94-Y94 -> 0
A95: 1294 | B95: 45671 | C95: INV-10252 | D95: I-Venture Experts Inc. | E95: 22056.4 | F95: Use of Address, July 13, 2025 to December 31, 2025 | G95: Bank Transfer | H95: UBP | I95: UB1247017 | J95: Virtual Office | K95: =E95 -> 22056.4 | L95: 0 | M95: =K95-L95 -> 22056.4 | N95: =E95-M95 -> 0 | X95: =E95 -> 22056.4 | Y95: =X95/1.12 -> 19693.214 | Z95: =Y95*0.12 -> 2363.1857 | AB95: 22056.4 | AC95: 19693.214 | AD95: 2363.1857 | AF95: =AC95-Y95 -> 0
A96: 1295 | D96: CANCELLED | K96: =E96 | L96: 0 | M96: =K96-L96 -> 0 | N96: =E96-M96 -> 0 | AF96: =AC96-Y96 -> 0
A97: 1296 | B97: 45671 | C97: INV-10254 | D97: Mahana Travel and Tours | E97: 3152.68 | F97: Virtual Office and Locker rental, Jan 1, 2025 - Jan 31, 2025 | G97: Check | H97: UBP | I97: BPI 6000126332 | J97: Virtual Office | K97: 3300 | L97: =K97/1.12*0.05 -> 147.32143 | M97: =K97-L97 -> 3152.6786 | N97: =E97-M97 -> 0.0014285714 | X97: =K97 -> 3300 | Y97: =X97/1.12 -> 2946.4286 | Z97: =Y97*0.12 -> 353.57143 | AB97: 3300 | AC97: 2946.4286 | AD97: 353.57143 | AF97: =AC97-Y97 -> 0
A98: 1297 | B98: 45671 | C98: INV-10142 | D98: Fujitsu Engineering Technologies Philippines, Inc. | E98: 2006.25 | F98: Astra 2, 2:00 pm to 5:00 pm - Dec 18, 2024 | G98: Bank Transfer | H98: UBP | I98: UB548240 | J98: Meeting Rooms | K98: 2100 | L98: =K98/1.12*0.05 -> 93.75 | M98: =K98-L98 -> 2006.25 | N98: =E98-M98 -> 0 | X98: =K98 -> 2100 | Y98: =X98/1.12 -> 1875 | Z98: =Y98*0.12 -> 225 | AB98: 2100 | AC98: 1875 | AD98: 225 | AE98: Dec sales | AF98: =AC98-Y98 -> 0
A99: 1298 | B99: 45672 | C99: INV-10255 | D99: City Pacific Group Inc. | E99: 1400 | F99: Rocket Room, 11:30 am to 1:30 pm- Jan 16, 2025 | G99: Cash | H99: UBP | J99: Meeting Rooms | K99: =E99 -> 1400 | L99: 0 | M99: =K99-L99 -> 1400 | N99: =E99-M99 -> 0 | X99: =E99 -> 1400 | Y99: =X99/1.12 -> 1250 | Z99: =Y99*0.12 -> 150 | AB99: 1400 | AC99: 1250 | AD99: 150 | AF99: =AC99-Y99 -> 0
A100: 1299 | B100: 45672 | C100: INV-10256 | D100: Renchel Orate | E100: 550 | F100: Whole day Flypass | G100: Gcash QR Standee | H100: UBP | J100: Walk-Ins | K100: =E100 -> 550 | L100: 0 | M100: =K100-L100 -> 550 | N100: =E100-M100 -> 0 | P100: 13.4 | Q100: =E100-P100 -> 536.6 | X100: =E100 -> 550 | Y100: =X100/1.12 -> 491.07143 | Z100: =Y100*0.12 -> 58.928571 | AB100: 550 | AC100: 491.07143 | AD100: 58.928571 | AF100: =AC100-Y100 -> 0
...

Sheet AR
A1: SI | B1: Date | C1: Invoice | D1: Client Name | E1: AR Amount | F1: Description | G1: Mode of Payment | H1: Cash / Check Deposit | I1: Remarks | K1: GROSS | L1: CWT | M1: TOTAL | N1: Checking | P1: CC Fee | Q1: Net Amount
A3: 384 | B3: 45295 | D3: Team Bluefish Incorporated | E3: 3000 | F3: VO (Jan 3 - Feb 2, 2024) | G3: Check | H3: UBP | I3: CBC 0000039761
A4: 385 | B4: 45295 | D4: Karla Kris Properties Corporation | E4: 3000 | F4: VO (Jan 4 - Feb 3, 2024) | G4: Check | H4: UBP | I4: BDO 0000998782
A5: 386 | B5: 45301 | D5: FiveTwenty I.T Services | E5: 2866.08 | F5: Use of Address (Nov 1, 2023 - Jan 31, 2024) | G5: Check | H5: UBP | I5: UBP 0006438819
A6: 387 | B6: 45301 | D6: FiveTwenty I.T Services | E6: 2866.08 | F6: Use of Address (Feb 1 - Apr 30, 2024) | G6: Check | H6: UBP | I6: UBP 0006438820
A7: 388 | B7: 45303 | C7: INV-8288 | D7: Rendco Water Infrastructure Inc | E7: 251750 | F7: Security Deposit and Advance Subscription for Apollo 3 and Apollo 4/5 | G7: Check | H7: UBP | I7: BPI 1000131292
A8: 389 | B8: 45303 | D8: Rendco Water Infrastructure Inc | E8: 181723.21 | F8: Apollo 3 and 4/5 January 2024 Rental | G8: Check | H8: UBP
A9: 390 | B9: 45303 | D9: Irvine Analytics Solutions Inc | E9: 3000 | F9: VO (Jan 9 - Feb 8, 2024) | G9: Check | H9: UBP | I9: EWB 0000106104
A10: 391 | B10: 45303 | D10: Juan Enrique Flojo | E10: 1950 | F10: 50% DP for Rocket Room. Jan 14, 2024, 3p-8p | G10: Bank Transfer | H10: UBP | I10: UB490446
A11: 392 | B11: 45303 | D11: Mayfair We Care Philippines Inc | E11: 15000 | F11: Use of Address (Jan 8, 2024 - Jan 7, 2025) | G11: Check | H11: UBP | I11: MBTC 6434444696
A12: 393 | B12: 45307 | D12: Atty. Leo Malapitan Yatco | E12: 3000 | F12: VO (Jan 15 - Feb 14, 2024) | G12: Check | H12: UBP | I12: SB 0000154883
A13: 394 | B13: 45308 | C13: INV-8378 | D13: Therabilities South Inc | E13: =61250+65537.5 -> 126787.5 | F13: Security Deposit and Advanced Subscription for Voyager 4 (Applicable to June 2024) | G13: Check | H13: UBP | I13: MBTC 4950997969
A14: 395 | B14: 45308 | D14: Therabilities South Inc | E14: 65537.5 | F14: Voyager 4 Rent, Jan 22 - Feb 21, 2024 | G14: Check | H14: UBP | I14: MBTC 4950997969
A15: 396 | B15: 45309 | D15: Vets Tour Travel Service | E15: 3000 | F15: VO (Jan 18 - Feb 17, 2024) | G15: Check | H15: UBP | I15: BDO 0000340112
A16: 397 | B16: 45309 | D16: Stellar Forwarding & Transport Inc. | E16: 12801.79 | F16: Fixed Desk for 2 seats (Jan 22 - Feb 21, 2024) | G16: Check | H16: UBP | I16: BPI 6000109811
A17: 398 | B17: 45315 | D17: Star8 Asia Corporation | E17: 11464.29 | F17: Use of Address (Jan 28, 2024 - Jan 27, 2025) | G17: Check | H17: UBP | I17: PNB 2000001958 | K17: 12000 | L17: =K17/1.12*0.05 -> 535.71429 | M17: =K17-L17 -> 11464.286 | N17: =M17-E17 -> -0.0042857143
A18: 399 | B18: 45315 | D18: Wonderpark Orbis Amusement Inc | E18: 11464.29 | F18: Use of Address (Jan 28, 2024 - Jan 27, 2025) | G18: Check | H18: UBP | I18: BDO 0001611485 | K18: 12000 | L18: =K18/1.12*0.05 -> 535.71429 | M18: =K18-L18 -> 11464.286 | N18: =M18-E18 -> -0.0042857143
A19: 400 | B19: 45317 | D19: Baoya Propery Solutions Inc. | E19: 39200 | F19: Apollo 1 Rent February 2024 | G19: Check | H19: UBP | I19: BPI 1000293284
A20: 401 | B20: 45321 | D20: Onspec Global Research Solution Corp | E20: 12000 | F20: Use of Address (Feb 2, 2024 - Feb 1, 2025) | G20: Check | H20: UBP | I20: BDO 0000605992
A21: 402 | B21: 45321 | D21: Hygienic Process and Packaging Phil Inc | E21: 1250 | F21: Use of Address (Jan 17 - Feb 16, 2024) | G21: Check | H21: UBP | I21: SB 0000903642
A22: 403 | B22: 45321 | D22: Ad Tapia Petroleum Products Trading | E22: 2500 | F22: VO (Jan 25 - Feb 24, 2024) | G22: Check | H22: UBP | I22: BDO 00006554731
A23: 404 | B23: 45323 | D23: Onergy Safety Training Center | E23: 14250 | F23: Use of Address (Feb 9, 2024 - Feb 8, 2025) | G23: Bank Transfer | H23: UBP | I23: UB694781
A24: 405 | B24: 45323 | D24: Neufoods Venditio, (NFV) Corp | E24: 2500 | F24: VO (Feb 1 - Feb 29, 2024) | G24: Check | H24: UBP | I24: BPI 6000055587
A25: 406 | B25: 45323 | D25: Mahana Travel and Tours | E25: 2675 | F25: VO and Locker Rental (Feb 1-29, 2024) | G25: Check | H25: UBP | I25: BPI 6000126302 | K25: 2800 | L25: =K25/1.12*0.05 -> 125 | M25: =K25-L25 -> 2675 | N25: =M25-E25 -> 0
A26: 407 | B26: 45324 | D26: Garida Foods Inc | E26: 3000 | F26: VO (Feb 1 - Feb 29, 2024) | G26: Check | H26: UBP | I26: CB 0000062677
A27: 408 | B27: 45324 | D27: RLTY Property Corp | E27: 1000 | F27: Use of Address (Feb 1-29, 2024) | G27: Check | H27: UBP | I27: CBC 0000017022
A28: 409 | B28: 45324 | D28: JFAQ Enterprise | E28: 3000 | F28: VO (Feb 1 - Feb 29, 2024) | G28: Check | H28: UBP | I28: EWB 0008372224
A29: 410 | B29: 45324 | D29: qResults Group Philippines Incorporated | E29: 2866.07 | F29: VO (Feb 1 - Feb 29, 2024) | G29: Check | H29: UBP | I29: SB 0000830845 | K29: 3000 | L29: =K29/1.12*0.05 -> 133.92857 | M29: =K29-L29 -> 2866.0714 | N29: =M29-E29 -> 0.0014285714
A30: 411 | B30: 45324 | D30: Arian Publishing Corporation | E30: 955.36 | F30: Use of Address (Jan 28 - Feb 27, 2024) | G30: Check | H30: UBP | I30: BDO 0000452796 | K30: 1000 | L30: =K30/1.12*0.05 -> 44.642857 | M30: =K30-L30 -> 955.35714 | N30: =M30-E30 -> -0.0028571429
A31: 412 | B31: 45328 | D31: Karla Kris Properties Corporation | E31: 3000 | F31: VO (Feb 4 - Mar 3, 2024) | G31: Check | H31: UBP | I31: BDO 0000998783
A32: 413 | B32: 45328 | D32: Birch Registries Inc | E32: 1000 | F32: Use of Address (Feb 2 - Mar 1, 2024) | G32: Check | H32: UBP | I32: BPI 1000162413
A33: 414 | B33: 45328 | D33: Team Bluefish Incorporated | E33: 3000 | F33: VO (Feb 2 - Mar 1, 2024) | G33: Check | H33: UBP | I33: CBC 0000039762
A34: 415 | B34: 45329 | D34: Pastor Jojo Baldo | E34: 1150 | F34: 50% DP for Rocket Room, 2p-6p | G34: Maya QR Ph | H34: UBP | P34: =E34*0.015 -> 17.25 | Q34: =E34-P34 -> 1132.75
A35: 416 | B35: 45329 | D35: Kyoma Plant Tech Corporation | E35: 84262.5 | F35: Voyager 3 Rent March 2024 | G35: Check | H35: UBP | I35: BDO 0000433678 | K35: 88200 | L35: =K35/1.12*0.05 -> 3937.5 | M35: =K35-L35 -> 84262.5 | N35: =M35-E35 -> 0
A36: 417 | B36: 45331 | D36: Cindy Fernandez | E36: 1200 | F36: 50% DP for Rocket Room, Feb 15, 2024, 1p-5p | G36: Bank Transfer | H36: UBP | I36: UB232769
A37: 418 | B37: 45331 | D37: Environmentors Training Consultancy Services | E37: 36000 | F37: VO (Feb 15, 2024 - Feb 14, 2025) | G37: Cash | H37: UBP
A38: 419 | B38: 45348 | D38: Baoya Propery Solutions Inc. | E38: 39200 | F38: Apollo 1 Rental, March 2024 | G38: Check | H38: UBP | I38: BPI 1000118268
A39: 420 | B39: 45336 | D39: Jonathan Ortiz | E39: 400 | F39: DP for Apollo 2 (Call Room) Feb 24, 2024, 1p-3p | G39: Cash | H39: MBTC
A40: 421 | B40: 45338 | D40: Irvine Analytics Solutions Inc | E40: 3000 | F40: VO (Feb 9 - Mar 8, 2024) | G40: Check | H40: UBP | I40: EWB 0000106105
A41: 422 | B41: 45338 | D41: Atty Leo Malapitan Yatco | E41: 3000 | F41: VO (Feb 9 - Mar 8, 2024) | G41: Check | H41: UBP | I41: SB 0000154927
A42: 423 | B42: 45341 | D42: Lion Lamb Graphic Design Services | E42: 1250 | F42: Use of Address (Feb 17 - Mar 16, 2024) | G42: Check | H42: UBP | I42: BPI 0000771472
A43: 424 | B43: 45341 | D43: Absolute Advantage Trading and General Services Inc | E43: 3000 | F43: VO (Feb 19 - Mar 18, 2024) | G43: Check | H43: UBP | I43: EWB 0000029311
A44: 425 | B44: 45341 | D44: Hygienic Process and Packaging Phil. Inc | E44: 1250 | F44: Use of Address (Feb 17 - Mar 16, 2024) | G44: Check | H44: UBP | I44: SB 0000903643
A45: 426 | B45: 45341 | D45: Vets Tour Travel Service | E45: 3000 | F45: VO (Feb 18 - Mar 17, 2024) | G45: Check | H45: UBP | I45: BDO 0000340113
A46: 427 | B46: 45342 | D46: Rendco Water Infrastructure Inc | E46: 187250 | F46: Apollo 3. 4 & 5 Feb 2024 Rent | G46: Check | H46: UBP | I46: BPI 1000131428
A47: 428 | B47: 45345 | D47: Therabilities South Inc | E47: 65537.5 | F47: Voyager 4 Rent (Feb 22 - Mar 21, 2024) | G47: Check | H47: UBP | I47: MBTC 4950997978
A48: 429 | B48: 45345 | D48: Global Ventures | E48: 1000 | F48: Use of Address (Feb 20 - Mar 19, 2024) | G48: Check | H48: UBP | I48: BDO 0000612155
A49: 430 | B49: 45349 | D49: Ad Tapia Petroleum Products Trading | E49: 2500 | F49: VO (Feb 25 - Mar 24, 2024) | G49: Check | H49: UBP | I49: BDO 0000554719
A50: 431 | B50: 45349 | D50: CP-DC Development Corporation | E50: 3000 | F50: VO (Feb 24 - Mar 24, 2024) | G50: Check | H50: UBP | I50: CB 0001902934
A51: 432
A52: 433 | B52: 45352 | D52: Arian Publishing Corporation | E52: 955.36 | F52: VO (Feb 28 - Mar 27, 2024) | G52: Check | H52: UBP | I52: BDO 0000452797 | K52: 1000 | L52: =K52/1.12*0.05 -> 44.642857 | M52: =K52-L52 -> 955.35714 | N52: =E52-M52 -> 0.0028571429
A53: 434 | B53: 45356 | D53: NeoFoods Venditio, Corp. | E53: 2500 | F53: VO (Mar 1 - 31, 2024) | G53: Check | H53: UBP | I53: BPI 6000055588
A54: 435 | B54: 45356 | D54: KarlaKris Properties Corporation | E54: 3000 | F54: VO (Mar 4 - April 3, 2024) | G54: Check | H54: UBP | I54: BDO 0000998784
A55: 436 | B55: 45356 | D55: Team Bluefish Incorporated | E55: 3000 | F55: VO (Mar 3 - April 2. 2024) | G55: Check | H55: UBP | I55: CBC 0000039763
A56: 437
A57: 438 | B57: 45356 | D57: Frances Rey | E57: 9800 | F57: Hubble Room Rent, March 2024 | G57: Check | H57: UBP | I57: PNB 2000000097
A58: 439 | B58: 45356 | D58: Mary Joy Celine Zarate | E58: 9800 | F58: Hubble Room Rent, March 2024 | G58: Check | H58: UBP | I58: PNB 2000000097
A59: 440 | B59: 45356 | D59: Mahana Travel and Tours | E59: 2675 | F59: VO and Locker Rental (March 1-31, 2024) | G59: Check | H59: UBP | I59: BPI 6000126303 | K59: 2800 | L59: =K59/1.12*0.05 -> 125 | M59: =K59-L59 -> 2675 | N59: =M59-E59 -> 0
A60: 441 | B60: 45356 | D60: Garida Foods Inc | E60: 3000 | F60: Virtual Office (Mar 1 - 31, 2024) | G60: Check | H60: UBP | I60: CBC 0000062678
A61: 442 | B61: 45356 | D61: Qresults Group Philippines Incorporated | E61: 2866.07 | F61: Virtual Office (Mar 1 - 31, 2024) | G61: Check | H61: UBP | I61: SB 0000830846 | K61: 3000 | L61: =K61/1.12*0.05 -> 133.92857 | M61: =K61-L61 -> 2866.0714 | N61: =M61-E61 -> 0.0014285714
A62: 443 | B62: 45359 | D62: Prime Accounting and Consultancy Inc. | E62: 955.36 | F62: Use of Address (Mar 1 - 31, 2024) | G62: Check | H62: UBP | I62: CB 0000057673 | K62: 1000 | L62: =K62/1.12*0.05 -> 44.642857 | M62: =K62-L62 -> 955.35714 | N62: =M62-E62 -> -0.0028571429
A63: 444 | B63: 45356 | D63: RLTY Property Corp | E63: 1000 | F63: Use of Address (Mar 1 - 31, 2024) | G63: Check | H63: UBP | I63: CB 00000017023
A64: 445 | B64: 45352 | D64: Gamboa, Inez | E64: 2200 | F64: 50% DP for Rocket Room Rent, Mar 13, 2024, 9am - 5pm | G64: Maya QR Ph | H64: UBP | P64: =E64*0.015 -> 33 | Q64: =E64-P64 -> 2167
A65: 446 | B65: 45362 | D65: Irvine Analytics Solutions Inc. | E65: 3000 | F65: VO (Mar 9 - April 8, 2024) | G65: Check | H65: UBP | I65: EB 0000106106
A66: 447 | B66: 45362 | D66: Inlink Marketing Corp | E66: 3000
A67: 448 | B67: 45365 | D67: Kyoma Plant Tech Corporation | E67: 84262.5 | F67: Voyager 3 Rent for Apr 2024 | G67: Check | H67: UBP | I67: BDO 0000433714 | K67: 88200 | L67: =K67/1.12*0.05 -> 3937.5 | M67: =K67-L67 -> 84262.5 | N67: =M67-E67 -> 0
A68: 449 | B68: 45369 | D68: Alessandra Sotero | E68: 900 | F68: Start Up Package (Mar 14 - Jun 13, 2024) | G68: Check | H68: UBP | I68: BDO 0000123229
A69: 450 | B69: 45369 | D69: Atty Leo Yatco Malapitan | E69: 3000 | F69: VO (Mar 15 - Apr 14, 2024) | G69: Check | H69: UBP | I69: SB 0000154935
A70: 451 | B70: 45369 | D70: Lion Lamb Graphic Design Services | E70: 1250 | F70: Use of Address (Mar 17 - Apr 16, 2024) | G70: Check | H70: UBP | I70: BPI 0000771473
A71: 452 | B71: 45369 | D71: Hygienic Process and Packaging Phil Inc | E71: 1250 | F71: Use of Address (Mar 17 - Apr 16, 2024) | G71: Check | H71: UBP | I71: SB 0000903644
A72: 453 | B72: 45369 | D72: Vets Tour Travel Service | E72: 3000 | F72: VO (Mar 18 - Apr 17, 2024) | G72: Check | H72: UBP | I72: BDO 0000340114
A73: 454 | B73: 45371 | D73: Beybie Daradar-Bonales | E73: 10000 | F73: Payment for Meeting Room Table and Center Table | G73: Cash | H73: MBTC
A74: 455 | B74: 45376 | D74: AD Tapia Petroleum Products Trading | E74: 2500 | F74: VO ( Mar 25 - April 24, 2024) | G74: Check | H74: UBP | I74: BDO 0000554720
A75: 456 | B75: 45376 | D75: CP-DC Development Corporation | E75: 3000 | F75: VO ( Mar 24 - April 23, 2024) | G75: Check | H75: UBP | I75: CB 0001902945
A76: 457 | B76: 45376 | D76: Therabilities South Inc. | E76: 65537.5 | F76: Voyager 4 Rent (Mar 22 - April 21, 2024) | G76: Check | H76: UBP | I76: MBTC 4950997979 | K76: 68600 | L76: =K76/1.12*0.05 -> 3062.5 | M76: =K76-L76 -> 65537.5 | N76: =M76-E76 -> 0
A77: 458 | B77: 45376 | D77: KC Carreon Realty | E77: 3000 | F77: Virtual Office (Mar 15 - April 14, 2024) | G77: Check | H77: UBP | I77: UBP 6052352603
A78: 459 | B78: 45376 | D78: Mpad Systems, Inc. | E78: 2388.39 | F78: Virtual Office (Mar 22 - April 21, 2024) | G78: Check | H78: UBP | I78: UBP 2002550987 | K78: 2500 | L78: =K78/1.12*0.05 -> 111.60714 | M78: =K78-L78 -> 2388.3929 | N78: =M78-E78 -> 0.0028571429
A79: 460 | B79: 45377 | D79: Rendco Water Infrastructure Inc. | E79: 187250 | F79: Apollo 3 and Apollo 4/5 March 2024 Rent | G79: Check | H79: UBP | I79: BPI 1000151890
A80: 461 | B80: 45378 | D80: Vets Tour Travel Service | E80: 2050 | F80: Locker Rental - 4mos (Mar 18 - July 17, 2024) and Whole day Flypass (Sherlyn Noato, 3hr Flypass (Katherine Pangilinan) | G80: Check | H80: UBP | I80: BDO 0000671035
A81: 462 | B81: 45384 | D81: Birch Registries Inc. | E81: 1000 | F81: Use of Address (April 1 - 30, 2024) | G81: Check | H81: UBP | I81: BPI 1000162415
A82: 463 | B82: 45384 | D82: Garida Foods Inc | E82: 3000 | F82: Virtual Office (April 1-30, 2024) | G82: Check | H82: UBP | I82: CB 0000062679
A83: 464 | B83: 45384 | D83: Prime Accounting and Consultancy Inc. | E83: 955.36 | F83: Use of Address (April 1 - 30, 2024) | G83: Check | H83: UBP | I83: CB 0000057674 | K83: 1000 | L83: =K83/1.12*0.05 -> 44.642857 | M83: =K83-L83 -> 955.35714 | N83: =M83-E83 -> -0.0028571429
A84: 465 | B84: 45384 | D84: Qresults Group Philippines Incorporated | E84: 3000 | F84: Virtual Office (April 1-30, 2024) | G84: Check | H84: UBP | I84: SB
A85: 466 | B85: 45384 | D85: Neofoods Venditio (NFV) Corp. | E85: 2500 | F85: Virtual Office (April 1-30, 2024) | G85: Check | H85: UBP | I85: BPI 6000055589
A86: 467 | B86: 45384 | D86: Mahana Travel and Tours | E86: 2675 | F86: Virtual Office and Locker Rental (April 1-30) | G86: Check | H86: UBP | I86: BPI 6000126304
A87: 468 | B87: 45384 | D87: Byld Construction Services | E87: 3000 | F87: Virtual Office (April 2 - May 1, 2024) | G87: Check | H87: UBP | I87: UBP 6057965809
A88: 469 | B88: 45385 | D88: Stellar Forwarding & Transport Inc | E88: 12801.79 | F88: Advance Subscription of Fixed Desk for two | G88: Cash | H88: MBTC | K88: 13400 | L88: =K88/1.12*0.05 -> 598.21429 | M88: =K88-L88 -> 12801.786 | N88: =M88-E88 -> -0.0042857143
A89: 470 | B89: 45394 | D89: Irvine Analytics Solutions Inc. | E89: 3000 | F89: Virtual Office (April 9 - May 8, 2024) | G89: Check | H89: UBP | I89: EB 0000106107
A90: 471 | B90: 45398 | D90: Inlink Marketing Corp | E90: 3000 | F90: Virtual Office (April 3 - May 2, 2024 | G90: Check | H90: UBP | I90: CB 0000307738
A91: 472 | B91: 45398 | D91: Atty Leo Yatco Malapitan | E91: 3000 | F91: Virtual Office (April 15, 2024 - May 14, 2024) | G91: Check | H91: UBP | I91: SB 0000154936
A92: 473 | B92: 45400 | D92: Hygienic Process and Packaging Phil Inc | E92: 1250 | F92: Use of Address (April 17 - May 16, 2024) | G92: Check | H92: UBP | I92: SB 0000903645
A93: 474 | B93: 45400 | D93: Lion Lamb Graphic Design Services | E93: 1250 | F93: Use of Address (April 17 - May 16, 2024) | G93: Check | H93: UBP | I93: BPI 0000771474
A94: 475 | B94: 45400 | D94: Offsite Solutions Inc. | E94: 2850 | F94: 50% Down Payment for Rocket Room Reservation, April 24, 2024, 10am - 7pm | G94: Bank Transfer | H94: UBP | I94: UB587593
A95: 476 | B95: 45400 | D95: Institute of Integrated Electrical Engineers of the Philippines Inc. | E95: 8000 | F95: Downpayment for Event Space Rent, April 20, 2024, 9am - 6pm | G95: Cash | H95: UBP
A96: 477 | B96: 45401 | D96: Absolute Advantage Trading and General Services Inc | E96: 3000 | F96: Virtual Office (April 19-May 18, 2024) | G96: Check | H96: UBP | I96: EB 0000044501
A97: 478 | B97: 45401 | D97: Vets Tour Travel Service | E97: 3000 | F97: Virtual Office (April 18-May 17, 2024) | G97: Check | H97: UBP | I97: BDO 0000340115
A98: 479 | B98: 45404 | D98: Therabilities South Inc. | E98: 65537.5 | F98: Voyager 4 Rent, Apr 22-May 21, 2024 | G98: Check | H98: UBP | I98: MBTC 4950997980 | K98: 68600 | L98: =K98/1.12*0.05 -> 3062.5 | M98: =K98-L98 -> 65537.5 | N98: =M98-E98 -> 0
A99: 480 | B99: 45405 | D99: Stellar Forwarding & Transport Inc. | E99: 12801.79 | F99: Fixed Desk for 2 seats (April 22-May 21, 2024) | G99: Check | H99: UBP | I99: BPI 6000109832 | K99: 13400 | L99: =K99/1.12*0.05 -> 598.21429 | M99: =K99-L99 -> 12801.786 | N99: =M99-E99 -> -0.0042857143
A100: 481 | B100: 45408 | D100: AD Tapia Petroleum Products Trading | E100: 2500 | F100: Virtual Office (April 25, 2024 - May 24, 2024) | G100: Check | H100: UBP | I100: BDO 0000554721
A101: 482 | B101: 45408 | D101: CP-DC Development Corporation | E101: 3000 | F101: Virtual Office (April 24, 2024 - May 23, 2024) | G101: Check | H101: UBP | I101: CBC 0001902936
...

Sheet Xero Sales
A1: Xero Sales Q1 2025
A2: Shirefolk, Inc. (Doing business under the name and style of Launchpad Coworking)
A3: For the period 1 January 2025 to 31 March 2025
A5: Source contains Receivable Prepayment, Receivable Payment, Receive Money, Receivable Invoice
A7: Date | B7: Source | C7: Contact | D7: Description | E7: Reference | F7: Debit | G7: Credit | H7: Gross | I7: Running Balance | J7: Tax | K7: Tax Rate | L7: Account
A9: Tax Exempt
A10: 45658 | B10: Receive Money | C10: Philippine Nutri-Foods Corporation | D10: Philippine Nutri-Foods Corporation - Solicitation from Clients for Christmas Party | F10: 0 | G10: 1000 | H10: 1000 | I10: =(G10 - F10) -> 1000 | J10: 0 | K10: 0 | L10: Other Revenue from Clients
A11: 45692 | B11: Receive Money | C11: Environmentors Training Consultancy Services | D11: Environmentors Training Consultancy Services - Excess payment | F11: 0 | G11: 0.52 | H11: 0.52 | I11: =((I10 + G11) - F11) -> 1000.52 | J11: 0 | K11: 0 | L11: Other Revenue from Clients
A12: 45670 | B12: Receivable Invoice | C12: Digibeacon BPO Inc. | D12: Digibeacon BPO Inc. - Office Suite 9 (Call Room), ₱1,400.00, 1:00 pm to 5:00 pm , Jan 13, 2025 | E12: INV-10227 | F12: 0 | G12: 1440 | H12: 1440 | I12: =((I11 + G12) - F12) -> 2440.52 | J12: 0 | K12: 0 | L12: Meeting Room
A13: 45667 | B13: Receivable Invoice | C13: Anxa Limited | D13: Anxa Limited - LPC - Virtual Office, ₱3,125.00, Jan 1, 2025 - Dec 31, 2025 | E13: INV-10251 | F13: 0 | G13: 37500 | H13: 37500 | I13: =((I12 + G13) - F13) -> 39940.52 | J13: 0 | K13: 0 | L13: Monthly Membership: Virtual Office with 10 Day Pass
A14: 45710 | B14: Receivable Invoice | C14: Bebang Enterprise, Inc. | D14: Bebang Enterprise, Inc. - Coworking Space, ₱1,500.00/ 10:00 am to 11:00 am - Feb 23, 2025 | E14: INV-10549 | F14: 0 | G14: 1500 | H14: 1500 | I14: =((I13 + G14) - F14) -> 41440.52 | J14: 0 | K14: 0 | L14: Meeting Room
A15: Total Tax Exempt | F15: =SUM(F10:F14) -> 0 | G15: =SUM(G10:G14) -> 41440.52 | H15: =SUM(H10:H14) -> 41440.52 | I15: =I14 -> 41440.52 | J15: =SUM(J10:J14) -> 0
A17: VAT on Sales (Services)
A18: 45658 | B18: Receivable Invoice | C18: Blue Point Properties, Inc. | D18: Blue Point Properties, Inc. - LPC - Virtual Office Renewal, ₱1,375.00, Jan 29, 2025 - Feb 27, 2025 | E18: INV-10408 | F18: 0 | G18: 1227.68 | H18: 1375 | I18: =((I17 + G18) - F18) -> 1227.68 | J18: 147.32 | K18: 12 | L18: Monthly Membership: Business Address Registration
A19: 45658 | B19: Receivable Invoice | C19: Joenafe Tinapan | D19: Joenafe Tinapan - LPC - Locker Rental, ₱300.00, Jan 1, 2025 - Jan 31, 2025 | E19: INV-10522 | F19: 0 | G19: 267.86 | H19: 300 | I19: =((I18 + G19) - F19) -> 1495.54 | J19: 32.14 | K19: 12 | L19: Add Ons: Locker Rental
A20: 45658 | B20: Receivable Invoice | C20: Lotti Consulting Inc. | D20: Lotti Consulting Inc. - LPC - Virtual Office, ₱3,500.00, Jan 1, 2025 - Dec 31, 2025 | E20: INV-10105 | F20: 0 | G20: 37500 | H20: 42000 | I20: =((I19 + G20) - F20) -> 38995.54 | J20: 4500 | K20: 12 | L20: Monthly Membership: Virtual Office with 10 Day Pass
A21: 45658 | B21: Receivable Invoice | C21: Marketing Master IO OPC | D21: MARKETING MASTER IO OPC - LPC - Virtual Office, ₱3,500.00, Jan 1, 2025 - Dec 31, 2025 | E21: INV-10154 | F21: 0 | G21: 37500 | H21: 42000 | I21: =((I20 + G21) - F21) -> 76495.54 | J21: 4500 | K21: 12 | L21: Monthly Membership: Virtual Office with 10 Day Pass
A22: 45658 | B22: Receivable Invoice | C22: MASO Fit Out Finishing Services | D22: MASO Fit Out Finishing Services - LPC - Virtual Office, ₱3,000.00, Dec 2, 2024 - Dec 1, 2025 | E22: INV-10070 | F22: 0 | G22: 32142.86 | H22: 36000 | I22: =((I21 + G22) - F22) -> 108638.4 | J22: 3857.14 | K22: 12 | L22: Monthly Membership: Virtual Office with 10 Day Pass
A23: 45658 | B23: Receivable Invoice | C23: MASO Fit Out Finishing Services | D23: MASO Fit Out Finishing Services - LPC - Virtual Office, ₱3,000.00, Dec 2, 2025 - Dec 31, 2025 (Pro-rated ) | E23: INV-10070 | F23: 0 | G23: 2592.05 | H23: 2903.1 | I23: =((I22 + G23) - F23) -> 111230.45 | J23: 311.05 | K23: 12 | L23: Monthly Membership: Virtual Office with 10 Day Pass
A24: 45658 | B24: Receivable Invoice | C24: MASO Fit Out Finishing Services | D24: MASO Fit Out Finishing Services - LPC - Locker Rental, ₱300.00, Dec 2, 2024 - Dec 1, 2025 | E24: INV-10070 | F24: 0 | G24: 3214.29 | H24: 3600 | I24: =((I23 + G24) - F24) -> 114444.74 | J24: 385.71 | K24: 12 | L24: Add Ons: Locker Rental
A25: 45658 | B25: Receivable Invoice | C25: MASO Fit Out Finishing Services | D25: MASO Fit Out Finishing Services - LPC - Locker Rental, ₱300.00, Dec 2, 2025 - Dec 31, 2025 (Pro-rated) | E25: INV-10070 | F25: 0 | G25: 259.82 | H25: 291 | I25: =((I24 + G25) - F25) -> 114704.56 | J25: 31.18 | K25: 12 | L25: Add Ons: Locker Rental
A26: 45658 | B26: Receivable Invoice | C26: Megaluck Prime Solutions Inc. | D26: Megaluck Prime Solutions Inc. - LPC - Virtual Office Renewal, ₱1,250.00, Jan 1, 2025 - Dec 31, 2025 | E26: INV-10162 | F26: 0 | G26: 13392.86 | H26: 15000 | I26: =((I25 + G26) - F26) -> 128097.42 | J26: 1607.14 | K26: 12 | L26: Monthly Membership: Business Address Registration
A27: 45658 | B27: Receivable Invoice | C27: Metals Focus Data Ltd. | D27: Metals Focus Data Ltd. - LP Suites Office 1, ₱33,600.00, Jan 1, 2025 - Jan 31, 2025 | E27: INV-10128 | F27: 0 | G27: 30000 | H27: 33600 | I27: =((I26 + G27) - F27) -> 158097.42 | J27: 3600 | K27: 12 | L27: Monthly Membership: Private Office
A28: 45658 | B28: Receivable Invoice | C28: NeuFoods Venditio, (NFV) Corp. | D28: NeuFoods Venditio, (NFV) Corp. - LPC - Virtual Office Renewal, ₱1,250.00, Jan 1, 2025 - Dec 31, 2025 | E28: INV-10032 | F28: 0 | G28: 13392.86 | H28: 15000 | I28: =((I27 + G28) - F28) -> 171490.28 | J28: 1607.14 | K28: 12 | L28: Monthly Membership: Business Address Registration
A29: 45658 | B29: Receivable Invoice | C29: Offsite Solutions Inc | D29: Offsite Solutions Inc - LPC - Virtual Office, Use of Address, ₱1,375.00, Jan 1, 2025 - Dec 31, 2025 | E29: INV-10490 | F29: 0 | G29: 14732.14 | H29: 16500 | I29: =((I28 + G29) - F29) -> 186222.42 | J29: 1767.86 | K29: 12 | L29: Monthly Membership: Business Address Registration
... A218: 45679 | B218: Receivable Invoice | C218: Fujitsu Engineering Technologies Philippines, Inc. | D218: Fujitsu Engineering Technologies Philippines, Inc. - Astra 1, ₱5,700.00 / 8:30 am to 5:30 pm - Jan 28, 2025 | E218: INV-10292 | F218: 0 | G218: 4580.36 | H218: 5130 | I218: =((I217 + G218) - F218) -> 1798324 | J218: 549.64 | K218: 12 | L218: Meeting Room
A219: 45679 | B219: Receive Money | C219: Global Ventures Inc. | D219: Global Ventures Inc. - Initial Deposit for UA Jan 2025 | F219: 0 | G219: 1116.07 | H219: 1250 | I219: =(G219 - F219) -> 1116.07 | J219: 133.93 | K219: 12 | L219: Monthly Membership: Business Address Registration
A220: 45679 | B220: Receivable Invoice | C220: Global Ventures Inc. | D220: Global Ventures Inc. - LPC - Virtual Office Renewal, ₱1,250.00, Jan 20, 2025 - Feb 19, 2025 | E220: INV-10319 | F220: 0 | G220: 1116.07 | H220: 1250 | I220: =((I219 + G220) - F220) -> 2232.14 | J220: 133.93 | K220: 12 | L220: Monthly Membership: Business Address Registration
A221: 45679 | B221: Receivable Invoice | C221: Grace Quizon | D221: Grace Quizon - LPC - Printing B&W | E221: INV-10296 | F221: 0 | G221: 758.93 | H221: 850 | I221: =((I220 + G221) - F221) -> 2991.07 | J221: 91.07 | K221: 12 | L221: Add Ons: Printing
A222: 45679 | B222: Receivable Invoice | C222: JLZ Import Export Corporation | D222: JLZ Import Export Corporation - LPC - Fixed Desk - Fixed Desk-01, ₱6,700.00, Jan 20, 2025 - Feb 19, 2025 | E222: INV-10302 | F222: 0 | G222: 5982.14 | H222: 6700 | I222: =((I221 + G222) - F222) -> 8973.21 | J222: 717.86 | K222: 12 | L222: Monthly Membership: Permanent Desk
A223: 45679 | B223: Receivable Invoice | C223: JP Aclan | D223: JP Aclan - Office Suite 10, ₱3,300.00, 10:30 am to 3:30 pm- Jan 21, 2025 | E223: INV-10304 | F223: 0 | G223: 2946.43 | H223: 3300 | I223: =((I222 + G223) - F223) -> 11919.64 | J223: 353.57 | K223: 12 | L223: Meeting Room
A224: 45679 | B224: Receivable Invoice | C224: Karina Tosca Feria | D224: Karina Tosca Feria - LPC - Whole Day Fly Pass | E224: INV-10299 | F224: 0 | G224: 491.07 | H224: 550 | I224: =((I223 + G224) - F224) -> 12410.71 | J224: 58.93 | K224: 12 | L224: Walk Ins: Whole Day Pass
A225: 45679 | B225: Receivable Invoice | C225: Lion Lamb Graphic Design Services | D225: Lion Lamb Graphic Design Services - LPC - Virtual Office Renewal, ₱1,250.00, Jan 17, 2025 - Feb 16, 2025 | E225: INV-10303 | F225: 0 | G225: 1116.07 | H225: 1250 | I225: =((I224 + G225) - F225) -> 13526.78 | J225: 133.93 | K225: 12 | L225: Monthly Membership: Business Address Registration
A226: 45679 | B226: Receivable Invoice | C226: Michelle Anne Cruz | D226: Michelle Anne Cruz - LPC - 3 Hour Fly Pass | E226: INV-10295 | F226: 0 | G226: 267.86 | H226: 300 | I226: =((I225 + G226) - F226) -> 13794.64 | J226: 32.14 | K226: 12 | L226: Walk Ins: 3 Hour Fly Pass
A227: 45679 | B227: Receivable Invoice | C227: mPAD Systems, Inc. | D227: mPAD Systems, Inc. - LPC - Virtual Office, ₱3,000.00, Jan 19, 2025 - Feb 18, 2025 | E227: INV-10351 | F227: 0 | G227: 2678.57 | H227: 3000 | I227: =((I226 + G227) - F227) -> 16473.21 | J227: 321.43 | K227: 12 | L227: Monthly Membership: Virtual Office with 10 Day Pass
A228: 45679 | B228: Receivable Invoice | C228: Noel Bernal | D228: Noel Bernal - LPC - 3 Hour Fly Pass | E228: INV-10298 | F228: 0 | G228: 267.86 | H228: 300 | I228: =((I227 + G228) - F228) -> 16741.07 | J228: 32.14 | K228: 12 | L228: Walk Ins: 3 Hour Fly Pass
A229: 45679 | B229: Receivable Invoice | C229: SynerPark Ventures Inc. | D229: SynerPark Ventures Inc. - Astra 2, ₱1,400.00, 10:00 am to 12:00 pm- Jan 22, 2025 | E229: INV-10294 | F229: 0 | G229: 1250 | H229: 1400 | I229: =((I228 + G229) - F229) -> 17991.07 | J229: 150 | K229: 12 | L229: Meeting Room
A230: 45679 | B230: Receivable Invoice | C230: Uphouse Business Professionals Consultancy Corporation | D230: Uphouse Business Professionals Consultancy Corporation - LPC - Virtual Office, ₱3,500.00, Jan 22, 2025 - Dec 21, 2025 | E230: INV-10345 | F230: 0 | G230: 34375 | H230: 38500 | I230: =((I229 + G230) - F230) -> 52366.07 | J230: 4125 | K230: 12 | L230: Monthly Membership: Virtual Office with 10 Day Pass
A231: 45679 | B231: Receivable Invoice | C231: Uphouse Business Professionals Consultancy Corporation | D231: Uphouse Business Professionals Consultancy Corporation - LPC - Virtual Office, ₱112.90, Dec 22, 2025 - Dec 31, 2025 | E231: INV-10345 | F231: 0 | G231: 1008.04 | H231: 1129 | I231: =((I230 + G231) - F231) -> 53374.11 | J231: 120.96 | K231: 12 | L231: Monthly Membership: Business Address Registration
... A292: 45688 | B292: Receivable Invoice | C292: WonderPark Orbis Amusement, Inc. | D292: WonderPark Orbis Amusement, Inc. - LPC - Virtual Office Renewal, ₱40.32, Dec 28, 2025 - Dec 31, 2025 (Prorated) | E292: INV-10360 | F292: 0 | G292: 144 | H292: 161.28 | I292: =((I291 + G292) - F292) -> 442351.14 | J292: 17.28 | K292: 12 | L292: Monthly Membership: Business Address Registration
A294: 45689 | B294: Receivable Invoice | C294: 5 Miles Lab Philippines Advertising OPC | D294: 5 Miles Lab Philippines Advertising OPC - LPC - Virtual Office, ₱3,500.00, Feb 1, 2025 - Dec 31, 2025 | E294: INV-10346 | F294: 0 | G294: 34375 | H294: 38500 | I294: =((I292 + G294) - F294) -> 476726.14 | J294: 4125 | K294: 12 | L294: Monthly Membership: Virtual Office with 10 Day Pass
A295: 45689 | B295: Receivable Invoice | C295: Blue Point Properties, Inc. | D295: Blue Point Properties, Inc. - LPC - Virtual Office Renewal, ₱1,375.00, Feb 29, 2025 - Mar 28, 2025 | E295: INV-10600 | F295: 0 | G295: 1227.68 | H295: 1375 | I295: =((I294 + G295) - F295) -> 477953.82 | J295: 147.32 | K295: 12 | L295: Monthly Membership: Business Address Registration
A296: 45689 | B296: Receivable Invoice | C296: Bon Conseil Realty OPC | D296: Bon Conseil Realty OPC - LPC - Virtual Office, ₱3,000.00, Feb 24, 2025 - Mar 23, 2025 | E296: INV-10455 | F296: 0 | G296: 2678.57 | H296: 3000 | I296: =((I295 + G296) - F296) -> 480632.39 | J296: 321.43 | K296: 12 | L296: Monthly Membership: Virtual Office with 10 Day Pass
A297: 45689 | B297: Receivable Invoice | C297: Chito Marcos | D297: Chito Marcos - LPC - Whole Day Fly Pass | E297: INV-10368 | F297: 0 | G297: 491.07 | H297: 550 | I297: =((I296 + G297) - F297) -> 481123.46 | J297: 58.93 | K297: 12 | L297: Walk Ins: Whole Day Pass
A298: 45689 | B298: Receivable Invoice | C298: CJ Philippines, Inc. | D298: CJ Philippines, Inc. - LP Suites Office 6, ₱73,920.00, Feb 24, 2025 - Mar 23, 2025 | E298: INV-10313 | F298: 0 | G298: 66000 | H298: 73920 | I298: =((I297 + G298) - F298) -> 547123.46 | J298: 7920 | K298: 12 | L298: Monthly Membership: Private Office
A299: 45689 | B299: Receivable Invoice | C299: Espirit Consultancy, Inc. | D299: Espirit Consultancy, Inc. - LPC - Virtual Office Renewal, ₱1,250.00, Feb 1, 2025 - Dec 31, 2025 | E299: INV-10548 | F299: 0 | G299: 12276.79 | H299: 13750 | I299: =((I298 + G299) - F299) -> 559400.25 | J299: 1473.21 | K299: 12 | L299: Monthly Membership: Business Address Registration
A300: 45689 | B300: Receivable Invoice | C300: Fujitsu Engineering Technologies Philippines, Inc. | D300: Fujitsu Engineering Technologies Philippines, Inc. - Astra 1, ₱5,700.00 / 8:30 am to 5:30 pm- Feb 5, 2025 | E300: INV-10337 | F300: 0 | G300: 4580.36 | H300: 5130 | I300: =((I299 + G300) - F300) -> 563980.61 | J300: 549.64 | K300: 12 | L300: Meeting Room
A301: 45689 | B301: Receivable Invoice | C301: Fujitsu Engineering Technologies Philippines, Inc. | D301: Fujitsu Engineering Technologies Philippines, Inc. - Rocket Room, ₱5,700.00 / 8:30 am to 5:30 pm - Feb 6, 2025 | E301: INV-10337 | F301: 0 | G301: 4580.36 | H301: 5130 | I301: =((I300 + G301) - F301) -> 568560.97 | J301: 549.64 | K301: 12 | L301: Meeting Room
A302: 45689 | B302: Receivable Invoice | C302: Fujitsu Engineering Technologies Philippines, Inc. | D302: Fujitsu Engineering Technologies Philippines, Inc. - Astra 1, ₱5,700.00 / 8:30 am to 5:30 pm - Feb 7, 2025 | E302: INV-10337 | F302: 0 | G302: 4580.36 | H302: 5130 | I302: =((I301 + G302) - F302) -> 573141.33 | J302: 549.64 | K302: 12 | L302: Meeting Room
A303: 45689 | B303: Receivable Invoice | C303: Fujitsu Engineering Technologies Philippines, Inc. | D303: Fujitsu Engineering Technologies Philippines, Inc. - Astra 1, ₱5,700.00 / 8:30 am to 5:30 pm - Feb 10, 2025 | E303: INV-10337 | F303: 0 | G303: 4580.36 | H303: 5130 | I303: =((I302 + G303) - F303) -> 577721.69 | J303: 549.64 | K303: 12 | L303: Meeting Room
A304: 45689 | B304: Receivable Invoice | C304: Fujitsu Engineering Technologies Philippines, Inc. | D304: Fujitsu Engineering Technologies Philippines, Inc. - Astra 1, ₱5,700.00 / 8:30 am to 5:30 pm - Feb 11, 2025 | E304: INV-10337 | F304: 0 | G304: 4580.36 | H304: 5130 | I304: =((I303 + G304) - F304) -> 582302.05 | J304: 549.64 | K304: 12 | L304: Meeting Room
A305: 45689 | B305: Receivable Invoice | C305: Fujitsu Engineering Technologies Philippines, Inc. | D305: Fujitsu Engineering Technologies Philippines, Inc. - Astra 1, ₱5,700.00 / 8:30 am to 5:30 pm - Feb 12, 2025 | E305: INV-10337 | F305: 0 | G305: 4580.36 | H305: 5130 | I305: =((I304 + G305) - F305) -> 586882.41 | J305: 549.64 | K305: 12 | L305: Meeting Room
A306: 45689 | B306: Receivable Invoice | C306: Fujitsu Engineering Technologies Philippines, Inc. | D306: Fujitsu Engineering Technologies Philippines, Inc. - Astra 1, ₱5,700.00 / 8:30 am to 5:30 pm - Feb 17, 2025 | E306: INV-10337 | F306: 0 | G306: 4580.36 | H306: 5130 | I306: =((I305 + G306) - F306) -> 591462.77 | J306: 549.64 | K306: 12 | L306: Meeting Room
... A536: 45716 | B536: Receivable Invoice | C536: Solventis Asia Pacific, Inc | D536: Solventis Asia Pacific, Inc - Call Room (Apollo 2), ₱360.00 / 1:00pm to 2:00 pm - Feb 28, 2025 | E536: INV-10620 | F536: 0 | G536: 321.43 | H536: 360 | I536: =((I535 + G536) - F536) -> 1743930.6 | J536: 38.57 | K536: 12 | L536: Meeting Room
A538: 45717 | B538: Receivable Invoice | C538: Absolute Advantage Trading and General Services Inc. | D538: Absolute Advantage Trading and General Services Inc. - LPC - Virtual Office, ₱3,000.00, Mar 19, 2025 - Apr 18, 2025 | E538: INV-10507 | F538: 0 | G538: 2678.57 | H538: 3000 | I538: =((I536 + G538) - F538) -> 1746609.2 | J538: 321.43 | K538: 12 | L538: Monthly Membership: Virtual Office with 10 Day Pass
A539: 45717 | B539: Receivable Invoice | C539: Atty. Leo Malapitan Yatco | D539: Atty. Leo Malapitan Yatco - LPC - Virtual Office, ₱3,000.00, Mar 15, 2025 - Apr 14, 2025 | E539: INV-10529 | F539: 0 | G539: 2678.57 | H539: 3000 | I539: =((I538 + G539) - F539) -> 1749287.8 | J539: 321.43 | K539: 12 | L539: Monthly Membership: Virtual Office with 10 Day Pass
A540: 45717 | B540: Receivable Invoice | C540: Birch Registries, Inc. | D540: Birch Registries, Inc. - LPC - Virtual Office Renewal, ₱1,250.00, Mar 1, 2025 - Mar 31, 2025 | E540: INV-10537 | F540: 0 | G540: 1116.07 | H540: 1250 | I540: =((I539 + G540) - F540) -> 1750403.8 | J540: 133.93 | K540: 12 | L540: Monthly Membership: Business Address Registration
A541: 45717 | B541: Receivable Invoice | C541: Blue Arch Freight Solutions OPC | D541: Blue Arch Freight Solutions OPC - LPC - Virtual Office, ₱3,500.00, Mar 3, 2025 - Sep 2, 2025 | E541: INV-10518 | F541: 0 | G541: 18750 | H541: 21000 | I541: =((I540 + G541) - F541) -> 1769153.8 | J541: 2250 | K541: 12 | L541: Monthly Membership: Virtual Office with 10 Day Pass
A542: 45717 | B542: Receivable Invoice | C542: Blue Point Properties, Inc. | D542: Blue Point Properties, Inc. - LPC - Virtual Office Renewal, ₱1,375.00, Mar 29, 2025 - Apr 28, 2025 | E542: INV-10601 | F542: 0 | G542: 1227.68 | H542: 1375 | I542: =((I541 + G542) - F542) -> 1770381.5 | J542: 147.32 | K542: 12 | L542: Monthly Membership: Business Address Registration
A543: 45717 | B543: Receivable Invoice | C543: Bon Conseil Realty OPC | D543: Bon Conseil Realty OPC - LPC - Virtual Office, ₱3,000.00, Mar 24, 2025 - Apr 23, 2025 | E543: INV-10575 | F543: 0 | G543: 2678.57 | H543: 3000 | I543: =((I542 + G543) - F543) -> 1773060.1 | J543: 321.43 | K543: 12 | L543: Monthly Membership: Virtual Office with 10 Day Pass
A544: 45717 | B544: Receivable Invoice | C544: CJ Philippines, Inc. | D544: CJ Philippines, Inc. - LP Suites Office 6 Security Deposit (Forfieted) | E544: INV-10623 | F544: 0 | G544: 58928.57 | H544: 66000 | I544: =((I543 + G544) - F544) -> 1831988.6 | J544: 7071.43 | K544: 12 | L544: Other Revenue from Clients
A545: 45717 | B545: Receivable Invoice | C545: CP Health Innovations Inc. | D545: CP Health Innovations Inc. - LPC - Virtual Office Renewal, ₱1,250.00, Mar 19, 2025 - Apr 18, 2025 | E545: INV-10543 | F545: 0 | G545: 1116.07 | H545: 1250 | I545: =((I544 + G545) - F545) -> 1833104.7 | J545: 133.93 | K545: 12 | L545: Monthly Membership: Business Address Registration
A546: 45717 | B546: Receivable Invoice | C546: Eratek Trading Corp. | D546: Eratek Trading Corp. - LPC - Virtual Office Renewal, ₱1,250.00, Feb 6, 2024 - Feb 5, 2025 | E546: INV-10599 | F546: 0 | G546: 13392.86 | H546: 15000 | I546: =((I545 + G546) - F546) -> 1846497.6 | J546: 1607.14 | K546: 12 | L546: Monthly Membership: Business Address Registration
A547: 45717 | B547: Receivable Invoice | C547: Eratek Trading Corp. | D547: Eratek Trading Corp. - LPC - Virtual Office Renewal, ₱1,250.00, Feb 6, 2025 - Dec 5, 2025 | E547: INV-10599 | F547: 0 | G547: 11160.71 | H547: 12500 | I547: =((I546 + G547) - F547) -> 1857658.3 | J547: 1339.29 | K547: 12 | L547: Monthly Membership: Business Address Registration
A548: 45717 | B548: Receivable Invoice | C548: Eratek Trading Corp. | D548: Eratek Trading Corp. - LPC - Virtual Office Renewal, ₱40.32, Dec 6, 2025 - Dec 31, 2025 (Prorated) | E548: INV-10599 | F548: 0 | G548: 936 | H548: 1048.32 | I548: =((I547 + G548) - F548) -> 1858594.3 | J548: 112.32 | K548: 12 | L548: Monthly Membership: Business Address Registration
A549: 45717 | B549: Receivable Invoice | C549: Feast Bellevue PM | D549: Feast Bellevue PM - Rocket Room, ₱2,100.00, 3 x ₱700.00 / hour - Mar 1, 2025 | E549: INV-10594 | F549: 0 | G549: 1875 | H549: 2100 | I549: =((I548 + G549) - F549) -> 1860469.3 | J549: 225 | K549: 12 | L549: Meeting Room
A550: 45717 | B550: Receivable Invoice | C550: Feast Bellevue PM | D550: Feast Bellevue PM - Rocket Room 1 hour Extension | E550: INV-10594 | F550: 0 | G550: 625 | H550: 700 | I550: =((I549 + G550) - F550) -> 1861094.3 | J550: 75 | K550: 12 | L550: Meeting Room
... A796: 45747 | B796: Receivable Invoice | C796: Mylene Padua | D796: Mylene Padua - LPC - Whole Day Fly Pass | E796: INV-10796 | F796: 0 | G796: 392.86 | H796: 440 | I796: =((I795 + G796) - F796) -> 3111396.1 | J796: 47.14 | K796: 12 | L796: Walk Ins: Whole Day Pass
A797: Total VAT on Sales (Services) | F797: =SUM(F18:F796) -> 0 | G797: =SUM(G18:G796) -> 4909720.2 | H797: =SUM(H18:H796) -> 5498885.8 | I797: =I796 -> 3111396.1 | J797: =SUM(J18:J796) -> 589165.68
A798: 45679 | B798: Receive Money | C798: Global Ventures Inc. | D798: Global Ventures Inc. - Initial Deposit for UA Jan 2025 | F798: 0 | G798: 1116.07 | H798: 1250 | I798: =(G798 - F798) -> 1116.07 | J798: 133.93
A799: Total VAT on Sales (Services) | G799: =G797-G798 -> 4908604.1 | H799: =H797-H798 -> 5497635.8
C801: REPORTED IN DEC 2024
A802: 45658 | B802: Receivable Invoice | C802: Lotti Consulting Inc. | D802: Lotti Consulting Inc. - LPC - Virtual Office, ₱3,500.00, Jan 1, 2025 - Dec 31, 2025 | E802: INV-10105 | F802: 0 | G802: 37500 | H802: 42000 | I802: =((I797 + G802) - F802) -> 3148896.1 | J802: 4500 | K802: 12 | L802: Monthly Membership: Virtual Office with 10 Day Pass
A803: 45658 | B803: Receivable Invoice | C803: NeuFoods Venditio, (NFV) Corp. | D803: NeuFoods Venditio, (NFV) Corp. - LPC - Virtual Office Renewal, ₱1,250.00, Jan 1, 2025 - Dec 31, 2025 | E803: INV-10105 | F803: 0 | G803: 13392.86 | H803: 15000 | I803: =((I802 + G803) - F803) -> 3162289 | J803: 1607.14 | K803: 12 | L803: Monthly Membership: Business Address Registration
A804: 45659 | B804: Receivable Invoice | C804: Plebeian B Medina | D804: Plebeian B Medina - Rocket Room, January 2, 2024, 8:00 am to 12:00 nn | E804: INV-10053 | F804: 0 | G804: 2321.43 | H804: 2600 | I804: =((I803 + G804) - F804) -> 3164610.4 | J804: 278.57 | K804: 12 | L804: Meeting Room
A805: 45689 | B805: Receivable Invoice | C805: Maison Nourriture Food Inc. | D805: Maison Nourriture Food Inc. - LPC - Virtual Office Renewal, ₱1,250.00, Feb 24, 2025 - Jan 31, 2026 | E805: INV-10031 | F805: 0 | G805: 13392.86 | H805: 15000 | I805: =((I804 + G805) - F805) -> 3178003.3 | J805: 1607.14 | K805: 12 | L805: Monthly Membership: Business Address Registration
A806: 45717 | B806: Receivable Invoice | C806: INEXT SOFTWARE OPC | D806: INEXT SOFTWARE OPC - LPC - Virtual Office Renewal, ₱1,250.00, Mar 1, 2025 - Apr 29, 2025 | E806: INV-9803 | F806: 0 | G806: 2232.14 | H806: 2500 | I806: 1924192.5 | J806: 267.86 | K806: 12 | L806: Monthly Membership: Business Address Registration
A807: 45696 | B807: Receivable Invoice | C807: April I. Boton | D807: April I. Boton - Astra 1, ₱2,600.00 / 1:00 pm to 5:00 pm - Feb 8, 2025 | E807: INV-9724 | F807: 0 | G807: 2321.43 | H807: 2600 | I807: =((I818 + G807) - F807) -> 3112717.5 | J807: 278.57 | K807: 12 | L807: Meeting Room
A808: 45696 | B808: Receivable Invoice | C808: April I. Boton | D808: April I. Boton - Astra 2, ₱2,600.00 / 1:00 pm to 5:00 pm - Feb 8, 2025 | E808: INV-9724 | F808: 0 | G808: 2321.43 | H808: 2600 | I808: =((I807 + G808) - F808) -> 3115039 | J808: 278.57 | K808: 12 | L808: Meeting Room
G809: =SUM(G802:G808) -> 73482.15 | H809: =SUM(H802:H808) -> 82300
C810: SI ISSUED ON APRIL 2025
A811: 45717 | B811: Receivable Invoice | C811: Rendco Water Infrastructure, Inc. | D811: Rendco Water Infrastructure, Inc. - LP Suites Office 5, ₱73,920.00, Mar 16, 2025 - Mar 31, 2025 (Prorated) | E811: INV-10494 | F811: 0 | G811: 33000 | H811: 36960 | I811: 2263138.9 | J811: 3960 | K811: 12 | L811: Monthly Membership: Private Office
A812: 45717 | B812: Receivable Invoice | C812: Rendco Water Infrastructure, Inc. | D812: Rendco Water Infrastructure, Inc. - LP Suites Office 7, ₱135,520.00, Mar 16, 2025 - Mar 31, 2025 (Prorated) | E812: INV-10494 | F812: 0 | G812: 60500 | H812: 67760 | I812: 2323638.9 | J812: 7260 | K812: 12 | L812: Monthly Membership: Private Office
A813: 45742 | B813: Receivable Invoice | C813: Vikain Philippines Corp | D813: Vikain Philippines Corp - LPC - 10-Day Fly Pass (Mar 26, 2025 to April 25, 2025) | E813: INV-10783 | F813: 0 | G813: 2678.57 | H813: 3000 | I813: 3060019.4 | J813: 321.43 | K813: 12 | L813: Walk Ins: 10-Day Fly Pass
A814: 45743 | B814: Receivable Invoice | C814: MASO Fit Out Finishing Services | D814: MASO Fit Out Finishing Services - Rocket Room, ₱2,100.00 / 2:00 pm to 5:00 pm - Apr 3, 2025 | E814: INV-10775 | F814: 0 | G814: 1875 | H814: 2100 | I814: 3072269.4 | J814: 225 | K814: 12 | L814: Meeting Room
A815: 45743 | B815: Receivable Invoice | C815: MASO Fit Out Finishing Services | D815: MASO Fit Out Finishing Services - Meeting Room (Voyager 1 & 2), ₱2,100.00 / 2:00 pm to 5:00 pm - Apr 10, 2025 | E815: INV-10775 | F815: 0 | G815: 2142.86 | H815: 2400 | I815: 3074412.2 | J815: 257.14 | K815: 12 | L815: Meeting Room
A816: 45743 | B816: Receivable Invoice | C816: MASO Fit Out Finishing Services | D816: MASO Fit Out Finishing Services - Rocket Room, ₱2,100.00 / 2:00 pm to 5:00 pm - Apr 24, 2025 | E816: INV-10775 | F816: 0 | G816: 1875 | H816: 2100 | I816: 3076287.2 | J816: 225 | K816: 12 | L816: Meeting Room
A817: 45746 | B817: Receivable Invoice | C817: JV8 Rental Services Corporation | D817: JV8 Rental Services Corporation - LPC - Virtual Office Renewal, ₱1,250.00, Mar 30, 2025 - Dec 29, 2025 | E817: INV-10875 | F817: 0 | G817: 10044.64 | H817: 11250 | I817: 3110324.1 | J817: 1205.36 | K817: 12 | L817: Monthly Membership: Business Address Registration
A818: 45746 | B818: Receivable Invoice | C818: JV8 Rental Services Corporation | D818: JV8 Rental Services Corporation - LPC - Virtual Office Renewal, ₱1,250.00, Dec 30, 2025 - Dec 31, 2025 | E818: INV-10875 | F818: 0 | G818: 72 | H818: 80.64 | I818: 3110396.1 | J818: 8.64 | K818: 12 | L818: Monthly Membership: Business Address Registration
A819: 45717 | B819: Receivable Invoice | C819: Bon Conseil Realty OPC | D819: Bon Conseil Realty OPC - LPC - Virtual Office, ₱3,000.00, Mar 24, 2025 - Apr 23, 2025 | E819: INV-10575 | F819: 0 | G819: 2678.57 | H819: 3000 | I819: =((I818 + G819) - F819) -> 3113074.7 | J819: 321.43 | K819: 12 | L819: Monthly Membership: Virtual Office with 10 Day Pass
A820: 45743 | B820: Receivable Invoice | C820: Digibeacon BPO Inc. | D820: Digibeacon BPO Inc. - Rocket Room, ₱1,400.00, 2 x ₱700.00 / hour - Mar 27, 2025 | E820: INV-10780 | F820: 0 | G820: 1250 | H820: 1400 | I820: =((I819 + G820) - F820) -> 3114324.7 | J820: 150 | K820: 12 | L820: Meeting Room
A821: 45743 | B821: Receivable Invoice | C821: Digibeacon BPO Inc. | D821: Digibeacon BPO Inc. - Meeting Room (Voyager 1 & 2), ₱800.00 / 4:00 pm to 5:00 - Mar 27, 2025 | E821: INV-10781 | F821: 0 | G821: 714.29 | H821: 800 | I821: =((I820 + G821) - F821) -> 3115039 | J821: 85.71 | K821: 12 | L821: Meeting Room
A822: 45717 | B822: Receivable Invoice | C822: Ilustrado Productions Inc. | D822: Ilustrado Productions Inc. - LPC - Virtual Office, ₱3,500.00, Mar 1, 2025 - Dec 31, 2025 | E822: INV-10800 | F822: 0 | G822: 31250 | H822: 35000 | I822: =((I821 + G822) - F822) -> 3146289 | J822: 3750 | K822: 12 | L822: Monthly Membership: Virtual Office with 10 Day Pass
G823: =H823/1.12 -> 148080.93 | H823: =SUM(H811:H822) -> 165850.64
C825: RECORDED AS NON VAT
A826: 45670 | B826: Receivable Invoice | C826: Digibeacon BPO Inc. | D826: Digibeacon BPO Inc. - Office Suite 9 (Call Room), ₱1,400.00, 1:00 pm to 5:00 pm , Jan 13, 2025 | E826: INV-10227 | F826: 0 | G826: =1440/1.12 -> 1285.7143 | H826: 1440 | I826: 2440.52 | J826: =G826*12% -> 154.28571 | K826: 0 | L826: Meeting Room
A827: 45710 | B827: Receivable Invoice | C827: Bebang Enterprise, Inc. | D827: Bebang Enterprise, Inc. - Coworking Space, ₱1,500.00/ 10:00 am to 11:00 am - Feb 23, 2025 | E827: INV-10549 | F827: 0 | G827: =1500/1.12 -> 1339.2857 | H827: 1500 | I827: 41440.52 | J827: =G827*12% -> 160.71429 | K827: 0 | L827: Meeting Room
G828: =H828/1.12 -> 2625 | H828: =SUM(H826:H827) -> 2940
C829: ADVANCED INVOICE
C830: RCL Business Solutions, Management and Consultancy OPC | E830: INV-10650 | G830: =H830/1.12 -> 9936.5714 | H830: 11128.96
...

Sheet Xero Purchases G
A1: Xero Purchases Goods 2025
A2: Shirefolk, Inc. (Doing business under the name and style of Launchpad Coworking)
A3: For the period 1 January 2025 to 31 March 2025
A5: Source contains Payable Invoice, Payable Payment, Spend Money
A6: Tax Rate Name contains VAT on Purchases (Goods), VAT on Purchases (Capital Goods), VAT on Purchases (Goods Not Qual for Input Tax)
A8: Date | B8: Source | C8: Contact | D8: Description | E8: Reference | F8: Credit | G8: Gross | H8: Net | I8: Running Balance | J8: Tax | K8: Tax Rate | L8: Account
A10: VAT on Purchases (Goods Not Qual for Input Tax)
A11: 45663 | B11: Spend Money | C11: Aquaholix Water Refilling Station | D11: Aquaholix Water Refilling Station - Purified water | E11: PCF-2888 | F11: 0 | G11: 270 | H11: 270 | I11: 0 | J11: 0 | K11: 0 | L11: Office and Pantry Supplies
A12: 45665 | B12: Spend Money | C12: Edwin C. Nopuente - Prop | D12: Edwin C. Napuente - Prop - 5 Bottles Purified Water | E12: PCF 2893 | F12: 0 | G12: 150 | H12: 150 | I12: 0 | J12: 0 | K12: 0 | L12: Office and Pantry Supplies
A13: 45666 | B13: Spend Money | C13: Patricio L Boncayao Jr Law Office | D13: Patricio L Boncayao Jr Law Office - Notorial Fee for BIR Affidavit | E13: PCF 2895 | F13: 0 | G13: 150 | H13: 150 | I13: 0 | J13: 0 | K13: 0 | L13: Miscellaneous Expense
A14: 45673 | B14: Spend Money | C14: BIR | D14: BIR - Documentary stamp for Sworn Declaration ( 6-Xchange) | E14: PCF 2906 | F14: 0 | G14: 60 | H14: 60 | I14: 0 | J14: 0 | K14: 0 | L14: Miscellaneous Expense
A16: 45695 | B16: Spend Money | C16: Edwin C. Nopuente - Prop | D16: Edwin C. Napuente - Prop - 3 Bottles of Purified water | E16: PCF - 2936 | F16: 0 | G16: 90 | H16: 90 | I16: 0 | J16: 0 | K16: 0 | L16: Office and Pantry Supplies - Others
A17: 45707 | B17: Spend Money | C17: Edwin C. Nopuente - Prop | D17: Edwin C. Napuente - Prop - 7 Bottles of Purified Water | E17: PCF 2955 | F17: 0 | G17: 210 | H17: 210 | I17: 0 | J17: 0 | K17: 0 | L17: Office and Pantry Supplies
A18: 45716 | B18: Payable Invoice | C18: GBrothers Foods, Inc. | D18: GBrothers Foods, Inc. - Marketing Expense for July 2024 Ref: SI 0005447 | E18: UBP-0724-829 (4) | F18: 0 | G18: 136.07 | H18: 136.07 | I18: 0 | J18: 0 | K18: 0 | L18: Marketing Expense
A20: 45728 | B20: Spend Money | C20: Grand Union Supermarket, Inc. | D20: Grand Union Supermarket, Inc. - Pantry Supplies - Tax Exempt | E20: PCF-2984 | F20: 0 | G20: 588 | H20: 588 | I20: 0 | J20: 0 | K20: 0 | L20: Office and Pantry Supplies
A21: 45728 | B21: Spend Money | C21: Edwin C. Nopuente - Prop | D21: Edwin C. Napuente - Prop - Water (4 bottles) | E21: PCF-2985 | F21: 0 | G21: 120 | H21: 120 | I21: 0 | J21: 0 | K21: 0 | L21: Office and Pantry Supplies
A22: 45729 | B22: Spend Money | C22: Edwin C. Nopuente - Prop | D22: Edwin C. Napuente - Prop - Water - 3 bottles | E22: PCF-2986 | F22: 0 | G22: 90 | H22: 90 | I22: 0 | J22: 0 | K22: 0 | L22: Office and Pantry Supplies
A23: 45730 | B23: Spend Money | C23: Edwin C. Nopuente - Prop | D23: Edwin C. Napuente - Prop - Water - 4 bottles | E23: PCF-2987 | F23: 0 | G23: 120 | H23: 120 | I23: 0 | J23: 0 | K23: 0 | L23: Office and Pantry Supplies
A24: 45733 | B24: Spend Money | C24: Edwin C. Nopuente - Prop | D24: Edwin C. Napuente - Prop - Water- 5 bottles | E24: PCF-2988 | F24: 0 | G24: 150 | H24: 150 | I24: 0 | J24: 0 | K24: 0 | L24: Office and Pantry Supplies
... A36: 45747 | B36: Payable Invoice | C36: Grand Union Supermarket, Inc. | D36: Grand Union Supermarket, Inc. - Marketing Expense for Aug 2024 Ref: SI41000247 | E36: UBP-0824-855 (3) | F36: 0 | G36: 170.3 | H36: 170.3 | I36: 0 | J36: 0 | K36: 0 | L36: Marketing Expense
A37: Total VAT on Purchases (Goods Not Qual for Input Tax) | F37: 0 | G37: 4244.37 | H37: 4244.37 | I37: 0 | J37: 0
A39: VAT on Purchases (Goods)
A40: 45664 | B40: Spend Money | C40: Grand Union Supermarket, Inc. | D40: Grand Union Supermarket, Inc. - Pantry Supplies | E40: PCF-2889 | F40: 0 | G40: 835.05 | H40: 745.58 | I40: 0 | J40: 89.47 | K40: 0.12 | L40: Office and Pantry Supplies
A41: 45665 | B41: Payable Invoice | C41: HEBREWSKAPE TRADING INC. | D41: HEBREWSKAPE TRADING INC. - Coffee Beans (Hazel Nut 12 kg.) | E41: UBP-0125-934 | F41: 0 | G41: 7929.6 | H41: 7080 | I41: 0 | J41: 849.6 | K41: 0.12 | L41: Office and Pantry Supplies
A42: 45665 | B42: Spend Money | C42: Alabang Supermarket Corp | D42: Alabang Supermarket Corp - Pantry Supplies | E42: PCF 2892 | F42: 0 | G42: 150 | H42: 133.93 | I42: 0 | J42: 16.07 | K42: 0.12 | L42: Office and Pantry Supplies
A43: 45666 | B43: Spend Money | C43: Grand Union Supermarket, Inc. | D43: Grand Union Supermarket, Inc. - Office and Pantry Supplies | E43: PCF 2894 | F43: 0 | G43: 2225.5 | H43: 1987.05 | I43: 0 | J43: 238.45 | K43: 0.12 | L43: Office and Pantry Supplies
A44: 45667 | B44: Spend Money | C44: Edwin C. Nopuente - Prop | D44: Edwin C. Napuente - Prop - 8 bottles Purifiied water | E44: PCF 2897 | F44: 0 | G44: 240 | H44: 214.29 | I44: 0 | J44: 25.71 | K44: 0.12 | L44: Office and Pantry Supplies - Others
A45: 45670 | B45: Spend Money | C45: Edwin C. Nopuente - Prop | D45: Edwin C. Napuente - Prop - 5 bottles purified water | E45: PCF 2899 | F45: 0 | G45: 150 | H45: 133.93 | I45: 0 | J45: 16.07 | K45: 0.12 | L45: Office and Pantry Supplies - Others
A46: 45670 | B46: Spend Money | C46: Grand Union Supermarket, Inc. | D46: Grand Union Supermarket, Inc. - Pantry Supplies | E46: PCF 2898 | F46: 0 | G46: 3591.3 | H46: 3206.52 | I46: 0 | J46: 384.78 | K46: 0.12 | L46: Office and Pantry Supplies
A47: 45671 | B47: Spend Money | C47: Edwin C. Nopuente - Prop | D47: Edwin C. Napuente - Prop - 3 Bottles of purified water | E47: PCF 2900 | F47: 0 | G47: 90 | H47: 80.36 | I47: 0 | J47: 9.64 | K47: 0.12 | L47: Office and Pantry Supplies - Others
A48: 45672 | B48: Spend Money | C48: Edwin C. Nopuente - Prop | D48: Edwin C. Napuente - Prop - 5 bottles of Purified water | E48: PCF 2903 | F48: 0 | G48: 150 | H48: 133.93 | I48: 0 | J48: 16.07 | K48: 0.12 | L48: Office and Pantry Supplies - Others
A49: 45674 | B49: Spend Money | C49: Edwin C. Nopuente - Prop | D49: Edwin C. Napuente - Prop - 2 Bottles Purified Water | E49: PCF-2910 | F49: 0 | G49: 60 | H49: 53.57 | I49: 0 | J49: 6.43 | K49: 0.12 | L49: Office and Pantry Supplies - Others
A50: 45675 | B50: Spend Money | C50: Wilcon Depot, Inc. | D50: Wilcon Depot, Inc. - Light Bulb for Reception Area | E50: PCF 2902 | F50: 0 | G50: 521.55 | H50: 465.67 | I50: 0 | J50: 55.88 | K50: 0.12 | L50: Office and Pantry Supplies - Others
A51: 45675 | B51: Spend Money | C51: shopee | D51: shopee - LP3 Government permit Holder for Display | E51: PCF-2908 | F51: 0 | G51: 299 | H51: 266.96 | I51: 0 | J51: 32.04 | K51: 0.12 | L51: Office and Pantry Supplies - Others
... A116: 45747 | B116: Payable Invoice | C116: New Quepe Hardware Co., Inc. | D116: New Quepe Hardware Co., Inc. - Progress Billing No. 4 Materials Ref: Sales Invoice 425270 | E116: UBP-0424-837(148) | F116: 0 | G116: 23430 | H116: 20919.64 | I116: 0 | J116: 2510.36 | K116: 0.12 | L116: Leasehold Improvements
A117: Total VAT on Purchases (Goods) | F117: 0 | G117: 252687.87 | H117: 225614.23 | I117: 0 | J117: 27073.64
A119: Total | F119: 0 | G119: 256932.24 | H119: 229858.6 | I119: 0 | J119: 27073.64
A123: Xero Goods Q2 2025
A124: Shirefolk, Inc. (Doing business under the name and style of Launchpad Coworking)
A125: For the period April 1, 2025 to June 30, 2025
A127: Source contains Payable Invoice, Payable Payment, Spend Money
A128: Tax Rate Name contains VAT on Purchases (Goods), VAT on Purchases (Capital Goods), VAT on Purchases (Goods Not Qual for Input Tax)
A130: Date | B130: Source | C130: Contact | D130: Description | E130: Reference | F130: Credit | G130: Gross | H130: Net | I130: Running Balance | J130: Tax | K130: Tax Rate | L130: Account
A132: VAT on Purchases (Goods Not Qual for Input Tax)
A133: 45749 | B133: Spend Money | C133: Edwin C. Nopuente - Prop | D133: Edwin C. Napuente - Prop - Water | E133: PCF-3004 | F133: 0 | G133: 180 | H133: 180 | I133: =(0 - F133) -> 0 | J133: 0 | K133: 0 | L133: Office and Pantry Supplies
A134: 45749 | B134: Spend Money | C134: Edwin C. Nopuente - Prop | D134: Edwin C. Nopuente - Prop - 6 BOTTLES OF PURIFIED WATER | E134: PCF-3004 | F134: 0 | G134: 180 | H134: 180 | I134: =((I133 + 0) - F134) -> 0 | J134: 0 | K134: 0 | L134: Office and Pantry Supplies
A135: 45751 | B135: Spend Money | C135: Edwin C. Nopuente - Prop | D135: Edwin C. Nopuente - Prop - Water | E135: PCF-3005 | F135: 0 | G135: 120 | H135: 120 | I135: =((I134 + 0) - F135) -> 0 | J135: 0 | K135: 0 | L135: Office and Pantry Supplies
A136: 45751 | B136: Spend Money | C136: Edwin C. Nopuente - Prop | D136: Edwin C. Nopuente - Prop - 4 BOTTLES OF PURIFIED WATER | E136: PCF-3005 | F136: 0 | G136: 120 | H136: 120 | I136: =((I135 + 0) - F136) -> 0 | J136: 0 | K136: 0 | L136: Office and Pantry Supplies
A137: 45754 | B137: Spend Money | C137: Edwin C. Nopuente - Prop | D137: Edwin C. Nopuente - Prop - Water | E137: PCF-3006 | F137: 0 | G137: 240 | H137: 240 | I137: =((I136 + 0) - F137) -> 0 | J137: 0 | K137: 0 | L137: Office and Pantry Supplies
A138: 45754 | B138: Spend Money | C138: Edwin C. Nopuente - Prop | D138: Edwin C. Nopuente - Prop - 8 BOTTLES OF PURIFIED WATER | E138: PCF-3006 | F138: 0 | G138: 240 | H138: 240 | I138: =((I137 + 0) - F138) -> 0 | J138: 0 | K138: 0 | L138: Office and Pantry Supplies
A139: 45756 | B139: Spend Money | C139: Edwin C. Nopuente - Prop | D139: Edwin C. Nopuente - Prop - Water | E139: PCF-3009 | F139: 0 | G139: 150 | H139: 150 | I139: =((I138 + 0) - F139) -> 0 | J139: 0 | K139: 0 | L139: Office and Pantry Supplies
A140: 45756 | B140: Spend Money | C140: Edwin C. Nopuente - Prop | D140: Edwin C. Nopuente - Prop - 5 BOTTLES OF PURIFIED WATER | E140: PCF-3009 | F140: 0 | G140: 150 | H140: 150 | I140: =((I139 + 0) - F140) -> 0 | J140: 0 | K140: 0 | L140: Office and Pantry Supplies
A141: 45757 | B141: Spend Money | C141: Edwin C. Nopuente - Prop | D141: Edwin C. Nopuente - Prop - Water | E141: PCF-3010 | F141: 0 | G141: 90 | H141: 90 | I141: =((I140 + 0) - F141) -> 0 | J141: 0 | K141: 0 | L141: Office and Pantry Supplies
A142: 45757 | B142: Spend Money | C142: Edwin C. Nopuente - Prop | D142: Edwin C. Nopuente - Prop - 3 BOTTLES OF PURIFIED WATER | E142: PCF-3010 | F142: 0 | G142: 90 | H142: 90 | I142: =((I141 + 0) - F142) -> 0 | J142: 0 | K142: 0 | L142: Office and Pantry Supplies
A143: 45757 | B143: Payable Invoice | C143: Cabeguin, Clarita Labrador | D143: Cabeguin, Clarita Labrador - Replacement LP1 main door floorhinge | E143: UBP-0425-1007 | F143: 0 | G143: 10500 | H143: 10500 | I143: =((I142 + 0) - F143) -> 0 | J143: 0 | K143: 0 | L143: Repairs and Maintenance
A144: 45757 | B144: Payable Invoice | C144: Cabeguin, Clarita Labrador | D144: Cabeguin, Clarita Labrador - Replacement LP1 main door top patch | E144: UBP-0425-1007 | F144: 0 | G144: 2800 | H144: 2800 | I144: =((I143 + 0) - F144) -> 0 | J144: 0 | K144: 0 | L144: Repairs and Maintenance
A145: 45757 | B145: Payable Invoice | C145: Cabeguin, Clarita Labrador | D145: Cabeguin, Clarita Labrador - Replacement LP1 main door bottom patch | E145: UBP-0425-1007 | F145: 0 | G145: 2800 | H145: 2800 | I145: =((I144 + 0) - F145) -> 0 | J145: 0 | K145: 0 | L145: Repairs and Maintenance
... A156: 45777 | B156: Spend Money | C156: Edwin C. Nopuente - Prop | D156: Edwin C. Nopuente - Prop - Water | E156: PCF-3024 | F156: 0 | G156: 90 | H156: 90 | I156: =((I155 + 0) - F156) -> 0 | J156: 0 | K156: 0 | L156: Office and Pantry Supplies
A158: 45779 | B158: Spend Money | C158: Grand Union Supermarket, Inc. | D158: Grand Union Supermarket, Inc. - Sugar | E158: PCF-3025 | F158: 0 | G158: 246 | H158: 246 | I158: =((I156 + 0) - F158) -> 0 | J158: 0 | K158: 0 | L158: Office and Pantry Supplies
A159: 45783 | B159: Spend Money | C159: Edwin C. Nopuente - Prop | D159: Edwin C. Nopuente - Prop - Water | E159: PCF-3030 | F159: 0 | G159: 210 | H159: 210 | I159: =((I158 + 0) - F159) -> 0 | J159: 0 | K159: 0 | L159: Office and Pantry Supplies
A160: 45783 | B160: Spend Money | C160: Edwin C. Nopuente - Prop | D160: Edwin C. Nopuente - Prop - Water | E160: PCF-3031 | F160: 0 | G160: 150 | H160: 150 | I160: =((I159 + 0) - F160) -> 0 | J160: 0 | K160: 0 | L160: Office and Pantry Supplies
A161: 45784 | B161: Spend Money | C161: Edwin C. Nopuente - Prop | D161: Edwin C. Nopuente - Prop - Water | E161: PCF-3034 | F161: 0 | G161: 90 | H161: 90 | I161: =((I160 + 0) - F161) -> 0 | J161: 0 | K161: 0 | L161: Office and Pantry Supplies
A162: 45784 | B162: Spend Money | C162: Edwin C. Nopuente - Prop | D162: Edwin C. Nopuente - Prop - Water | E162: PCF-3033 | F162: 0 | G162: 120 | H162: 120 | I162: =((I161 + 0) - F162) -> 0 | J162: 0 | K162: 0 | L162: Office and Pantry Supplies
A163: 45785 | B163: Spend Money | C163: Edwin C. Nopuente - Prop | D163: Edwin C. Nopuente - Prop - Water | E163: PCF-3035 | F163: 0 | G163: 120 | H163: 120 | I163: =((I162 + 0) - F163) -> 0 | J163: 0 | K163: 0 | L163: Office and Pantry Supplies
A164: 45785 | B164: Spend Money | C164: Edwin C. Nopuente - Prop | D164: Edwin C. Nopuente - Prop - 4 BOTTLES OF PURIFIED WATER | E164: PCF-3035 | F164: 0 | G164: 120 | H164: 120 | I164: =((I163 + 0) - F164) -> 0 | J164: 0 | K164: 0 | L164: Office and Pantry Supplies
A165: 45790 | B165: Spend Money | C165: Edwin C. Nopuente - Prop | D165: Edwin C. Nopuente - Prop - Water | E165: PCF-3040 | F165: 0 | G165: 150 | H165: 150 | I165: =((I164 + 0) - F165) -> 0 | J165: 0 | K165: 0 | L165: Office and Pantry Supplies
A166: 45790 | B166: Spend Money | C166: Edwin C. Nopuente - Prop | D166: Edwin C. Nopuente - Prop - Water | E166: PCF-3041 | F166: 0 | G166: 120 | H166: 120 | I166: =((I165 + 0) - F166) -> 0 | J166: 0 | K166: 0 | L166: Office and Pantry Supplies
A167: 45790 | B167: Spend Money | C167: Edwin C. Nopuente - Prop | D167: Edwin C. Nopuente - Prop - 5 BOTTLES PURIFIED WATER MAY 9, 2025 | E167: PCF-3040 | F167: 0 | G167: 150 | H167: 150 | I167: =((I166 + 0) - F167) -> 0 | J167: 0 | K167: 0 | L167: Office and Pantry Supplies
A168: 45790 | B168: Spend Money | C168: Edwin C. Nopuente - Prop | D168: Edwin C. Nopuente - Prop - 4 BOTTLES PURIFIED WATER MAY 12, 2025 | E168: PCF-3041 | F168: 0 | G168: 120 | H168: 120 | I168: =((I167 + 0) - F168) -> 0 | J168: 0 | K168: 0 | L168: Office and Pantry Supplies
A169: 45791 | B169: Spend Money | C169: Edwin C. Nopuente - Prop | D169: Edwin C. Nopuente - Prop - 5 BOTTLES PURIFIED WATER | E169: PCF-3045 | F169: 0 | G169: 150 | H169: 150 | I169: =((I168 + 0) - F169) -> 0 | J169: 0 | K169: 0 | L169: Office and Pantry Supplies
A170: 45798 | B170: Spend Money | C170: Edwin C. Nopuente - Prop | D170: Edwin C. Nopuente - Prop - 3 BOTTLES PURIFIED WATER | E170: PCF-3057 | F170: 0 | G170: 90 | H170: 90 | I170: =((I169 + 0) - F170) -> 0 | J170: 0 | K170: 0 | L170: Office and Pantry Supplies
... A175: 45807 | B175: Spend Money | C175: Edwin C. Nopuente - Prop | D175: Edwin C. Nopuente - Prop - 7 BOTTLES OF PURIFIED WATER | E175: PCF-3066 | F175: 0 | G175: 210 | H175: 210 | I175: =((I174 + 0) - F175) -> 0 | J175: 0 | K175: 0 | L175: Office and Pantry Supplies
A177: 45811 | B177: Spend Money | C177: Edwin C. Nopuente - Prop | D177: Edwin C. Nopuente - Prop - 10 BOTTLES OF PURIFIED WATER | E177: PCF-3069 | F177: 0 | G177: 300 | H177: 300 | I177: =((I175 + 0) - F177) -> 0 | J177: 0 | K177: 0 | L177: Office and Pantry Supplies
A178: 45812 | B178: Spend Money | C178: Grand Union Supermarket, Inc. | D178: Grand Union Supermarket, Inc. - Sugar | E178: PCF-3070 | F178: 0 | G178: 229.2 | H178: 229.2 | I178: =((I177 + 0) - F178) -> 0 | J178: 0 | K178: 0 | L178: Office and Pantry Supplies
A179: 45819 | B179: Spend Money | C179: Grand Union Supermarket, Inc. | D179: Grand Union Supermarket, Inc. - Sugar | E179: PCF-3077 | F179: 0 | G179: 152 | H179: 152 | I179: =((I178 + 0) - F179) -> 0 | J179: 0 | K179: 0 | L179: Office and Pantry Supplies
A180: 45834 | B180: Spend Money | C180: Grand Union Supermarket, Inc. | D180: Grand Union Supermarket, Inc. - Sugar | E180: PCF-3097 | F180: 0 | G180: 74.2 | H180: 74.2 | I180: =((I179 + 0) - F180) -> 0 | J180: 0 | K180: 0 | L180: Office and Pantry Supplies
A181: Total VAT on Purchases (Goods Not Qual for Input Tax) | F181: =SUM(F133:F180) -> 0 | G181: =SUM(G133:G180) -> 22900.2 | H181: =SUM(H133:H180) -> 22900.2 | I181: =I180 -> 0 | J181: =SUM(J133:J180) -> 0
A183: VAT on Purchases (Goods)
A184: 45748 | B184: Payable Invoice | C184: Ikano (Philippines), Inc. | D184: Ikano (Philippines), Inc. - Flygfisk place mat dark grey 38x30 | E184: UBP-0425-1011* | F184: 0 | G184: 270 | H184: 241.07 | I184: =(0 - F184) -> 0 | J184: 28.93 | K184: 12 | L184: Repairs and Maintenance
A185: 45748 | B185: Payable Invoice | C185: Ikano (Philippines), Inc. | D185: Ikano (Philippines), Inc. - Oftast bowl 15 white | E185: UBP-0425-1011* | F185: 0 | G185: 800 | H185: 714.29 | I185: =((I184 + 0) - F185) -> 0 | J185: 85.71 | K185: 12 | L185: Office Equipment
A186: 45748 | B186: Payable Invoice | C186: Ikano (Philippines), Inc. | D186: Ikano (Philippines), Inc. - Oftast plate 25 white | E186: UBP-0425-1011* | F186: 0 | G186: 800 | H186: 714.29 | I186: =((I185 + 0) - F186) -> 0 | J186: 85.71 | K186: 12 | L186: Office Equipment
A187: 45748 | B187: Payable Invoice | C187: Ikano (Philippines), Inc. | D187: Ikano (Philippines), Inc. - Avsteg cutlery stand 13 white | E187: UBP-0425-1011* | F187: 0 | G187: 300 | H187: 267.86 | I187: =((I186 + 0) - F187) -> 0 | J187: 32.14 | K187: 12 | L187: Office Equipment
A188: 45750 | B188: Payable Invoice | C188: United CMYK Digital Printing Corporation | D188: United CMYK Digital Printing Corporation - Mugs with sublimation print | E188: UBP-0425-1002 | F188: 0 | G188: 3000 | H188: 2678.57 | I188: =((I187 + 0) - F188) -> 0 | J188: 321.43 | K188: 12 | L188: Office and Pantry Supplies - Others
A189: 45754 | B189: Spend Money | C189: Grand Union Supermarket, Inc. | D189: Grand Union Supermarket, Inc. - Pantry Supplies | E189: PCF-3007 | F189: 0 | G189: 1699.3 | H189: 1517.23 | I189: =((I188 + 0) - F189) -> 0 | J189: 182.07 | K189: 12 | L189: Office and Pantry Supplies
A190: 45754 | B190: Spend Money | C190: Grand Union Supermarket, Inc. | D190: Grand Union Supermarket, Inc. - PANTRY & OFFICE SUPPLIES | E190: PCF-3007 | F190: 0 | G190: 1699.3 | H190: 1517.23 | I190: =((I189 + 0) - F190) -> 0 | J190: 182.07 | K190: 12 | L190: Office and Pantry Supplies
A191: 45758 | B191: Spend Money | C191: Grand Union Supermarket, Inc. | D191: Grand Union Supermarket, Inc. - Pantry Supplies | E191: PCF-3011 | F191: 0 | G191: 1466 | H191: 1308.93 | I191: =((I190 + 0) - F191) -> 0 | J191: 157.07 | K191: 12 | L191: Office and Pantry Supplies
A192: 45768 | B192: Spend Money | C192: Grand Union Supermarket, Inc. | D192: Grand Union Supermarket, Inc. - Pantry Supplies | E192: PCF-3016 | F192: 0 | G192: 2385.7 | H192: 2130.09 | I192: =((I191 + 0) - F192) -> 0 | J192: 255.61 | K192: 12 | L192: Office and Pantry Supplies
A193: 45771 | B193: Spend Money | C193: Grand Union Supermarket, Inc. | D193: Grand Union Supermarket, Inc. - Pantry Supplies | E193: PCF-3019 | F193: 0 | G193: 2260.25 | H193: 2018.08 | I193: =((I192 + 0) - F193) -> 0 | J193: 242.17 | K193: 12 | L193: Office and Pantry Supplies
A195: 45778 | B195: Payable Invoice | C195: HEBREWSKAPE TRADING INC. | D195: HEBREWSKAPE TRADING INC. - Coffee Beans (Hazel Nut 12 kg.) | E195: UBP-0525-1027 | F195: 0 | G195: 8064 | H195: 7200 | I195: =((I193 + 0) - F195) -> 0 | J195: 864 | K195: 12 | L195: Office and Pantry Supplies
A196: 45779 | B196: Spend Money | C196: Grand Union Supermarket, Inc. | D196: Grand Union Supermarket, Inc. - Pantry Supplies | E196: PCF-3025 | F196: 0 | G196: 3322.1 | H196: 2966.16 | I196: =((I195 + 0) - F196) -> 0 | J196: 355.94 | K196: 12 | L196: Office and Pantry Supplies
A197: 45782 | B197: Spend Money | C197: Bebang Starmall Alabang Inc | D197: Bebang Starmall Alabang Inc - Treats for LP Staff for Labor Day | E197: PCF-3029 | F197: 0 | G197: 790 | H197: 705.36 | I197: =((I196 + 0) - F197) -> 0 | J197: 84.64 | K197: 12 | L197: Representation and Entertainment Expense
A198: 45782 | B198: Spend Money | C198: Midpoint Gas Center Corporation | D198: Midpoint Gas Center Corporation - Gas expense- pick up printed mugs | E198: PCF-3027 | F198: 0 | G198: 50 | H198: 44.64 | I198: =((I197 + 0) - F198) -> 0 | J198: 5.36 | K198: 12 | L198: Transportation and Travel
A199: 45783 | B199: Spend Money | C199: Grand Union Supermarket, Inc. | D199: Grand Union Supermarket, Inc. - Pantry Supplies | E199: PCF-3032 | F199: 0 | G199: 513 | H199: 458.04 | I199: =((I198 + 0) - F199) -> 0 | J199: 54.96 | K199: 12 | L199: Office and Pantry Supplies
A200: 45785 | B200: Spend Money | C200: JRF Gasoline Station | D200: JRF Gasoline Station - Gas Expense going to BFP to pick up FSIC | E200: PCF-3036 | F200: 0 | G200: 100 | H200: 89.29 | I200: =((I199 + 0) - F200) -> 0 | J200: 10.71 | K200: 12 | L200: Transportation and Travel
A201: 45786 | B201: Spend Money | C201: Office Warehouse, Inc. Festival Mall BR10 | D201: Office Warehouse, Inc. Festival Mall BR10 - Printer Ink | E201: PCF-3038 | F201: 0 | G201: 2160 | H201: 1928.57 | I201: =((I200 + 0) - F201) -> 0 | J201: 231.43 | K201: 12 | L201: Office and Pantry Supplies
A202: 45786 | B202: Spend Money | C202: Office Warehouse, Inc. | D202: Office Warehouse, Inc. - OFFICE SUPPLIES | E202: PCF-3038 | F202: 0 | G202: 2160 | H202: 1928.57 | I202: =((I201 + 0) - F202) -> 0 | J202: 231.43 | K202: 12 | L202: Office and Pantry Supplies - Others
A203: 45789 | B203: Payable Invoice | C203: Grato Philippines Inc. | D203: Grato Philippines Inc. - Descaler | E203: UBP-0525-1031 | F203: 0 | G203: 900 | H203: 803.57 | I203: =((I202 + 0) - F203) -> 0 | J203: 96.43 | K203: 12 | L203: Repairs and Maintenance
A204: 45789 | B204: Payable Invoice | C204: Grato Philippines Inc. | D204: Grato Philippines Inc. - Water Inlet Valve | E204: UBP-0525-1031 | F204: 0 | G204: 775 | H204: 691.96 | I204: =((I203 + 0) - F204) -> 0 | J204: 83.04 | K204: 12 | L204: Repairs and Maintenance
A205: 45790 | B205: Spend Money | C205: Primera Clase Gas Station Inc | D205: Primera Clase Gas Station Inc - Transpo for GIS Notarization | E205: PCF-3043 | F205: 0 | G205: 50 | H205: 44.64 | I205: =((I204 + 0) - F205) -> 0 | J205: 5.36 | K205: 12 | L205: Transportation and Travel
A206: 45792 | B206: Spend Money | C206: Grand Union Supermarket, Inc. | D206: Grand Union Supermarket, Inc. - OFFICE AND PANTRY SUPPLIES | E206: PCF-3046 | F206: 0 | G206: 2703.35 | H206: 2413.71 | I206: =((I205 + 0) - F206) -> 0 | J206: 289.64 | K206: 12 | L206: Office and Pantry Supplies
...

Sheet Schedule of CG Input Tax
A1: CAPITAL GOODS (AGGREGATE AMOUNT EXCEEDS 1M)
A2: INPUT TAX
A4: LEASEHOLD IMPROVEMENTS
A5: DATE PURCHASED | B5: Amount (Net of VAT) | C5: Input Tax | D5: Estimated Life | E5: Monthly Allowable Input Tax | F5: 45292 | G5: 45323 | H5: 45352 | I5: 45383 | J5: 45413 | K5: 45444 | L5: 45474 | M5: 45505 | N5: 45536 | O5: 45566 | P5: 45597 | Q5: 45627 | R5: 45658 | S5: 45689 | T5: 45717 | U5: 45748 | V5: 45778 | W5: 45809 | X5: 45839 | Y5: 45870 | Z5: 45901 | AA5: RUNNING BALANCE
A6: 45323 | B6: 1029347.7 | C6: =B6*12% -> 123521.72 | D6: 60 | E6: =C6/D6 -> 2058.6954 | F6: 0 | G6: =$E$6 -> 2058.6954 | H6: =$E$6 -> 2058.6954 | I6: =$E$6 -> 2058.6954 | J6: =$E$6 -> 2058.6954 | K6: =$E$6 -> 2058.6954 | L6: =$E$6 -> 2058.6954 | M6: =$E$6 -> 2058.6954 | N6: =$E$6 -> 2058.6954 | ... Z6: =$E$6 -> 2058.6954 | AA6: =C6-SUM(G6:W6) -> 88523.901 | AB6: =AA6+T6+S6+R6 -> 94699.987
A7: 45412 | B7: 1600801.7 | C7: =B7*12% -> 192096.21 | D7: 60 | E7: =C7/D7 -> 3201.6034 | I7: =$E$7 -> 3201.6034 | J7: =$E$7 -> 3201.6034 | K7: =$E$7 -> 3201.6034 | L7: =$E$7 -> 3201.6034 | M7: =$E$7 -> 3201.6034 | N7: =$E$7 -> 3201.6034 | O7: =$E$7 -> 3201.6034 | P7: =$E$7 -> 3201.6034 | ... Z7: =$E$7 -> 3201.6034 | AA7: =C7-SUM(G7:W7) -> 144072.15 | AB7: =AA7+T7+S7+R7 -> 153676.97
A10: AIRCON AND LEASED LINE SERVER
A11: DATE PURCHASED | B11: Amount (Net of VAT) | C11: Input Tax | D11: Estimated Life | E11: Monthly Allowable Input Tax | F11: 45292 | G11: 45323 | H11: 45352 | I11: 45383 | J11: 45413 | K11: 45444 | L11: 45474 | M11: 45505 | N11: 45536 | O11: 45566 | P11: 45597 | Q11: 45627 | R11: =R5 -> 45658 | S11: =S5 -> 45689 | T11: =T5 -> 45717 | U11: =U5 -> 45748 | V11: =V5 -> 45778 | W11: =W5 -> 45809 | X11: =X5 -> 45839 | Y11: =Y5 -> 45870 | Z11: =Z5 -> 45901 | AA11: RUNNING BALANCE
A12: 45301 | B12: 1191785.7 | C12: =B12*12% -> 143014.29 | D12: 60 | E12: =C12/D12 -> 2383.5714 | F12: =$E$12 -> 2383.5714 | G12: =$E$12 -> 2383.5714 | H12: =$E$12 -> 2383.5714 | I12: =$E$12 -> 2383.5714 | J12: =$E$12 -> 2383.5714 | K12: =$E$12 -> 2383.5714 | L12: =$E$12 -> 2383.5714 | M12: =$E$12 -> 2383.5714 | ... Z12: =$E$12 -> 2383.5714 | AA12: =C12-SUM(F12:W12) -> 100110 | AB12: =AA12+T12+S12+R12 -> 107260.71
F14: 45292 | G14: 45323 | H14: 45352 | I14: 45383 | J14: 45413 | K14: 45444 | L14: 45474 | M14: 45505 | N14: 45536 | O14: 45566 | P14: 45597 | Q14: 45627 | R14: =R11 -> 45658 | S14: =S11 -> 45689 | T14: =T11 -> 45717 | U14: =U11 -> 45748 | V14: =V11 -> 45778 | W14: =W11 -> 45809 | X14: =X11 -> 45839 | Y14: =Y11 -> 45870 | Z14: =Z11 -> 45901 | AA14: RUNNING BALANCE
A15: TOTAL | F15: =F6+F12+F7 -> 2383.5714 | G15: =G6+G12+G7 -> 4442.2668 | H15: =H6+H12+H7 -> 4442.2668 | I15: =I6+I12+I7 -> 7643.8703 | J15: =J6+J12+J7 -> 7643.8703 | K15: =K6+K12+K7 -> 7643.8703 | L15: =L6+L12+L7 -> 7643.8703 | M15: =M6+M12+M7 -> 7643.8703 | N15: =N6+N12+N7 -> 7643.8703 | O15: =SUM(O6:O7,O12) -> 7643.8703 | P15: =SUM(P6:P7,P12) -> 7643.8703 | Q15: =SUM(Q6:Q7,Q12) -> 7643.8703 | R15: =SUM(R6:R7,R12) -> 7643.8703 | S15: =SUM(S6:S7,S12) -> 7643.8703 | T15: =SUM(T6:T7,T12) -> 7643.8703 | U15: =SUM(U6:U7,U12) -> 7643.8703 | V15: =SUM(V6:V7,V12) -> 7643.8703 | ... Z15: =SUM(Z6:Z7,Z12) -> 7643.8703 | AA15: =AA6+AA12+AA7 -> 332706.06 | AB15: =AA15+T15+S15+R15 -> 355637.67

Sheet Xero Purchases S
A1: Xero Purchases Services 2025
A2: Shirefolk, Inc. (Doing business under the name and style of Launchpad Coworking)
A3: For the period 1 January 2025 to 31 March 2025
A5: Source contains Payable Payment, Payable Prepayment, Spend Money
A6: Tax Rate Name contains VAT on Purchases (Services by Non-residents), VAT on Purchases (Services Not Qual for Input Tax), VAT on Purchases (Services), VAT on Purchases
A8: Date | B8: Source | C8: Contact | D8: Description | E8: Reference | F8: Credit | G8: Gross | H8: Net | I8: Running Balance | J8: Tax | K8: Tax Rate | L8: Account
A10: VAT on Purchases
A11: 45693 | B11: Spend Money | C11: Philippine Allied Enterprises Corporation | D11: Philippine Allied Enterprises Corporation - Parking fee of Sir Bon Excess of the tree 3hrs Parking | E11: PCF - 2932 | F11: 0 | G11: 15 | H11: 13.39 | I11: 0 | J11: 1.61 | K11: 0.12 | L11: Toll and Parking - Others
A12: Total VAT on Purchases | F12: 0 | G12: 15 | H12: 13.39 | I12: 0 | J12: 1.61
A14: VAT on Purchases (Services Not Qual for Input Tax)
A15: 45671 | B15: Spend Money | C15: Patricio L Boncayao Jr Law Office | D15: Patricio L Boncayao Jr Law Office - Notarial fee of Sworn declaration | E15: PCF 2901 | F15: 0 | G15: 150 | H15: 150 | I15: 0 | J15: 0 | K15: 0 | L15: Miscellaneous Expense
A16: 45673 | B16: Spend Money | C16: Patricio L Boncayao Jr Law Office | D16: Patricio L Boncayao Jr Law Office - Notorial fee of private office lease contract (CJ Philipines Inc.) | E16: PCF 2905 | F16: 0 | G16: 230 | H16: 230 | I16: 0 | J16: 0 | K16: 0 | L16: Miscellaneous Expense
A17: 45681 | B17: Spend Money | C17: Lizardo Carlos& Lizardo III | D17: Lizardo Carlos& Lizardo III - Notorial Fee of Gross Sales (shirefolk inc) | E17: PCF-2917 | F17: 0 | G17: 200 | H17: 200 | I17: 0 | J17: 0 | K17: 0 | L17: Miscellaneous Expense
A19: 45708 | B19: Payable Payment | C19: Jesaly A. Dacara - Prop. | D19: Payment: Jesaly A. Dacara - Prop. | E19: UB499278 | F19: 0 | G19: 2400 | H19: 2400 | I19: 0 | J19: 0 | K19: 0 | L19: Other General and Administrative Expenses
A20: 45716 | B20: Payable Payment | C20: Randy Benedict F. Ferrer- Prop. | D20: Payment: Randy Benedict F. Ferrer- Prop. | E20: UB499333 | F20: 0 | G20: 8000 | H20: 8000 | I20: 0 | J20: 0 | K20: 0 | L20: Other Employee Benefits
A22: 45724 | B22: Payable Payment | C22: Ohana Domestic Services | D22: Payment: Ohana Domestic Services | E22: UB534099 | F22: 0 | G22: 6000 | H22: 6000 | I22: 0 | J22: 0 | K22: 0 | L22: Repairs and Maintenance
A23: 45724 | B23: Payable Payment | C23: Ohana Domestic Services | D23: Payment: Ohana Domestic Services | E23: UB534099 | F23: 0 | G23: 4800 | H23: 4800 | I23: 0 | J23: 0 | K23: 0 | L23: Repairs and Maintenance
A24: 45724 | B24: Payable Payment | C24: Ohana Domestic Services | D24: Payment: Ohana Domestic Services | E24: UB534099 | F24: 0 | G24: 6000 | H24: 6000 | I24: 0 | J24: 0 | K24: 0 | L24: Repairs and Maintenance
A25: 45724 | B25: Payable Payment | C25: Ohana Domestic Services | D25: Payment: Ohana Domestic Services | E25: UB534099 | F25: 0 | G25: 1500 | H25: 1500 | I25: 0 | J25: 0 | K25: 0 | L25: Repairs and Maintenance
A26: Total VAT on Purchases (Services Not Qual for Input Tax) | F26: 0 | G26: 29280 | H26: 29280 | I26: 0 | J26: 0
A28: VAT on Purchases (Services)
A29: 45664 | B29: Spend Money | C29: Golden Arches Development Corporation - Commerce Avenue | D29: Golden Arches Development Corporation - Commerce Avenue - Lundi for Accounting Endorsement | E29: PCF 2891 | F29: 0 | G29: 380.58 | H29: 339.8 | I29: 0 | J29: 40.78 | K29: 0.12 | L29: Meals Expense - Others
A30: 45666 | B30: Payable Payment | C30: PLDT Inc. | D30: Payment: PLDT Inc. | E30: UB 2002548176 | F30: 0 | G30: 54432 | H30: 48600 | I30: 0 | J30: 5832 | K30: 0.12 | L30: Communication Expense
A31: 45666 | B31: Spend Money | C31: Lalamove Philippines | D31: Lalamove Philippines - Coffee Beans Delivery Fee (50/50) Shared with SVI | E31: PCF 2896 | F31: 0 | G31: 75 | H31: 66.96 | I31: 0 | J31: 8.04 | K31: 0.12 | L31: Shipping and Delivery Expense
A32: 45666 | B32: Payable Payment | C32: Pestman Specialists Inc | D32: Payment: Pestman Specialists Inc | E32: UB 2002548170 | F32: 0 | G32: 2000 | H32: 1785.71 | I32: 0 | J32: 214.29 | K32: 0.12 | L32: Repairs and Maintenance
A33: 45666 | B33: Payable Payment | C33: Pestman Specialists Inc | D33: Payment: Pestman Specialists Inc | E33: UB 2002548170 | F33: 0 | G33: 1500 | H33: 1339.29 | I33: 0 | J33: 160.71 | K33: 0.12 | L33: Repairs and Maintenance
A34: 45666 | B34: Payable Payment | C34: Pestman Specialists Inc | D34: Payment: Pestman Specialists Inc | E34: UB 2002548170 | F34: 0 | G34: 1000 | H34: 892.86 | I34: 0 | J34: 107.14 | K34: 0.12 | L34: Repairs and Maintenance
A35: 45669 | B35: Payable Payment | C35: PLDT Inc. | D35: Payment: PLDT Inc. | E35: S82906083 | F35: 0 | G35: 1546.01 | H35: 1380.37 | I35: 0 | J35: 165.64 | K35: 0.12 | L35: Communication Expense
A36: 45669 | B36: Payable Payment | C36: PLDT Inc. | D36: Payment: PLDT Inc. | E36: S82906083 | F36: 0 | G36: 74501.99 | H36: 66519.63 | I36: 0 | J36: 7982.36 | K36: 0.12 | L36: Communication Expense
A37: 45669 | B37: Payable Payment | C37: PLDT Inc. | D37: Payment: PLDT Inc. | E37: S82909092 | F37: 0 | G37: 32.09 | H37: 28.65 | I37: 0 | J37: 3.44 | K37: 0.12 | L37: Communication Expense
A38: 45669 | B38: Payable Payment | C38: PLDT Inc. | D38: Payment: PLDT Inc. | E38: S82909092 | F38: 0 | G38: 1546.01 | H38: 1380.37 | I38: 0 | J38: 165.64 | K38: 0.12 | L38: Communication Expense
A39: 45678 | B39: Payable Payment | C39: Philippine Allied Enterprises Corporation | D39: Payment: Philippine Allied Enterprises Corporation | E39: UB 2002548173 | F39: 0 | G39: 23829.12 | H39: 21276 | I39: 0 | J39: 2553.12 | K39: 0.12 | L39: Common Area Charges
A40: 45678 | B40: Payable Payment | C40: Philippine Allied Enterprises Corporation | D40: Payment: Philippine Allied Enterprises Corporation | E40: UB 2002548173 | F40: 0 | G40: 11914.56 | H40: 10638 | I40: 0 | J40: 1276.56 | K40: 0.12 | L40: Common Area Charges
... A109: 45743 | B109: Spend Money | C109: GP LOAD N GO INC. | D109: GP LOAD N GO INC. - Company phone load | E109: PCF- 2998 | F109: 0 | G109: 105 | H109: 93.75 | I109: 0 | J109: 11.25 | K109: 0.12 | L109: Communication Expense
A110: Total VAT on Purchases (Services) | F110: 0 | G110: 1962104.5 | H110: 1751879 | I110: 0 | J110: 210225.49
A112: Total | F112: 0 | G112: 1991399.5 | H112: 1781172.4 | I112: 0 | J112: 210227.1
A116: Xero Services Q2 2025
A117: Shirefolk, Inc. (Doing business under the name and style of Launchpad Coworking)
A118: For the period 1 April 2025 to 30 June 2025
A120: Source contains Payable Invoice, Payable Payment, Payable Prepayment, Spend Money
A121: Tax Rate Name contains VAT on Purchases, VAT on Purchases (Services), VAT on Purchases (Services by Non-residents), VAT on Purchases (Services Not Qual for Input Tax)
A123: Date | B123: Source | C123: Contact | D123: Description | E123: Reference | F123: Credit | G123: Gross | H123: Net | I123: Running Balance | J123: Tax | K123: Tax Rate | L123: Account
A125: VAT on Purchases (Services Not Qual for Input Tax)
A126: 45757 | B126: Payable Invoice | C126: Cabeguin, Clarita Labrador | D126: Cabeguin, Clarita Labrador - Dismantle and Reinstallation | E126: UBP-0425-1007 | F126: 0 | G126: 1921.32 | H126: 1921.32 | I126: =(0 - F126) -> 0 | J126: 0 | K126: 0 | L126: Repairs and Maintenance
A128: 45785 | B128: Spend Money | C128: Philippine Allied Enterprises Corporation | D128: Philippine Allied Enterprises Corporation - SIR RYE'S PARKING TICKET GOING TO BFP TO PICK UP FIRE SAFTY INSPECTION CERTIFICATE | E128: PCF-3037 | F128: 0 | G128: 15 | H128: 15 | I128: =((I126 + 0) - F128) -> 0 | J128: 0 | K128: 0 | L128: Toll and Parking
A129: 45803 | B129: Payable Invoice | C129: Cadiz Jr, Jovito Pongos | D129: Cadiz Jr, Jovito Pongos - LP1 and LP2 Sink Declogging and Cleaning of Grease Trap | E129: UBP-0525-1032 | F129: 0 | G129: 8500 | H129: 8500 | I129: =((I128 + 0) - F129) -> 0 | J129: 0 | K129: 0 | L129: Repairs and Maintenance
A130: Total VAT on Purchases (Services Not Qual for Input Tax) | F130: =SUM(F126:F129) -> 0 | G130: =SUM(G126:G129) -> 10436.32 | H130: =SUM(H126:H129) -> 10436.32 | I130: =I129 -> 0 | J130: =SUM(J126:J129) -> 0
A132: VAT on Purchases (Services)
A133: 45748 | B133: Payable Invoice | C133: PLDT Inc. | D133: PLDT Inc. - I-Gate Premium 100 MBPS- Apr 2025 SOA | E133: UBP-0425-1005 | F133: 0 | G133: 54432 | H133: 48600 | I133: =(0 - F133) -> 0 | J133: 5832 | K133: 12 | L133: Communication Expense
A134: 45748 | B134: Payable Invoice | C134: Ronaldo Barreto Bassig | D134: Ronaldo Barreto Bassig - 10 bklts of Acknowledgment Receipts | E134: UBP-0425-945 | F134: 0 | G134: 2500 | H134: 2232.14 | I134: =((I133 + 0) - F134) -> 0 | J134: 267.86 | K134: 12 | L134: Stationery and Printing
A135: 45748 | B135: Payable Invoice | C135: Ikano (Philippines), Inc. | D135: Ikano (Philippines), Inc. - Delivery Fee | E135: UBP-0425-1011* | F135: 0 | G135: 170 | H135: 151.79 | I135: =((I134 + 0) - F135) -> 0 | J135: 18.21 | K135: 12 | L135: Shipping and Delivery Expense
A136: 45748 | B136: Payable Invoice | C136: Bridge Consulting Inc. | D136: Bridge Consulting Inc. - AFs and ITR 2024 | E136: UBP-0425-1004 | F136: 0 | G136: 33600 | H136: 30000 | I136: =((I135 + 0) - F136) -> 0 | J136: 3600 | K136: 12 | L136: Professional Fees
A137: 45748 | B137: Payable Invoice | C137: Globalbridge Resources Corporation | D137: Globalbridge Resources Corporation - TOTAL MONTHLY RETAINER FEE (APRIL 2025) Ref: INV-0838 | E137: UBP-0425-1003 | F137: 0 | G137: 7616 | H137: 6800 | I137: =((I136 + 0) - F137) -> 0 | J137: 816 | K137: 12 | L137: Professional Fees
A138: 45750 | B138: Payable Invoice | C138: Philippine Allied Enterprises Corporation | D138: Philippine Allied Enterprises Corporation - LP1 Rent for Apr 2025 Ref: SRV 130000825 | E138: UBP-0425-1014 | F138: 0 | G138: 113523.46 | H138: 101360.23 | I138: =((I137 + 0) - F138) -> 0 | J138: 12163.23 | K138: 12 | L138: Rent Expense
A139: 45750 | B139: Payable Invoice | C139: Philippine Allied Enterprises Corporation | D139: Philippine Allied Enterprises Corporation - LP2 Rent for Apr 2025 Ref: SRV 130000827 | E139: UBP-0425-1014 | F139: 0 | G139: 53548.8 | H139: 47811.43 | I139: =((I138 + 0) - F139) -> 0 | J139: 5737.37 | K139: 12 | L139: Rent Expense
A140: 45750 | B140: Payable Invoice | C140: Philippine Allied Enterprises Corporation | D140: Philippine Allied Enterprises Corporation - LP3 Rent for Apr 2025 Ref: SRV 130000780 | E140: UBP-0425-1014 | F140: 0 | G140: 96588.8 | H140: 86240 | I140: =((I139 + 0) - F140) -> 0 | J140: 10348.8 | K140: 12 | L140: Rent Expense
A141: 45750 | B141: Payable Invoice | C141: Philippine Allied Enterprises Corporation | D141: Philippine Allied Enterprises Corporation - LP1 CUSA for Apr 2025 Ref: SRV 130000826 | E141: UBP-0425-1014 | F141: 0 | G141: 23829.12 | H141: 21276 | I141: =((I140 + 0) - F141) -> 0 | J141: 2553.12 | K141: 12 | L141: Common Area Charges
A142: 45750 | B142: Payable Invoice | C142: Philippine Allied Enterprises Corporation | D142: Philippine Allied Enterprises Corporation - LP2 CUSA for Apr 2025 Ref: SRV 130000828 | E142: UBP-0425-1014 | F142: 0 | G142: 11914.56 | H142: 10638 | I142: =((I141 + 0) - F142) -> 0 | J142: 1276.56 | K142: 12 | L142: Common Area Charges
A143: 45750 | B143: Payable Invoice | C143: Philippine Allied Enterprises Corporation | D143: Philippine Allied Enterprises Corporation - LP3 CUSA for Apr 2025 Ref: SRV 130000781 | E143: UBP-0425-1014 | F143: 0 | G143: 23654.4 | H143: 21120 | I143: =((I142 + 0) - F143) -> 0 | J143: 2534.4 | K143: 12 | L143: Common Area Charges
A144: 45752 | B144: Payable Invoice | C144: LT1 Development Corporation | D144: LT1 Development Corporation - LP Staff Summer Outing 2025 Venue: Balai Paraiso Magallanes | E144: UBP-0425-971 | F144: 0 | G144: 14915 | H144: 13316.96 | I144: =((I143 + 0) - F144) -> 0 | J144: 1598.04 | K144: 12 | L144: Representation and Entertainment Expense
A145: 45754 | B145: Payable Invoice | C145: Gascon, Dennis Gellecanao - Prop. | D145: Gascon, Dennis Gellecanao - Prop. - Apollo 4 AC Ceiling Cassette Repair Busted Capacitor | E145: UBP-0425-1006 | F145: 0 | G145: 6000 | H145: 5357.14 | I145: =((I144 + 0) - F145) -> 0 | J145: 642.86 | K145: 12 | L145: Repairs and Maintenance
... A159: 45777 | B159: Payable Invoice | C159: PLDT Inc. | D159: PLDT Inc. - PLDT iGate - April 2025 SOA Note's: ADA | E159: UBP-0425-1017 | F159: 0 | G159: 54432 | H159: 48600 | I159: =((I158 + 0) - F159) -> 0 | J159: 5832 | K159: 12 | L159: Communication Expense
A161: 45778 | B161: Payable Invoice | C161: Ronaldo Barreto Bassig | D161: Ronaldo Barreto Bassig - 20 bklts of Service Invoice Duplicate copies- carbonless | E161: UBP-0525-1015 | F161: 0 | G161: 4700 | H161: 4196.43 | I161: =((I159 + 0) - F161) -> 0 | J161: 503.57 | K161: 12 | L161: Stationery and Printing
A162: 45778 | B162: Payable Invoice | C162: PLDT Inc. | D162: PLDT Inc. - LP3 I-Gate Premium 100 MBPS- May 2025 SOA | E162: UBP-0525-1033* | F162: 0 | G162: 54432 | H162: 48600 | I162: =((I161 + 0) - F162) -> 0 | J162: 5832 | K162: 12 | L162: Communication Expense
A163: 45778 | B163: Payable Invoice | C163: Bridge Consulting Inc. | D163: Bridge Consulting Inc. - SI Share on Accounting Services May 2025 | E163: UBP-0525-1018 | F163: 0 | G163: 14230.59 | H163: 12705.88 | I163: =((I162 + 0) - F163) -> 0 | J163: 1524.71 | K163: 12 | L163: Professional Fees
A164: 45779 | B164: Spend Money | C164: Parkingpro Inc. | D164: Parkingpro Inc. - Parking Ticket- UnionBank | E164: PCF-3026 | F164: 0 | G164: 40 | H164: 35.71 | I164: =((I163 + 0) - F164) -> 0 | J164: 4.29 | K164: 12 | L164: Toll and Parking
A165: 45782 | B165: Spend Money | C165: Philippine Allied Enterprises Corporation | D165: Philippine Allied Enterprises Corporation - Parking Ticket to pick up mugs | E165: PCF-3028 | F165: 0 | G165: 15 | H165: 13.39 | I165: =((I164 + 0) - F165) -> 0 | J165: 1.61 | K165: 12 | L165: Toll and Parking
A166: 45785 | B166: Spend Money | C166: JRF Gasoline Station | D166: JRF Gasoline Station - GAS EXPENSE OF SIR RYE GOING TO BFP TO PICK-UP SHIREFOLK INC'S FIRE SAFETY INSPECTION CERTIFICATE | E166: PCF-3036 | F166: 0 | G166: 100 | H166: 89.29 | I166: =((I165 + 0) - F166) -> 0 | J166: 10.71 | K166: 12 | L166: Transportation and Travel
A167: 45785 | B167: Spend Money | C167: Philippine Allied Enterprises Corporation | D167: Philippine Allied Enterprises Corporation - Water | E167: PCF-3037 | F167: 0 | G167: 15 | H167: 13.39 | I167: =((I166 + 0) - F167) -> 0 | J167: 1.61 | K167: 12 | L167: Toll and Parking
A168: 45786 | B168: Payable Invoice | C168: Philippine Allied Enterprises Corporation | D168: Philippine Allied Enterprises Corporation - LP1 Rent for May2025 Ref: SRV 130000958 | E168: UBP-0525-1019 | F168: 0 | G168: 113523.46 | H168: 101360.23 | I168: =((I167 + 0) - F168) -> 0 | J168: 12163.23 | K168: 12 | L168: Rent Expense
A169: 45786 | B169: Payable Invoice | C169: Philippine Allied Enterprises Corporation | D169: Philippine Allied Enterprises Corporation - LP2 Rent for May 2025 Ref: SRV 130000960 | E169: UBP-0525-1019 | F169: 0 | G169: 53548.8 | H169: 47811.43 | I169: =((I168 + 0) - F169) -> 0 | J169: 5737.37 | K169: 12 | L169: Rent Expense
A170: 45786 | B170: Payable Invoice | C170: Philippine Allied Enterprises Corporation | D170: Philippine Allied Enterprises Corporation - LP3 Rent for May 2025 Ref: SRV 130000911 | E170: UBP-0525-1019 | F170: 0 | G170: 96588.8 | H170: 86240 | I170: =((I169 + 0) - F170) -> 0 | J170: 10348.8 | K170: 12 | L170: Rent Expense
A171: 45786 | B171: Payable Invoice | C171: Philippine Allied Enterprises Corporation | D171: Philippine Allied Enterprises Corporation - LP1 CUSA for May 2025 Ref: SRV 130000959 | E171: UBP-0525-1019 | F171: 0 | G171: 23829.12 | H171: 21276 | I171: =((I170 + 0) - F171) -> 0 | J171: 2553.12 | K171: 12 | L171: Common Area Charges
A172: 45786 | B172: Payable Invoice | C172: Philippine Allied Enterprises Corporation | D172: Philippine Allied Enterprises Corporation - LP2 CUSA for May 2025 Ref: SRV 130000961 | E172: UBP-0525-1019 | F172: 0 | G172: 11914.56 | H172: 10638 | I172: =((I171 + 0) - F172) -> 0 | J172: 1276.56 | K172: 12 | L172: Common Area Charges
A173: 45786 | B173: Payable Invoice | C173: Philippine Allied Enterprises Corporation | D173: Philippine Allied Enterprises Corporation - LP3 CUSA for May 2025 Ref: SRV 130000912 | E173: UBP-0525-1019 | F173: 0 | G173: 23654.4 | H173: 21120 | I173: =((I172 + 0) - F173) -> 0 | J173: 2534.4 | K173: 12 | L173: Common Area Charges
... A184: 45807 | B184: Payable Invoice | C184: PLDT Inc. | D184: PLDT Inc. - PLDT iGate - May 2025 SOA Note's: ADA | E184: UBP-0525-1033 | F184: 0 | G184: 54432 | H184: 48600 | I184: =((I183 + 0) - F184) -> 0 | J184: 5832 | K184: 12 | L184: Communication Expense
A186: 45809 | B186: Payable Invoice | C186: PLDT Inc. | D186: PLDT Inc. - LP3 I-Gate Premium 100 MBPS- June 2025 SOA | E186: UBP-0625-1040* | F186: 0 | G186: 54432 | H186: 48600 | I186: =((I184 + 0) - F186) -> 0 | J186: 5832 | K186: 12 | L186: Communication Expense
A187: 45818 | B187: Spend Money | C187: Philippine Allied Enterprises Corporation | D187: Philippine Allied Enterprises Corporation - Parking ticket | E187: PCF-3074 | F187: 0 | G187: 15 | H187: 13.39 | I187: =((I186 + 0) - F187) -> 0 | J187: 1.61 | K187: 12 | L187: Toll and Parking
A188: 45824 | B188: Payable Invoice | C188: Philippine Allied Enterprises Corporation | D188: Philippine Allied Enterprises Corporation - LP1 CUSA for June 2025 Ref: SRV 130001094 | E188: UBP-0625-1041 | F188: 0 | G188: 23829.12 | H188: 21276 | I188: =((I187 + 0) - F188) -> 0 | J188: 2553.12 | K188: 12 | L188: Common Area Charges
A189: 45824 | B189: Payable Invoice | C189: Philippine Allied Enterprises Corporation | D189: Philippine Allied Enterprises Corporation - LP2 CUSA for June 2025 Ref: SRV 130001096 | E189: UBP-0625-1041 | F189: 0 | G189: 11914.56 | H189: 10638 | I189: =((I188 + 0) - F189) -> 0 | J189: 1276.56 | K189: 12 | L189: Common Area Charges
A190: 45824 | B190: Payable Invoice | C190: Philippine Allied Enterprises Corporation | D190: Philippine Allied Enterprises Corporation - LP3 CUSA for June 2025 Ref: SRV 130001046 | E190: UBP-0625-1041 | F190: 0 | G190: 23654.4 | H190: 21120 | I190: =((I189 + 0) - F190) -> 0 | J190: 2534.4 | K190: 12 | L190: Common Area Charges
A191: 45824 | B191: Payable Invoice | C191: Philippine Allied Enterprises Corporation | D191: Philippine Allied Enterprises Corporation - LP1 Rent for June 2025 Ref: SRV 1300001093 | E191: UBP-0625-1041 | F191: 0 | G191: 113523.46 | H191: 101360.23 | I191: =((I190 + 0) - F191) -> 0 | J191: 12163.23 | K191: 12 | L191: Rent Expense
A192: 45824 | B192: Payable Invoice | C192: Philippine Allied Enterprises Corporation | D192: Philippine Allied Enterprises Corporation - LP2 Rent for June2025 Ref: SRV 130001095 | E192: UBP-0625-1041 | F192: 0 | G192: 53548.8 | H192: 47811.43 | I192: =((I191 + 0) - F192) -> 0 | J192: 5737.37 | K192: 12 | L192: Rent Expense
A193: 45824 | B193: Payable Invoice | C193: Philippine Allied Enterprises Corporation | D193: Philippine Allied Enterprises Corporation - LP3 Rent for June 2025 Ref: SRV 130001045 | E193: UBP-0625-1041 | F193: 0 | G193: 96588.8 | H193: 86240 | I193: =((I192 + 0) - F193) -> 0 | J193: 10348.8 | K193: 12 | L193: Rent Expense
A194: 45825 | B194: Spend Money | C194: Black Dog Graphic Design and Print Services | D194: Black Dog Graphic Design and Print Services - Launchpad poster | E194: PCF-3084 | F194: 0 | G194: 766.07 | H194: 683.99 | I194: =((I193 + 0) - F194) -> 0 | J194: 82.08 | K194: 12 | L194: Office and Pantry Supplies
A195: 45833 | B195: Spend Money | C195: Philippine Allied Enterprises Corporation | D195: Philippine Allied Enterprises Corporation - parking ticket | E195: PCF-3095 | F195: 0 | G195: 15 | H195: 13.39 | I195: =((I194 + 0) - F195) -> 0 | J195: 1.61 | K195: 12 | L195: Toll and Parking
A196: 45835 | B196: Spend Money | C196: Lalamove Philippines | D196: Lalamove Philippines - Coffee beans delivery | E196: PCF-3099 | F196: 0 | G196: 75 | H196: 66.96 | I196: =((I195 + 0) - F196) -> 0 | J196: 8.04 | K196: 12 | L196: Shipping and Delivery Expense
A197: 45838 | B197: Payable Invoice | C197: Bridge Consulting Inc. | D197: Bridge Consulting Inc. - SI Share on Accounting Services June 2025 | E197: UBP-0625-1045 | F197: 0 | G197: 14230.59 | H197: 12705.88 | I197: =((I196 + 0) - F197) -> 0 | J197: 1524.71 | K197: 12 | L197: Professional Fees
A198: Total VAT on Purchases (Services) | F198: =SUM(F133:F197) -> 0 | G198: =SUM(G133:G197) -> 1504100.6 | H198: =SUM(H133:H197) -> 1342947 | I198: =I197 -> 0 | J198: =SUM(J133:J197) -> 161153.69
A200: Total | F200: =SUM(F130,F198) -> 0 | G200: =SUM(G130,G198) -> 1514537 | H200: =SUM(H130,H198) -> 1353383.3 | I200: =(0 - F200) -> 0 | J200: =SUM(J130,J198) -> 161153.69
A203: Account Transactions
A204: Shirefolk, Inc. (Doing business under the name and style of Launchpad Coworking)
A205: For the period 1 July 2025 to 31 July 2025
A207: Source contains Payable Invoice, Spend Money
A208: Tax Rate Name contains VAT on Purchases, VAT on Purchases (Services), VAT on Purchases (Services by Non-residents), VAT on Purchases (Services Not Qual for Input Tax)
A210: Date | B210: Source | C210: Contact | D210: Description | E210: Reference | F210: Credit | G210: Gross | H210: Net | I210: Running Balance | J210: Tax | K210: Tax Rate | L210: Account
A212: VAT on Purchases (Services Not Qual for Input Tax)
A213: 45839 | B213: Payable Invoice | C213: Randy Benedict F. Ferrer- Prop. | D213: Randy Benedict F. Ferrer- Prop. - Sublimation Printing of Company Uniform | E213: UBP-0725-1052 | F213: 0 | G213: 800 | H213: 800 | I213: 0 | J213: 0 | K213: 0 | L213: Other Employee Benefits
A214: Total VAT on Purchases (Services Not Qual for Input Tax) | F214: 0 | G214: 800 | H214: 800 | I214: 0 | J214: 0
A216: VAT on Purchases (Services)
...

Sheet FF
A1: LIST OF OR WITHOUT INVOICE IN XERO
A2: Shirefolk Inc
A3: as of April 1, 2022
B5: OR No | C5: Date | D5: Client Name | E5: OR Amount | F5: Description | G5: Remarks
B6: YEAR 2022
A7: 1 | B7: 2440 | C7: 44743 | D7: MASO | E7: 15000 | F7: VO: Dec 2, 2021 - Dec 1, 2022
A8: 2 | B8: 2441 | C8: 44835 | D8: Ambray Castillo Law Firm | E8: 12000 | F8: UA: Jan 1- Dec 31, 2022
A9: 3 | B9: 2445 | C9: 01/14/2022 | D9: Sinaya Corp | E9: 15285.72 | F9: UA: Oct 19, 2022 - Feb 18, 2024
A10: 4 | B10: 2517 | C10: 44627 | D10: MASO | E10: 18600 | F10: VO & Locker: Dec 2, 2021 - Dec 1, 2022
A11: 5 | B11: 2527 | C11: 44628 | D11: Baoya Property Solutions Inc | E11: 23200 | F11: VO: Mar 17, 2021 - Mar 16, 2022 & UA: Mar 17 - Sep 16, 2022
A12: 6 | B12: 2538 | C12: 44635 | D12: Lion Lamb Graphic Design Services | E12: 12000 | F12: UA: Mar 15, 2020 - Mar 14, 2023
A13: 7 | B13: 2544 | C13: 44636 | D13: ALM Agri Trading Fertilizer | E13: 12000 | F13: UA: Mar 6, 2022 - Mar 5, 2023
A14: 8 | B14: 2548 | C14: 44637 | D14: Ascensoft Inc | E14: 12000 | F14: UA: Mar 13, 2022 - Mar 12, 2023
A15: 9 | B15: 2563 | C15: 44643 | D15: Zvoid Studios | E15: 38080 | F15: A1: Mar 23 - Apr 22, 2022
A16: 10 | B16: 2564 | C16: 44643 | D16: Andie Villegas | E16: 500 | F16: Whole Day Pass
A17: 11 | B17: 2569 | C17: 44645 | D17: Roberto Laceda | E17: 30000 | F17: VO: Apr 4, 2022 - Apr 3, 2023
A18: 12 | B18: 2579 | C18: 44650 | D18: Johanne Lim | E18: 500 | F18: whole day pass
A19: 13 | B19: 2580 | C19: 44651 | D19: Kevin Iwabuchi | E19: 750 | F19: 3 hrs pass (3)
B20: YEAR 2021
A21: 9 | B21: 2114 | C21: 44273 | D21: Meaningful Ventures Inc | E21: 30000 | F21: VO: Mar 18, 2021 - Mar 17, 2022 | G21: made dummy invoice in Xero
A22: 10 | B22: 2124 | C22: 44279 | D22: Front Media Entertainment Talent Agency Inc | E22: 30000 | F22: VO: Mar 25, 2021 - Mar 24, 2022 | G22: made dummy invoice in Xero
A23: 11 | B23: 2216 | C23: 44391 | D23: Ernest Troyss B. Pilapil | E23: 36000 | F23: Start Up: July 19, 2021 - July 18, 2022
A24: 12 | B24: 2403 | C24: 44543 | D24: Lumenaire Specialized Goods Trading | E24: 30000 | F24: VO: Jan 1 - Dec 31, 2022
A25: 13 | B25: 2418 | C25: 44550 | D25: Southmain Real Estate Brokerage | E25: 12000 | F25: UA: July 1, 2021 to June 30, 2022
B26: YEAR 2020
A27: 14 | B27: 1871 | C27: 44063 | D27: Baoya | E27: 12340.64 | F27: UA, locker & RR | G27: made dummy invoice in Xero
A28: 15 | B28: 1908 | C28: 44109 | D28: Rouse and Foster | E28: 24000 | F28: UA: Sep 11, 2019 - Sep 10, 2021 | G28: made dummy invoice in Xero
A29: 16 | B29: 1958 | C29: 44085 | D29: Plain Lamp | E29: 12000 | F29: UA: Oct 31, 2020 to Oct 30, 2021 | G29: made dummy invoice in Xero
D30: TOTAL | E30: =SUM(E6:E29) -> 376256.36
