Workbook

Sheet Summary of CG Purchased 
A1: PURCHASES OF CAPITAL GOODS
A5: APRIL 2019 | C5: MONTHS | D5: AMOUNT NET OF VAT | E5: INPUT TAX | F5: ALLOWABLE DEDUCTIONS | G5: BALANCE OF INPUT TAX | H5: TO BE CARRIED UNTIL | I5: PER MONTH | K5: (Per Month x 3Months)
B6: FURNITURE & FIXTURES | C6: =3*12 -> 36 | D6: 2934806.6 | E6: =D6*0.12 -> 352176.8 | F6: =E6/C6 -> 9782.6888 | G6: =E6-F6 -> 342394.11 | H6: MARCH 2022 | I6: =F6 -> 9782.6888 | K6: =I6*3 -> 29348.066
B7: LEASEHOLD IMPROVEMENT | C7: =5*12 -> 60 | D7: 5737496.5 | E7: =D7*0.12 -> 688499.58 | F7: =E7/C7 -> 11474.993 | G7: =E7-F7 -> 677024.58 | H7: MARCH 2024 | I7: =F7 -> 11474.993 | K7: =I7*3 -> 34424.979
B8: OFFICE EQUIPMENT | C8: =3*12 -> 36 | D8: 301766.26 | E8: =D8*0.12 -> 36211.951 | F8: =E8 -> 36211.951 | G8: =E8-F8 -> 0
B10: TOTAL | D10: 8974069.4 | E10: =SUM(E6:E8) -> 1076888.3 | F10: =SUM(F6:F8) -> 57469.633 | G10: =SUM(G6:G8) -> 1019418.7 | I10: =SUM(I6:I8) -> 21257.682 | K10: =I10*3 -> 63773.045
A13: MAY 2019 | C13: MONTHS | D13: AMOUNT NET OF VAT | E13: INPUT TAX | F13: ALLOWABLE DEDUCTIONS | G13: BALANCE OF INPUT TAX | H13: TO BE CARRIED UNTIL | I13: PER MONTH
B14: FURNITURE & FIXTURES | C14: =3*12 -> 36 | D14: 0 | E14: =D14*0.12 -> 0 | F14: =E14/C14 -> 0 | G14: =E14-F14 -> 0 | I14: =F14 -> 0
B15: LEASEHOLD IMPROVEMENT | C15: =5*12 -> 60 | D15: 597634.03 | E15: =D15*0.12 -> 71716.084 | F15: =E15 -> 71716.084 | G15: =E15-F15 -> 0 | M15: =L16/36 -> 81522.406 | N15: =M16*0.12 -> 264132.6 | O15: =N15/27 -> 9782.6888
B16: OFFICE EQUIPMENT | C16: =3*12 -> 36 | E16: =D16*0.12 -> 0 | F16: =E16 -> 0 | G16: =E16-F16 -> 0 | L16: =D6 -> 2934806.6 | M16: 2201105 | N16: =L16-M16 -> 733701.66 | O16: =N16/M15 -> 9
L17: 5737496.5 | M17: 4876872 | N17: =L17-M17 -> 860624.47 | O17: =(L17/60)*9 -> 860624.47 | P17: =N17-O17 -> -0.0019999994
B18: TOTAL | D18: 597634.03 | E18: =SUM(E14:E16) -> 71716.084 | F18: =SUM(F14:F16) -> 71716.084 | G18: =SUM(G14:G16) -> 0 | L18: =SUM(L16:L17) -> 8672303.1 | M18: =SUM(M16:M17) -> 7077977 | N18: =SUM(N16:N17) -> 1594326.1
A21: JUNE 2019 | C21: MONTHS | D21: AMOUNT NET OF VAT | E21: INPUT TAX | F21: ALLOWABLE DEDUCTIONS | G21: BALANCE OF INPUT TAX | H21: TO BE CARRIED UNTIL | I21: PER MONTH
B22: FURNITURE & FIXTURES | C22: =3*12 -> 36 | D22: 105000 | E22: =D22*0.12 -> 12600 | F22: =E22 -> 12600 | G22: =E22-F22 -> 0 | I22: 0
B23: LEASEHOLD IMPROVEMENT | C23: =5*12 -> 60 | D23: 159618.7 | E23: =D23*0.12 -> 19154.244 | F23: =E23 -> 19154.244 | G23: =E23-F23 -> 0
B24: OFFICE EQUIPMENT | C24: =3*12 -> 36 | D24: 1071.43 | E24: =D24*0.12 -> 128.5716 | F24: =E24 -> 128.5716 | G24: =E24-F24 -> 0
B26: TOTAL | D26: 265690.13 | E26: =SUM(E22:E24) -> 31882.816 | F26: =SUM(F22:F24) -> 31882.816 | G26: =SUM(G22:G24) -> 0
A29: JULY 2019 | C29: MONTHS | D29: AMOUNT NET OF VAT | E29: INPUT TAX | F29: ALLOWABLE DEDUCTIONS | G29: BALANCE OF INPUT TAX | H29: TO BE CARRIED UNTIL | I29: PER MONTH
B30: FURNITURE & FIXTURES | C30: =3*12 -> 36 | D30: 0 | E30: =D30*0.12 -> 0 | F30: =E30 -> 0 | G30: =E30-F30 -> 0 | I30: 0
B31: LEASEHOLD IMPROVEMENT | C31: =5*12 -> 60 | D31: 174808.8 | E31: =D31*0.12 -> 20977.056 | F31: =E31 -> 20977.056 | G31: =E31-F31 -> 0
B32: OFFICE EQUIPMENT | C32: =3*12 -> 36 | D32: 0 | E32: =D32*0.12 -> 0 | F32: =E32 -> 0 | G32: =E32-F32 -> 0
B34: TOTAL | D34: 174808.8 | E34: =SUM(E30:E32) -> 20977.056 | F34: =SUM(F30:F32) -> 20977.056 | G34: =SUM(G30:G32) -> 0
A37: AUG 2019 | C37: MONTHS | D37: AMOUNT NET OF VAT | E37: INPUT TAX | F37: ALLOWABLE DEDUCTIONS | G37: BALANCE OF INPUT TAX | H37: TO BE CARRIED UNTIL | I37: PER MONTH
B38: FURNITURE & FIXTURES | C38: =3*12 -> 36 | D38: 0 | E38: =D38*0.12 -> 0 | F38: =E38 -> 0 | G38: =E38-F38 -> 0 | I38: 0
B39: LEASEHOLD IMPROVEMENT | C39: =5*12 -> 60 | D39: 0 | E39: =D39*0.12 -> 0 | F39: =E39 -> 0 | G39: =E39-F39 -> 0
B40: OFFICE EQUIPMENT | C40: =3*12 -> 36 | D40: 0 | E40: =D40*0.12 -> 0 | F40: =E40 -> 0 | G40: =E40-F40 -> 0
B42: TOTAL | D42: 0 | E42: =SUM(E38:E40) -> 0 | F42: =SUM(F38:F40) -> 0 | G42: =SUM(G38:G40) -> 0
A45: SEPT 2019 | C45: MONTHS | D45: AMOUNT NET OF VAT | E45: INPUT TAX | F45: ALLOWABLE DEDUCTIONS | G45: BALANCE OF INPUT TAX | H45: TO BE CARRIED UNTIL | I45: PER MONTH
B46: FURNITURE & FIXTURES | C46: =3*12 -> 36 | D46: 135625 | E46: =D46*0.12 -> 16275 | F46: =E46 -> 16275 | G46: =E46-F46 -> 0 | I46: 0
B47: LEASEHOLD IMPROVEMENT | C47: =5*12 -> 60 | D47: 93973.57 | E47: =D47*0.12 -> 11276.828 | F47: =E47 -> 11276.828 | G47: =E47-F47 -> 0
B48: OFFICE EQUIPMENT | C48: =3*12 -> 36 | D48: 0 | E48: =D48*0.12 -> 0 | F48: =E48 -> 0 | G48: =E48-F48 -> 0
B50: TOTAL | D50: 229598.57 | E50: =SUM(E46:E48) -> 27551.828 | F50: =SUM(F46:F48) -> 27551.828 | G50: =SUM(G46:G48) -> 0
A53: OCT 2019 | C53: MONTHS | D53: AMOUNT NET OF VAT | E53: INPUT TAX | F53: ALLOWABLE DEDUCTIONS | G53: BALANCE OF INPUT TAX | H53: TO BE CARRIED UNTIL | I53: PER MONTH
B54: FURNITURE & FIXTURES | C54: =3*12 -> 36 | D54: 0 | E54: =D54*0.12 -> 0 | F54: =E54 -> 0 | G54: =E54-F54 -> 0 | I54: 0
B55: LEASEHOLD IMPROVEMENT | C55: =5*12 -> 60 | D55: 0 | E55: =D55*0.12 -> 0 | F55: =E55 -> 0 | G55: =E55-F55 -> 0
B56: OFFICE EQUIPMENT | C56: =3*12 -> 36 | D56: 0 | E56: =D56*0.12 -> 0 | F56: =E56 -> 0 | G56: =E56-F56 -> 0
B58: TOTAL | D58: 0 | E58: =SUM(E54:E56) -> 0 | F58: =SUM(F54:F56) -> 0 | G58: =SUM(G54:G56) -> 0
A61: NOV 2019 | C61: MONTHS | D61: AMOUNT NET OF VAT | E61: INPUT TAX | F61: ALLOWABLE DEDUCTIONS | G61: BALANCE OF INPUT TAX | H61: TO BE CARRIED UNTIL | I61: PER MONTH
B62: FURNITURE & FIXTURES | C62: =3*12 -> 36 | D62: 0 | E62: =D62*0.12 -> 0 | F62: =E62 -> 0 | G62: =E62-F62 -> 0 | I62: 0
B63: LEASEHOLD IMPROVEMENT | C63: =5*12 -> 60 | D63: 4973.57 | E63: =D63*0.12 -> 596.8284 | F63: =E63 -> 596.8284 | G63: =E63-F63 -> 0
B64: OFFICE EQUIPMENT | C64: =3*12 -> 36 | D64: 0 | E64: =D64*0.12 -> 0 | F64: =E64 -> 0 | G64: =E64-F64 -> 0
B66: TOTAL | D66: 4973.57 | E66: =SUM(E62:E64) -> 596.8284 | F66: =SUM(F62:F64) -> 596.8284 | G66: =SUM(G62:G64) -> 0
A69: DEC 2019 | C69: MONTHS | D69: AMOUNT NET OF VAT | E69: INPUT TAX | F69: ALLOWABLE DEDUCTIONS | G69: BALANCE OF INPUT TAX | H69: TO BE CARRIED UNTIL | I69: PER MONTH
B70: FURNITURE & FIXTURES | C70: =3*12 -> 36 | D70: 0 | E70: =D70*0.12 -> 0 | F70: =E70 -> 0 | G70: =E70-F70 -> 0 | I70: 0
B71: LEASEHOLD IMPROVEMENT | C71: =5*12 -> 60 | D71: 0 | E71: =D71*0.12 -> 0 | F71: =E71 -> 0 | G71: =E71-F71 -> 0
B72: OFFICE EQUIPMENT | C72: =3*12 -> 36 | D72: 0 | E72: =D72*0.12 -> 0 | F72: =E72 -> 0 | G72: =E72-F72 -> 0
B74: TOTAL | D74: 0 | E74: =SUM(E70:E72) -> 0 | F74: =SUM(F70:F72) -> 0 | G74: =SUM(G70:G72) -> 0
A76: JAN 2020 | C76: MONTHS | D76: AMOUNT NET OF VAT | E76: INPUT TAX | F76: ALLOWABLE DEDUCTIONS | G76: BALANCE OF INPUT TAX | H76: TO BE CARRIED UNTIL | I76: PER MONTH
B77: FURNITURE & FIXTURES | C77: =3*12 -> 36 | D77: 23249.55 | E77: =D77*0.12 -> 2789.946 | F77: =E77 -> 2789.946 | G77: =E77-F77 -> 0 | I77: 0
B78: LEASEHOLD IMPROVEMENT | C78: =5*12 -> 60 | D78: 0 | E78: =D78*0.12 -> 0 | F78: =E78 -> 0 | G78: =E78-F78 -> 0
B79: OFFICE EQUIPMENT | C79: =3*12 -> 36 | D79: 8640.63 | E79: =D79*0.12 -> 1036.8756 | F79: =E79 -> 1036.8756 | G79: =E79-F79 -> 0
B81: TOTAL | D81: 31890.18 | E81: =SUM(E77:E79) -> 3826.8216 | F81: =SUM(F77:F79) -> 3826.8216 | G81: =SUM(G77:G79) -> 0
A83: FEB 2020 | C83: MONTHS | D83: AMOUNT NET OF VAT | E83: INPUT TAX | F83: ALLOWABLE DEDUCTIONS | G83: BALANCE OF INPUT TAX | H83: TO BE CARRIED UNTIL | I83: PER MONTH
B84: FURNITURE & FIXTURES | C84: =3*12 -> 36 | E84: =D84*0.12 -> 0 | F84: =E84 -> 0 | G84: =E84-F84 -> 0 | I84: 0
B85: LEASEHOLD IMPROVEMENT | C85: =5*12 -> 60 | D85: 42268.71 | E85: =D85*0.12 -> 5072.2452 | F85: =E85 -> 5072.2452 | G85: =E85-F85 -> 0
B86: OFFICE EQUIPMENT | C86: =3*12 -> 36 | D86: 0 | E86: =D86*0.12 -> 0 | F86: =E86 -> 0 | G86: =E86-F86 -> 0
B88: TOTAL | D88: 42268.71 | E88: =SUM(E84:E86) -> 5072.2452 | F88: =SUM(F84:F86) -> 5072.2452 | G88: =SUM(G84:G86) -> 0
A90: MAR 2020 | C90: MONTHS | D90: AMOUNT NET OF VAT | E90: INPUT TAX | F90: ALLOWABLE DEDUCTIONS | G90: BALANCE OF INPUT TAX | H90: TO BE CARRIED UNTIL | I90: PER MONTH
B91: FURNITURE & FIXTURES | C91: =3*12 -> 36 | D91: 37495.54 | E91: =D91*0.12 -> 4499.4648 | F91: =E91 -> 4499.4648 | G91: =E91-F91 -> 0 | I91: 0
B92: LEASEHOLD IMPROVEMENT | C92: =5*12 -> 60 | D92: 72000 | E92: =D92*0.12 -> 8640 | F92: =E92 -> 8640 | G92: =E92-F92 -> 0
B93: OFFICE EQUIPMENT | C93: =3*12 -> 36 | D93: 0 | E93: =D93*0.12 -> 0 | F93: =E93 -> 0 | G93: =E93-F93 -> 0
B95: TOTAL | D95: 109495.54 | E95: =SUM(E91:E93) -> 13139.465 | F95: =SUM(F91:F93) -> 13139.465 | G95: =SUM(G91:G93) -> 0
A97: APR 2020 | C97: MONTHS | D97: AMOUNT NET OF VAT | E97: INPUT TAX | F97: ALLOWABLE DEDUCTIONS | G97: BALANCE OF INPUT TAX | H97: TO BE CARRIED UNTIL | I97: PER MONTH
B98: FURNITURE & FIXTURES | C98: =3*12 -> 36 | D98: 0 | E98: =D98*0.12 -> 0 | F98: =E98 -> 0 | G98: =E98-F98 -> 0 | I98: 0
B99: LEASEHOLD IMPROVEMENT | C99: =5*12 -> 60 | D99: 0 | E99: =D99*0.12 -> 0 | F99: =E99 -> 0 | G99: =E99-F99 -> 0
B100: OFFICE EQUIPMENT | C100: =3*12 -> 36 | D100: 0 | E100: =D100*0.12 -> 0 | F100: =E100 -> 0 | G100: =E100-F100 -> 0
B102: TOTAL | D102: 0 | E102: =SUM(E98:E100) -> 0 | F102: =SUM(F98:F100) -> 0 | G102: =SUM(G98:G100) -> 0
A104: MAY 2020 | C104: MONTHS | D104: AMOUNT NET OF VAT | E104: INPUT TAX | F104: ALLOWABLE DEDUCTIONS | G104: BALANCE OF INPUT TAX | H104: TO BE CARRIED UNTIL | I104: PER MONTH
B105: FURNITURE & FIXTURES | C105: =3*12 -> 36 | D105: 17000 | E105: =D105*0.12 -> 2040 | F105: =E105 -> 2040 | G105: =E105-F105 -> 0 | I105: 0
B106: LEASEHOLD IMPROVEMENT | C106: =5*12 -> 60 | D106: 0 | E106: =D106*0.12 -> 0 | F106: =E106 -> 0 | G106: =E106-F106 -> 0
B107: OFFICE EQUIPMENT | C107: =3*12 -> 36 | D107: 0 | E107: =D107*0.12 -> 0 | F107: =E107 -> 0 | G107: =E107-F107 -> 0
B109: TOTAL | D109: 17000 | E109: =SUM(E105:E107) -> 2040 | F109: =SUM(F105:F107) -> 2040 | G109: =SUM(G105:G107) -> 0
A111: JUNE 2020 | C111: MONTHS | D111: AMOUNT NET OF VAT | E111: INPUT TAX | F111: ALLOWABLE DEDUCTIONS | G111: BALANCE OF INPUT TAX | H111: TO BE CARRIED UNTIL | I111: PER MONTH
B112: FURNITURE & FIXTURES | C112: =3*12 -> 36 | D112: 0 | E112: =D112*0.12 -> 0 | F112: =E112 -> 0 | G112: =E112-F112 -> 0 | I112: 0
B113: LEASEHOLD IMPROVEMENT | C113: =5*12 -> 60 | D113: 1433790.1 | E113: =D113*0.12 -> 172054.81 | F113: =E113/C113 -> 2867.5801 | G113: =E113-F113 -> 169187.23 | H113: MAY 2025 | I113: =F113 -> 2867.5801
B114: OFFICE EQUIPMENT | C114: =3*12 -> 36 | E114: =D114*0.12 -> 0 | F114: =E114 -> 0 | G114: =E114-F114 -> 0
B116: TOTAL | D116: 1433790.1 | E116: =SUM(E112:E114) -> 172054.81 | F116: =SUM(F112:F114) -> 2867.5801 | G116: =SUM(G112:G114) -> 169187.23
A118: JUNE 2020 | C118: MONTHS | D118: AMOUNT NET OF VAT | E118: INPUT TAX | F118: ALLOWABLE DEDUCTIONS | G118: BALANCE OF INPUT TAX | H118: TO BE CARRIED UNTIL | I118: PER MONTH
B119: FURNITURE & FIXTURES | C119: =3*12 -> 36 | D119: 0 | E119: =D119*0.12 -> 0 | F119: =E119 -> 0 | G119: =E119-F119 -> 0 | I119: 0
B120: LEASEHOLD IMPROVEMENT | C120: =5*12 -> 60 | D120: 0 | E120: =D120*0.12 -> 0 | F120: =E120/C120 -> 0 | G120: =E120-F120 -> 0 | I120: =F120 -> 0
B121: OFFICE EQUIPMENT | C121: =3*12 -> 36 | E121: =D121*0.12 -> 0 | F121: =E121 -> 0 | G121: =E121-F121 -> 0
B123: TOTAL | D123: 0 | E123: =SUM(E119:E121) -> 0 | F123: =SUM(F119:F121) -> 0 | G123: =SUM(G119:G121) -> 0
A125: JULY 2020 | C125: MONTHS | D125: AMOUNT NET OF VAT | E125: INPUT TAX | F125: ALLOWABLE DEDUCTIONS | G125: BALANCE OF INPUT TAX | H125: TO BE CARRIED UNTIL | I125: PER MONTH
B126: FURNITURE & FIXTURES | C126: =3*12 -> 36 | D126: 0 | E126: =D126*0.12 -> 0 | F126: =E126 -> 0 | G126: =E126-F126 -> 0 | I126: 0
B127: LEASEHOLD IMPROVEMENT | C127: =5*12 -> 60 | D127: 0 | E127: =D127*0.12 -> 0 | F127: =E127/C127 -> 0 | G127: =E127-F127 -> 0 | I127: =F127 -> 0
B128: OFFICE EQUIPMENT | C128: =3*12 -> 36 | E128: =D128*0.12 -> 0 | F128: =E128 -> 0 | G128: =E128-F128 -> 0
B130: TOTAL | D130: 0 | E130: =SUM(E126:E128) -> 0 | F130: =SUM(F126:F128) -> 0 | G130: =SUM(G126:G128) -> 0
A132: AUG 2020 | C132: MONTHS | D132: AMOUNT NET OF VAT | E132: INPUT TAX | F132: ALLOWABLE DEDUCTIONS | G132: BALANCE OF INPUT TAX | H132: TO BE CARRIED UNTIL | I132: PER MONTH
B133: FURNITURE & FIXTURES | C133: =3*12 -> 36 | D133: 0 | E133: =D133*0.12 -> 0 | F133: =E133 -> 0 | G133: =E133-F133 -> 0 | I133: 0
B134: LEASEHOLD IMPROVEMENT | C134: =5*12 -> 60 | D134: 0 | E134: =D134*0.12 -> 0 | F134: =E134/C134 -> 0 | G134: =E134-F134 -> 0 | I134: =F134 -> 0
B135: OFFICE EQUIPMENT | C135: =3*12 -> 36 | E135: =D135*0.12 -> 0 | F135: =E135 -> 0 | G135: =E135-F135 -> 0
B137: TOTAL | D137: 0 | E137: =SUM(E133:E135) -> 0 | F137: =SUM(F133:F135) -> 0 | G137: =SUM(G133:G135) -> 0
A139: SEP 2020 | C139: MONTHS | D139: AMOUNT NET OF VAT | E139: INPUT TAX | F139: ALLOWABLE DEDUCTIONS | G139: BALANCE OF INPUT TAX | H139: TO BE CARRIED UNTIL | I139: PER MONTH
B140: FURNITURE & FIXTURES | C140: =3*12 -> 36 | D140: 0 | E140: =D140*0.12 -> 0 | F140: =E140 -> 0 | G140: =E140-F140 -> 0 | I140: 0
B141: LEASEHOLD IMPROVEMENT | C141: =5*12 -> 60 | D141: 0 | E141: =D141*0.12 -> 0 | F141: =E141/C141 -> 0 | G141: =E141-F141 -> 0 | I141: =F141 -> 0
B142: OFFICE EQUIPMENT | C142: =3*12 -> 36 | E142: =D142*0.12 -> 0 | F142: =E142 -> 0 | G142: =E142-F142 -> 0
B144: TOTAL | D144: 0 | E144: =SUM(E140:E142) -> 0 | F144: =SUM(F140:F142) -> 0 | G144: =SUM(G140:G142) -> 0
A146: OCT 2020 | C146: MONTHS | D146: AMOUNT NET OF VAT | E146: INPUT TAX | F146: ALLOWABLE DEDUCTIONS | G146: BALANCE OF INPUT TAX | H146: TO BE CARRIED UNTIL | I146: PER MONTH
B147: FURNITURE & FIXTURES | C147: =3*12 -> 36 | D147: 0 | E147: =D147*0.12 -> 0 | F147: =E147 -> 0 | G147: =E147-F147 -> 0 | I147: 0
B148: LEASEHOLD IMPROVEMENT | C148: =5*12 -> 60 | D148: 0 | E148: =D148*0.12 -> 0 | F148: =E148/C148 -> 0 | G148: =E148-F148 -> 0 | I148: =F148 -> 0
...

Sheet VAT Schedule
A2: Shirefolk Ventures Inc.
A3: YEAR 2025
B4: Zero-Rated Sales | C4: Vatable-Sales | D4: Vat on Sales (Output Tax) | E4: Input Tax Carried Over | F4: VAT on Purchases (Goods Not Qual for Input Tax) | G4: VAT on Purchases (Services Not Qualified for Input Tax) | H4: Purchases Capital Goods | I4: Purchases of Goods (Other than Capital Goods) | J4: Purchases of Services | K4: Vat on Purchases of Capital Goods (Input Tax) | L4: Allowable Vat on Purchases of Capital Goods (Input Tax) | M4: Vat on Purchases of Goods other than Capital Goods & Services (Input Tax) | N4: Total Vat on Purchases (Input Tax) | O4: VAT Payable | P4: in eBIR Form | Q4: difference | R4: Def | S4: Amount Filed | T4: Date Filed | U4: Date Paid | V4: SLSP
A6: Beg. Bal. | O6: -3893209.4
A7: January | B7: =SI!S33+SI!S54 -> 3584965.3 | C7: =SUM(SI!T2:T56) -> 469932.75 | D7: =C7*0.12 -> 56391.93 | E7: =O6 -> -3893209.4 | F7: - | G7: 31021.02 | H7: 0 | I7: 25893.44 | J7: 1177215.4 | K7: =H7*0.12 -> 0 | L7: ='Schedule of CG Input Tax'!BZ144 -> 2867.5801 | M7: =SUM(I7:J7)*0.12 -> 144373.06 | N7: =SUM(K7:M7) -> 147240.64 | O7: =$D7+$E7-$N7 -> -3984058.1
A8: February | B8: =SI!S86 -> 1792482.7 | C8: =SUM(SI!T58:T94) -> 283831.88 | D8: =C8*0.12 -> 34059.826 | E8: =O7 -> -3984058.1 | F8: 504 | G8: 10390 | H8: 0 | I8: 50742.38 | J8: 1199276.3 | K8: =H8*0.12 -> 0 | L8: ='Schedule of CG Input Tax'!CA144 -> 2867.5801 | M8: =SUM(I8:J8)*0.12 -> 150002.24 | N8: =SUM(K8:M8) -> 152869.82 | O8: =$D8+$E8-$N8 -> -4102868.1
A9: March | B9: 0 | C9: =SUM(SI!T96:T132) -> 153426.48 | D9: =C9*0.12 -> 18411.178 | E9: =O8 -> -4102868.1 | F9: 3270 | G9: 21317 | H9: 0 | I9: 34955.36 | J9: 1219543.8 | K9: =H9*0.12 -> 0 | L9: ='Schedule of CG Input Tax'!CB144 -> 2867.5801 | M9: =SUM(I9:J9)*0.12 -> 150539.9 | N9: =SUM(K9:M9) -> 153407.48 | O9: =$D9+$E9-$N9 -> -4237864.4
A10: 1st Quarter | B10: =SUM(B7:B9) -> 5377448 | C10: =SUM(C7:C9) -> 907191.12 | D10: =C10*0.12 -> 108862.93 | E10: =O6 -> -3893209.4 | F10: =SUM(F7:F9) -> 3774 | G10: =SUM(G7:G9) -> 62728.02 | H10: =SUM(H7:H9) -> 0 | I10: =SUM(I7:I9) -> 111591.18 | J10: =SUM(J7:J9) -> 3596035.5 | K10: =SUM(K7:K9) -> 0 | L10: =SUM(L7:L9) -> 8602.7403 | M10: =SUM(M7:M9) -> 444915.2 | N10: =SUM(N7:N9) -> 453517.94 | O10: =$D10+$E10-$N10-0.01 -> -4237864.4 | P10: -4225435.8 | Q10: =O10-P10 -> -12428.576
K11: =K10-'Xero Purchases G 2025'!I143 -> 0
A12: Amended
A13: Beg. Bal. | O13: -3893209.4
A14: January | B14: =sum('Q1 Amendment'!H282:H295) -> 1594105.1 | C14: =sum('Q1 Amendment'!G25:G30,'Q1 Amendment'!G32:G37,'Q1 Amendment'!G39:G100,'Q1 Amendment'!G261:G264) -> 535735 | D14: =C14*0.12 -> 64288.201 | E14: =O13 -> -3893209.4 | F14: 0 | G14: =SUM('Xero Purchases S 2025'!I20:I21) -> 450 | H14: =SUM('Xero Purchases G 2025'!E148:E149) -> 0 | I14: =SUM('Xero Purchases G 2025'!F34:F49) -> 25893.44 | J14: =SUM('Xero Purchases S 2025'!I35:I49) -> 1202218.4 | K14: =H14*0.12 -> 0 | L14: ='Schedule of CG Input Tax'!BZ144 -> 2867.5801 | M14: =SUM(I14:J14)*0.12 -> 147373.42 | N14: =SUM(K14:M14) -> 150241 | O14: =$D14+$E14-$N14 -> -3979162.2
A15: February | B15: =sum('Q1 Amendment'!H296:H309) -> 1594105.1 | C15: =sum('Q1 Amendment'!G101:G102,'Q1 Amendment'!G104:G178) -> 549685.9 | D15: =C15*0.12 -> 65962.308 | E15: =O14 -> -3979162.2 | F15: =SUM('Xero Purchases G 2025'!F10:F12) -> 504 | G15: =sum('Xero Purchases S 2025'!I23:I26) -> 10390 | H15: 0 | I15: =sum('Xero Purchases G 2025'!F51:F73) -> 50742.38 | J15: =sum('Xero Purchases S 2025'!I51:I65) -> 1197826.5 | K15: =H15*0.12 -> 0 | L15: ='Schedule of CG Input Tax'!CA144 -> 2867.5801 | M15: =SUM(I15:J15)*0.12 -> 149828.27 | N15: =SUM(K15:M15) -> 152695.85 | O15: =$D15+$E15-$N15 -> -4065895.7
A16: March | B16: =sum('Q1 Amendment'!H310:H323) -> 1594105.1 | C16: =sum('Q1 Amendment'!G179:G248) -> 360326.05 | D16: =C16*0.12 -> 43239.126 | E16: =O15 -> -4065895.7 | F16: =SUM('Xero Purchases G 2025'!F14:F30) -> 3270 | G16: =SUM('Xero Purchases S 2025'!I28:I31) -> 2817 | H16: 0 | I16: =sum('Xero Purchases G 2025'!F75:F89) -> 34955.36 | J16: =SUM('Xero Purchases S 2025'!I67:I82) -> 1224259.3 | K16: =H16*0.12 -> 0 | L16: ='Schedule of CG Input Tax'!CB144 -> 2867.5801 | M16: =SUM(I16:J16)*0.12 -> 151105.76 | N16: =SUM(K16:M16) -> 153973.34 | O16: =$D16+$E16-$N16 -> -4176629.9
A17: 1st Quarter Amended | B17: =SUM(B14:B16) -> 4782315.4 | C17: =SUM(C14:C16) -> 1445747 | D17: =C17*0.12 -> 173489.63 | E17: =O13 -> -3893209.4 | F17: =SUM(F14:F16) -> 3774 | G17: =SUM(G14:G16) -> 13657 | H17: =SUM(H14:H16) -> 0 | I17: =SUM(I14:I16) -> 111591.18 | J17: =SUM(J14:J16) -> 3624304.2 | K17: =SUM(K14:K16) -> 0 | L17: =SUM(L14:L16) -> 8602.7403 | M17: =SUM(M14:M16) -> 448307.45 | N17: =SUM(N14:N16) -> 456910.19 | O17: =$D17+$E17-$N17 -> -4176629.9 | Q17: =O17-P17 -> -4176629.9
B18: =B17-'Q1 Amendment'!G327 -> 9.3132257e-10 | C18: =C17-'Q1 Amendment'!G268 -> 0.0042857144 | F18: =F17-'Xero Purchases G 2025'!F31 -> 0 | H18: =H17-'Xero Purchases G 2025'!E150 -> 0 | I18: =I17-'Xero Purchases G 2025'!F90 -> 0 | J18: =J17-'Xero Purchases S 2025'!I83 -> 0 | K18: =K17-'Xero Purchases G 2025'!I150 -> 0
A20: April | E20: =O10 -> -4237864.4 | N20: =SUM(K20:M20) -> 0 | O20: =$D20+$E20-$N20 -> -4237864.4
A21: May | E21: =O20 -> -4237864.4 | N21: =SUM(K21:M21) -> 0 | O21: =$D21+$E21-$N21 -> -4237864.4
A22: June | E22: =O21 -> -4237864.4 | N22: =SUM(K22:M22) -> 0 | O22: =$D22+$E22-$N22 -> -4237864.4
A23: 2nd Quarter | B23: =SUM(B20:B22) -> 0 | C23: =SUM(C20:C22) -> 0 | D23: =C23*0.12 -> 0 | E23: =E20 -> -4237864.4 | N23: =SUM(K23:M23) -> 0 | O23: =D23+E23-N23 -> -4237864.4 | Q23: =O23-P23 -> -4237864.4
A25: July | E25: =O23 -> -4237864.4 | N25: =SUM(K25:M25) -> 0 | O25: =$D25+$E25-$N25 -> -4237864.4
A26: August | E26: =O25 -> -4237864.4 | N26: =SUM(K26:M26) -> 0 | O26: =$D26+$E26-$N26 -> -4237864.4
A27: September | E27: =O26 -> -4237864.4 | N27: =SUM(K27:M27) -> 0 | O27: =$D27+$E27-$N27 -> -4237864.4
A28: 3rd Quarter | B28: =SUM(B25:B27) -> 0 | C28: =SUM(C25:C27) -> 0 | D28: =C28*0.12 -> 0 | E28: =E25 -> -4237864.4 | F28: =SUM(F25:F27) -> 0 | G28: =SUM(G25:G27) -> 0 | H28: =SUM(H25:H27) -> 0 | I28: =SUM(I25:I27) -> 0 | J28: =SUM(J25:J27) -> 0 | K28: =SUM(K25:K27) -> 0 | M28: =SUM(M25:M27) -> 0 | N28: =SUM(L28:M28) -> 0 | O28: =D28+E28-N28 -> -4237864.4 | Q28: =O28-P28 -> -4237864.4
A30: Oct | C30: 0 | D30: =C30*12% -> 0 | E30: =O28 -> -4237864.4 | K30: =H30*0.12 -> 0 | M30: =(SUM(I30:J30)*0.12) -> 0 | N30: =SUM(K30:M30) -> 0 | O30: =$D30+$E30-$N30 -> -4237864.4
A31: Nov | C31: 0 | D31: =C31*12% -> 0 | E31: =O30 -> -4237864.4 | K31: =H31*0.12 -> 0 | M31: =(SUM(I31:J31)*0.12) -> 0 | N31: =SUM(K31:M31) -> 0 | O31: =$D31+$E31-$N31 -> -4237864.4
A32: Dec | C32: 0 | D32: =C32*12% -> 0 | E32: =O31 -> -4237864.4 | K32: =H32*0.12 -> 0 | M32: =(SUM(I32:J32)*0.12) -> 0 | N32: =SUM(K32:M32) -> 0 | O32: =$D32+$E32-$N32-0.01 -> -4237864.4
A33: 4th Quarter | B33: =SUM(B30:B32) -> 0 | C33: =SUM(C30:C32) -> 0 | D33: =C33*0.12 -> 0 | E33: =O28 -> -4237864.4 | F33: =SUM(F30:F32) -> 0 | G33: =SUM(G30:G32) -> 0 | H33: =SUM(H30:H32) -> 0 | I33: =SUM(I30:I32) -> 0 | J33: =SUM(J30:J32) -> 0 | K33: =SUM(K30:K32) -> 0 | L33: =SUM(L30:L32) -> 0 | M33: =SUM(M30:M32) -> 0 | N33: =SUM(N30:N32) -> 0 | O33: =D33+E33-N33 -> -4237864.4
C34: =C33 -> 0 | F34: =F33 -> 0 | H34: =H33 -> 0 | I34: =I33 -> 0 | J34: =J33 -> 0 | K34: =K33 -> 0
A35: Year Total | B35: =B10+B23+B28+B33 -> 5377448 | C35: =C10+C23+C28+C33 -> 907191.12 | D35: =D10+D23+D28+D33 -> 108862.93 | E35: =E10+E23+E28+E33 -> -16606803 | F35: =F10+F23+F28+F33 -> 3774 | G35: =G10+G23+G28+G33 -> 62728.02 | H35: =H10+H23+H28+H33 -> 0 | I35: =I10+I23+I28+I33 -> 111591.18 | ... N35: =N10+N23+N28+N33 -> 453517.94 | O35: =O33 -> -4237864.4

Sheet SI
A1: SI | B1: Date | C1: Invoice Number | D1: Client Name | E1: OR Amount | F1: Description | G1: Mode of Payment | H1: Cash / Check Deposit | I1: Remarks | J1: Type of Service | K1: GROSS | L1: CWT | M1: TOTAL | O1: CC Fee/Charge | P1: Net Amount | Q1: Checking | S1: GROSS AMOUNT | T1: NET AMOUNT | U1: VAT AMOUNT
A2: 0353 | B2: 45660 | C2: INV-2426 | D2: Timedly Solutions, Inc. | E2: 3500 | F2: Virtual Office, Jan 1, 2025 - Jan 31, 2025 | G2: Check | H2: UBP | I2: Security Bank 0000509610 | J2: Virtual Office | K2: 3500 | S2: =E2 -> 3500 | T2: =S2/1.12 -> 3125 | U2: =T2*12% -> 375 | V2: =T2+U2-S2 -> 0
A3: 0354 | B3: 45663 | C3: INV-2435 | D3: Intertool Precision Group Inc | E3: 2100 | F3: Meeting Room 3, 3:00 pm to 6:00 pm | G3: Maya QR Standee | H3: UBP | J3: Meeting Rooms | K3: 2100 | O3: 9.38 | P3: =E3-O3 -> 2090.62 | S3: =E3 -> 2100 | T3: =S3/1.12 -> 1875 | U3: =T3*12% -> 225 | V3: =T3+U3-S3 -> 0
A4: 0355 | D4: CANCELLED | S4: =E4 | T4: =S4/1.12 -> 0 | U4: =T4*12% -> 0 | V4: =T4+U4-S4 -> 0
A5: 0356 | B5: 45664 | C5: INV-2437 | D5: Bluvision Surveillance and Analytics Inc. | E5: 4500 | F5: Meeting Room 1, Jan 8, 2025, 9:00 am to 1:00 pm | G5: Maya QR Standee | H5: UBP | J5: Meeting Rooms | K5: 4500 | O5: 20.09 | P5: =E5-O5 -> 4479.91 | S5: =E5 -> 4500 | T5: =S5/1.12 -> 4017.8571 | U5: =T5*12% -> 482.14286 | V5: =T5+U5-S5 -> 0
A6: 0357 | B6: 45665 | C6: INV-2467 | D6: Lawrence Alexander | E6: 20 | F6: Printing | G6: Maya QR Standee | H6: UBP | J6: Add-Ons | K6: 20 | O6: 0.09 | P6: =E6-O6 -> 19.91 | S6: =E6 -> 20 | T6: =S6/1.12 -> 17.857143 | U6: =T6*12% -> 2.1428571 | V6: =T6+U6-S6 -> 0
A7: 0358 | B7: 45665 | C7: INV-2438 | D7: Limuel Libres | E7: 350 | F7: Wholeday Flypass (Student) | G7: Cash | H7: MBTC | J7: Walk-Ins | K7: 350 | S7: =E7 -> 350 | T7: =S7/1.12 -> 312.5 | U7: =T7*12% -> 37.5 | V7: =T7+U7-S7 -> 0
A8: 0359 | B8: 45666 | C8: INV-2441 | D8: Margarita Bariring | E8: 5500 | F8: Monthly Flypass | G8: Maya Card | H8: UBP | J8: Monthly Membership | K8: 5500 | O8: 180.6 | P8: =E8-O8 -> 5319.4 | S8: =E8 -> 5500 | T8: =S8/1.12 -> 4910.7143 | U8: =T8*12% -> 589.28571 | V8: =T8+U8-S8 -> 0
A9: 0360 | B9: 45666 | C9: INV-2442 | D9: MARRO FASHION STYLING STUDIO | E9: 2400 | F9: Meeting Room 2, 9:30 am to 12:00 nn | G9: Maya Card | H9: UBP | J9: Meeting Rooms | K9: 2400 | O9: 78.81 | P9: =E9-O9 -> 2321.19 | S9: =E9 -> 2400 | T9: =S9/1.12 -> 2142.8571 | U9: =T9*12% -> 257.14286 | V9: =T9+U9-S9 -> 0
A10: 0361 | B10: 45666 | C10: INV-2443 | D10: F.A BAUTISTA & PARTNERS | E10: 5500 | F10: Meeting Room 3, January 10, 2025, 8:30 am to 5:00 pm | G10: Maya QR Standee | H10: UBP | J10: Meeting Rooms | K10: 5500 | O10: 24.55 | P10: =E10-O10 -> 5475.45 | Q10: =SUM(P8:P10) -> 13116.04 | S10: =E10 -> 5500 | T10: =S10/1.12 -> 4910.7143 | U10: =T10*12% -> 589.28571 | V10: =T10+U10-S10 -> 0
A11: 0362 | B11: 45666 | C11: INV-2436 | D11: Moom Health Services Corp | E11: 4000 | F11: Virtual Office, Jan 4, 2025 - Feb 3, 2025 | G11: Check | H11: UBP | I11: BDO 0000158359 | J11: Virtual Office | K11: 4000 | S11: =E11 -> 4000 | T11: =S11/1.12 -> 3571.4286 | U11: =T11*12% -> 428.57143 | V11: =T11+U11-S11 -> 0
A12: 0363 | B12: 45667 | C12: INV-2468 | D12: Lawrence Alexander | E12: 10 | F12: Printing | G12: Maya QR Standee | H12: UBP | J12: Add-Ons | K12: 10 | O12: 0.04 | P12: =E12-O12 -> 9.96 | S12: =E12 -> 10 | T12: =S12/1.12 -> 8.9285714 | U12: =T12*12% -> 1.0714286 | V12: =T12+U12-S12 -> 0
A13: 0364 | B13: 45667 | C13: INV-2445 | D13: Kevin Carmelina | E13: 1600 | F13: Meeting Room 2, 1:00 pm to 3:00 pm | G13: Maya Card | H13: UBP | J13: Meeting Rooms | K13: 1600 | O13: 52.54 | P13: =E13-O13 -> 1547.46 | S13: =E13 -> 1600 | T13: =S13/1.12 -> 1428.5714 | U13: =T13*12% -> 171.42857 | V13: =T13+U13-S13 -> 0
A14: 0365 | D14: CANCELLED | S14: =E14 | T14: =S14/1.12 -> 0 | U14: =T14*12% -> 0 | V14: =T14+U14-S14 -> 0
A15: 0366 | D15: CANCELLED | S15: =E15 | T15: =S15/1.12 -> 0 | U15: =T15*12% -> 0 | V15: =T15+U15-S15 -> 0
A16: 0367 | B16: 45667 | C16: INV-2446 | D16: Paolo De Asis | E16: 600 | F16: Wholeday Flypass | G16: Cash | H16: MBTC | K16: 600 | S16: =E16 -> 600 | T16: =S16/1.12 -> 535.71429 | U16: =T16*12% -> 64.285714 | V16: =T16+U16-S16 -> 0
A17: 0368 | B17: 45667 | C17: INV-2447 | D17: Brey Reyes | E17: 2400 | F17: Meeting Room 2, 4:30 pm to 6:00 pm | G17: Maya Card | H17: UBP | J17: Walk-Ins | K17: 2400 | O17: 78.81 | P17: =E17-O17 -> 2321.19 | Q17: =P13+P17+P19+AR!N127 -> 22073.19 | S17: =E17 -> 2400 | T17: =S17/1.12 -> 2142.8571 | U17: =T17*12% -> 257.14286 | V17: =T17+U17-S17 -> 0
A18: 0369 | B18: 45668 | C18: INV-2450 | D18: AIMS Industrial Supplies | E18: 84400 | F18: Meeting Room 1, 2 and 3, February 3-7, 2025 | G18: AR 435 (42200) Maya Card (42200) | H18: UBP | I18: UB1297258 | J18: Meeting Rooms | K18: 84400 | O18: 1385.72 | P18: =42200-O18 -> 40814.28 | Q18: =42200-O18 -> 40814.28 | S18: =E18 -> 84400 | T18: =S18/1.12 -> 75357.143 | U18: =T18*12% -> 9042.8571 | V18: =T18+U18-S18 -> 0
A19: 0370 | B19: 45670 | C19: INV-2448 | D19: E Gonzales Law Office | E19: 17322.63 | F19: Use of Address, Jan 15, 2025 to Dec 31, 2025 | G19: Maya Card (Jan 10) | H19: UBP | J19: Virtual Office | K19: 17322.63 | O19: 568.83 | P19: =E19-O19 -> 16753.8 | S19: =E19 -> 17322.63 | T19: =S19/1.12 -> 15466.634 | U19: =T19*12% -> 1855.9961 | V19: =T19+U19-S19 -> 0
A20: 0371 | B20: 45670 | C20: INV-2452 | D20: Arkiya Francine Orosco | E20: 2400 | F20: Meeting Room 2, Jan 13, 2025, 9:00 am to 12:00 pm | G20: Cash | H20: MBTC | J20: Meeting Rooms | K20: 2400 | S20: =E20 -> 2400 | T20: =S20/1.12 -> 2142.8571 | U20: =T20*12% -> 257.14286 | V20: =T20+U20-S20 -> 0
A21: 0372 | D21: CANCELLED | S21: =E21 | T21: =S21/1.12 -> 0 | U21: =T21*12% -> 0 | V21: =T21+U21-S21 -> 0
A22: 0373 | B22: 45670 | C22: INV-2451 | D22: Sightechs Corporation | E22: 24000 | F22: Virtual Office, Jan 1, 2025 - Jun 30, 2025 | G22: Bank Transfer | H22: UBP | I22: UB1060687 | J22: Virtual Office | K22: 24000 | S22: =E22 -> 24000 | T22: =S22/1.12 -> 21428.571 | U22: =T22*12% -> 2571.4286 | V22: =T22+U22-S22 -> 0
A23: 0374 | B23: 45671 | C23: INV-2432/INV-2433/INV-2428/INV-2429/INV-2430/INV-2431 | D23: iHub Solutions (Philippines) Inc. | E23: 127841.68 | F23: Meeting Room 2, 7am to 4pm, Jan (full) , Feb - Apr (DP) & Locker Rental (jan-Apr) & Virtual Office (Jan 20 - Dec 31, 2025) | G23: Bank Transfer | H23: UBP | I23: UB799581 | J23: Meeting Rooms | K23: 127841.68 | S23: =E23 -> 127841.68 | T23: =S23/1.12 -> 114144.36 | U23: =T23*12% -> 13697.323 | V23: =T23+U23-S23 -> 0
A24: 0375 | B24: 45671 | C24: INV-2427/INV-2425 | D24: Recruitgo Philippines Inc. | E24: =8500+34300 -> 42800 | F24: Meeting Room 1 rental, Jan 9, 16, 23, 30 & Locker Rental (Jan 2025) | G24: Bank Transfer | H24: UBP | I24: UB1200210 | J24: Meeting Rooms | K24: =8500+34300 -> 42800 | S24: =E24 -> 42800 | T24: =S24/1.12 -> 38214.286 | U24: =T24*12% -> 4585.7143 | V24: =T24+U24-S24 -> 0
A25: 0376 | B25: 45672 | C25: INV-2454 | D25: Ramona Tagum | E25: 80 | F25: Printing Bkwh P4 x 20 pages | G25: Cash | H25: UBP | J25: Add-Ons | K25: 80 | S25: =E25 -> 80 | T25: =S25/1.12 -> 71.428571 | U25: =T25*12% -> 8.5714286 | V25: =T25+U25-S25 -> 0
A26: 0377 | B26: 45672 | C26: INV-2453 | D26: BRANDSPEAKASIA INC. | E26: 19480.75 | F26: Use of address, Jan 7, 2025 to Dec 31, 2025 | G26: Bank Transfer | H26: UBP | I26: UB495547 | J26: Virtual Office | K26: 19480.75 | S26: =E26 -> 19480.75 | T26: =S26/1.12 -> 17393.527 | U26: =T26*12% -> 2087.2232 | V26: =T26+U26-S26 -> 0
A27: 0378 | D27: CANCELLED | J27: Meeting Rooms | S27: =E27 | T27: =S27/1.12 -> 0 | U27: =T27*12% -> 0 | V27: =T27+U27-S27 -> 0
A28: 0379 | B28: 45672 | C28: INV-2456 | D28: CoinAlpha Inc. | E28: 6900 | F28: Meeting Room 1, Jan 15, 2025, 11:00 am to 5:00 pm | G28: Maya Card | H28: UBP | J28: Add-Ons | K28: 6900 | O28: 226.58 | P28: =E28-O28 -> 6673.42 | Q28: =P28 -> 6673.42 | S28: =E28 -> 6900 | T28: =S28/1.12 -> 6160.7143 | U28: =T28*12% -> 739.28571 | V28: =T28+U28-S28 -> 0
A29: 0380 | B29: 45672 | C29: INV-2457 | D29: Cyril Cayasa | E29: 368 | F29: Printing P4 x 92 pages | G29: Maya QR Standee | H29: UBP | J29: Add-Ons | K29: 368 | O29: 1.64 | P29: =E29-O29 -> 366.36 | Q29: =P29 -> 366.36 | S29: =E29 -> 368 | T29: =S29/1.12 -> 328.57143 | U29: =T29*12% -> 39.428571 | V29: =T29+U29-S29 -> 0
A30: 0381 | B30: 45673 | C30: INV-2458 | D30: Norio-Olegario Consultancy Inc. | E30: 600 | F30: Printing B&W (P2x280 pages) ; Colored (P10x 4 pages) | G30: Maya QR Standee | H30: UBP | J30: Add-Ons | K30: 600 | O30: 2.68 | P30: =E30-O30 -> 597.32 | S30: =E30 -> 600 | T30: =S30/1.12 -> 535.71429 | U30: =T30*12% -> 64.285714 | V30: =T30+U30-S30 -> 0
A31: 0382 | B31: 45673 | C31: INV-2460 | D31: Cyril Cayasa | E31: 12 | F31: Printing B&W P2 x 6 | G31: Maya QR Standee | H31: UBP | J31: Add-Ons | K31: 12 | O31: 0.05 | P31: =E31-O31 -> 11.95 | S31: =E31 -> 12 | T31: =S31/1.12 -> 10.714286 | U31: =T31*12% -> 1.2857143 | V31: =T31+U31-S31 -> 0
A32: 0383 | B32: 45674 | C32: INV-2461 | D32: Leo Manabat | E32: 1680 | F32: Meeting room 3, 8 pm to 10 pm (w/ after hour access) | G32: Maya Card (Jan 16) | H32: UBP | J32: Meeting Rooms | K32: 1680 | O32: 55.17 | P32: =E32-O32 -> 1624.83 | Q32: =SUM(P30:P32) -> 2234.1 | S32: =E32 -> 1680 | T32: =S32/1.12 -> 1500 | U32: =T32*12% -> 180 | V32: =T32+U32-S32 -> 0
A33: 0384 | B33: 45674 | C33: INV-2393 | D33: QBE Group Shared Services Ltd- Philippine Branch | E33: 1703921.3 | F33: Private Office and Parking Rental January 2025 | G33: Check | H33: MBTC | I33: BPI 0001040674 | J33: Private Office | K33: 1792482.7 | L33: 88561.4 | M33: =K33-L33 -> 1703921.3 | N33: =E33-M33 -> 0.01 | S33: =K33 -> 1792482.7 | T33: 0 | U33: =T33*12% -> 0 | V33: 0
A34: 0385 | B34: 45674 | C34: INV-2455 | D34: SG ECOMMERCE CENTRE PHILIPPINES CORP. | E34: 4000 | F34: Virtual Office, Jan14, 2024 - Feb 13, 2025 | G34: Check | H34: UBP | I34: BDO 0000105976 | J34: Virtual Office | K34: 4000 | S34: =E34 -> 4000 | T34: =S34/1.12 -> 3571.4286 | U34: =T34*12% -> 428.57143 | V34: =T34+U34-S34 -> 0
A35: 0386 | B35: 45674 | C35: INV-2459 | D35: Zenko Enterprises OPC | E35: 15763.39 | F35: Use of Address, Feb 1, 2025 - Dec 31, 2025 | G35: Bank Transfer | H35: UBP | I35: S84967905 | J35: Virtual Office | K35: 16500 | L35: =K35/1.12*0.05 -> 736.60714 | M35: =K35-L35 -> 15763.393 | N35: =E35-M35 -> -0.0028571429 | S35: =K35 -> 16500 | T35: =S35/1.12 -> 14732.143 | U35: =T35*12% -> 1767.8571 | V35: =T35+U35-S35 -> 0
A36: 0387 | D36: CANCELLED | S36: =E36 | T36: =S36/1.12 -> 0 | U36: =T36*12% -> 0 | V36: =T36+U36-S36 -> 0
A37: 0388 | B37: 45677 | C37: INV-2337 | D37: DrinkAid Corp. | E37: 20903.31 | F37: Use of Address, November 3, 2024 to December 31, 2025 | G37: Maya Card | H37: UBP | J37: Virtual Office | K37: 20903.31 | O37: 686.4 | P37: =E37-O37 -> 20216.91 | S37: =E37 -> 20903.31 | T37: =S37/1.12 -> 18663.67 | U37: =T37*12% -> 2239.6404 | V37: =T37+U37-S37 -> 0
A38: 0389 | B38: 45677 | C38: INV-2370 | D38: Norio-Olegario Consultancy Inc. | E38: 24522.63 | F38: Use of Address and Locker rental, November 15, 2024 to December 31, 2025 | G38: Maya Card | H38: UBP | J38: Virtual Office | K38: 24522.63 | O38: 805.25 | P38: =E38-O38 -> 23717.38 | Q38: =SUM(P37:P38) -> 43934.29 | S38: =E38 -> 24522.63 | T38: =S38/1.12 -> 21895.205 | U38: =T38*12% -> 2627.4246 | V38: =T38+U38-S38 -> 0
A39: 0390 | D39: CANCELLED | S39: =E39 | T39: =S39/1.12 -> 0 | U39: =T39*12% -> 0 | V39: =T39+U39-S39 -> 0
A40: 0391 | B40: 45677 | C40: INV-2462 | D40: Radiance Image Consultancy and Training Inc. | E40: 18580.68 | F40: Use of Address, December 20, 2024 to December 31, 2025 | G40: Bank Transfer | H40: UBP | I40: UB495547 | J40: Meeting Rooms | K40: 18580.68 | S40: =E40 -> 18580.68 | T40: =S40/1.12 -> 16589.893 | U40: =T40*12% -> 1990.7871 | V40: =T40+U40-S40 -> 0
A41: 0392 | B41: 45677 | C41: INV-2470 | D41: Daisy Ree Kate Gomintong | E41: 900 | F41: Whole Day Flypass (After Hour Access) | G41: Maya QR Standee | H41: UBP | J41: Walk-Ins | K41: 900 | O41: 4.02 | P41: =E41-O41 -> 895.98 | Q41: =P41 -> 895.98 | S41: =E41 -> 900 | T41: =S41/1.12 -> 803.57143 | U41: =T41*12% -> 96.428571 | V41: =T41+U41-S41 -> 0
A42: 0393 | B42: 45679 | C42: INV-2471 | D42: Paolo Luigi De Asis | E42: 600 | F42: Wholeday Flypass | G42: Cash | H42: MBTC | J42: Walk-Ins | K42: 600 | S42: =E42 -> 600 | T42: =S42/1.12 -> 535.71429 | U42: =T42*12% -> 64.285714 | V42: =T42+U42-S42 -> 0
A43: 0394 | B43: 45680 | C43: INV-2472 | D43: Amiel Cruz | E43: 20 | F43: Printing (P10 x 2pages) | G43: Maya QR Standee | H43: UBP | J43: Add-Ons | K43: 20 | O43: 0.09 | P43: =E43-O43 -> 19.91 | Q43: =P43 -> 19.91 | S43: =E43 -> 20 | T43: =S43/1.12 -> 17.857143 | U43: =T43*12% -> 2.1428571 | V43: =T43+U43-S43 -> 0
A44: 0395 | B44: 45680 | C44: INV-2473 | D44: Innoprince Inc. | E44: 1400 | F44: Meeting Room 3, Jan 23, 2025, 1:00 pm to 3:00 pm | G44: Bank Transfer | H44: UBP | I44: UB457951 | J44: Meeting Rooms | K44: 1400 | S44: =E44 -> 1400 | T44: =S44/1.12 -> 1250 | U44: =T44*12% -> 150 | V44: =T44+U44-S44 -> 0
A45: 0396 | B45: 45681 | C45: INV-2474 | D45: Cabauatan Lee-Rosales & Co, CPA's | E45: 6300 | F45: Meeting Room 2, January 24, 2025, 9:00 am to 6:00 pm | G45: AR 442 (3150) Cash (3150) | H45: MBTC | I45: UB574440 | J45: Meeting Rooms | K45: 6300 | S45: =E45 -> 6300 | T45: =S45/1.12 -> 5625 | U45: =T45*12% -> 675 | V45: =T45+U45-S45 -> 0
A46: 0397 | B46: 45681 | C46: INV-2475 | D46: The Feast Bellevue AM | E46: 10500 | F46: Event Space rental, 3pm to 6pm, Jan 26, 2025 | G46: Bank Transfer | H46: UBP | I46: UB387801 | J46: Events | K46: 10500 | S46: =E46 -> 10500 | T46: =S46/1.12 -> 9375 | U46: =T46*12% -> 1125 | V46: =T46+U46-S46 -> 0
A47: 0398 | B47: 45681 | C47: INV-2476 | D47: Annie Ferreras | E47: 600 | F47: Wholeday Flypass | G47: Cash | H47: MBTC | K47: 600 | S47: =E47 -> 600 | T47: =S47/1.12 -> 535.71429 | U47: =T47*12% -> 64.285714 | V47: =T47+U47-S47 -> 0
A48: 0399 | D48: CANCELLED | S48: =E48 | T48: =S48/1.12 -> 0 | U48: =T48*12% -> 0 | V48: =T48+U48-S48 -> 0
A49: 0400 | B49: 45684 | C49: INV-2469 | D49: SwipeEdge Corp. | E49: 48000 | F49: Virtual Office, Jan 1, 2025 - Jun 30, 2025 | G49: Bank Transfer (24000) Check (24000) | H49: MBTC | I49: 589252 / Metrobank 0968586559 | J49: Virtual Office | K49: 48000 | S49: =E49 -> 48000 | T49: =S49/1.12 -> 42857.143 | U49: =T49*12% -> 5142.8571 | V49: =T49+U49-S49 -> 0
A50: 0401 | B50: 45684 | C50: INV-2477 | D50: Lorelei D. Jane | E50: 448 | F50: Access Card (LPOG- 0749 Lorelei D. Jane) | G50: Cash | H50: MBTC | J50: Add-Ons | K50: 448 | S50: =E50 -> 448 | T50: =S50/1.12 -> 400 | U50: =T50*12% -> 48 | V50: =T50+U50-S50 -> 0
A51: 0402 | B51: 45684 | C51: INV-2478 | D51: VTMCI | E51: 9700 | F51: Meeting Room 1 Rent, 10 am to 7pm | G51: Maya Card | H51: UBP | J51: Meeting Rooms | K51: 9700 | O51: 318.52 | P51: =E51-O51 -> 9381.48 | S51: =E51 -> 9700 | T51: =S51/1.12 -> 8660.7143 | U51: =T51*12% -> 1039.2857 | V51: =T51+U51-S51 -> 0
A52: 0403 | D52: CANCELLED | S52: =E52 | T52: =S52/1.12 -> 0 | U52: =T52*12% -> 0 | V52: =T52+U52-S52 -> 0
A53: 0404 | B53: 45685 | C53: INV-2479 | D53: Rusell John Santiaguel | E53: 35 | F53: Printing | G53: Maya QR Standee | H53: UBP | J53: Add-Ons | K53: 35 | O53: 0.16 | P53: =E53-O53 -> 34.84 | S53: =E53 -> 35 | T53: =S53/1.12 -> 31.25 | U53: =T53*12% -> 3.75 | V53: =T53+U53-S53 -> 0
A54: 0405 | B54: 45688 | C54: INV-2440 | D54: QBE Group Shared Services Ltd- Philippine Branch | E54: 1703921.3 | F54: Private Office and Parking Rental February 2025 | G54: Check | H54: UBP | I54: BPI 1051484 | J54: Private Office | K54: 1792482.7 | L54: 88561.4 | M54: =K54-L54 -> 1703921.3 | N54: =E54-M54 -> 0.01 | S54: 1792482.7 | T54: 0 | U54: =T54*12% -> 0 | V54: 0
A55: 0406 | B55: 45688 | C55: INV-2480 | D55: Paolo Luigi De Asis | E55: 550 | F55: Wholeday Flypass | G55: Cash | H55: MBTC | J55: Walk-Ins | K55: 550 | S55: =E55 -> 550 | T55: =S55/1.12 -> 491.07143 | U55: =T55*12% -> 58.928571 | V55: =T55+U55-S55 -> 0
A56: 0407 | B56: 45688 | C56: INV-2481 | D56: Innoprince Inc. | E56: 2400 | F56: Meeting Room 2, 4 pm to 6 pm | G56: Bank Transfer | H56: UBP | I56: UB1194845 | J56: Meeting Rooms | K56: 2400 | S56: =E56 -> 2400 | T56: =S56/1.12 -> 2142.8571 | U56: =T56*12% -> 257.14286 | V56: =T56+U56-S56 -> 0
A58: 0408 | B58: 45691 | C58: INV-2484 | D58: Jay-Ar Espallardo | E58: 486 | F58: Printing B&W | G58: Cash | H58: MBTC | J58: Add-Ons | K58: 486 | S58: =E58 -> 486 | T58: =S58/1.12 -> 433.92857 | U58: =T58*12% -> 52.071429 | V58: =T58+U58-S58 -> 0
A59: 0409 | B59: 45691 | C59: INV-2465 | D59: Ihub Solutions I(Philippines) Inc | E59: 22275 | F59: Meeting Room 2, full payment, Feb 2025 | G59: Bank Transfer | H59: UBP | I59: UB622861 | J59: Meeting Rooms | K59: 22275 | S59: =E59 -> 22275 | T59: =S59/1.12 -> 19888.393 | U59: =T59*12% -> 2386.6071 | V59: =T59+U59-S59 -> 0
A60: 0410 | B60: 45691 | C60: INV-2483 | D60: 9 Life Lessons Inc | E60: 84549.11 | F60: Use of Address , Feb 1, 2025 - Jan 31, 2029 | G60: Check | H60: UBP | I60: BPI 1000381424 | J60: Virtual Office | K60: 88500 | L60: =K60/1.12*0.05 -> 3950.8929 | M60: =K60-L60 -> 84549.107 | N60: =M60-E60 -> -0.0028571429 | S60: =K60 -> 88500 | T60: =S60/1.12 -> 79017.857 | U60: =T60*12% -> 9482.1429 | V60: =T60+U60-S60 -> 0
A61: 0411 | B61: 45691 | C61: INV-2463 | D61: Judicial Advocacy Law Firm | E61: 24000 | F61: Virtual Office, Jan 1, 2025 - Jun 30, 2025 | G61: Bank Transfer | H61: MBTC | I61: Direct Deposit | J61: Virtual Office | K61: 24000 | S61: =E61 -> 24000 | T61: =S61/1.12 -> 21428.571 | U61: =T61*12% -> 2571.4286 | V61: =T61+U61-S61 -> 0
A62: 0412 | B62: 45692 | C62: INV-2485 | D62: Slingshot Global Inc. | E62: 15967.8 | F62: Use of Address, Feb 12, 2025 to Dec 31, 2025 | G62: Bank Transfer | H62: UBP | I62: UB169450 | J62: Virtual Office | K62: 15967.8 | S62: =E62 -> 15967.8 | T62: =S62/1.12 -> 14256.964 | U62: =T62*12% -> 1710.8357 | V62: =T62+U62-S62 -> 0
A63: 0413 | B63: 45692 | C63: INV-2486 | D63: Timedly Solutions, Inc. | E63: 3500 | F63: Virtual Office, Feb 1, 2025 - Feb 28, 2025 | G63: Check | H63: UBP | I63: SECURITY BANK 0000509611 | J63: Virtual Office | K63: 3500 | S63: =E63 -> 3500 | T63: =S63/1.12 -> 3125 | U63: =T63*12% -> 375 | V63: =T63+U63-S63 -> 0
A64: 0414 | B64: 45692 | C64: INV-2487 | D64: Cosmic Design Collective Company | E64: 24000 | F64: Virtual Office, Jan 30, 2025 - July 29, 2025 | G64: Check | H64: UBP | I64: BPI 6000089262 | J64: Virtual Office | K64: 24000 | S64: =E64 -> 24000 | T64: =S64/1.12 -> 21428.571 | U64: =T64*12% -> 2571.4286 | V64: =T64+U64-S64 -> 0
A65: 0415 | B65: 45692 | C65: INV-2488 | D65: Alyannah Marie Mangahis | E65: 331 | F65: Printing B&W | G65: Cash | H65: MBTC | J65: Add-Ons | K65: 331 | S65: =E65 -> 331 | T65: =S65/1.12 -> 295.53571 | U65: =T65*12% -> 35.464286 | V65: =T65+U65-S65 -> 0
A66: 0416 | B66: 45693 | C66: INV-2489 | D66: Blessilda Sunico | E66: 217 | F66: Printing B&W | G66: Cash | H66: MBTC | J66: Add-Ons | K66: 217 | S66: =E66 -> 217 | T66: =S66/1.12 -> 193.75 | U66: =T66*12% -> 23.25 | V66: =T66+U66-S66 -> 0
A67: 0417 | B67: 45694 | C67: INV-2490 | D67: AIMS Industrial Supplies | E67: 9600 | F67: Meeting Room 3, Feb 6-7, 2025, 7:30 am to 4:30mpm | G67: Maya Card | H67: UBP | J67: Meeting Rooms | K67: 9600 | O67: 315.24 | P67: =E67-O67 -> 9284.76 | S67: =E67 -> 9600 | T67: =S67/1.12 -> 8571.4286 | U67: =T67*12% -> 1028.5714 | V67: =T67+U67-S67 -> 0
A68: 0418 | B68: 45695 | C68: INV-2491 | D68: Daisili Ann V Pelegrina | E68: 1400 | F68: 3 hour flypass for 4 seats | G68: Maya Card | H68: UBP | J68: Walk-Ins | K68: 1400 | O68: 45.97 | P68: =E68-O68 -> 1354.03 | S68: =E68 -> 1400 | T68: =S68/1.12 -> 1250 | U68: =T68*12% -> 150 | V68: =T68+U68-S68 -> 0
A69: 0419 | B69: 45695 | C69: INV-2492 | D69: Joyce Ann Defante | E69: 120 | F69: Printing | G69: Cash(87) Maya QR ph Feb 6 (12) Feb 7 (14) (7) | H69: UBP | J69: Add-Ons | K69: 120 | O69: =0.05+0.09 -> 0.14 | P69: =19-O69 -> 18.86 | S69: =E69 -> 120 | T69: =S69/1.12 -> 107.14286 | U69: =T69*12% -> 12.857143 | V69: =T69+U69-S69 -> 0
A70: 0420 | B70: 45698 | C70: INV-2493 | D70: Jan | E70: 448 | F70: Access Card (LPOG- 0750) | G70: Cash | H70: MBTC | J70: Add-Ons | K70: 448 | S70: =E70 -> 448 | T70: =S70/1.12 -> 400 | U70: =T70*12% -> 48 | V70: =T70+U70-S70 -> 0
A71: 0421 | B71: 45698 | C71: INV-2495 | D71: Shard Sound Production | E71: 17404.91 | F71: Use of Address, Feb 15, 2025 to Dec 31, 2025 | G71: Bank Transfer | H71: MBTC | I71: SN586013 | J71: Virtual Office | K71: 17404.91 | S71: =E71 -> 17404.91 | T71: =S71/1.12 -> 15540.098 | U71: =T71*12% -> 1864.8118 | V71: =T71+U71-S71 -> 0
A72: 0422 | B72: 45699 | C72: INV-2494 | D72: Moom Health Services Corp | E72: 4000 | F72: Virtual Office, Feb 4, 2025 to Mar 3, 2025 | G72: Check | H72: UBP | I72: BDO 0000158360 | J72: Virtual Office | K72: 4000 | S72: =E72 -> 4000 | T72: =S72/1.12 -> 3571.4286 | U72: =T72*12% -> 428.57143 | V72: =T72+U72-S72 -> 0
A73: 0423 | B73: 45700 | C73: INV-2498 | D73: Alberto Teves Jr. | E73: 251 | F73: Printing | G73: Cash | H73: MBTC | J73: Add-Ons | K73: 251 | S73: =E73 -> 251 | T73: =S73/1.12 -> 224.10714 | U73: =T73*12% -> 26.892857 | V73: =T73+U73-S73 -> 0
A74: 0424 | B74: 45700 | C74: INV-2496 | D74: SG ECOMMERCE CENTRE PHILIPPINES CORP. | E74: 4000 | F74: Virtual Office,Feb 14, 2025 - Mar 13, 2025 | G74: Check | H74: UBP | I74: BDO 0000105977 | J74: Virtual Office | K74: 4000 | S74: =E74 -> 4000 | T74: =S74/1.12 -> 3571.4286 | U74: =T74*12% -> 428.57143 | V74: =T74+U74-S74 -> 0
A75: 0425 | B75: 45700 | C75: INV-2444 | D75: 2911 Grand Management Consulting Services | E75: 1500 | F75: Use of Address, Feb 6, 2025 - Mar 5, 2025 | G75: Bank Transfer | H75: MBTC | I75: SN252919 | J75: Virtual Office | K75: 1500 | S75: =E75 -> 1500 | T75: =S75/1.12 -> 1339.2857 | U75: =T75*12% -> 160.71429 | V75: =T75+U75-S75 -> 0
A76: 0426 | B76: 45700 | C76: INV-2464 | D76: Recruitgo Philippines Inc. | E76: 34300 | F76: Meeting Room 1 and locker rental, Feb 6,13,20,27, 2025 | G76: Bank Transfer | H76: UBP | I76: UB380189 | J76: Meeting Rooms | K76: 34300 | S76: =E76 -> 34300 | T76: =S76/1.12 -> 30625 | U76: =T76*12% -> 3675 | V76: =T76+U76-S76 -> 0
A77: 0427 | B77: 45700 | C77: INV-2466/INV-2482 | D77: Norio-Olegario Consultancy Inc. | E77: 382 | F77: Printing B&W | G77: Maya Qr Standee | H77: UBP | J77: Add-Ons | K77: 382 | O77: 1.71 | P77: =E77-O77 -> 380.29 | S77: =E77 -> 382 | T77: =S77/1.12 -> 341.07143 | U77: =T77*12% -> 40.928571 | V77: =T77+U77-S77 -> 0
A78: 0428 | B78: 45702 | C78: INV-2501 | D78: Annie Ferreras | E78: 600 | F78: Wholeday Flypass | G78: Cash | H78: MBTC | J78: Walk-Ins | K78: 600 | S78: =E78 -> 600 | T78: =S78/1.12 -> 535.71429 | U78: =T78*12% -> 64.285714 | V78: =T78+U78-S78 -> 0
A79: 0429 | B79: 45702 | C79: INV-2502 | D79: Leo Manabat | E79: 17400 | F79: Meetiing Room 3 rent, Feb 17-21, 2025, 4pm to 9pm | G79: Bank Transfer (8700) Bank Transfer (8700) | H79: UBP | I79: UB701385/UB697350 | J79: Meeting Rooms | K79: 17400 | S79: =E79 -> 17400 | T79: =S79/1.12 -> 15535.714 | U79: =T79*12% -> 1864.2857 | V79: =T79+U79-S79 -> 0
A80: 0430 | D80: CANCELLED | S80: =E80 | T80: =S80/1.12 -> 0 | U80: =T80*12% -> 0 | V80: =T80+U80-S80 -> 0
A81: 0431 | D81: CANCELLED | J81: Meeting Rooms | S81: =E81 | T81: =S81/1.12 -> 0 | U81: =T81*12% -> 0 | V81: =T81+U81-S81 -> 0
A82: 0432 | D82: CANCELLED | S82: =E82 | T82: =S82/1.12 -> 0 | U82: =T82*12% -> 0 | V82: =T82+U82-S82 -> 0
A83: 0433 | B83: 45706 | C83: INV-2504 | D83: Gerard Gudes | E83: 210 | F83: Printing | G83: Cash | H83: MBTC | J83: Add-Ons | K83: 210 | S83: =E83 -> 210 | T83: =S83/1.12 -> 187.5 | U83: =T83*12% -> 22.5 | V83: =T83+U83-S83 -> 0
A84: 0434 | B84: 45707 | C84: INV-2505 | D84: Kaycee Velazquez | E84: 700 | F84: Wholeday Flypass | G84: Maya QR Standee | H84: UBP | K84: 700 | O84: 3.12 | P84: =E84-O84 -> 696.88 | S84: =E84 -> 700 | T84: =S84/1.12 -> 625 | U84: =T84*12% -> 75 | V84: =T84+U84-S84 -> 0
A85: 0435 | D85: CANCELLED | S85: =E85 | T85: =S85/1.12 -> 0 | U85: =T85*12% -> 0 | V85: =T85+U85-S85 -> 0
A86: 0436 | B86: 45709 | C86: INV-2500 | D86: QBE Group Shared Services Ltd- Philippine Branch | E86: 1703921.3 | F86: Private Office and Parking Rental March 2025 | G86: Check | H86: MBTC | I86: BPI 106314 | J86: Private Office | K86: 1792482.7 | L86: 88561.4 | M86: =K86-L86 -> 1703921.3 | N86: =E86-M86 -> 0.01 | S86: =K86 -> 1792482.7 | T86: 0 | U86: =T86*12% -> 0 | V86: 0
A87: 0437 | B87: 45709 | C87: INV-2512 | D87: Lou Joanna Aguila | E87: 175 | F87: Printing | G87: Cash | H87: MBTC | K87: 175 | S87: =E87 -> 175 | T87: =S87/1.12 -> 156.25 | U87: =T87*12% -> 18.75 | V87: =T87+U87-S87 -> 0
A88: 0438 | B88: 45709 | C88: INV-2513 | D88: iVoice 7 Trading Corp. | E88: 24000 | F88: Virtual Office, Feb 18, 2025 - Aug 17, 2025 | G88: Check | H88: UBP | I88: Metrobank 0968586516 | J88: Virtual Office | K88: 24000 | S88: =E88 -> 24000 | T88: =S88/1.12 -> 21428.571 | U88: =T88*12% -> 2571.4286 | V88: =T88+U88-S88 -> 0
A89: 0439 | B89: 45709 | C89: INV-2515 | D89: Paolo Luigi De Asis | E89: 600 | F89: Wholeday Flypass | G89: Cash | H89: MBTC | K89: 600 | S89: =E89 -> 600 | T89: =S89/1.12 -> 535.71429 | U89: =T89*12% -> 64.285714 | V89: =T89+U89-S89 -> 0
A90: 0440 | B90: 45713 | C90: INV-2503 | D90: BrandSpeakAsia, Inc | E90: 8500 | F90: Meeting Room 1 rental, Feb 16, 2025, 9 am to 6pm | G90: Bank Transfer (5600) Bank Transfer (2900) | H90: UBP | I90: UB1087167/UB482242 | J90: Meeting Rooms | K90: 8500 | S90: =E90 -> 8500 | T90: =S90/1.12 -> 7589.2857 | U90: =T90*12% -> 910.71429 | V90: =T90+U90-S90 -> 0
A91: 0441 | B91: 45713 | C91: INV-2517 | D91: Aubrey Lucero | E91: 24 | F91: Printing | G91: Maya QR Standee | H91: UBP | J91: Add-Ons | K91: 24 | O91: =E91-P91 -> 0.11 | P91: 23.89 | S91: =E91 -> 24 | T91: =S91/1.12 -> 21.428571 | U91: =T91*12% -> 2.5714286 | V91: =T91+U91-S91 -> 0
A92: 0442 | B92: 45713 | C92: INV-2518 | D92: Orange Juice Asia | E92: 3900 | F92: Meeting Room 3, 10am to 4pm | G92: Maya QR ph | H92: UBP | J92: Meeting Rooms | K92: 3900 | O92: 75.65 | P92: =E92-O92 -> 3824.35 | S92: =E92 -> 3900 | T92: =S92/1.12 -> 3482.1429 | U92: =T92*12% -> 417.85714 | V92: =T92+U92-S92 -> 0
A93: 0443 | B93: 45714 | C93: INV-2516 | D93: Estate of Remedios G. Suntay | E93: 8500 | F93: Meeting Room 1, 12:00 pm to 8:00 pm, Feb 22, 2025 | G93: Bank Transfer | H93: UBP | I93: S959614 | J93: Meeting Rooms | K93: 8500 | S93: =E93 -> 8500 | T93: =S93/1.12 -> 7589.2857 | U93: =T93*12% -> 910.71429 | V93: =T93+U93-S93 -> 0
A94: 0444 | B94: 45714 | C94: INV-2392/INV-2521 | D94: Mereb Realty | E94: 600 | F94: Locker rental, Dec 9, 2025 to Feb 8, 2025 | J94: Add-Ons | K94: 600 | S94: =E94 -> 600 | T94: =S94/1.12 -> 535.71429 | U94: =T94*12% -> 64.285714 | V94: =T94+U94-S94 -> 0
A96: 0445 | B96: 45720 | C96: INV-2497 | D96: ACTINUTRITION | E96: 350 | F96: 3 Hour Fly Pass, Feb 12, 2025 - Morgan Pincaro | G96: Bank Transfer from SI to SVI | H96: UBP | I96: UB934938 | J96: Walk-Ins | K96: 350 | S96: =E96 -> 350 | T96: =S96/1.12 -> 312.5 | U96: =T96*12% -> 37.5 | V96: =T96+U96-S96 -> 0
A97: 0446 | B97: 45720 | C97: INV-2519 | D97: ACTINUTRITION | E97: 350 | F97: 3 Hour Fly Pass, Mar 4, 2025 - Morgan Pincaro | G97: Bank Transfer from SI to SVI | H97: UBP | I97: UB45091 | J97: Walk-Ins | K97: 350 | S97: =E97 -> 350 | T97: =S97/1.12 -> 312.5 | U97: =T97*12% -> 37.5 | V97: =T97+U97-S97 -> 0
A98: 0447 | B98: 45720 | C98: INV-2506 | D98: Recruitgo Philippines Inc. | E98: 34300 | F98: Meeting rooms and locker rent, Mar2025 | G98: Bank Transfer | H98: UBP | I98: UB1513061 | J98: Meeting Rooms | K98: 34300 | S98: =E98 -> 34300 | T98: =S98/1.12 -> 30625 | U98: =T98*12% -> 3675 | V98: =T98+U98-S98 -> 0
A99: 0448 | B99: 45720 | C99: INV-2507 | D99: iHub Solutions (Philippines) Inc. | E99: 29700 | F99: Meeting Room 2 rental, March 2025, full payment | G99: Bank Transfer | H99: UBP | I99: UB500943 | J99: Meeting Rooms | K99: 29700 | S99: =E99 -> 29700 | T99: =S99/1.12 -> 26517.857 | U99: =T99*12% -> 3182.1429 | V99: =T99+U99-S99 -> 0
A100: 0449 | B100: 45720 | C100: INV-2510 | D100: 2911 Grand Management Consulting | E100: 1500 | F100: Use of Address, ₱1,500.00, Mar 6, 2024 - Apr 5, 2025 | G100: Bank Transfer | H100: MBTC | I100: SN776110 | J100: Virtual Office | K100: 1500 | S100: =E100 -> 1500 | T100: =S100/1.12 -> 1339.2857 | U100: =T100*12% -> 160.71429 | V100: =T100+U100-S100 -> 0
A101: 0450 | B101: 45720 | C101: INV-2508 | D101: Galleon Sciences R&D Corporation | E101: 15000 | F101: Use of Address, Mar 5, 2025 - Dec 31, 2025 | G101: Check | H101: UBP | I101: BPI 6000390854 | J101: Virtual Office | K101: 15000 | S101: =E101 -> 15000 | T101: =S101/1.12 -> 13392.857 | U101: =T101*12% -> 1607.1429 | V101: =T101+U101-S101 -> 0
A102: 0451 | B102: 45720 | C102: INV-2524 | D102: Raquel Alisangco | E102: 672 | F102: RFID Sticker | G102: Maya QR Standee | H102: UBP | J102: Add-Ons | K102: 672 | O102: 3 | P102: =E102-O102 -> 669 | S102: =E102 -> 672 | T102: =S102/1.12 -> 600 | U102: =T102*12% -> 72 | V102: =T102+U102-S102 -> 0
...

Sheet AR
A1: SI | B1: Date | C1: Client Name | D1: AR Amount | E1: Description | F1: Mode of Payment | G1: Cash/Check Deposit | H1: Remarks | J1: GROSS | K1: CWT | L1: TOTAL | M1: CC Fee | N1: Net Amount | P1: Gcash Fee | Q1: Net Amount
A2: 317 | B2: 45293 | C2: Kre8 Construction Services | D2: 3500 | E2: VO (Jan 1-31, 2024) | F2: Check | G2: UBP | H2: SB 0000887954
A3: 318 | B3: 45293 | C3: Cryo-Asia Philippines Corp. | D3: 3500 | E3: VO (Jan 1-31, 2024) | F3: Check | G3: UBP | H3: SB 0000483712
A4: 319 | B4: 45293 | C4: MB Areta ENgineering & Consultancy | D4: 3000 | E4: VO (Jan 2 - Feb 1, 2024) | F4: Check | G4: UBP | H4: BPI 1000045108
A5: 320 | B5: 45294 | C5: Jane Vacunua | D5: 4250 | E5: 50% DP for MR1 (Jan 13, 2024, 9a-5p) | F5: Bank Transfer | G5: UBP | H5: S1828540
A6: 321 | B6: 45295 | C6: Edward Guinto | D6: 1000 | E6: DP for MR3 (Jan 4, 2024, 12p-3p) | F6: Bank Transfer | G6: MBTC | H6: SN 359796
A7: 322 | B7: 45299 | C7: DrinkAid Corp | D7: 3500 | E7: VO (Jan 3 - Feb 2, 2024) | F7: Check | G7: UBP | H7: BDO 0000105736
A8: 323 | B8: 45299 | C8: Tohoku University | D8: 6000 | E8: 50% DP for MR3 Reservation on Jan 15-17, 2024, 8a-4p | F8: Cash | G8: MBTC
A9: 324 | B9: 45299 | C9: Werner Access Products Philippines Inc | D9: 7500 | E9: 50% DP for Feb 5 & 19, 2024 MR1 Reservation | F9: Maya Card | G9: UBP | M9: =D9*0.0285 -> 213.75 | N9: =D9-M9 -> 7286.25
A10: 325 | B10: 45308 | C10: Zenko Enterpries OPC | D10: 28660.71 | E10: VO (Feb 1, 2024 - Jan 31, 2025) | F10: Bank Transfer | G10: MBTC | H10: SN 000043
A11: 326 | B11: 45309 | C11: Cherry Love | D11: 1125 | E11: 50% DP for MR2, Jan 19, 2024, 3p-6p | F11: Bank Transfer | G11: UBP | H11: S9859862
A12: 327 | B12: 45310 | C12: Griffinstone Inc | D12: 15261 | E12: Access Card of Sir Miel | F12: Check | G12: UBP | H12: CB 0009648814
A13: 328 | B13: 45316 | C13: Health Channels Innovators Inc | D13: 3343.75 | E13: VO (Jan 24 - Feb 23, 2024) | F13: Check | G13: UBP | H13: CB 0000284599
A14: 329 | B14: 45316 | C14: 9 Life Lessons Inc | D14: 36000 | E14: VO (Feb 1, 2024 - Jan 31, 2025) | F14: Check | G14: UBP | H14: BPI 0002187622
A15: 330 | B15: 45316 | C15: Daniel Valerio | D15: 10000 | E15: Event Space 2 (Jan 28, 2024. 3p-7p) | F15: Cash
A16: 331 | B16: 45316 | C16: Alexander Uy | D16: 6250 | E16: 50% DP for Event Space 2, Feb 17, 2024. 3p-7p | F16: Check | G16: UBP | H16: BDO 0000119008
A17: 332 | B17: 45323 | C17: Innoprince Inc | D17: 3000 | E17: VO (Feb 1-29, 2024) | F17: Check (BT From SI) | G17: UBP
A18: 333 | B18: 45327 | C18: Werner Access Products Philippines Inc | D18: 7500 | E18: 50% DP for MR1, Mar 4 & Mar 25, 2024 | F18: Maya Card | G18: UBP | M18: =D18*0.0285 -> 213.75 | N18: =D18-M18 -> 7286.25
A19: 334 | B19: 45327 | C19: MB Areta ENgineering & Consultancy | D19: 3000 | E19: VO (Feb 2 - Mar 1, 2024) | F19: Check | G19: UBP | H19: BPI 100045109
A20: 335 | B20: 45327 | C20: DrinkAid Corp | D20: 3500 | E20: VO (Feb 3 - Mar 2, 2024) | F20: Check | G20: UBP | H20: BDO 0000105732
A21: 335 | B21: 45331 | C21: Offsite Solutions Inc | D21: 2300 | E21: 50% DP for MR3, Feb 15, 2024. 10a-7p | F21: Bank Transfer | G21: UBP | H21: UB476294
A22: 336 | B22: 45334 | C22: Dania Tablizo | D22: 6500 | E22: 50% DP for Event Sapce 2, Mar 2, 2024. 1p-5p | F22: Bank Transfer | G22: UBP | H22: S20646478
A23: 337 | B23: 45339 | C23: Alexander Uy | D23: 6250 | E23: Full Payment for Event Space 2, Feb 17, 2024, 1p-8p | F23: Check | G23: UBP | H23: BDO 0000119011
A24: 338 | B24: 45341 | C24: E.Gonzales Law Office | D24: 3500 | E24: VO (Feb 15 - Mar 14, 2024) | F24: Check | G24: UBP | H24: BDO 0001149553
A25: 339 | B25: 45341 | C25: Goetz Moving and Storage Inc. | D25: 7500 | E25: 50% DP for MR1, Mar 6 & 8, 2024, 9a-5p | F25: Bank Transfer | G25: UBP | H25: UB648449
A26: 340 | B26: 45349 | C26: Insightscs | D26: 6000 | E26: DP for MR 1 - Feb 28, 2024, 9am - 3pm | F26: Bank Transfer | G26: UBP | H26: UB1057342
A27: 341 | B27: 45355 | C27: Werner Access Products Philippines Inc | D27: 7500 | E27: 50% DP for MR 1, Apr 8 and Apr 29, 2024 | F27: Maya Card | G27: UBP | M27: =D27*0.0285 -> 213.75 | N27: =D27-M27 -> 7286.25
A28: 342 | B28: 45355 | C28: MB Areta ENgineering & Consultancy | D28: 3000 | E28: VO (Mar 7 - April 1, 2024) | F28: Check | G28: UBP | H28: BPI 1000045110
A29: 343 | B29: 45355 | C29: KRE8 Construction Services | D29: 3500 | E29: VO (Mar 1 - Mar 31, 2024) | F29: Check | G29: UBP | H29: SB 0000887956
A30: 344 | B30: 45355 | C30: DrinkAid Corp | D30: 3500 | E30: VO (Mar 3 - April 2, 2024) | F30: Check | G30: UBP | H30: BDO 0000105738
A31: 345 | B31: 45351 | C31: Health Channels Innovators, Inc. | D31: 3343.75 | E31: VO (Feb 24 - Mar 23, 2024) | F31: Check | G31: UBP | H31: CTBC 0000284600
A32: 346 | B32: 45357 | C32: Profitable Personnel Pty Ltd | D32: 3000 | E32: VO (Mar 1 - Mar 31, 2024) | F32: Check | G32: UBP | H32: BDO 0000011874
A33: 347 | B33: 45369 | C33: E Gonzales Law Office | D33: 3500 | E33: VO (Mar 15, 2024 - April 14, 2024) | F33: Check | G33: UBP | H33: BDO 0001149554
A34: 348 | B34: 45376 | C34: Health Channels Innovators Inc. | D34: 3343.75 | E34: VO (Mar 24, 2024 - April 23, 2024) | F34: Check | G34: UBP | H34: CTBC 0000284601 | J34: 3500 | K34: =J34/1.12*0.05 -> 156.25 | L34: =J34-K34 -> 3343.75
A35: 349 | B35: 45384 | C35: Galleon Sciences R&D Corporation | D35: 3500 | E35: VO (Apr 5, 2024 - May 4, 2024) | F35: Check | G35: UBP | H35: BDO 0000620240
A36: 350 | B36: 45384 | C36: Timedly Solutions, Inc. | D36: 3500 | E36: VO (Apr 1, 2024 - Apr 30, 2024) | F36: Check | G36: UBP | H36: SB 0000509601
A37: 351 | B37: 45384 | C37: MBAreta Engineering & Consultancy Services | D37: 3000 | E37: VO (Apr 2, 2024 - May 1, 2024) | F37: Check | G37: UBP | H37: BPI 1000045111
A38: 352 | B38: 45384 | C38: Kre8 Construction Services | D38: 3500 | E38: VO (Apr 1, 2024 - Apr 30, 2024) | F38: Check | G38: UBP | H38: SB 0000887957
A39: 353 | B39: 45386 | C39: Anytime Fitness Evia | D39: 1995.71 | E39: 50% DP for Meeting Room 3, April 8, 2024 (9am to 5pm) | F39: Bank Transfer | G39: MBTC | H39: SN000101
A40: 354 | B40: 45386 | C40: Nutrition Center of the Philippines | D40: 4394.64 | E40: Meeting Room 3 (March 18, 2024, 9am - 6pm) | F40: Bank Transfer | G40: UBP | H40: UB14802 | J40: 4600 | K40: =J40/1.12*0.05 -> 205.35714 | L40: =J40-K40 -> 4394.6429
A41: 355 | B41: 45390 | C41: Profitable Personnel Pty Ltd | D41: 3000 | E41: VO (Apr 1, 2024 - Apr 30, 2024) | F41: Check | G41: UBP | H41: BDO 0000011871
A42: 356 | B42: 45390 | C42: DrinkAid Corp | D42: 3500 | E42: VO (Apr 3, 2024 - May 2, 2024) | F42: Check | G42: UBP | H42: BDO 0000105739
A43: 357 | B43: 45390 | C43: Werner Access Products Philippines Inc | D43: 15000 | E43: Full Payment Meeting Room 1 (Apr 8 & 29, 2024, 9a-5p) | F43: AR 0341 (7,500), Maya Card (7, 500) | G43: UBP | M43: =7500*0.0285 -> 213.75 | N43: =7500-M43 -> 7286.25
A44: 358 | B44: 45390 | C44: Werner Access Products Philippines Inc | D44: 7500 | E44: 50% DP for Meeting Room 1 (May 6 & 20, 2024) | F44: Maya Card | G44: UBP | M44: =7500*0.0285 -> 213.75 | N44: =7500-M44 -> 7286.25
A45: 359 | B45: 45390 | C45: Anytime Fitness Evia | D45: 2000 | E45: Meeting Room 3 (March 18, 2024, 9am - 6pm) | F45: Check | G45: UBP | H45: BDO 0001327320
A46: 360 | B46: 45393 | C46: Sean Mendoza | D46: 20 | E46: Printing | F46: Cash
A47: 361 | B47: 45393 | C47: Don Valerio (Feast Youth Alabang) | D47: 12000 | E47: Event Space (Apr 14, 2024, 3p-7p) | F47: Maya QR | G47: UBP | H47: Ref: 259572
A48: 362 | B48: 45393 | C48: Cryo-Asia Philippines Corp. | D48: 448 | E48: Access Card of Sir Miel | F48: Cash
A49: 363 | B49: 45393 | C49: Alabang South Doctors | D49: 4320 | E49: Meeting Room 1 (Apr 11, 2024. 7p-10p) | F49: Bank Transfer | G49: UBP | H49: S47925400
A50: 364 | B50: 45393 | C50: Genedrift, Inc. | D50: 2100 | E50: Meeting Room 1 (Apr 15, 2024, 1p-4p) | F50: Bank Transfer | G50: UBP
A51: 365 | B51: 45394 | C51: OAA Online Advertising Agency | D51: 42000 | E51: VO (Mar 13, 2024 - Mar 12, 2025) | F51: Check | G51: UBP | H51: EWB 0001855574
A52: 366 | B52: 45394 | C52: Norio-Olegario Consultancy Inc. | D52: 4500 | E52: Meeting Room 1 (Apr 22, 2024, 10a-5p) | F52: Maya Card | G52: UBP | M52: =D52*0.0285 -> 128.25 | N52: =D52-M52 -> 4371.75
A53: 367 | B53: 45394 | C53: Philippine Nutri-Foods Corporation | D53: 7690.62 | E53: Meeting Room 1 (9a-5p) | F53: Bank Transfer | G53: UBP | H53: UB1450631 | J53: 8050 | K53: =J53/1.12*0.05 -> 359.375 | L53: =J53-K53 -> 7690.625
A54: 368 | B54: 45394 | C54: Christine Joy Catapang | D54: 40 | E54: Printing | F54: Cash | G54: MBTC
A55: 369 | B55: 45397 | C55: John Leo Manabat | D55: 12250 | E55: MR3 (Apr 22, 23, 24, 26 & 29, 2024, 2p-9p) | F55: Bank Transfer | G55: UBP | H55: UB1195499
A56: 370 | B56: 45398 | C56: E. Gonzales Law Office | D56: 3000 | E56: Virtual Office (April 15, 2024 to May 14, 2024) | F56: Check | G56: UBP | H56: BDO 0001149555
A57: 371 | B57: 45411 | C57: Feast Alabang District | D57: 5250 | E57: 50% DP of Feast Alabang District c/o Kirae | F57: Bank Transfer | G57: UBP | H57: S55871003
A58: 372 | B58: 45414 | C58: Timedly Solutions, Inc. | D58: 3500 | E58: Virtual Office (May 1, 2024 to May 31, 2024) | F58: Check | G58: UBP | H58: SB 0000509602
A59: 373 | B59: 45414 | C59: Health Channels Innovators, Inc. | D59: 3343.75 | E59: Virtual Office - April 24, 2024 to May 23, 2024 | F59: Check | G59: UBP | H59: CB 0000284602
A60: 374 | B60: 45414 | C60: Kre8 Construction Services | D60: 3500 | E60: Virtual Office (May 1, 2024 to May 31, 2024) | F60: Check | G60: UBP | H60: SB 0000887958
A61: 375 | B61: 45419 | C61: MBAreta Engineering & Consultancy Services | D61: 3000 | E61: Virtual Office (May 2, 2024 to June 1, 2024) | F61: Check | G61: UBP | H61: BPI 1000045112
A62: 376 | B62: 45419 | C62: Galleon Sciences R&D Corporation | D62: 14000 | E62: Virtual Office (May 5, 2024 to August 4, 2024) | F62: Check | G62: UBP | H62: BPI 6000390851
A63: 377 | B63: 45419 | C63: DrinkAid Corp | D63: 3500 | E63: Virtual Office (May 3, 2024 to June 2, 2024) | F63: Check | G63: UBP | H63: BDO 0000105740
A64: 378 | B64: 45426 | C64: SG Ecommerce Centre Philippines Corp. | D64: 4000 | E64: Virtual Office (May 10, 2024 to June 9, 2024) | F64: Check | G64: UBP | H64: BDO 0001149556
A65: 379 | B65: 45428 | C65: E Gonzales Law Office | D65: 3500 | E65: Virtual Office (May 15, 2024 to June 14, 2024) | F65: Check | G65: UBP
A66: 380 | B66: 45432 | C66: Werner Access Products Philippines Inc | D66: 8500 | E66: 50% DP of Meeting Room 1 on June 3 & 17, 2024 (9am to 5pm) | F66: Maya Card | G66: UBP | M66: =D66*0.0285 -> 242.25 | N66: =D66-M66 -> 8257.75
A67: 381 | B67: 45397 | C67: OAA Online Advertising Agency | D67: 1875 | E67: Excess Payment (to be deducted on next renewal) | F67: Check | G67: UBP | H67: EB 0001855574
A68: 382 | B68: 45433 | C68: Leo Manabat | D68: 5850 | E68: 50% DP Meeting Room 3 (May 27-29, 2024) 8am to 2pm (6hrs) | F68: Bank Transfer | G68: UBP
A69: 383 | B69: 45433 | C69: Gretz Moving and Storage, Inc. | D69: 2550 | E69: 50% DP Meeting Room 1 (June 25, 2024) 12:30pm-5pm | F69: Bank Transfer | G69: UBP
A70: 384 | B70: 45439 | C70: Health Channels Innovators, Inc. | D70: 3343.75 | E70: Virtual Office (May 24, 2024 to June 23, 2024) | F70: Check | G70: UBP | H70: CB 0000284603
A71: 385 | B71: 45443 | C71: Use of Address (June 13, 2024 to Dec 12, 2024) | D71: 2400 | E71: 50% DP - Meeting Room 3, June 3, 2024, 8am to 5pm) | F71: Maya QR | G71: UBP
A72: 386 | B72: 45448 | C72: Sw7 Solagratia Inc | D72: 8598.21 | E72: Use of Address (June 13, 2024 to Dec 12, 2024) | F72: Check | G72: UBP | H72: BDO 0000909201 | J72: 9000 | K72: 401.79 | L72: 8598.21
A73: 387 | B73: 45448 | C73: Rapha Jirei Holdings Inc | D73: 8598.21 | E73: Use of Address (June 13, 2024 to Dec 12, 2024) | F73: Check | G73: UBP | H73: BDO 0000561178 | J73: 9000 | K73: 401.79 | L73: 8598.21
A74: 388 | B74: 45448 | C74: Acton Tpwn Inc | D74: 8598.21 | E74: Use of Address (June 13, 2024 to Dec 12, 2024) | F74: Check | G74: UBP | H74: BDO 0000561178 | J74: 9000 | K74: 401.79 | L74: 8598.21
A75: 389 | B75: 45448 | C75: Gesegnet Hodlings Inc | D75: 8598.21 | E75: Use of Address (June 13, 2024 to Dec 12, 2024) | F75: Check | G75: UBP | H75: BDO 0000561178 | J75: 9000 | K75: 401.79 | L75: 8598.21
A76: 390 | B76: 45448 | C76: La Vie Inc | D76: 74088 | E76: Full Payment, Combined Meeting Room 1&2, June 15-16, 22-23, 29-30 | F76: Check Dep to Bank | G76: UBP | H76: S74485814
A77: 391 | B77: 45461 | C77: SG Ecommerce Centre Philippines Corp. | D77: 4000 | E77: Virtual Office (June 10 - July 9, 2024) | F77: Check | G77: UBP | H77: BDO 0000105969
A78: 392 | B78: 45464 | C78: E Gonzales Law Office | D78: 3500 | E78: Virtual Office, Jun 15, 2024 - Jul 14, 2024 | F78: Check | G78: UBP | H78: BDO 0001149557
A79: 393 | B79: 45464 | C79: Avant Welness | D79: 48000 | E79: Virtual Office, June 21, 2024 - June 20, 2025 | F79: Check | G79: UBP | H79: PSB 0000891678
A80: 394 | B80: 45468 | C80: Judicial Advocacy Law Firm | D80: 24000 | E80: Virtual Office, Jan 1, 2025 - June 30, 2024 | F80: Check, not yet deposited | H80: BPI 1000138773
A81: 395 | B81: 45469 | C81: Health Channels Innovators, Inc. | D81: 3343.75 | E81: Virtual Office, Jun 24, 2024 - Jul 23, 2024 | F81: Check | G81: UBP | H81: Chinabank 000284604 | J81: 3500 | K81: 156.25 | L81: 3343.75
A82: 396 | B82: 45470 | C82: The Feast Alabang | D82: 4000 | E82: 50% DP, Event Space 1, July 6, 2024, 6am to 10pm | F82: Maya QR | G82: UBP | H82: 815185
A83: 397 | B83: 45482 | C83: Philippine Nutri-Foods Corporation | D83: 1337.5 | E83: Overpayment | F83: Bank Transfer | G83: UBP | H83: UB943077
A84: 398 | B84: 45482 | C84: kre8 Construction Services | D84: 3500 | E84: Virtual Office, Jul 1, 2024 - Jul 31, 2024 | F84: Check | G84: UBP | H84: Security bank 0000887960
A85: 399 | B85: 45489 | C85: Mereb Realty | D85: 24000 | E85: Virtual Office, Jul 16, 2024 - Jan 15, 2025 | F85: Check | G85: UBP | H85: BPI 6000287551
A86: 400 | B86: 45505 | C86: Personetics Technologies Pte. Ltd. | D86: 19900 | E86: MR 3 Aug 5 - 9, 12 2024, MR 2 August 13 - 14, 2024, 8 am - 5pm | F86: Bank Transfer | G86: UBP | H86: UB183064
A87: 401 | B87: 45505 | C87: Eunice Sara Vibal | D87: 24000 | E87: Virtual Office (July 30, 2024 to Jan 29, 2025) | F87: Bank Transfer | G87: UBP | H87: S2355772
A88: 402 | B88: 45505 | C88: The Feast Alabang | D88: 9500 | E88: 50 % DP Event Space 2, August 3, 2024, 8 am - 11am & Sept 15, 2024 11am to 2pm | F88: Bank Transfer | G88: UBP | H88: S1747350
A89: 403 | B89: 45509 | C89: DrinkAid Corp. | D89: 3500 | E89: Virtual Office, Aug 3, 2024 - Sep 2, 2024 | F89: Check | G89: UBP | H89: BDO 0000105743
A90: 404 | B90: 45511 | C90: Innoprince Inc | D90: 3000 | E90: Virtual Office, Aug 1, 2024 - Aug 31, 2024 | F90: Check | G90: UBP | H90: Unionbank 2002519549
A91: 405 | B91: 45511 | C91: Timedly Solutions, Inc. | D91: 3500 | E91: Virtual Office, Aug 1, 2024 - Aug 31, 2024 | F91: Check | G91: UBP | H91: Security Bank 0000509605
A92: 406 | B92: 45518 | C92: Health Channels Innovators, Inc. | D92: 14330.36 | E92: Use of Address Renewal, Jul 24, 2024 - Jul 23, 2025 | F92: Check | G92: UBP | H92: CTBC Bank 0000292467 | J92: 15000 | K92: =J92/1.12*0.05 -> 669.64286 | L92: =J92-K92 -> 14330.357 | M92: =L92-D92 -> -0.0028571429
A93: 407 | B93: 45526 | C93: Light of Jesus Family Mega Manila Feast Alabang District Inc | D93: 7000 | E93: DP for Event Space 2 Sept 8, 2PM-5PM | F93: Maya Card | G93: UBP | M93: =D93*0.0285 -> 199.5 | N93: =D93-M93 -> 6800.5
A94: 408 | B94: 45519 | C94: Axis (Automation Experts for Industrial Solutions) Corporation | D94: 4700 | E94: Meeting Room 1 & 2, 10am to 3pm - Sep 3, 2024 | F94: Cash | G94: MBTC
A95: 409 | B95: 45520 | C95: E Gonzales Law Office | D95: 3500 | E95: Virtual Office, Aug 15, 2024 - Sep 14, 2024 | F95: Check | G95: UBP | H95: BDO 0001149559
A96: 410 | B96: 45520 | C96: SG Ecommerce Centre Philippines Corp. | D96: 4000 | E96: Virtual Office, ₱4,000.00, Aug 14, 2024 - Sep 13, 2024 | F96: Check | G96: UBP | H96: BDO 0000105971 - returned check
A97: 411 | B97: 45531 | C97: John Leo Manabat | D97: 12500 | E97: 50% DP Meeting room 3, Aug 21 -25, 2024 2pm-10pm | F97: Bank Transfer | G97: UBP | H97: UB1303859
A98: 412 | B98: 45533 | C98: Cleiint Ariez D. Jane | D98: 24000 | E98: Virtual Office (August 18, 2024 - August 17, 2025) | F98: Check | G98: UBP | H98: Metrobank 0968586515
A99: 413 | B99: 45540 | C99: Thaison Builder and Developer, Inc. | D99: 64.28 | E99: Advance Payment (to be deducted on next reservation) | F99: Bank Transfer | G99: UBP | H99: UB411026
A100: 414 | B100: 45540 | C100: Thaison Builder and Developer, Inc. | D100: 2400 | E100: Advance Payment Payment (to be deducted on next reservation) | F100: Bank Transfer | G100: UBP | H100: UB518591
...

Sheet SI Amendment
A1: SI | B1: Date | C1: Invoice Number | D1: Client Name | E1: OR Amount | F1: Description | G1: Mode of Payment | H1: Cash / Check Deposit | I1: Remarks | J1: Type of Service | K1: GROSS | L1: CWT | M1: TOTAL | O1: CC Fee/Charge | P1: Net Amount | Q1: Checking | S1: GROSS AMOUTN | T1: NET AMOUNT | U1: VAT AMOUNT | W1: GROSS AMOUNT | X1: NET AMOUNT | Y1: VAT AMOUNT
A2: 0353 | B2: 45660 | C2: INV-2426 | D2: Timedly Solutions, Inc. | E2: 3500 | F2: Virtual Office, Jan 1, 2025 - Jan 31, 2025 | G2: Check | H2: UBP | I2: Security Bank 0000509610 | J2: Virtual Office | S2: =E2 -> 3500 | T2: =S2/1.12 -> 3125 | U2: =T2*0.12 -> 375 | W2: =E2 -> 3500 | X2: =W2/1.12 -> 3125 | Y2: =X2*0.12 -> 375
A3: 0354 | B3: 45663 | C3: INV-2435 | D3: Intertool Precision Group Inc | E3: 2100 | F3: Meeting Room 3, 3:00 pm to 6:00 pm | G3: Maya QR Standee | H3: UBP | J3: Meeting Rooms | O3: 9.38 | P3: =E3-O3 -> 2090.62 | S3: =E3 -> 2100 | T3: =S3/1.12 -> 1875 | U3: =T3*0.12 -> 225 | W3: =E3 -> 2100 | X3: =W3/1.12 -> 1875 | Y3: =X3*0.12 -> 225
A4: 0355 | D4: CANCELLED | S4: =E4 | T4: =S4/1.12 -> 0 | U4: =T4*0.12 -> 0 | W4: =E4 | X4: =W4/1.12 -> 0 | Y4: =X4*0.12 -> 0
A5: 0356 | B5: 45664 | C5: INV-2437 | D5: Bluvision Surveillance and Analytics Inc. | E5: 4500 | F5: Meeting Room 1, Jan 8, 2025, 9:00 am to 1:00 pm | G5: Maya QR Standee | H5: UBP | J5: Meeting Rooms | O5: 20.09 | P5: =E5-O5 -> 4479.91 | S5: =E5 -> 4500 | T5: =S5/1.12 -> 4017.8571 | U5: =T5*0.12 -> 482.14286 | W5: =E5 -> 4500 | X5: =W5/1.12 -> 4017.8571 | Y5: =X5*0.12 -> 482.14286
A6: 0357 | B6: 45665 | C6: INV-2467 | D6: Lawrence Alexander | E6: 20 | F6: Printing | G6: Maya QR Standee | H6: UBP | J6: Add-Ons | O6: 0.09 | P6: =E6-O6 -> 19.91 | S6: =E6 -> 20 | T6: =S6/1.12 -> 17.857143 | U6: =T6*0.12 -> 2.1428571 | W6: =E6 -> 20 | X6: =W6/1.12 -> 17.857143 | Y6: =X6*0.12 -> 2.1428571
A7: 0358 | B7: 45665 | C7: INV-2438 | D7: Limuel Libres | E7: 350 | F7: Wholeday Flypass (Student) | G7: Cash | H7: MBTC | J7: Walk-Ins | S7: =E7 -> 350 | T7: =S7/1.12 -> 312.5 | U7: =T7*0.12 -> 37.5 | W7: =E7 -> 350 | X7: =W7/1.12 -> 312.5 | Y7: =X7*0.12 -> 37.5
A8: 0359 | B8: 45666 | C8: INV-2441 | D8: Margarita Bariring | E8: 5500 | F8: Monthly Flypass | G8: Maya Card | H8: UBP | J8: Monthly Membership | O8: 180.6 | P8: =E8-O8 -> 5319.4 | S8: =E8 -> 5500 | T8: =S8/1.12 -> 4910.7143 | U8: =T8*0.12 -> 589.28571 | W8: =E8 -> 5500 | X8: =W8/1.12 -> 4910.7143 | Y8: =X8*0.12 -> 589.28571
A9: 0360 | B9: 45666 | C9: INV-2442 | D9: MARRO FASHION STYLING STUDIO | E9: 2400 | F9: Meeting Room 2, 9:30 am to 12:00 nn | G9: Maya Card | H9: UBP | J9: Meeting Rooms | O9: 78.81 | P9: =E9-O9 -> 2321.19 | S9: =E9 -> 2400 | T9: =S9/1.12 -> 2142.8571 | U9: =T9*0.12 -> 257.14286 | W9: =E9 -> 2400 | X9: =W9/1.12 -> 2142.8571 | Y9: =X9*0.12 -> 257.14286
A10: 0361 | B10: 45666 | C10: INV-2443 | D10: F.A BAUTISTA & PARTNERS | E10: 5500 | F10: Meeting Room 3, January 10, 2025, 8:30 am to 5:00 pm | G10: Maya QR Standee | H10: UBP | J10: Meeting Rooms | O10: 24.55 | P10: =E10-O10 -> 5475.45 | Q10: =SUM(P8:P10) -> 13116.04 | S10: =E10 -> 5500 | T10: =S10/1.12 -> 4910.7143 | U10: =T10*0.12 -> 589.28571 | W10: =E10 -> 5500 | X10: =W10/1.12 -> 4910.7143 | Y10: =X10*0.12 -> 589.28571
A11: 0362 | B11: 45666 | C11: INV-2436 | D11: Moom Health Services Corp | E11: 4000 | F11: Virtual Office, Jan 4, 2025 - Feb 3, 2025 | G11: Check | H11: UBP | I11: BDO 0000158359 | J11: Virtual Office | S11: =E11 -> 4000 | T11: =S11/1.12 -> 3571.4286 | U11: =T11*0.12 -> 428.57143 | W11: =E11 -> 4000 | X11: =W11/1.12 -> 3571.4286 | Y11: =X11*0.12 -> 428.57143
A12: 0363 | B12: 45667 | C12: INV-2468 | D12: Lawrence Alexander | E12: 10 | F12: Printing | G12: Maya QR Standee | H12: UBP | J12: Add-Ons | O12: 0.04 | P12: =E12-O12 -> 9.96 | S12: =E12 -> 10 | T12: =S12/1.12 -> 8.9285714 | U12: =T12*0.12 -> 1.0714286 | W12: =E12 -> 10 | X12: =W12/1.12 -> 8.9285714 | Y12: =X12*0.12 -> 1.0714286
A13: 0364 | B13: 45667 | C13: INV-2445 | D13: Kevin Carmelina | E13: 1600 | F13: Meeting Room 2, 1:00 pm to 3:00 pm | G13: Maya Card | H13: UBP | J13: Meeting Rooms | O13: 52.54 | P13: =E13-O13 -> 1547.46 | S13: =E13 -> 1600 | T13: =S13/1.12 -> 1428.5714 | U13: =T13*0.12 -> 171.42857 | W13: =E13 -> 1600 | X13: =W13/1.12 -> 1428.5714 | Y13: =X13*0.12 -> 171.42857
A14: 0365 | D14: CANCELLED | S14: =E14 | T14: =S14/1.12 -> 0 | U14: =T14*0.12 -> 0 | W14: =E14 | X14: =W14/1.12 -> 0 | Y14: =X14*0.12 -> 0
A15: 0366 | D15: CANCELLED | S15: =E15 | T15: =S15/1.12 -> 0 | U15: =T15*0.12 -> 0 | W15: =E15 | X15: =W15/1.12 -> 0 | Y15: =X15*0.12 -> 0
A16: 0367 | B16: 45667 | C16: INV-2446 | D16: Paolo De Asis | E16: 600 | F16: Wholeday Flypass | G16: Cash | H16: MBTC | S16: =E16 -> 600 | T16: =S16/1.12 -> 535.71429 | U16: =T16*0.12 -> 64.285714 | W16: =E16 -> 600 | X16: =W16/1.12 -> 535.71429 | Y16: =X16*0.12 -> 64.285714
A17: 0368 | B17: 45667 | C17: INV-2447 | D17: Brey Reyes | E17: 2400 | F17: Meeting Room 2, 4:30 pm to 6:00 pm | G17: Maya Card | H17: UBP | J17: Walk-Ins | O17: 78.81 | P17: =E17-O17 -> 2321.19 | Q17: =P13+P17+P19+[1]AR!N127 -> #ERROR! | S17: =E17 -> 2400 | T17: =S17/1.12 -> 2142.8571 | U17: =T17*0.12 -> 257.14286 | W17: =E17 -> 2400 | X17: =W17/1.12 -> 2142.8571 | Y17: =X17*0.12 -> 257.14286
A18: 0369 | B18: 45668 | C18: INV-2450 | D18: AIMS Industrial Supplies | E18: 84400 | F18: Meeting Room 1, 2 and 3, February 3-7, 2025 | G18: AR 435 (42200) Maya Card (42200) | H18: UBP | I18: UB1297258 | J18: Meeting Rooms | O18: 1385.72 | P18: =42200-O18 -> 40814.28 | Q18: =42200-O18 -> 40814.28 | S18: =E18 -> 84400 | T18: =S18/1.12 -> 75357.143 | U18: =T18*0.12 -> 9042.8571 | W18: =E18 -> 84400 | X18: =W18/1.12 -> 75357.143 | Y18: =X18*0.12 -> 9042.8571
A19: 0370 | B19: 45670 | C19: INV-2448 | D19: E Gonzales Law Office | E19: 17322.63 | F19: Use of Address, Jan 15, 2025 to Dec 31, 2025 | G19: Maya Card (Jan 10) | H19: UBP | J19: Virtual Office | O19: 568.83 | P19: =E19-O19 -> 16753.8 | S19: =E19 -> 17322.63 | T19: =S19/1.12 -> 15466.634 | U19: =T19*0.12 -> 1855.9961 | W19: =E19 -> 17322.63 | X19: =W19/1.12 -> 15466.634 | Y19: =X19*0.12 -> 1855.9961
A20: 0371 | B20: 45670 | C20: INV-2452 | D20: Arkiya Francine Orosco | E20: 2400 | F20: Meeting Room 2, Jan 13, 2025, 9:00 am to 12:00 pm | G20: Cash | H20: MBTC | J20: Meeting Rooms | S20: =E20 -> 2400 | T20: =S20/1.12 -> 2142.8571 | U20: =T20*0.12 -> 257.14286 | W20: =E20 -> 2400 | X20: =W20/1.12 -> 2142.8571 | Y20: =X20*0.12 -> 257.14286
A21: 0372 | D21: CANCELLED | S21: =E21 | T21: =S21/1.12 -> 0 | U21: =T21*0.12 -> 0 | W21: =E21 | X21: =W21/1.12 -> 0 | Y21: =X21*0.12 -> 0
A22: 0373 | B22: 45670 | C22: INV-2451 | D22: Sightechs Corporation | E22: 24000 | F22: Virtual Office, Jan 1, 2025 - Jun 30, 2025 | G22: Bank Transfer | H22: UBP | I22: UB1060687 | J22: Virtual Office | S22: =E22 -> 24000 | T22: =S22/1.12 -> 21428.571 | U22: =T22*0.12 -> 2571.4286 | W22: =E22 -> 24000 | X22: =W22/1.12 -> 21428.571 | Y22: =X22*0.12 -> 2571.4286
A23: 0374 | B23: 45671 | C23: INV-2432/INV-2433/INV-2428/INV-2429/INV-2430/INV-2431 | D23: iHub Solutions (Philippines) Inc. | E23: 127841.68 | F23: Meeting Room 2, 7am to 4pm, Jan (full) , Feb - Apr (DP) & Locker Rental (jan-Apr) & Virtual Office (Jan 20 - Dec 31, 2025) | G23: Bank Transfer | H23: UBP | I23: UB799581 | J23: Meeting Rooms | S23: =E23 -> 127841.68 | T23: =S23/1.12 -> 114144.36 | U23: =T23*0.12 -> 13697.323 | W23: =E23 -> 127841.68 | X23: =W23/1.12 -> 114144.36 | Y23: =X23*0.12 -> 13697.323
A24: 0375 | B24: 45671 | C24: INV-2427/INV-2425 | D24: Recruitgo Philippines Inc. | E24: =8500+34300 -> 42800 | F24: Meeting Room 1 rental, Jan 9, 16, 23, 30 & Locker Rental (Jan 2025) | G24: Bank Transfer | H24: UBP | I24: UB1200210 | J24: Meeting Rooms | S24: =E24 -> 42800 | T24: =S24/1.12 -> 38214.286 | U24: =T24*0.12 -> 4585.7143 | W24: =E24 -> 42800 | X24: =W24/1.12 -> 38214.286 | Y24: =X24*0.12 -> 4585.7143
A25: 0376 | B25: 45672 | C25: INV-2454 | D25: Ramona Tagum | E25: 80 | F25: Printing Bkwh P4 x 20 pages | G25: Cash | H25: UBP | J25: Add-Ons | S25: =E25 -> 80 | T25: =S25/1.12 -> 71.428571 | U25: =T25*0.12 -> 8.5714286 | W25: =E25 -> 80 | X25: =W25/1.12 -> 71.428571 | Y25: =X25*0.12 -> 8.5714286
A26: 0377 | B26: 45672 | C26: INV-2453 | D26: BRANDSPEAKASIA INC. | E26: 19480.75 | F26: Use of address, Jan 7, 2025 to Dec 31, 2025 | G26: Bank Transfer | H26: UBP | I26: UB495547 | J26: Virtual Office | S26: =E26 -> 19480.75 | T26: =S26/1.12 -> 17393.527 | U26: =T26*0.12 -> 2087.2232 | W26: =E26 -> 19480.75 | X26: =W26/1.12 -> 17393.527 | Y26: =X26*0.12 -> 2087.2232
A27: 0378 | D27: CANCELLED | J27: Meeting Rooms | S27: =E27 | T27: =S27/1.12 -> 0 | U27: =T27*0.12 -> 0 | W27: =E27 | X27: =W27/1.12 -> 0 | Y27: =X27*0.12 -> 0
A28: 0379 | B28: 45672 | C28: INV-2456 | D28: CoinAlpha Inc. | E28: 6900 | F28: Meeting Room 1, Jan 15, 2025, 11:00 am to 5:00 pm | G28: Maya Card | H28: UBP | J28: Add-Ons | O28: 226.58 | P28: =E28-O28 -> 6673.42 | Q28: =P28 -> 6673.42 | S28: =E28 -> 6900 | T28: =S28/1.12 -> 6160.7143 | U28: =T28*0.12 -> 739.28571 | W28: =E28 -> 6900 | X28: =W28/1.12 -> 6160.7143 | Y28: =X28*0.12 -> 739.28571
A29: 0380 | B29: 45672 | C29: INV-2457 | D29: Cyril Cayasa | E29: 368 | F29: Printing P4 x 92 pages | G29: Maya QR Standee | H29: UBP | J29: Add-Ons | O29: 1.64 | P29: =E29-O29 -> 366.36 | Q29: =P29 -> 366.36 | S29: =E29 -> 368 | T29: =S29/1.12 -> 328.57143 | U29: =T29*0.12 -> 39.428571 | W29: =E29 -> 368 | X29: =W29/1.12 -> 328.57143 | Y29: =X29*0.12 -> 39.428571
A30: 0381 | B30: 45673 | C30: INV-2458 | D30: Norio-Olegario Consultancy Inc. | E30: 600 | F30: Printing B&W (P2x280 pages) ; Colored (P10x 4 pages) | G30: Maya QR Standee | H30: UBP | J30: Add-Ons | O30: 2.68 | P30: =E30-O30 -> 597.32 | S30: =E30 -> 600 | T30: =S30/1.12 -> 535.71429 | U30: =T30*0.12 -> 64.285714 | W30: =E30 -> 600 | X30: =W30/1.12 -> 535.71429 | Y30: =X30*0.12 -> 64.285714
A31: 0382 | B31: 45673 | C31: INV-2460 | D31: Cyril Cayasa | E31: 12 | F31: Printing B&W P2 x 6 | G31: Maya QR Standee | H31: UBP | J31: Add-Ons | O31: 0.05 | P31: =E31-O31 -> 11.95 | S31: =E31 -> 12 | T31: =S31/1.12 -> 10.714286 | U31: =T31*0.12 -> 1.2857143 | W31: =E31 -> 12 | X31: =W31/1.12 -> 10.714286 | Y31: =X31*0.12 -> 1.2857143
A32: 0383 | B32: 45674 | C32: INV-2461 | D32: Leo Manabat | E32: 1680 | F32: Meeting room 3, 8 pm to 10 pm (w/ after hour access) | G32: Maya Card (Jan 16) | H32: UBP | J32: Meeting Rooms | O32: 55.17 | P32: =E32-O32 -> 1624.83 | Q32: =SUM(P30:P32) -> 2234.1 | S32: =E32 -> 1680 | T32: =S32/1.12 -> 1500 | U32: =T32*0.12 -> 180 | W32: =E32 -> 1680 | X32: =W32/1.12 -> 1500 | Y32: =X32*0.12 -> 180
A33: 0384 | B33: 45674 | C33: INV-2393 | D33: QBE Group Shared Services Ltd- Philippine Branch | E33: 1703921.3 | F33: Private Office and Parking Rental January 2025 | G33: Check | H33: MBTC | I33: BPI 0001040674 | J33: Private Office | K33: 1792482.7 | L33: 88561.4 | M33: =K33-L33 -> 1703921.3 | N33: =E33-M33 -> 0.01 | S33: =K33 -> 1792482.7 | T33: 0 | U33: =T33*0.12 -> 0 | W33: 198377.52 | X33: =W33/1.12 -> 177122.79 | Y33: =X33*0.12 -> 21254.734
A34: 0385 | B34: 45674 | C34: INV-2455 | D34: SG ECOMMERCE CENTRE PHILIPPINES CORP. | E34: 4000 | F34: Virtual Office, Jan14, 2024 - Feb 13, 2025 | G34: Check | H34: UBP | I34: BDO 0000105976 | J34: Virtual Office | S34: =E34 -> 4000 | T34: =S34/1.12 -> 3571.4286 | U34: =T34*0.12 -> 428.57143 | W34: =E34 -> 4000 | X34: =W34/1.12 -> 3571.4286 | Y34: =X34*0.12 -> 428.57143
A35: 0386 | B35: 45674 | C35: INV-2459 | D35: Zenko Enterprises OPC | E35: 15763.39 | F35: Use of Address, Feb 1, 2025 - Dec 31, 2025 | G35: Bank Transfer | H35: UBP | I35: S84967905 | J35: Virtual Office | K35: 16500 | L35: =K35/1.12*0.05 -> 736.60714 | M35: =K35-L35 -> 15763.393 | N35: =E35-M35 -> -0.0028571429 | S35: =K35 -> 16500 | T35: =S35/1.12 -> 14732.143 | U35: =T35*0.12 -> 1767.8571 | W35: 16500 | X35: =W35/1.12 -> 14732.143 | Y35: =X35*0.12 -> 1767.8571
A36: 0387 | D36: CANCELLED | S36: =E36 | T36: =S36/1.12 -> 0 | U36: =T36*0.12 -> 0 | W36: =E36 | X36: =W36/1.12 -> 0 | Y36: =X36*0.12 -> 0
A37: 0388 | B37: 45677 | C37: INV-2337 | D37: DrinkAid Corp. | E37: 20903.31 | F37: Use of Address, November 3, 2024 to December 31, 2025 | G37: Maya Card | H37: UBP | J37: Virtual Office | O37: 686.4 | P37: =E37-O37 -> 20216.91 | S37: =E37 -> 20903.31 | T37: =S37/1.12 -> 18663.67 | U37: =T37*0.12 -> 2239.6404 | W37: =E37 -> 20903.31 | X37: =W37/1.12 -> 18663.67 | Y37: =X37*0.12 -> 2239.6404
A38: 0389 | B38: 45677 | C38: INV-2370 | D38: Norio-Olegario Consultancy Inc. | E38: 24522.63 | F38: Use of Address and Locker rental, November 15, 2024 to December 31, 2025 | G38: Maya Card | H38: UBP | J38: Virtual Office | O38: 805.25 | P38: =E38-O38 -> 23717.38 | Q38: =SUM(P37:P38) -> 43934.29 | S38: =E38 -> 24522.63 | T38: =S38/1.12 -> 21895.205 | U38: =T38*0.12 -> 2627.4246 | W38: =E38 -> 24522.63 | X38: =W38/1.12 -> 21895.205 | Y38: =X38*0.12 -> 2627.4246
A39: 0390 | D39: CANCELLED | S39: =E39 | T39: =S39/1.12 -> 0 | U39: =T39*0.12 -> 0 | W39: =E39 | X39: =W39/1.12 -> 0 | Y39: =X39*0.12 -> 0
A40: 0391 | B40: 45677 | C40: INV-2462 | D40: Radiance Image Consultancy and Training Inc. | E40: 18580.68 | F40: Use of Address, December 20, 2024 to December 31, 2025 | G40: Bank Transfer | H40: UBP | I40: UB495547 | J40: Meeting Rooms | S40: =E40 -> 18580.68 | T40: =S40/1.12 -> 16589.893 | U40: =T40*0.12 -> 1990.7871 | W40: =E40 -> 18580.68 | X40: =W40/1.12 -> 16589.893 | Y40: =X40*0.12 -> 1990.7871 | Z40: 2024 Sales but not reported
A41: 0392 | B41: 45677 | C41: INV-2470 | D41: Daisy Ree Kate Gomintong | E41: 900 | F41: Whole Day Flypass (After Hour Access) | G41: Maya QR Standee | H41: UBP | J41: Walk-Ins | O41: 4.02 | P41: =E41-O41 -> 895.98 | Q41: =P41 -> 895.98 | S41: =E41 -> 900 | T41: =S41/1.12 -> 803.57143 | U41: =T41*0.12 -> 96.428571 | W41: =E41 -> 900 | X41: =W41/1.12 -> 803.57143 | Y41: =X41*0.12 -> 96.428571
A42: 0393 | B42: 45679 | C42: INV-2471 | D42: Paolo Luigi De Asis | E42: 600 | F42: Wholeday Flypass | G42: Cash | H42: MBTC | J42: Walk-Ins | S42: =E42 -> 600 | T42: =S42/1.12 -> 535.71429 | U42: =T42*0.12 -> 64.285714 | W42: =E42 -> 600 | X42: =W42/1.12 -> 535.71429 | Y42: =X42*0.12 -> 64.285714
A43: 0394 | B43: 45680 | C43: INV-2472 | D43: Amiel Cruz | E43: 20 | F43: Printing (P10 x 2pages) | G43: Maya QR Standee | H43: UBP | J43: Add-Ons | O43: 0.09 | P43: =E43-O43 -> 19.91 | Q43: =P43 -> 19.91 | S43: =E43 -> 20 | T43: =S43/1.12 -> 17.857143 | U43: =T43*0.12 -> 2.1428571 | W43: =E43 -> 20 | X43: =W43/1.12 -> 17.857143 | Y43: =X43*0.12 -> 2.1428571
A44: 0395 | B44: 45680 | C44: INV-2473 | D44: Innoprince Inc. | E44: 1400 | F44: Meeting Room 3, Jan 23, 2025, 1:00 pm to 3:00 pm | G44: Bank Transfer | H44: UBP | I44: UB457951 | J44: Meeting Rooms | S44: =E44 -> 1400 | T44: =S44/1.12 -> 1250 | U44: =T44*0.12 -> 150 | W44: =E44 -> 1400 | X44: =W44/1.12 -> 1250 | Y44: =X44*0.12 -> 150
A45: 0396 | B45: 45681 | C45: INV-2474 | D45: Cabauatan Lee-Rosales & Co, CPA's | E45: 6300 | F45: Meeting Room 2, January 24, 2025, 9:00 am to 6:00 pm | G45: AR 442 (3150) Cash (3150) | H45: MBTC | I45: UB574440 | J45: Meeting Rooms | S45: =E45 -> 6300 | T45: =S45/1.12 -> 5625 | U45: =T45*0.12 -> 675 | W45: =E45 -> 6300 | X45: =W45/1.12 -> 5625 | Y45: =X45*0.12 -> 675
A46: 0397 | B46: 45681 | C46: INV-2475 | D46: The Feast Bellevue AM | E46: 10500 | F46: Event Space rental, 3pm to 6pm, Jan 26, 2025 | G46: Bank Transfer | H46: UBP | I46: UB387801 | J46: Events | S46: =E46 -> 10500 | T46: =S46/1.12 -> 9375 | U46: =T46*0.12 -> 1125 | W46: =E46 -> 10500 | X46: =W46/1.12 -> 9375 | Y46: =X46*0.12 -> 1125
A47: 0398 | B47: 45681 | C47: INV-2476 | D47: Annie Ferreras | E47: 600 | F47: Wholeday Flypass | G47: Cash | H47: MBTC | S47: =E47 -> 600 | T47: =S47/1.12 -> 535.71429 | U47: =T47*0.12 -> 64.285714 | W47: =E47 -> 600 | X47: =W47/1.12 -> 535.71429 | Y47: =X47*0.12 -> 64.285714
A48: 0399 | D48: CANCELLED | S48: =E48 | T48: =S48/1.12 -> 0 | U48: =T48*0.12 -> 0 | W48: =E48 | X48: =W48/1.12 -> 0 | Y48: =X48*0.12 -> 0
A49: 400 | B49: 45684 | C49: INV-2469 | D49: SwipeEdge Corp. | E49: 24000 | F49: Virtual Office, Jan 1, 2025 - Jun 30, 2025 | G49: Bank Transfer | H49: MBTC | I49: 589252 | J49: Virtual Office | S49: =E49 -> 24000 | T49: =S49/1.12 -> 21428.571 | U49: =T49*0.12 -> 2571.4286 | W49: 48000 | X49: =W49/1.12 -> 42857.143 | Y49: =X49*12% -> 5142.8571
A50: 0401 | B50: 45684 | C50: INV-2477 | D50: Lorelei D. Jane/SwipeEdge | E50: 448 | F50: Access Card (LPOG- 0749 Lorelei D. Jane) | G50: Cash | H50: MBTC | J50: Add-Ons | S50: =E50 -> 448 | T50: =S50/1.12 -> 400 | U50: =T50*0.12 -> 48 | W50: =E50 -> 448 | X50: =W50/1.12 -> 400 | Y50: =X50*0.12 -> 48
A51: 0402 | B51: 45684 | C51: INV-2478 | D51: VTMCI | E51: 9700 | F51: Meeting Room 1 Rent, 10 am to 7pm | G51: Maya Card | H51: UBP | J51: Meeting Rooms | O51: 318.52 | P51: =E51-O51 -> 9381.48 | S51: =E51 -> 9700 | T51: =S51/1.12 -> 8660.7143 | U51: =T51*0.12 -> 1039.2857 | W51: =E51 -> 9700 | X51: =W51/1.12 -> 8660.7143 | Y51: =X51*0.12 -> 1039.2857
A52: 0403 | D52: CANCELLED | S52: =E52 | T52: =S52/1.12 -> 0 | U52: =T52*0.12 -> 0 | W52: =E52 | X52: =W52/1.12 -> 0 | Y52: =X52*0.12 -> 0
A53: 0404 | B53: 45685 | C53: INV-2479 | D53: Rusell John Santiaguel | E53: 35 | F53: Printing | G53: Maya QR Standee | H53: UBP | J53: Add-Ons | O53: 0.16 | P53: =E53-O53 -> 34.84 | S53: =E53 -> 35 | T53: =S53/1.12 -> 31.25 | U53: =T53*0.12 -> 3.75 | W53: =E53 -> 35 | X53: =W53/1.12 -> 31.25 | Y53: =X53*0.12 -> 3.75
A54: 0405 | B54: 45688 | C54: INV-2440 | D54: QBE Group Shared Services Ltd- Philippine Branch | E54: 1703921.3 | F54: Private Office and Parking Rental February 2025 | G54: Check | H54: UBP | I54: BPI 1051484 | J54: Private Office | K54: 1792482.7 | L54: 88561.4 | M54: =K54-L54 -> 1703921.3 | N54: =E54-M54 -> 0.01 | S54: =K54 -> 1792482.7 | T54: 0 | U54: =T54*0.12 -> 0 | W54: 198377.52 | X54: =W54/1.12 -> 177122.79 | Y54: =X54*0.12 -> 21254.734
A55: 0406 | B55: 45688 | C55: INV-2480 | D55: Paolo Luigi De Asis | E55: 550 | F55: Wholeday Flypass | G55: Cash | H55: MBTC | J55: Walk-Ins | S55: =E55 -> 550 | T55: =S55/1.12 -> 491.07143 | U55: =T55*0.12 -> 58.928571 | W55: 600 | X55: =W55/1.12 -> 535.71429 | Y55: =X55*12% -> 64.285714
A56: 0407 | B56: 45688 | C56: INV-2481 | D56: Innoprince Inc. | E56: 2400 | F56: Meeting Room 2, 4 pm to 6 pm | G56: Bank Transfer | H56: UBP | I56: UB1194845 | J56: Meeting Rooms | S56: =E56 -> 2400 | T56: =S56/1.12 -> 2142.8571 | U56: =T56*0.12 -> 257.14286 | W56: =E56 -> 2400 | X56: =W56/1.12 -> 2142.8571 | Y56: =X56*0.12 -> 257.14286
A57: 0408 | B57: 45691 | C57: INV-2484 | D57: Jay-Ar Espallardo | E57: 486 | F57: Printing B&W | G57: Cash | H57: MBTC | J57: Add-Ons | S57: =E57 -> 486 | T57: =S57/1.12 -> 433.92857 | U57: =T57*0.12 -> 52.071429 | V57: =T57+U57-S57 -> 0 | W57: =E57 -> 486 | X57: =W57/1.12 -> 433.92857 | Y57: =X57*0.12 -> 52.071429
A58: 0409 | B58: 45691 | C58: INV-2465 | D58: Ihub Solutions I(Philippines) Inc | E58: 22275 | F58: Meeting Room 2, full payment, Feb 2025 | G58: Bank Transfer | H58: UBP | I58: UB622861 | J58: Meeting Rooms | S58: =E58 -> 22275 | T58: =S58/1.12 -> 19888.393 | U58: =T58*0.12 -> 2386.6071 | V58: =T58+U58-S58 -> 0 | W58: =E58 -> 22275 | X58: =W58/1.12 -> 19888.393 | Y58: =X58*0.12 -> 2386.6071
A59: 0410 | B59: 45691 | C59: INV-2483 | D59: 9 Life Lessons Inc | E59: 84549.11 | F59: Use of Address , Feb 1, 2025 - Jan 31, 2029 | G59: Check | H59: UBP | I59: BPI 1000381424 | J59: Virtual Office | K59: 88500 | L59: =K59/1.12*0.05 -> 3950.8929 | M59: =K59-L59 -> 84549.107 | N59: =M59-E59 -> -0.0028571429 | S59: =K59 -> 88500 | T59: =S59/1.12 -> 79017.857 | U59: =T59*0.12 -> 9482.1429 | V59: =T59+U59-S59 -> 0 | W59: 88500 | X59: =W59/1.12 -> 79017.857 | Y59: =X59*0.12 -> 9482.1429
A60: 0411 | B60: 45691 | C60: INV-2463 | D60: Judicial Advocacy Law Firm | E60: 24000 | F60: Virtual Office, Jan 1, 2025 - Jun 30, 2025 | G60: Bank Transfer | H60: MBTC | I60: Direct Deposit | J60: Virtual Office | S60: =E60 -> 24000 | T60: =S60/1.12 -> 21428.571 | U60: =T60*0.12 -> 2571.4286 | V60: =T60+U60-S60 -> 0 | W60: =E60 -> 24000 | X60: =W60/1.12 -> 21428.571 | Y60: =X60*0.12 -> 2571.4286
A61: 0412 | B61: 45692 | C61: INV-2485 | D61: Slingshot Global Inc. | E61: 15967.8 | F61: Use of Address, Feb 12, 2025 to Dec 31, 2025 | G61: Bank Transfer | H61: UBP | I61: UB169450 | J61: Virtual Office | S61: =E61 -> 15967.8 | T61: =S61/1.12 -> 14256.964 | U61: =T61*0.12 -> 1710.8357 | V61: =T61+U61-S61 -> 0 | W61: =E61 -> 15967.8 | X61: =W61/1.12 -> 14256.964 | Y61: =X61*0.12 -> 1710.8357
A62: 0413 | B62: 45692 | C62: INV-2486 | D62: Timedly Solutions, Inc. | E62: 3500 | F62: Virtual Office, Feb 1, 2025 - Feb 28, 2025 | G62: Check | H62: UBP | I62: SECURITY BANK 0000509611 | J62: Virtual Office | S62: =E62 -> 3500 | T62: =S62/1.12 -> 3125 | U62: =T62*0.12 -> 375 | V62: =T62+U62-S62 -> 0 | W62: =E62 -> 3500 | X62: =W62/1.12 -> 3125 | Y62: =X62*0.12 -> 375
A63: 0414 | B63: 45692 | C63: INV-2487 | D63: Cosmic Design Collective Company | E63: 24000 | F63: Virtual Office, Jan 30, 2025 - July 29, 2025 | G63: Check | H63: UBP | I63: BPI 6000089262 | J63: Virtual Office | S63: =E63 -> 24000 | T63: =S63/1.12 -> 21428.571 | U63: =T63*0.12 -> 2571.4286 | V63: =T63+U63-S63 -> 0 | W63: =E63 -> 24000 | X63: =W63/1.12 -> 21428.571 | Y63: =X63*0.12 -> 2571.4286
A64: 0415 | B64: 45692 | C64: INV-2488 | D64: Alyannah Marie Mangahis | E64: 331 | F64: Printing B&W | G64: Cash | H64: MBTC | J64: Add-Ons | S64: =E64 -> 331 | T64: =S64/1.12 -> 295.53571 | U64: =T64*0.12 -> 35.464286 | V64: =T64+U64-S64 -> 0 | W64: =E64 -> 331 | X64: =W64/1.12 -> 295.53571 | Y64: =X64*0.12 -> 35.464286
A65: 0416 | B65: 45693 | C65: INV-2489 | D65: Blessilda Sunico | E65: 217 | F65: Printing B&W | G65: Cash | H65: MBTC | J65: Add-Ons | S65: =E65 -> 217 | T65: =S65/1.12 -> 193.75 | U65: =T65*0.12 -> 23.25 | V65: =T65+U65-S65 -> 0 | W65: =E65 -> 217 | X65: =W65/1.12 -> 193.75 | Y65: =X65*0.12 -> 23.25
A66: 0417 | B66: 45694 | C66: INV-2490 | D66: AIMS Industrial Supplies | E66: 9600 | F66: Meeting Room 3, Feb 6-7, 2025, 7:30 am to 4:30mpm | G66: Maya Card | H66: UBP | J66: Meeting Rooms | O66: 315.24 | P66: =E66-O66 -> 9284.76 | S66: =E66 -> 9600 | T66: =S66/1.12 -> 8571.4286 | U66: =T66*0.12 -> 1028.5714 | V66: =T66+U66-S66 -> 0 | W66: =E66 -> 9600 | X66: =W66/1.12 -> 8571.4286 | Y66: =X66*0.12 -> 1028.5714
A67: 0418 | B67: 45695 | C67: INV-2491 | D67: Daisili Ann V Pelegrina | E67: 1400 | F67: 3 hour flypass for 4 seats | G67: Maya Card | H67: UBP | J67: Walk-Ins | O67: 45.97 | P67: =E67-O67 -> 1354.03 | S67: =E67 -> 1400 | T67: =S67/1.12 -> 1250 | U67: =T67*0.12 -> 150 | V67: =T67+U67-S67 -> 0 | W67: =E67 -> 1400 | X67: =W67/1.12 -> 1250 | Y67: =X67*0.12 -> 150
A68: 0419 | B68: 45695 | C68: INV-2492 | D68: Joyce Ann Defante | E68: 120 | F68: Printing | G68: Cash(87) Maya QR ph Feb 6 (12) Feb 7 (14) (7) | H68: UBP | J68: Add-Ons | O68: =0.05+0.09 -> 0.14 | P68: =19-O68 -> 18.86 | S68: =E68 -> 120 | T68: =S68/1.12 -> 107.14286 | U68: =T68*0.12 -> 12.857143 | V68: =T68+U68-S68 -> 0 | W68: =E68 -> 120 | X68: =W68/1.12 -> 107.14286 | Y68: =X68*0.12 -> 12.857143
A69: 0420 | B69: 45698 | C69: INV-2493 | D69: Robert Miguel Gantuangco/Shard | E69: 448 | F69: Access Card (LPOG- 0750) | G69: Cash | H69: MBTC | J69: Add-Ons | S69: =E69 -> 448 | T69: =S69/1.12 -> 400 | U69: =T69*0.12 -> 48 | V69: =T69+U69-S69 -> 0 | W69: =E69 -> 448 | X69: =W69/1.12 -> 400 | Y69: =X69*0.12 -> 48
A70: 0421 | B70: 45698 | C70: INV-2495 | D70: Shard Sound Production | E70: 17404.91 | F70: Use of Address, Feb 15, 2025 to Dec 31, 2025 | G70: Bank Transfer | H70: MBTC | I70: SN586013 | J70: Virtual Office | S70: =E70 -> 17404.91 | T70: =S70/1.12 -> 15540.098 | U70: =T70*0.12 -> 1864.8118 | V70: =T70+U70-S70 -> 0 | W70: =E70 -> 17404.91 | X70: =W70/1.12 -> 15540.098 | Y70: =X70*0.12 -> 1864.8118
A71: 0422 | B71: 45699 | C71: INV-2494 | D71: Moom Health Services Corp | E71: 4000 | F71: Virtual Office, Feb 4, 2025 to Mar 3, 2025 | G71: Check | H71: UBP | I71: BDO 0000158360 | J71: Virtual Office | S71: =E71 -> 4000 | T71: =S71/1.12 -> 3571.4286 | U71: =T71*0.12 -> 428.57143 | V71: =T71+U71-S71 -> 0 | W71: =E71 -> 4000 | X71: =W71/1.12 -> 3571.4286 | Y71: =X71*0.12 -> 428.57143
A72: 0423 | B72: 45700 | C72: INV-2498 | D72: Alberto Teves Jr. | E72: 251 | F72: Printing | G72: Cash | H72: MBTC | J72: Add-Ons | S72: =E72 -> 251 | T72: =S72/1.12 -> 224.10714 | U72: =T72*0.12 -> 26.892857 | V72: =T72+U72-S72 -> 0 | W72: =E72 -> 251 | X72: =W72/1.12 -> 224.10714 | Y72: =X72*0.12 -> 26.892857
A73: 0424 | B73: 45700 | C73: INV-2496 | D73: SG ECOMMERCE CENTRE PHILIPPINES CORP. | E73: 4000 | F73: Virtual Office,Feb 14, 2025 - Mar 13, 2025 | G73: Check | H73: UBP | I73: BDO 0000105977 | J73: Virtual Office | S73: =E73 -> 4000 | T73: =S73/1.12 -> 3571.4286 | U73: =T73*0.12 -> 428.57143 | V73: =T73+U73-S73 -> 0 | W73: =E73 -> 4000 | X73: =W73/1.12 -> 3571.4286 | Y73: =X73*0.12 -> 428.57143
A74: 0425 | B74: 45700 | C74: INV-2444 | D74: 2911 Grand Management Consulting Services | E74: 1500 | F74: Use of Address, Feb 6, 2025 - Mar 5, 2025 | G74: Bank Transfer | H74: MBTC | I74: SN252919 | J74: Virtual Office | S74: =E74 -> 1500 | T74: =S74/1.12 -> 1339.2857 | U74: =T74*0.12 -> 160.71429 | V74: =T74+U74-S74 -> 0 | W74: =E74 -> 1500 | X74: =W74/1.12 -> 1339.2857 | Y74: =X74*0.12 -> 160.71429
A75: 0426 | B75: 45700 | C75: INV-2464 | D75: Recruitgo Philippines Inc. | E75: 34300 | F75: Meeting Room 1 and locker rental, Feb 6,13,20,27, 2025 | G75: Bank Transfer | H75: UBP | I75: UB380189 | J75: Meeting Rooms | S75: =E75 -> 34300 | T75: =S75/1.12 -> 30625 | U75: =T75*0.12 -> 3675 | V75: =T75+U75-S75 -> 0 | W75: =E75 -> 34300 | X75: =W75/1.12 -> 30625 | Y75: =X75*0.12 -> 3675
A76: 0427 | B76: 45700 | C76: INV-2466/INV-2482 | D76: Norio-Olegario Consultancy Inc. | E76: 382 | F76: Printing B&W | G76: Maya Qr Standee | H76: UBP | J76: Add-Ons | O76: 1.71 | P76: =E76-O76 -> 380.29 | S76: =E76 -> 382 | T76: =S76/1.12 -> 341.07143 | U76: =T76*0.12 -> 40.928571 | V76: =T76+U76-S76 -> 0 | W76: =E76 -> 382 | X76: =W76/1.12 -> 341.07143 | Y76: =X76*0.12 -> 40.928571
A77: 0428 | B77: 45702 | C77: INV-2501 | D77: Annie Ferreras | E77: 600 | F77: Wholeday Flypass | G77: Cash | H77: MBTC | J77: Walk-Ins | S77: =E77 -> 600 | T77: =S77/1.12 -> 535.71429 | U77: =T77*0.12 -> 64.285714 | V77: =T77+U77-S77 -> 0 | W77: =E77 -> 600 | X77: =W77/1.12 -> 535.71429 | Y77: =X77*0.12 -> 64.285714
A78: 0429 | B78: 45702 | C78: INV-2502 | D78: Leo Manabat | E78: 17400 | F78: Meetiing Room 3 rent, Feb 17-21, 2025, 4pm to 9pm | G78: Bank Transfer (8700) Bank Transfer (8700) | H78: UBP | I78: UB701385/UB697350 | J78: Meeting Rooms | S78: =E78 -> 17400 | T78: =S78/1.12 -> 15535.714 | U78: =T78*0.12 -> 1864.2857 | V78: =T78+U78-S78 -> 0 | W78: =E78 -> 17400 | X78: =W78/1.12 -> 15535.714 | Y78: =X78*0.12 -> 1864.2857
A79: 0430 | D79: CANCELLED | S79: =E79 | T79: =S79/1.12 -> 0 | U79: =T79*0.12 -> 0 | V79: =T79+U79-S79 -> 0 | W79: =E79 | X79: =W79/1.12 -> 0 | Y79: =X79*0.12 -> 0
A80: 0431 | D80: CANCELLED | J80: Meeting Rooms | S80: =E80 | T80: =S80/1.12 -> 0 | U80: =T80*0.12 -> 0 | V80: =T80+U80-S80 -> 0 | W80: =E80 | X80: =W80/1.12 -> 0 | Y80: =X80*0.12 -> 0
A81: 0432 | D81: CANCELLED | S81: =E81 | T81: =S81/1.12 -> 0 | U81: =T81*0.12 -> 0 | V81: =T81+U81-S81 -> 0 | W81: =E81 | X81: =W81/1.12 -> 0 | Y81: =X81*0.12 -> 0
A82: 0433 | B82: 45706 | C82: INV-2504 | D82: Gerard Gudes | E82: 210 | F82: Printing | G82: Cash | H82: MBTC | J82: Add-Ons | S82: =E82 -> 210 | T82: =S82/1.12 -> 187.5 | U82: =T82*0.12 -> 22.5 | V82: =T82+U82-S82 -> 0 | W82: =E82 -> 210 | X82: =W82/1.12 -> 187.5 | Y82: =X82*0.12 -> 22.5
A83: 0434 | B83: 45707 | C83: INV-2505 | D83: Kaycee Velazquez | E83: 700 | F83: Wholeday Flypass | G83: Maya QR Standee | H83: UBP | O83: 3.12 | P83: =E83-O83 -> 696.88 | S83: =E83 -> 700 | T83: =S83/1.12 -> 625 | U83: =T83*0.12 -> 75 | V83: =T83+U83-S83 -> 0 | W83: =E83 -> 700 | X83: =W83/1.12 -> 625 | Y83: =X83*0.12 -> 75
A84: 0435 | D84: CANCELLED | S84: =E84 | T84: =S84/1.12 -> 0 | U84: =T84*0.12 -> 0 | V84: =T84+U84-S84 -> 0 | W84: =E84 | X84: =W84/1.12 -> 0 | Y84: =X84*0.12 -> 0
A85: 0436 | B85: 45709 | C85: INV-2500 | D85: QBE Group Shared Services Ltd- Philippine Branch | E85: 1703921.3 | F85: Private Office and Parking Rental March 2025 | G85: Check | H85: MBTC | I85: BPI 106314 | J85: Private Office | K85: 1792482.7 | L85: 88561.4 | M85: =K85-L85 -> 1703921.3 | N85: =E85-M85 -> 0.01 | S85: =K85 -> 1792482.7 | T85: 0 | U85: =T85*0.12 -> 0 | W85: 198377.52 | X85: =W85/1.12 -> 177122.79 | Y85: =X85*0.12 -> 21254.734
A86: 0437 | B86: 45709 | C86: INV-2512 | D86: Lou Joanna Aguila | E86: 175 | F86: Printing | G86: Cash | H86: MBTC | S86: =E86 -> 175 | T86: =S86/1.12 -> 156.25 | U86: =T86*0.12 -> 18.75 | V86: =T86+U86-S86 -> 0 | W86: =E86 -> 175 | X86: =W86/1.12 -> 156.25 | Y86: =X86*0.12 -> 18.75
A87: 0438 | B87: 45709 | C87: INV-2513 | D87: iVoice 7 Trading Corp. | E87: 24000 | F87: Virtual Office, Feb 18, 2025 - Aug 17, 2025 | G87: Check | H87: UBP | I87: Metrobank 0968586516 | J87: Virtual Office | S87: =E87 -> 24000 | T87: =S87/1.12 -> 21428.571 | U87: =T87*0.12 -> 2571.4286 | V87: =T87+U87-S87 -> 0 | W87: =E87 -> 24000 | X87: =W87/1.12 -> 21428.571 | Y87: =X87*0.12 -> 2571.4286
A88: 0439 | B88: 45709 | C88: INV-2515 | D88: Paolo Luigi De Asis | E88: 600 | F88: Wholeday Flypass | G88: Cash | H88: MBTC | S88: =E88 -> 600 | T88: =S88/1.12 -> 535.71429 | U88: =T88*0.12 -> 64.285714 | V88: =T88+U88-S88 -> 0 | W88: =E88 -> 600 | X88: =W88/1.12 -> 535.71429 | Y88: =X88*0.12 -> 64.285714
A89: 0440 | B89: 45713 | C89: INV-2503 | D89: BrandSpeakAsia, Inc | E89: 8500 | F89: Meeting Room 1 rental, Feb 16, 2025, 9 am to 6pm | G89: Bank Transfer (5600) Bank Transfer (2900) | H89: UBP | I89: UB1087167/UB482242 | J89: Meeting Rooms | S89: =E89 -> 8500 | T89: =S89/1.12 -> 7589.2857 | U89: =T89*0.12 -> 910.71429 | V89: =T89+U89-S89 -> 0 | W89: =E89 -> 8500 | X89: =W89/1.12 -> 7589.2857 | Y89: =X89*0.12 -> 910.71429
A90: 0441 | B90: 45713 | C90: INV-2517 | D90: Aubrey Lucero | E90: 24 | F90: Printing | G90: Maya QR Standee | H90: UBP | J90: Add-Ons | O90: =E90-P90 -> 0.11 | P90: 23.89 | S90: =E90 -> 24 | T90: =S90/1.12 -> 21.428571 | U90: =T90*0.12 -> 2.5714286 | V90: =T90+U90-S90 -> 0 | W90: =E90 -> 24 | X90: =W90/1.12 -> 21.428571 | Y90: =X90*0.12 -> 2.5714286
A91: 0442 | B91: 45713 | C91: INV-2518 | D91: Orange Juice Asia | E91: 3900 | F91: Meeting Room 3, 10am to 4pm | G91: Maya QR ph | H91: UBP | J91: Meeting Rooms | O91: 75.65 | P91: =E91-O91 -> 3824.35 | S91: =E91 -> 3900 | T91: =S91/1.12 -> 3482.1429 | U91: =T91*0.12 -> 417.85714 | V91: =T91+U91-S91 -> 0 | W91: =E91 -> 3900 | X91: =W91/1.12 -> 3482.1429 | Y91: =X91*0.12 -> 417.85714
A92: 0443 | B92: 45714 | C92: INV-2516 | D92: Estate of Remedios G. Suntay | E92: 8500 | F92: Meeting Room 1, 12:00 pm to 8:00 pm, Feb 22, 2025 | G92: Bank Transfer | H92: UBP | I92: S959614 | J92: Meeting Rooms | S92: =E92 -> 8500 | T92: =S92/1.12 -> 7589.2857 | U92: =T92*0.12 -> 910.71429 | V92: =T92+U92-S92 -> 0 | W92: =E92 -> 8500 | X92: =W92/1.12 -> 7589.2857 | Y92: =X92*0.12 -> 910.71429
A93: 0444 | B93: 45714 | C93: INV-2392/INV-2521 | D93: Mereb Realty | E93: 600 | F93: Locker rental, Dec 9, 2025 to Feb 8, 2025 | J93: Add-Ons | S93: =E93 -> 600 | T93: =S93/1.12 -> 535.71429 | U93: =T93*0.12 -> 64.285714 | V93: =T93+U93-S93 -> 0 | W93: =E93 -> 600 | X93: =W93/1.12 -> 535.71429 | Y93: =X93*0.12 -> 64.285714
A94: 0445 | B94: 45720 | C94: INV-2497 | D94: ACTINUTRITION | E94: 350 | F94: 3 Hour Fly Pass, Feb 12, 2025 - Morgan Pincaro | G94: Bank Transfer from SI to SVI | H94: UBP | I94: UB934938 | J94: Walk-Ins | S94: =E94 -> 350 | T94: =S94/1.12 -> 312.5 | U94: =T94*0.12 -> 37.5 | V94: =T94+U94-S94 -> 0 | W94: =E94 -> 350 | X94: =W94/1.12 -> 312.5 | Y94: =X94*0.12 -> 37.5
A95: 0446 | B95: 45720 | C95: INV-2519 | D95: ACTINUTRITION | E95: 350 | F95: 3 Hour Fly Pass, Mar 4, 2025 - Morgan Pincaro | G95: Bank Transfer from SI to SVI | H95: UBP | I95: UB45091 | J95: Walk-Ins | S95: =E95 -> 350 | T95: =S95/1.12 -> 312.5 | U95: =T95*0.12 -> 37.5 | V95: =T95+U95-S95 -> 0 | W95: =E95 -> 350 | X95: =W95/1.12 -> 312.5 | Y95: =X95*0.12 -> 37.5
A96: 0447 | B96: 45720 | C96: INV-2506 | D96: Recruitgo Philippines Inc. | E96: 34300 | F96: Meeting rooms and locker rent, Mar2025 | G96: Bank Transfer | H96: UBP | I96: UB1513061 | J96: Meeting Rooms | S96: =E96 -> 34300 | T96: =S96/1.12 -> 30625 | U96: =T96*0.12 -> 3675 | V96: =T96+U96-S96 -> 0 | W96: =E96 -> 34300 | X96: =W96/1.12 -> 30625 | Y96: =X96*0.12 -> 3675
A97: 0448 | B97: 45720 | C97: INV-2507 | D97: iHub Solutions (Philippines) Inc. | E97: 29700 | F97: Meeting Room 2 rental, March 2025, full payment | G97: Bank Transfer | H97: UBP | I97: UB500943 | J97: Meeting Rooms | S97: =E97 -> 29700 | T97: =S97/1.12 -> 26517.857 | U97: =T97*0.12 -> 3182.1429 | V97: =T97+U97-S97 -> 0 | W97: =E97 -> 29700 | X97: =W97/1.12 -> 26517.857 | Y97: =X97*0.12 -> 3182.1429
A98: 0449 | B98: 45720 | C98: INV-2510 | D98: 2911 Grand Management Consulting | E98: 1500 | F98: Use of Address, ₱1,500.00, Mar 6, 2024 - Apr 5, 2025 | G98: Bank Transfer | H98: MBTC | I98: SN776110 | J98: Virtual Office | S98: =E98 -> 1500 | T98: =S98/1.12 -> 1339.2857 | U98: =T98*0.12 -> 160.71429 | V98: =T98+U98-S98 -> 0 | W98: =E98 -> 1500 | X98: =W98/1.12 -> 1339.2857 | Y98: =X98*0.12 -> 160.71429
A99: 0450 | B99: 45720 | C99: INV-2508 | D99: Galleon Sciences R&D Corporation | E99: 15000 | F99: Use of Address, Mar 5, 2025 - Dec 31, 2025 | G99: Check | H99: UBP | I99: BPI 6000390854 | J99: Virtual Office | S99: =E99 -> 15000 | T99: =S99/1.12 -> 13392.857 | U99: =T99*0.12 -> 1607.1429 | V99: =T99+U99-S99 -> 0 | W99: =E99 -> 15000 | X99: =W99/1.12 -> 13392.857 | Y99: =X99*0.12 -> 1607.1429
A100: 0451 | B100: 45720 | C100: INV-2524 | D100: Raquel Alisangco | E100: 672 | F100: RFID Sticker | G100: Maya QR Standee | H100: UBP | J100: Add-Ons | O100: 3 | P100: =E100-O100 -> 669 | S100: =E100 -> 672 | T100: =S100/1.12 -> 600 | U100: =T100*0.12 -> 72 | V100: =T100+U100-S100 -> 0 | W100: =E100 -> 672 | X100: =W100/1.12 -> 600 | Y100: =X100*0.12 -> 72
...

Sheet Xero Purchases G 2025
A1: Xero Purchases Goods 2025
A2: Shirefolk Ventures, Inc.
A3: For the period 1 January 2025 to 31 March 2025
A5: Tax Rate Name contains VAT on Purchases (Capital Goods), VAT on Purchases (Goods Not Qual for Input Tax), VAT on Purchases (Goods)
A7: Date | B7: Source | C7: Contact | D7: Description | E7: Reference | F7: Debit | G7: Credit | H7: Gross | I7: Net | J7: Tax | K7: Account
A9: VAT on Purchases (Goods Not Qual for Input Tax)
A10: 45691 | B10: Spend Money | C10: Grand Union Supermarket Inc. | D10: Grand Union Supermarket Inc. - Pantry supplies- Vat exempt | E10: PCF 2359 | F10: 168 | G10: 0 | H10: 168 | I10: 168 | J10: 0 | K10: Office and Pantry Supplies
A11: 45699 | B11: Spend Money | C11: Grand Union Supermarket Inc. | D11: Grand Union Supermarket Inc. - Pantry and office Supplies- Vat exempt | E11: PCF 2371 | F11: 168 | G11: 0 | H11: 168 | I11: 168 | J11: 0 | K11: Office and Pantry Supplies
A12: 45703 | B12: Spend Money | C12: Grand Union Supermarket Inc. | D12: Grand Union Supermarket Inc. - Pantry Supplies- Vat exempt | E12: PCF 2382 | F12: 168 | G12: 0 | H12: 168 | I12: 168 | J12: 0 | K12: Office and Pantry Supplies
A14: 45719 | B14: Spend Money | C14: Edwin C. Nopuente Prop. | D14: Edwin C. Nopuente Prop. - 4 gallons purified water | E14: PCF 2405 | F14: 120 | G14: 0 | H14: 120 | I14: 120 | J14: 0 | K14: Office and Pantry Supplies
A15: 45728 | B15: Spend Money | C15: Edwin C. Nopuente Prop. | D15: Edwin C. Nopuente Prop. - water - 12 bottles | E15: PCF- 2430 | F15: 360 | G15: 0 | H15: 360 | I15: 360 | J15: 0 | K15: Office and Pantry Supplies
A16: 45728 | B16: Spend Money | C16: Grand Union Supermarket Inc. | D16: Grand Union Supermarket Inc. - Pantry Supplies- Vat exempt | E16: PCF- 2431 | F16: 84 | G16: 0 | H16: 84 | I16: 84 | J16: 0 | K16: Office and Pantry Supplies
A17: 45729 | B17: Spend Money | C17: Edwin C. Nopuente Prop. | D17: Edwin C. Nopuente Prop. - Water- 9 bottles | E17: PCF- 2432 | F17: 270 | G17: 0 | H17: 270 | I17: 270 | J17: 0 | K17: Office and Pantry Supplies
A18: 45730 | B18: Spend Money | C18: Edwin C. Nopuente Prop. | D18: Edwin C. Nopuente Prop. - Water | E18: PCF- 2434 | F18: 240 | G18: 0 | H18: 240 | I18: 240 | J18: 0 | K18: Office and Pantry Supplies
A19: 45733 | B19: Spend Money | C19: Edwin C. Nopuente Prop. | D19: Edwin C. Nopuente Prop. - Water | E19: PCF- 2435 | F19: 180 | G19: 0 | H19: 180 | I19: 180 | J19: 0 | K19: Office and Pantry Supplies
A20: 45734 | B20: Spend Money | C20: Grand Union Supermarket Inc. | D20: Grand Union Supermarket Inc. - Pantry Supplies- Vat Exempt | E20: PCF- 2437 | F20: 168 | G20: 0 | H20: 168 | I20: 168 | J20: 0 | K20: Office and Pantry Supplies
A21: 45736 | B21: Spend Money | C21: Edwin C. Nopuente Prop. | D21: Edwin C. Nopuente Prop. - Water | E21: PCF- 2439 | F21: 390 | G21: 0 | H21: 390 | I21: 390 | J21: 0 | K21: Office and Pantry Supplies
A22: 45737 | B22: Spend Money | C22: Grand Union Supermarket Inc. | D22: Grand Union Supermarket Inc. - Pantry Supplies- VAt exempt | E22: PCF- 2440 | F22: 84 | G22: 0 | H22: 84 | I22: 84 | J22: 0 | K22: Office and Pantry Supplies
... A30: 45747 | B30: Spend Money | C30: Edwin C. Nopuente Prop. | D30: Edwin C. Nopuente Prop. - Water | E30: PCF- 2452 | F30: 120 | G30: 0 | H30: 120 | I30: 120 | J30: 0 | K30: Office and Pantry Supplies
A31: Total VAT on Purchases (Goods Not Qual for Input Tax) | F31: 3774 | G31: 0 | H31: 3774 | I31: 3774 | J31: 0
A33: VAT on Purchases (Goods)
A34: 45663 | B34: Spend Money | C34: Grand Union Supermarket Inc. | D34: Grand Union Supermarket Inc. - Pantry Supplies | E34: PCF 2311 | F34: 1903.53 | G34: 0 | H34: 2131.95 | I34: 1903.53 | J34: 228.42 | K34: Office and Pantry Supplies
A35: 45665 | B35: Payable Invoice | C35: HEBREWSKAPE TRADING INC. | D35: HEBREWSKAPE TRADING INC. - Coffee Beans (Hazel Nut 13 kg.) Jan 2025 | E35: UBP-0125-922 | F35: 7670 | G35: 0 | H35: 8590.4 | I35: 7670 | J35: 920.4 | K35: Office and Pantry Supplies
A36: 45665 | B36: Spend Money | C36: Grand Union Supermarket Inc. | D36: Grand Union Supermarket Inc. - Pantry Supplies | E36: PCF 2314 | F36: 1710.89 | G36: 0 | H36: 1916.2 | I36: 1710.89 | J36: 205.31 | K36: Office and Pantry Supplies
A37: 45671 | B37: Spend Money | C37: Grand Union Supermarket Inc. | D37: Grand Union Supermarket Inc. - Pantry Supplies | E37: PCF 2322 | F37: 1016.07 | G37: 0 | H37: 1138 | I37: 1016.07 | J37: 121.93 | K37: Office and Pantry Supplies
A38: 45672 | B38: Spend Money | C38: Grand Union Supermarket Inc. | D38: Grand Union Supermarket Inc. - Pantry Supplies | E38: PCF 2323 | F38: 1206.21 | G38: 0 | H38: 1350.95 | I38: 1206.21 | J38: 144.74 | K38: Office and Pantry Supplies
A39: 45673 | B39: Spend Money | C39: Grand Union Supermarket Inc. | D39: Grand Union Supermarket Inc. - Pantry supplies | E39: PCF 2331 | F39: 964.73 | G39: 0 | H39: 1080.5 | I39: 964.73 | J39: 115.77 | K39: Office and Pantry Supplies
A40: 45673 | B40: Spend Money | C40: Grand Union Supermarket Inc. | D40: Grand Union Supermarket Inc. - A4 Bond Paper 2 reams | E40: PCF 2332 | F40: 478.57 | G40: 0 | H40: 536 | I40: 478.57 | J40: 57.43 | K40: Office and Pantry Supplies
A41: 45673 | B41: Spend Money | C41: Shakey's Pizza Asia Ventures Inc | D41: Shakey's Pizza Asia Ventures Inc - Food for Mancom meeting Jan 15 2025 | E41: PCF 2329 | F41: 900.89 | G41: 0 | H41: 1009 | I41: 900.89 | J41: 108.11 | K41: Meals Expense
A42: 45677 | B42: Spend Money | C42: Grand Union Supermarket Inc. | D42: Grand Union Supermarket Inc. - Pantry supplies | E42: PCF 2339 | F42: 2358.53 | G42: 0 | H42: 2641.55 | I42: 2358.53 | J42: 283.02 | K42: Office and Pantry Supplies
A43: 45679 | B43: Spend Money | C43: Grand Union Supermarket Inc. | D43: Grand Union Supermarket Inc. - Pantry Supplies | E43: PCF 2342 | F43: 1573.13 | G43: 0 | H43: 1761.9 | I43: 1573.13 | J43: 188.77 | K43: Office and Pantry Supplies
A44: 45681 | B44: Spend Money | C44: Grand Union Supermarket Inc. | D44: Grand Union Supermarket Inc. - Office Supplies | E44: PCF 2343 | F44: 89.29 | G44: 0 | H44: 100 | I44: 89.29 | J44: 10.71 | K44: Office and Pantry Supplies
A45: 45685 | B45: Spend Money | C45: Grand Union Supermarket Inc. | D45: Grand Union Supermarket Inc. - Pantry Supplies | E45: PCF 2350 | F45: 1557.32 | G45: 0 | H45: 1744.2 | I45: 1557.32 | J45: 186.88 | K45: Office and Pantry Supplies
... A89: 45747 | B89: Payable Invoice | C89: Puregold Price Club Inc.- GMA Cavite | D89: Puregold Price Club Inc.- GMA Cavite - Marketing Expense for July 2024 Ref: SI 127-009-00290911 | E89: UBP-0724-800 (3) | F89: 2036.61 | G89: 0 | H89: 2281 | I89: 2036.61 | J89: 244.39 | K89: Marketing Expense
A90: Total VAT on Purchases (Goods) | F90: 111591.18 | G90: 0 | H90: 124982.15 | I90: 111591.18 | J90: 13390.97
A92: Total | F92: 115365.18 | G92: 0 | H92: 128756.15 | I92: 115365.18 | J92: 13390.97

Sheet Q1 Amendment
A1: Account Transactions
A2: Shirefolk Ventures, Inc.
A3: For the period 1 January 2025 to 31 March 2025
A5: Source contains Adjustment, Bank Transfer, Conversion Balance Journal, Expense Claim, Expense Claim Payment, Manual Journal, Payable Credit Note, Payable Credit Note Allocation, Payable Credit Note Refund, Payable Invoice, Payable Overpayment, Payable Overpayment Allocation, Payable Overpayment Refund, Payable Payment, Payable Prepayment, Payable Prepayment Allocation, Payable Prepayment Refund, Receivable Credit Note, Receivable Credit Note Allocation, Receivable Credit Note Refund, Receivable Invoice, Receivable Overpayment, Receivable Overpayment Allocation, Receivable Overpayment Refund, Receivable Payment, Receivable Prepayment, Receivable Prepayment Refund, Receive Money, Spend Money
A6: Tax Rate Name contains VAT on Sales (Services), Zero Rated Sales (Services), Non-Tax, Tax Exempt
A8: Date | B8: Source | C8: Contact | D8: Description | E8: Reference | F8: Debit | G8: Credit | H8: Gross | I8: Tax | J8: Tax Rate | K8: Account
A10: Tax Exempt
A11: 45659 | B11: Receive Money | C11: Judicial Advocacy Law Firm | D11: Judicial Advocacy Law Firm - VO Balance initial deposit | F11: 0 | G11: 24000 | H11: 24000 | I11: 0 | J11: 0 | K11: Monthly Membership: Virtual Office with 10 Day Pass
A12: 45660 | B12: Spend Money | C12: Judicial Advocacy Law Firm | D12: Judicial Advocacy Law Firm - VO Balance initial deposit- returned due to insufficient fund | F12: 24000 | G12: 0 | H12: -24000 | I12: 0 | J12: 0 | K12: Monthly Membership: Virtual Office with 10 Day Pass
A13: 45719 | B13: Receive Money | C13: Unionbank | D13: Unionbank - Interest Income Feb 2025 | F13: 0 | G13: 13.89 | H13: 13.89 | I13: 0 | J13: 0 | K13: Interest Income
A14: 45719 | B14: Spend Money | C14: Unionbank | D14: Unionbank - Interest Income Feb 2025 Final tax | F14: 2.78 | G14: 0 | H14: -2.78 | I14: 0 | J14: 0 | K14: Interest Income
A15: 45747 | B15: Spend Money | C15: Metrobank | D15: Metrobank - Interest Income Final Tax Mar 2025 | F15: 11.45 | G15: 0 | H15: -11.45 | I15: 0 | J15: 0 | K15: Interest Income
A16: 45747 | B16: Receive Money | C16: Metrobank | D16: Metrobank - Interest Income Mar 2025 | F16: 0 | G16: 57.26 | H16: 57.26 | I16: 0 | J16: 0 | K16: Interest Income
A17: Total Tax Exempt | F17: =SUM(F11:F16) -> 24014.23 | G17: =SUM(G11:G16) -> 24071.15 | H17: =SUM(H11:H16) -> 56.92 | I17: =SUM(I11:I16) -> 0
A19: VAT on Sales (Services)
A20: 45658 | B20: Receivable Invoice | C20: Galleon Sciences R&D Corporation | D20: Galleon Sciences R&D Corporation - LPOG - Virtual Office, ₱3,500.00, Jan 1, 2025 - Jan 31, 2025 | E20: INV-2320 | F20: 0 | G20: 3125 | H20: 3500 | I20: 375 | J20: 12 | K20: Monthly Membership: Virtual Office with 10 Day Pass
A21: 45658 | B21: Receivable Invoice | C21: 2911 Grand Management Consulting Services | D21: 2911 Grand Management Consulting Services - LPOG - Virtual Office Renewal, ₱1,500.00, Jan 6, 2024 - Feb 5, 2025 | E21: INV-2410 | F21: 0 | G21: 1339.29 | H21: 1500 | I21: 160.71 | J21: 12 | K21: Add Ons: Business Address Registration
A22: 45658 | B22: Receivable Invoice | C22: Acton Town Inc | D22: Acton Town Inc - LPOG - Virtual Office Renewal, ₱1,500.00, Jan 13, 2025 - Dec 31, 2025 | E22: INV-2422 | F22: 0 | G22: 16071.43 | H22: 18000 | I22: 1928.57 | J22: 12 | K22: Add Ons: Business Address Registration
A23: 45658 | B23: Receivable Invoice | C23: Gesegnet Holdings Inc | D23: Gesegnet Holdings Inc - LPOG - Virtual Office Renewal, ₱1,500.00, Jan 1, 2025 - Dec 31, 2025 | E23: INV-2424 | F23: 0 | G23: 16071.43 | H23: 18000 | I23: 1928.57 | J23: 12 | K23: Add Ons: Business Address Registration
A24: 45658 | B24: Receivable Invoice | C24: Innoprince Inc. | D24: Innoprince Inc. - LPOG - Virtual Office Renewal, ₱1,500.00, Jan 1, 2025 - Dec 31, 2025 | E24: INV-2420 | F24: 0 | G24: 16071.43 | H24: 18000 | I24: 1928.57 | J24: 12 | K24: Add Ons: Business Address Registration
A25: 45658 | B25: Receivable Invoice | C25: Judicial Advocacy Law Firm | D25: Judicial Advocacy Law Firm - LPOG - Virtual Office, ₱4,000.00, Jan 1, 2025 - Jun 30, 2025 | E25: INV-2463 | F25: 0 | G25: 21428.57 | H25: 24000 | I25: 2571.43 | J25: 12 | K25: Monthly Membership: Virtual Office with 10 Day Pass
A26: 45658 | B26: Receivable Invoice | C26: Mereb Realty | D26: Mereb Realty - LPOG - Locker Rental, ₱300.00, Dec 9, 2024 - Jan 8, 2025 | E26: INV-2392 | F26: 0 | G26: 267.86 | H26: 300 | I26: 32.14 | J26: 12 | K26: Add Ons: Locker Rental
A27: 45658 | B27: Receivable Invoice | C27: Mereb Realty | D27: Mereb Realty - LPOG - Locker Rental, ₱300.00, Jan 9, 2025 - Feb 8, 2025 | E27: INV-2521 | F27: 0 | G27: 267.86 | H27: 300 | I27: 32.14 | J27: 12 | K27: Add Ons: Locker Rental
A28: 45658 | B28: Receivable Invoice | C28: Mereb Realty | D28: Mereb Realty - LPOG - Virtual Office, ₱4,000.00, Jan 16, 2025 - Feb 15, 2025 | E28: INV-2522 | F28: 0 | G28: 3571.43 | H28: 4000 | I28: 428.57 | J28: 12 | K28: Monthly Membership: Virtual Office with 10 Day Pass
A29: 45658 | B29: Receivable Invoice | C29: QBE Group Shared Services Ltd- Philippine Branch | D29: QBE Group Shared Services Ltd- Philippine Branch - 10% of PRIVATE OFFICE RENTAL with VAT | E29: INV-2393 | F29: 0 | G29: 175560 | H29: 196627.2 | I29: 21067.2 | J29: 12 | K29: Monthly Membership: Private Office
A30: 45658 | B30: Receivable Invoice | C30: QBE Group Shared Services Ltd- Philippine Branch | D30: QBE Group Shared Services Ltd- Philippine Branch - 10% of PRIVATE OFFICE RENTAL with VAT | E30: INV-2393 | F30: 0 | G30: 1562.79 | H30: 1750.32 | I30: 187.53 | J30: 12 | K30: Other Revenue from Clients
A31: 45658 | B31: Receivable Invoice | C31: Rapha Jirei Holdings Inc | D31: Rapha Jirei Holdings Inc - LPOG - Virtual Office Renewal, ₱1,500.00, Jan 1, 2025 - Dec 31, 2025 | E31: INV-2423 | F31: 0 | G31: 16071.43 | H31: 18000 | I31: 1928.57 | J31: 12 | K31: Add Ons: Business Address Registration
... A248: 45746 | B248: Receivable Invoice | C248: Feast Bellevue PM | D248: Feast Bellevue PM - LPOG - Basic PA system | E248: INV-2549 | F248: 0 | G248: 892.86 | H248: 1000 | I248: 107.14 | J248: 12 | K248: Events: Equipment Rental
A249: Total VAT on Sales (Services) | F249: =SUM(F20:F248) -> 0 | G249: =SUM(G20:G248) -> 1468889.2 | H249: =SUM(H20:H248) -> 1645155.9 | I249: =SUM(I20:I248) -> 176266.71
D250: REPORTED IN Q4 2024
A251: 45658 | B251: Receivable Invoice | C251: Galleon Sciences R&D Corporation | D251: Galleon Sciences R&D Corporation - LPOG - Virtual Office, ₱3,500.00, Jan 1, 2025 - Jan 31, 2025 | E251: INV-2320 | F251: 0 | G251: 3125 | H251: 3500 | I251: 375 | J251: 12 | K251: Monthly Membership: Virtual Office with 10 Day Pass
A252: 45689 | B252: Receivable Invoice | C252: Galleon Sciences R&D Corporation | D252: Galleon Sciences R&D Corporation - LPOG - Virtual Office, ₱3,500.00, Feb 1, 2025 - Feb 28, 2025 | E252: INV-2321 | F252: 0 | G252: 3125 | H252: 3500 | I252: 375 | J252: 12 | K252: Monthly Membership: Virtual Office with 10 Day Pass
A253: 45658 | B253: Receivable Invoice | C253: 2911 Grand Management Consulting Services | D253: 2911 Grand Management Consulting Services - LPOG - Virtual Office Renewal, ₱1,500.00, Jan 6, 2024 - Feb 5, 2025 | E253: INV-2410 | F253: 0 | G253: 1339.29 | H253: 1500 | I253: 160.71 | J253: 12 | K253: Add Ons: Business Address Registration
A254: 45658 | B254: Receivable Invoice | C254: Innoprince Inc. | D254: Innoprince Inc. - LPOG - Virtual Office Renewal, ₱1,500.00, Jan 1, 2025 - Dec 31, 2025 | E254: INV-2420 | F254: 0 | G254: 16071.43 | H254: 18000 | I254: 1928.57 | J254: 12 | K254: Add Ons: Business Address Registration
A255: 45658 | B255: Receivable Invoice | C255: Sw7 Solagratia Inc | D255: Sw7 Solagratia Inc - LPOG - Virtual Office Renewal, ₱1,500.00, Jan 1, 2025 - Dec 31, 2025 | E255: INV-2421 | F255: 0 | G255: 16071.43 | H255: 18000 | I255: 1928.57 | J255: 12 | K255: Add Ons: Business Address Registration
A256: 45658 | B256: Receivable Invoice | C256: Acton Town Inc | D256: Acton Town Inc - LPOG - Virtual Office Renewal, ₱1,500.00, Jan 13, 2025 - Dec 31, 2025 | E256: INV-2422 | F256: 0 | G256: 16071.43 | H256: 18000 | I256: 1928.57 | J256: 12 | K256: Add Ons: Business Address Registration
A257: 45658 | B257: Receivable Invoice | C257: Rapha Jirei Holdings Inc | D257: Rapha Jirei Holdings Inc - LPOG - Virtual Office Renewal, ₱1,500.00, Jan 1, 2025 - Dec 31, 2025 | E257: INV-2423 | F257: 0 | G257: 16071.43 | H257: 18000 | I257: 1928.57 | J257: 12 | K257: Add Ons: Business Address Registration
A258: 45658 | B258: Receivable Invoice | C258: Gesegnet Holdings Inc | D258: Gesegnet Holdings Inc - LPOG - Virtual Office Renewal, ₱1,500.00, Jan 1, 2025 - Dec 31, 2025 | E258: INV-2424 | F258: 0 | G258: 16071.43 | H258: 18000 | I258: 1928.57 | J258: 12 | K258: Add Ons: Business Address Registration
G259: =SUM(G251:G258) -> 87946.44 | H259: =SUM(H251:H258) -> 98500 | I259: =SUM(I251:I258) -> 10553.56
D260: SALES INVOICES ISSUED IN Q1 2025
A261: 45677 | B261: Receivable Payment | C261: Radiance Image Consultancy and Training Inc. | D261: Payment: Radiance Image Consultancy and Training Inc. | E261: SI 0391 | F261: 0 | G261: 16071.43 | H261: 18000 | I261: 1928.57 | J261: 12 | K261: Add Ons: Business Address Registration
A262: 45677 | B262: Receivable Payment | C262: Radiance Image Consultancy and Training Inc. | D262: Payment: Radiance Image Consultancy and Training Inc. | E262: SI 0391 | F262: 0 | G262: 518.46 | H262: 580.68 | I262: 62.22 | J262: 12 | K262: Add Ons: Business Address Registration
C263: iHub Solutions (Philippines) Inc. | D263: iHub Solutions (Philippines) Inc. | E263: INV-2431 | G263: =30000/1.12 -> 26785.714 | H263: 30000 | I263: =G263*12% -> 3214.2857
A264: 45658 | B264: Receivable Invoice | C264: SwipeEdge Corp. | D264: SwipeEdge Corp. - LPOG - Virtual Office, ₱4,000.00, Jan 1, 2025 - Jun 30, 2025 | E264: INV-2469 | F264: 0 | G264: 21428.57 | H264: 24000 | I264: 2571.43 | J264: 12 | K264: Monthly Membership: Virtual Office with 10 Day Pass
G265: =SUM(G261:G264) -> 64804.174
D267: Q1 REPORTED VAT | G267: 885762.54 | H267: Q1 Accrual | I267: =G249 -> 1468889.2
D268: SHOULD BE | G268: 1445746.9 | H268: Reported In Q4 | I268: =-G259 -> -87946.44
D269: DIFFERENCE | G269: =G267-G268 -> -559984.41 | H269: INV-2462/SI 0391 | I269: =G261+G262 -> 16589.89 | J269: Sales invoices were issued in Q1 2025, but the Xero invoices were dated 2024.
D270: QBE INVOICE REPORTED THE GROSS AMOUNT AS ZERO RATED | E270: INV-2393 | G270: 177122.79 | H270: INV-2431/SI 0374 | I270: =G263 -> 26785.714 | J270: Sales invoices were issued in Q1 2025, but the Xero invoices were dated April 2025.
E271: INV-2440 | G271: 177122.79 | H271: INV-2469/SI 0400 | I271: =G264 -> 21428.57 | J271: The Sales Invoice amount is Php 48,000, but only Php 24,000 was recorded in both the working paper and Xero.
E272: INV-2500 | G272: 177122.79 | H272: Q1: SHOULD BE | I272: =SUM(I267:I271) -> 1445747
D273: The actual sales should be Php 600, but only Php 550 was recorded in the working paper. | E273: INV-2480 | G273: =I276 -> 44.642857
D274: The actual sales should be Php 11,500, but only Php 3,500 was recorded in the working paper. | E274: INV-2549 | G274: =I280 -> 7142.8571 | H274: INV-2480 | I274: =600/1.12 -> 535.71429
D275: The Sales Invoice amount is Php 48,000, but only Php 24,000 was recorded in both the working paper and Xero. | E275: INV-2469 | G275: 21428.57 | H275: Reported | I275: =550/1.12 -> 491.07143
G276: =SUM(G270:G275) -> 559984.44 | H276: Diff: | I276: =I274-I275 -> 44.642857
G277: =SUM(G269,G276) -> 0.03
H278: INV-2549 | I278: =11500/1.12 -> 10267.857
H279: Reported | I279: =3500/1.12 -> 3125
H280: Diff: | I280: =I278-I279 -> 7142.8571
A282: 45658 | B282: Receivable Invoice | C282: QBE Group Shared Services Ltd- Philippine Branch | D282: QBE Group Shared Services Ltd- Philippine Branch - Large Room 1, Jan 1, 2025 - Jan 31, 2025 | E282: INV-2393 | F282: 0 | G282: 311850 | H282: 311850 | I282: 0 | J282: 0 | K282: Monthly Membership: Private Office
A283: 45658 | B283: Receivable Invoice | C283: QBE Group Shared Services Ltd- Philippine Branch | D283: QBE Group Shared Services Ltd- Philippine Branch - Large Room 2, Jan 1, 2025 - Jan 31, 2025 | E283: INV-2393 | F283: 0 | G283: 166320 | H283: 166320 | I283: 0 | J283: 0 | K283: Monthly Membership: Private Office
A284: 45658 | B284: Receivable Invoice | C284: QBE Group Shared Services Ltd- Philippine Branch | D284: QBE Group Shared Services Ltd- Philippine Branch - Large Room 3, Jan 1, 2025 - Jan 31, 2025 | E284: INV-2393 | F284: 0 | G284: 259875 | H284: 259875 | I284: 0 | J284: 0 | K284: Monthly Membership: Private Office
A285: 45658 | B285: Receivable Invoice | C285: QBE Group Shared Services Ltd- Philippine Branch | D285: QBE Group Shared Services Ltd- Philippine Branch - Large Room 4, Jan 1, 2025 - Jan 31, 2025 | E285: INV-2393 | F285: 0 | G285: 187110 | H285: 187110 | I285: 0 | J285: 0 | K285: Monthly Membership: Private Office
A286: 45658 | B286: Receivable Invoice | C286: QBE Group Shared Services Ltd- Philippine Branch | D286: QBE Group Shared Services Ltd- Philippine Branch - Large Room 5, Jan 1, 2025 - Jan 31, 2025 | E286: INV-2393 | F286: 0 | G286: 259875 | H286: 259875 | I286: 0 | J286: 0 | K286: Monthly Membership: Private Office
A287: 45658 | B287: Receivable Invoice | C287: QBE Group Shared Services Ltd- Philippine Branch | D287: QBE Group Shared Services Ltd- Philippine Branch - Medium Room 1, Jan 1, 2025 - Jan 31, 2025 | E287: INV-2393 | F287: 0 | G287: 155925 | H287: 155925 | I287: 0 | J287: 0 | K287: Monthly Membership: Private Office
A288: 45658 | B288: Receivable Invoice | C288: QBE Group Shared Services Ltd- Philippine Branch | D288: QBE Group Shared Services Ltd- Philippine Branch - Small Room 1, Jan 1, 2025 - Jan 31, 2025 | E288: INV-2393 | F288: 0 | G288: 62370 | H288: 62370 | I288: 0 | J288: 0 | K288: Monthly Membership: Private Office
A289: 45658 | B289: Receivable Invoice | C289: QBE Group Shared Services Ltd- Philippine Branch | D289: QBE Group Shared Services Ltd- Philippine Branch - Small Room 2, Jan 1, 2025 - Jan 31, 2025 | E289: INV-2393 | F289: 0 | G289: 62370 | H289: 62370 | I289: 0 | J289: 0 | K289: Monthly Membership: Private Office
A290: 45658 | B290: Receivable Invoice | C290: QBE Group Shared Services Ltd- Philippine Branch | D290: QBE Group Shared Services Ltd- Philippine Branch - Small Room 3, Jan 1, 2025 - Jan 31, 2025 | E290: INV-2393 | F290: 0 | G290: 72765 | H290: 72765 | I290: 0 | J290: 0 | K290: Monthly Membership: Private Office
A291: 45658 | B291: Receivable Invoice | C291: QBE Group Shared Services Ltd- Philippine Branch | D291: QBE Group Shared Services Ltd- Philippine Branch - LPOG - Call Room 1, Jan 1, 2025 - Jan 31, 2025 | E291: INV-2393 | F291: 0 | G291: 10395 | H291: 10395 | I291: 0 | J291: 0 | K291: Monthly Membership: Private Office
A292: 45658 | B292: Receivable Invoice | C292: QBE Group Shared Services Ltd- Philippine Branch | D292: QBE Group Shared Services Ltd- Philippine Branch - LPOG - Call Room 2 - Call Room 2, Jan 1, 2025 - Jan 31, 2025 | E292: INV-2393 | F292: 0 | G292: 10395 | H292: 10395 | I292: 0 | J292: 0 | K292: Monthly Membership: Private Office
A293: 45658 | B293: Receivable Invoice | C293: QBE Group Shared Services Ltd- Philippine Branch | D293: QBE Group Shared Services Ltd- Philippine Branch - LPOG - Call Room 3, Jan 1, 2025 - Jan 31, 2025 | E293: INV-2393 | F293: 0 | G293: 10395 | H293: 10395 | I293: 0 | J293: 0 | K293: Monthly Membership: Private Office
... A323: 45717 | B323: Receivable Invoice | C323: QBE Group Shared Services Ltd- Philippine Branch | D323: QBE Group Shared Services Ltd- Philippine Branch - Parking rental (Car), Mar 1, 2025 - Mar 31, 2025 | E323: INV-2500 | F323: 0 | G323: 14065.14 | H323: 14065.14 | I323: 0 | J323: 0 | K323: Other Revenue from Clients
A324: Total Zero Rated Sales (Services) | F324: =SUM(F282:F323) -> 0 | G324: =SUM(G282:G323) -> 4782315.4 | H324: =SUM(H282:H323) -> 4782315.4 | I324: =SUM(I282:I323) -> 0
D326: Q1 REPORTED | G326: 5377448
D327: SHOULD BE | G327: =H324 -> 4782315.4
D328: DIFFERENCE | G328: =G326-G327 -> 595132.56
D329: QBE INVOICE REPORTED THE GROSS AMOUNT AS ZERO RATED | E329: INV-2393 | G329: =177122.79*1.12 -> 198377.52
E330: INV-2440 | G330: =177122.79*1.12 -> 198377.52
E331: INV-2500 | G331: =177122.79*1.12 -> 198377.52
G332: =SUM(G329:G331) -> 595132.57
G333: =G328-G332 -> -0.014399999
A335: Total | F335: =SUM(F17,F249,F324) -> 24014.23 | G335: =SUM(G17,G249,G324) -> 6275275.8 | H335: =SUM(H17,H249,H324) -> 6427528.3 | I335: =SUM(I17,I249,I324) -> 176266.71

Sheet 2550Q
A2: SVI 2550Q Schedule 3 (Q4 2023)
C35: 68849.97
C36: 57351.6
A38: SVI 2550Q Schedule 3 (Q1 2024)
A72: SVI 2550Q Schedule 3 (Q3 2024)

Sheet Xero Purchases S 2025
A1: Xero Purchases Goods 2025
A2: Shirefolk Ventures, Inc.
A3: For the period 1 January 2025 to 31 March 2025
A5: Tax Rate Name contains VAT on Purchases (Services), VAT on Purchases (Services Not Qual for Input Tax), VAT on Purchases (Services by Non-residents)
A7: Date | B7: Source | C7: Contact | D7: Description | E7: Reference | F7: Debit | G7: Credit | H7: Gross | I7: Net | J7: Tax | K7: Account
A9: VAT on Purchases (Services Not Qual for Input Tax)
A10: 45658 | B10: Payable Invoice | C10: Shirefolk, Inc. (Doing business under the name and style of Launchpad Coworking) | D10: Shirefolk, Inc. (Doing business under the name and style of Launchpad Coworking) - Share in OfficeRnd (Members) -Sept 2024 | E10: UBP-0924-939 | F10: 5968.13 | G10: 0 | H10: 5968.13 | I10: 5968.13 | J10: 0 | K10: Software Subscriptions
A11: 45658 | B11: Payable Invoice | C11: Shirefolk, Inc. (Doing business under the name and style of Launchpad Coworking) | D11: Shirefolk, Inc. (Doing business under the name and style of Launchpad Coworking) - Share in OfficeRnd (Esign) -Sept 2024 | E11: UBP-0924-939 | F11: 213.15 | G11: 0 | H11: 213.15 | I11: 213.15 | J11: 0 | K11: Software Subscriptions
A12: 45658 | B12: Payable Invoice | C12: Shirefolk, Inc. (Doing business under the name and style of Launchpad Coworking) | D12: Shirefolk, Inc. (Doing business under the name and style of Launchpad Coworking) - Share in Xero - Sept 2024 | E12: UBP-0924-939 | F12: 2529.85 | G12: 0 | H12: 2529.85 | I12: 2529.85 | J12: 0 | K12: Software Subscriptions
A13: 45658 | B13: Payable Invoice | C13: Shirefolk, Inc. (Doing business under the name and style of Launchpad Coworking) | D13: Shirefolk, Inc. (Doing business under the name and style of Launchpad Coworking) - Google GSuite -Sept 2024 | E13: UBP-0924-939 | F13: 2813.01 | G13: 0 | H13: 2813.01 | I13: 2813.01 | J13: 0 | K13: Software Subscriptions
A14: 45658 | B14: Payable Invoice | C14: Shirefolk, Inc. (Doing business under the name and style of Launchpad Coworking) | D14: Shirefolk, Inc. (Doing business under the name and style of Launchpad Coworking) - Facebook Ads | E14: UBP-0924-939 | F14: 5150.02 | G14: 0 | H14: 5150.02 | I14: 5150.02 | J14: 0 | K14: Marketing Expense
A15: 45658 | B15: Payable Invoice | C15: Shirefolk, Inc. (Doing business under the name and style of Launchpad Coworking) | D15: Shirefolk, Inc. (Doing business under the name and style of Launchpad Coworking) - Share in OfficeRnd (Members) -Aug2024 | E15: UBP-0824-938 | F15: 5609.09 | G15: 0 | H15: 5609.09 | I15: 5609.09 | J15: 0 | K15: Software Subscriptions
A16: 45658 | B16: Payable Invoice | C16: Shirefolk, Inc. (Doing business under the name and style of Launchpad Coworking) | D16: Shirefolk, Inc. (Doing business under the name and style of Launchpad Coworking) - Share in OfficeRnd (Esign) -Aug2024 | E16: UBP-0824-938 | F16: 69.25 | G16: 0 | H16: 69.25 | I16: 69.25 | J16: 0 | K16: Software Subscriptions
A17: 45658 | B17: Payable Invoice | C17: Shirefolk, Inc. (Doing business under the name and style of Launchpad Coworking) | D17: Shirefolk, Inc. (Doing business under the name and style of Launchpad Coworking) - Share in Xero - Aug2024 | E17: UBP-0824-938 | F17: 2622.31 | G17: 0 | H17: 2622.31 | I17: 2622.31 | J17: 0 | K17: Software Subscriptions
A18: 45658 | B18: Payable Invoice | C18: Shirefolk, Inc. (Doing business under the name and style of Launchpad Coworking) | D18: Shirefolk, Inc. (Doing business under the name and style of Launchpad Coworking) - Google GSuite -Aug2024 | E18: UBP-0824-938 | F18: 2813.51 | G18: 0 | H18: 2813.51 | I18: 2813.51 | J18: 0 | K18: Software Subscriptions
A19: 45658 | B19: Payable Invoice | C19: Shirefolk, Inc. (Doing business under the name and style of Launchpad Coworking) | D19: Shirefolk, Inc. (Doing business under the name and style of Launchpad Coworking) - Facebook Ads | E19: UBP-0824-938 | F19: 2782.7 | G19: 0 | H19: 2782.7 | I19: 2782.7 | J19: 0 | K19: Marketing Expense
A20: 45666 | B20: Spend Money | C20: Patricio L. Boncayao, Jr. Law Office | D20: Patricio L. Boncayao, Jr. Law Office - Notorial Fee - SVI | E20: PCF 2316 | F20: 150 | G20: 0 | H20: 150 | I20: 150 | J20: 0 | K20: Professional Fees
A21: 45673 | B21: Spend Money | C21: Patricio L. Boncayao, Jr. Law Office | D21: Patricio L. Boncayao, Jr. Law Office - Notary fee SVI Sworn Declaration | E21: PCF 2326 | F21: 300 | G21: 0 | H21: 300 | I21: 300 | J21: 0 | K21: Professional Fees
... A31: 45734 | B31: Payable Invoice | C31: National Privacy Commission | D31: National Privacy Commission - NPC Registration- Transaction Fee | E31: UBP-0325-974 | F31: 17 | G31: 0 | H31: 17 | I31: 17 | J31: 0 | K31: Miscellaneous Expense
A32: Total VAT on Purchases (Services Not Qual for Input Tax) | F32: 44388.02 | G32: 160 | H32: 44228.02 | I32: 44228.02 | J32: 0
A34: VAT on Purchases (Services)
A35: 45658 | B35: Payable Invoice | C35: Airlive Communications Inc. | D35: Airlive Communications Inc. - Direct Internet Access for the month of Jan 2025 | E35: UBP-0125-914 | F35: 150000 | G35: 0 | H35: 168000 | I35: 150000 | J35: 18000 | K35: Communication Expense
A36: 45658 | B36: Payable Invoice | C36: Griffinstone, Inc. | D36: Griffinstone, Inc. - Parking Rental for Jan 2025 Invoice: 4030 | E36: UBP-0125-917 | F36: 20420.52 | G36: 0 | H36: 22870.98 | I36: 20420.52 | J36: 2450.46 | K36: Parking Rental
A37: 45658 | B37: Payable Invoice | C37: Griffinstone, Inc. | D37: Griffinstone, Inc. - Rent for Jan 2025 Invoice No. 4028 | E37: MBT-0125-920 | F37: 678797.7 | G37: 0 | H37: 760253.42 | I37: 678797.7 | J37: 81455.72 | K37: Rent Expense
A38: 45658 | B38: Payable Invoice | C38: Griffinstone, Inc. | D38: Griffinstone, Inc. - CUSA for Jan 2025 Invoice No. 4059 | E38: MBT-0125-921 | F38: 175173.6 | G38: 0 | H38: 196194.43 | I38: 175173.6 | J38: 21020.83 | K38: Common Area Charges
A39: 45658 | B39: Payable Invoice | C39: Converge Information and Communications Technology Solutions Inc. | D39: Converge Information and Communications Technology Solutions Inc. - M. Line Subs Fee - Jan 2025 | E39: UBP-0125-924 | F39: 65000 | G39: 0 | H39: 72800 | I39: 65000 | J39: 7800 | K39: Communication Expense
A40: 45658 | B40: Payable Invoice | C40: GlobalBridge Resources Corporation | D40: GlobalBridge Resources Corporation - Contract services for bookkeeping and BIR filing support -Jan 2025 | E40: UBP-0125-928 | F40: 6800 | G40: 0 | H40: 7616 | I40: 6800 | J40: 816 | K40: Professional Fees
A41: 45674 | B41: Payable Invoice | C41: PLDT Inc. | D41: PLDT Inc. - PLDT Landline - Jan 2025 SOA Note/s: ADA | E41: UBP-0125-925 | F41: 1484.02 | G41: 0 | H41: 1662.1 | I41: 1484.02 | J41: 178.08 | K41: Communication Expense
A42: 45674 | B42: Spend Money | C42: Ayala Property Management Corporation | D42: Ayala Property Management Corporation - Parking ticket fee of sir Rye at BGC for QBE cheque pick up | E42: PCF 2335 | F42: 44.64 | G42: 0 | H42: 50 | I42: 44.64 | J42: 5.36 | K42: Toll and Parking Fees
A43: 45686 | B43: Payable Invoice | C43: Philhealthcare, Inc. | D43: Philhealthcare, Inc. - Plan Type: Emerald Open MBL: P200,00 (Semi-Private) with Dental Benefit Period Covered: 01/29/2024 - 10/16/2025 1. Tanyag, Nerrie- New Pro-rated rate | E43: UBP-0125-958 | F43: 7550.88 | G43: 0 | H43: 8456.99 | I43: 7550.88 | J43: 906.11 | K43: Other Employee Benefits
A44: 45688 | B44: Payable Invoice | C44: Griffinstone, Inc. | D44: Griffinstone, Inc. - Power Consumption for the period Jan 26 - Feb 25, 2025 Sales Invoice No. 4217 | E44: UBP-0125-970 | F44: 91923.52 | G44: 0 | H44: 102954.34 | I44: 91923.52 | J44: 11030.82 | K44: Utilities Expense
A45: 45688 | B45: Payable Invoice | C45: Griffinstone, Inc. | D45: Griffinstone, Inc. - Water Consumption for the period Jan 15 - Feb 14, 2025 Sales Invoice No. 4156 | E45: UBP-0125-970 | F45: 804.48 | G45: 0 | H45: 901.02 | I45: 804.48 | J45: 96.54 | K45: Utilities Expense
A46: 45688 | B46: Payable Invoice | C46: Griffinstone, Inc. | D46: Griffinstone, Inc. - Bio-Augmentation Program for February 2025 Sales Invoice No. 4228 | E46: UBP-0225-971 | F46: 1365 | G46: 0 | H46: 1528.8 | I46: 1365 | J46: 163.8 | K46: Repairs and Maintenance
... A82: 45747 | B82: Payable Invoice | C82: Griffinstone, Inc. | D82: Griffinstone, Inc. - Water Consumption for the period Mar 15 - Apr 14, 2025 Sales Invoice No. 4341 | E82: UBP-0325-1006 | F82: 800.32 | G82: 0 | H82: 896.36 | I82: 800.32 | J82: 96.04 | K82: Utilities Expense
A83: Total VAT on Purchases (Services) | F83: 3624304.2 | G83: 0 | H83: 4059220.7 | I83: 3624304.2 | J83: 434916.49
A85: Total | F85: 3668692.2 | G85: 160 | H85: 4103448.7 | I85: 3668532.2 | J85: 434916.49

Sheet Xero Sales 2025
A1: Account Transactions
A2: Shirefolk Ventures, Inc.
A3: For the period 1 January 2025 to 31 March 2025
A5: Source contains Adjustment, Bank Transfer, Conversion Balance Journal, Expense Claim, Expense Claim Payment, Manual Journal, Payable Credit Note, Payable Credit Note Allocation, Payable Credit Note Refund, Payable Invoice, Payable Overpayment, Payable Overpayment Allocation, Payable Overpayment Refund, Payable Payment, Payable Prepayment, Payable Prepayment Allocation, Payable Prepayment Refund, Receivable Credit Note, Receivable Credit Note Allocation, Receivable Credit Note Refund, Receivable Invoice, Receivable Overpayment, Receivable Overpayment Allocation, Receivable Overpayment Refund, Receivable Payment, Receivable Prepayment, Receivable Prepayment Refund, Receive Money, Spend Money
A6: Tax Rate Name contains VAT on Sales (Services), Zero Rated Sales (Services), Non-Tax, Tax Exempt
A8: Date | B8: Source | C8: Contact | D8: Description | E8: Reference | F8: Debit | G8: Credit | H8: Gross | I8: Tax | J8: Tax Rate | K8: Account
A10: Non-Tax
A11: 45671 | B11: Receivable Payment | C11: iHub Solutions (Philippines) Inc. | D11: Payment: iHub Solutions (Philippines) Inc. | E11: SI 0374 | F11: 0 | G11: 3136 | H11: 3136 | I11: 0 | J11: 0 | K11: Income from Access Cards
A12: 45684 | B12: Receivable Payment | C12: SwipeEdge Corp. | D12: Payment: SwipeEdge Corp. | E12: SI 0401 | F12: 0 | G12: 448 | H12: 448 | I12: 0 | J12: 0 | K12: Income from Access Cards
A13: 45692 | B13: Receivable Payment | C13: Slingshot Global Inc. | D13: Payment: Slingshot Global Inc. | E13: SI 0412 | F13: 0 | G13: 967.8 | H13: 967.8 | I13: 0 | J13: 0 | K13: Add Ons: Business Address Registration
A14: 45698 | B14: Receivable Payment | C14: Shard Sound Production | D14: Payment: Shard Sound Production | E14: SI 0420 | F14: 0 | G14: 448 | H14: 448 | I14: 0 | J14: 0 | K14: Income from Access Cards
A15: Total Non-Tax | F15: =SUM(F11:F14) -> 0 | G15: =SUM(G11:G14) -> 4999.8 | H15: =SUM(H11:H14) -> 4999.8 | I15: =SUM(I11:I14) -> 0
A17: Tax Exempt
A18: 45659 | B18: Receive Money | C18: Judicial Advocacy Law Firm | D18: Judicial Advocacy Law Firm - VO Balance initial deposit | F18: 0 | G18: 24000 | H18: 24000 | I18: 0 | J18: 0 | K18: Monthly Membership: Virtual Office with 10 Day Pass
A19: 45660 | B19: Spend Money | C19: Judicial Advocacy Law Firm | D19: Judicial Advocacy Law Firm - VO Balance initial deposit- returned due to insufficient fund | F19: 24000 | G19: 0 | H19: -24000 | I19: 0 | J19: 0 | K19: Monthly Membership: Virtual Office with 10 Day Pass
A20: 45713 | B20: Receive Money | C20: Metrobank | D20: Metrobank - Interest Income from Time Deposit | F20: 0 | G20: 7347.45 | H20: 7347.45 | I20: 0 | J20: 0 | K20: Interest Income
A21: 45719 | B21: Spend Money | C21: Unionbank | D21: Unionbank - Interest Income Feb 2025 Final tax | F21: 2.78 | G21: 0 | H21: -2.78 | I21: 0 | J21: 0 | K21: Interest Income
A22: 45719 | B22: Receive Money | C22: Unionbank | D22: Unionbank - Interest Income Feb 2025 | F22: 0 | G22: 13.89 | H22: 13.89 | I22: 0 | J22: 0 | K22: Interest Income
A23: 45747 | B23: Spend Money | C23: Metrobank | D23: Metrobank - Interest Income Final Tax Mar 2025 | F23: 11.45 | G23: 0 | H23: -11.45 | I23: 0 | J23: 0 | K23: Interest Income
A24: 45747 | B24: Receive Money | C24: Metrobank | D24: Metrobank - Interest Income Mar 2025 | F24: 0 | G24: 57.26 | H24: 57.26 | I24: 0 | J24: 0 | K24: Interest Income
A25: Total Tax Exempt | F25: =SUM(F18:F24) -> 24014.23 | G25: =SUM(G18:G24) -> 31418.6 | H25: =SUM(H18:H24) -> 7404.37 | I25: =SUM(I18:I24) -> 0
A27: VAT on Sales (Services)
A28: 45660 | B28: Receivable Payment | C28: Timedly Solutions, Inc. | D28: Payment: Timedly Solutions, Inc. | E28: SI 0353 | F28: 0 | G28: 3125 | H28: 3500 | I28: 375 | J28: 12 | K28: Monthly Membership: Virtual Office with 10 Day Pass
A29: 45663 | B29: Receivable Payment | C29: Intertool Precision Group Inc | D29: Payment: Intertool Precision Group Inc | E29: SI 0354 | F29: 0 | G29: 1875 | H29: 2100 | I29: 225 | J29: 12 | K29: Meeting Room
A30: 45664 | B30: Receivable Payment | C30: Bluvision Surveillance and Analytics Inc. | D30: Payment: Bluvision Surveillance and Analytics Inc. | E30: SI 0356 | F30: 0 | G30: 4017.86 | H30: 4500 | I30: 482.14 | J30: 12 | K30: Meeting Room
A31: 45665 | B31: Receivable Payment | C31: Lawrence Alexander | D31: Payment: Lawrence Alexander | E31: SI 0357 | F31: 0 | G31: 17.86 | H31: 20 | I31: 2.14 | J31: 12 | K31: Add Ons: Printing
A32: 45665 | B32: Receivable Payment | C32: Limuel Libres | D32: Payment: Limuel Libres | E32: SI 0358 | F32: 0 | G32: 312.5 | H32: 350 | I32: 37.5 | J32: 12 | K32: Walk Ins: Whole Day Pass
A33: 45666 | B33: Receivable Payment | C33: Margarita Bariring | D33: Payment: Margarita Bariring | E33: SI 0359 | F33: 0 | G33: 4910.71 | H33: 5500 | I33: 589.29 | J33: 12 | K33: Monthly Membership: Monthly Fly Pass
A34: 45666 | B34: Receivable Payment | C34: Moom Health Services Corp | D34: Payment: Moom Health Services Corp | E34: SI 0362 | F34: 0 | G34: 3571.43 | H34: 4000 | I34: 428.57 | J34: 12 | K34: Monthly Membership: Virtual Office with 10 Day Pass
A35: 45666 | B35: Receivable Payment | C35: MARRO FASHION STYLING STUDIO | D35: Payment: MARRO FASHION STYLING STUDIO | E35: SI 0360 | F35: 0 | G35: 2142.86 | H35: 2400 | I35: 257.14 | J35: 12 | K35: Meeting Room
A36: 45666 | B36: Receivable Payment | C36: F.A BAUTISTA & PARTNERS | D36: Payment: F.A BAUTISTA & PARTNERS | E36: SI 0361 | F36: 0 | G36: 4910.71 | H36: 5500 | I36: 589.29 | J36: 12 | K36: Meeting Room
A37: 45667 | B37: Receivable Payment | C37: Kevin Carmelina | D37: Payment: Kevin Carmelina | E37: SI 0364 | F37: 0 | G37: 1428.57 | H37: 1600 | I37: 171.43 | J37: 12 | K37: Meeting Room
A38: 45667 | B38: Receivable Payment | C38: Bry Reyes | D38: Payment: Bry Reyes | E38: SI 0368 | F38: 0 | G38: 2142.86 | H38: 2400 | I38: 257.14 | J38: 12 | K38: Meeting Room
A39: 45667 | B39: Receivable Payment | C39: Lawrence Alexander | D39: Payment: Lawrence Alexander | E39: SI 0363 | F39: 0 | G39: 8.93 | H39: 10 | I39: 1.07 | J39: 12 | K39: Add Ons: Printing
... A277: 45747 | B277: Receivable Payment | C277: Feast Bellevue PM | D277: Payment: Feast Bellevue PM | E277: SI 0481 | F277: 0 | G277: 1785.71 | H277: 2000 | I277: 214.29 | J277: 12 | K277: Events: Ingress / Egress
A278: Total VAT on Sales (Services) | F278: =SUM(F28:F277) -> 0 | G278: =SUM(G28:G277) -> 1415479.2 | H278: =SUM(H28:H277) -> 1585336.8 | I278: =SUM(I28:I277) -> 169857.56
A280: Zero Rated Sales (Services)
A281: 45674 | B281: Receivable Payment | C281: QBE Group Shared Services Ltd- Philippine Branch | D281: Payment: QBE Group Shared Services Ltd- Philippine Branch | E281: SI 0384 | F281: 0 | G281: 311850 | H281: 311850 | I281: 0 | J281: 0 | K281: Monthly Membership: Private Office
A282: 45674 | B282: Receivable Payment | C282: QBE Group Shared Services Ltd- Philippine Branch | D282: Payment: QBE Group Shared Services Ltd- Philippine Branch | E282: SI 0384 | F282: 0 | G282: 166320 | H282: 166320 | I282: 0 | J282: 0 | K282: Monthly Membership: Private Office
A283: 45674 | B283: Receivable Payment | C283: QBE Group Shared Services Ltd- Philippine Branch | D283: Payment: QBE Group Shared Services Ltd- Philippine Branch | E283: SI 0384 | F283: 0 | G283: 259875 | H283: 259875 | I283: 0 | J283: 0 | K283: Monthly Membership: Private Office
A284: 45674 | B284: Receivable Payment | C284: QBE Group Shared Services Ltd- Philippine Branch | D284: Payment: QBE Group Shared Services Ltd- Philippine Branch | E284: SI 0384 | F284: 0 | G284: 187110 | H284: 187110 | I284: 0 | J284: 0 | K284: Monthly Membership: Private Office
A285: 45674 | B285: Receivable Payment | C285: QBE Group Shared Services Ltd- Philippine Branch | D285: Payment: QBE Group Shared Services Ltd- Philippine Branch | E285: SI 0384 | F285: 0 | G285: 259875 | H285: 259875 | I285: 0 | J285: 0 | K285: Monthly Membership: Private Office
A286: 45674 | B286: Receivable Payment | C286: QBE Group Shared Services Ltd- Philippine Branch | D286: Payment: QBE Group Shared Services Ltd- Philippine Branch | E286: SI 0384 | F286: 0 | G286: 155925 | H286: 155925 | I286: 0 | J286: 0 | K286: Monthly Membership: Private Office
A287: 45674 | B287: Receivable Payment | C287: QBE Group Shared Services Ltd- Philippine Branch | D287: Payment: QBE Group Shared Services Ltd- Philippine Branch | E287: SI 0384 | F287: 0 | G287: 62370 | H287: 62370 | I287: 0 | J287: 0 | K287: Monthly Membership: Private Office
A288: 45674 | B288: Receivable Payment | C288: QBE Group Shared Services Ltd- Philippine Branch | D288: Payment: QBE Group Shared Services Ltd- Philippine Branch | E288: SI 0384 | F288: 0 | G288: 62370 | H288: 62370 | I288: 0 | J288: 0 | K288: Monthly Membership: Private Office
A289: 45674 | B289: Receivable Payment | C289: QBE Group Shared Services Ltd- Philippine Branch | D289: Payment: QBE Group Shared Services Ltd- Philippine Branch | E289: SI 0384 | F289: 0 | G289: 72765 | H289: 72765 | I289: 0 | J289: 0 | K289: Monthly Membership: Private Office
A290: 45674 | B290: Receivable Payment | C290: QBE Group Shared Services Ltd- Philippine Branch | D290: Payment: QBE Group Shared Services Ltd- Philippine Branch | E290: SI 0384 | F290: 0 | G290: 10395 | H290: 10395 | I290: 0 | J290: 0 | K290: Monthly Membership: Private Office
A291: 45674 | B291: Receivable Payment | C291: QBE Group Shared Services Ltd- Philippine Branch | D291: Payment: QBE Group Shared Services Ltd- Philippine Branch | E291: SI 0384 | F291: 0 | G291: 10395 | H291: 10395 | I291: 0 | J291: 0 | K291: Monthly Membership: Private Office
A292: 45674 | B292: Receivable Payment | C292: QBE Group Shared Services Ltd- Philippine Branch | D292: Payment: QBE Group Shared Services Ltd- Philippine Branch | E292: SI 0384 | F292: 0 | G292: 10395 | H292: 10395 | I292: 0 | J292: 0 | K292: Monthly Membership: Private Office
... A322: 45709 | B322: Receivable Payment | C322: QBE Group Shared Services Ltd- Philippine Branch | D322: Payment: QBE Group Shared Services Ltd- Philippine Branch | E322: SI 0436 | F322: 0 | G322: 10395 | H322: 10395 | I322: 0 | J322: 0 | K322: Monthly Membership: Private Office
A323: Total Zero Rated Sales (Services) | F323: =SUM(F281:F322) -> 0 | G323: =SUM(G281:G322) -> 4782315.4 | H323: =SUM(H281:H322) -> 4782315.4 | I323: =SUM(I281:I322) -> 0
A325: Total | F325: =SUM(F15,F25,F278,F323) -> 24014.23 | G325: =SUM(G15,G25,G278,G323) -> 6234213.1 | H325: =SUM(H15,H25,H278,H323) -> 6380056.4 | I325: =SUM(I15,I25,I278,I323) -> 169857.56

Sheet Schedule of CG Input Tax
A1: CAPITAL GOODS
A2: INPUT TAX
A4: FURNITURE & FIXTURES
C5: TAX PERIOD
B6: INPUT TAX | C6: =A8 -> APRIL 2019 | D6: =A9 -> MAY 2019 | E6: =A10 -> JUNE 2019 | F6: =A11 -> JULY 2019 | G6: =A12 -> AUGUST 2019 | H6: =A13 -> SEPTEMBER 2019 | I6: =A14 -> OCTOBER 2019 | J6: =A15 -> NOVEMBER 2019 | K6: =A16 -> DECEMBER 2019 | L6: 2019 TOTAL | M6: =A17 -> JANUARY 2020 | N6: =A18 -> FEBRUARY 2020 | O6: =A19 -> MARCH 2020 | P6: APRIL 2020 | Q6: MAY 2020 | R6: JUNE 2020 | S6: JULY 2020 | T6: AUG 2020 | U6: SEP 2020 | V6: OCT 2020 | W6: NOV 2020 | X6: DEC 2020 | Y6: 2020 TOTAL | Z6: 2021 TOTAL | AA6: JAN 2021 | AB6: FEB 2021 | AC6: MAR 2021 | AD6: APR 2021 | AE6: MAY 2021 | AF6: JUNE 2021 | AG6: JULY 2021 | AH6: AUGUST 2021 | AI6: SEPTEMBER 2021 | AJ6: OCTOBER 2021 | AK6: NOVEMBER 2021 | AL6: DECEMBER 2021 | AN6: JAN 2022 | AO6: FEB 2022 | AP6: MAR 2022 | AQ6: ARP 2022 | AR6: MAY 2022 | AS6: JUNE 2022 | AT6: JULY 2022 | AU6: AUG 2022 | AV6: SEP 2022 | AW6: OCT 2022 | AX6: NOV. 2022 | AY6: DEC. 2022 | AZ6: 2022 TOTAL | BA6: 44927 | BB6: 44958 | BC6: 44986 | BD6: 45017 | BE6: 45047 | BF6: 45078 | BG6: 45108 | BH6: 45139 | BI6: 45170 | BJ6: 45200 | BK6: 45231 | BL6: 45261 | BM6: 2023 TOTAL | BN6: 45292 | BO6: 45323 | BP6: 45352 | BQ6: 45383 | BR6: 45413 | BS6: 45444 | BT6: 45474 | BU6: 45505 | BV6: 45536 | BW6: 45566 | BX6: 45597 | BY6: 45627 | BZ6: 45658 | CA6: 45689 | CB6: 45717 | CC6: RUNNING BALANCE
A7: MONTH PURCHASED
A8: APRIL 2019 | B8: ='Summary of CG Purchased '!E6 -> 352176.8 | C8: ='Summary of CG Purchased '!F6 -> 9782.6888 | D8: =$C$8 -> 9782.6888 | E8: =$C$8 -> 9782.6888 | F8: =$C$8 -> 9782.6888 | G8: =$C$8 -> 9782.6888 | H8: =$C$8 -> 9782.6888 | I8: =$C$8 -> 9782.6888 | J8: =$C$8 -> 9782.6888 | K8: =$C$8 -> 9782.6888 | L8: =SUM(C8:K8) -> 88044.199 | M8: =$C$8 -> 9782.6888 | N8: =$C$8 -> 9782.6888 | O8: =$C$8 -> 9782.6888 | P8: =$C$8 -> 9782.6888 | Q8: =$C$8 -> 9782.6888 | R8: =$C$8 -> 9782.6888 | S8: =$C$8 -> 9782.6888 | T8: =$C$8 -> 9782.6888 | ... X8: =$C$8 -> 9782.6888 | Y8: =SUM(M8:X8) -> 117392.27 | Z8: =SUM(AA8:AL8) -> 117392.27 | AA8: =$C$8 -> 9782.6888 | AB8: =$C$8 -> 9782.6888 | AC8: =$C$8 -> 9782.6888 | AD8: =$C$8 -> 9782.6888 | AE8: =$C$8 -> 9782.6888 | AF8: =$C$8 -> 9782.6888 | AG8: =$C$8 -> 9782.6888 | AH8: =$C$8 -> 9782.6888 | ... AL8: =$C$8 -> 9782.6888 | AN8: =$C$8 -> 9782.6888 | AO8: =$C$8 -> 9782.6888 | AP8: =$C$8 -> 9782.6888 | AQ8: 0 | AR8: 0 | AS8: 0 | AT8: 0 | AU8: 0 | AV8: 0 | AW8: 0 | AZ8: =SUM(AN8:AY8) -> 29348.066 | BM8: =SUM(BA8:BL8) -> 0 | BN8: 0 | BO8: 0 | BP8: 0 | BQ8: 0 | BR8: 0 | BS8: 0 | BT8: 0 | BU8: 0 | BV8: 0 | CC8: =B8-L8-Y8-Z8-AZ8-BM8-SUM(BN8:BP8) -> 0
A9: MAY 2019 | B9: ='Summary of CG Purchased '!E14 -> 0 | D9: ='Summary of CG Purchased '!F14 -> 0 | E9: 0 | F9: 0 | G9: 0 | H9: 0 | I9: 0 | J9: 0 | K9: 0 | L9: =SUM(C9:K9) -> 0 | M9: 0 | N9: 0 | O9: 0 | P9: 0 | Q9: 0 | R9: 0 | S9: 0 | T9: 0 | U9: 0 | V9: 0 | W9: 0 | X9: 0 | Y9: =SUM(M9:X9) -> 0 | Z9: =SUM(AA9:AL9) -> 0 | AA9: 0 | AB9: 0 | AC9: 0 | AD9: 0 | AE9: 0 | AF9: 0 | AN9: 0 | AO9: 0 | AP9: 0 | AQ9: 0 | AR9: 0 | AS9: 0 | AT9: 0 | AU9: 0 | AV9: 0 | AW9: 0 | AZ9: =SUM(AN9:AY9) -> 0 | BM9: =SUM(BA9:BL9) -> 0 | CC9: =B9-L9-Y9-Z9-AZ9-BM9-SUM(BN9:BP9) -> 0
A10: JUNE 2019 | B10: ='Summary of CG Purchased '!E22 -> 12600 | E10: ='Summary of CG Purchased '!F22 -> 12600 | F10: 0 | G10: 0 | H10: 0 | I10: 0 | J10: 0 | K10: 0 | L10: =SUM(C10:K10) -> 12600 | M10: 0 | N10: 0 | O10: 0 | P10: 0 | Q10: 0 | R10: 0 | S10: 0 | T10: 0 | U10: 0 | V10: 0 | W10: 0 | X10: 0 | Y10: =SUM(M10:X10) -> 0 | Z10: =SUM(AA10:AL10) -> 0 | AA10: 0 | AB10: 0 | AC10: 0 | AD10: 0 | AE10: 0 | AF10: 0 | AG10: 0 | AH10: 0 | AI10: 0 | AJ10: 0 | AK10: 0 | AL10: 0 | AN10: 0 | AO10: 0 | AP10: 0 | AQ10: 0 | AR10: 0 | AS10: 0 | AT10: 0 | AU10: 0 | AV10: 0 | AW10: 0 | AZ10: =SUM(AN10:AY10) -> 0 | BM10: =SUM(BA10:BL10) -> 0 | BN10: 0 | BO10: 0 | BP10: 0 | BQ10: 0 | BR10: 0 | BS10: 0 | BT10: 0 | BU10: 0 | BV10: 0 | CC10: =B10-L10-Y10-Z10-AZ10-BM10-SUM(BN10:BP10) -> 0
A11: JULY 2019 | B11: ='Summary of CG Purchased '!E30 -> 0 | F11: 0 | G11: 0 | H11: 0 | I11: 0 | J11: 0 | K11: 0 | L11: =SUM(C11:K11) -> 0 | M11: 0 | N11: 0 | O11: 0 | P11: 0 | Q11: 0 | R11: 0 | S11: 0 | T11: 0 | U11: 0 | V11: 0 | W11: 0 | X11: 0 | Y11: =SUM(M11:X11) -> 0 | Z11: =SUM(AA11:AL11) -> 0 | AA11: 0 | AB11: 0 | AC11: 0 | AD11: 0 | AE11: 0 | AF11: 0 | AN11: 0 | AO11: 0 | AP11: 0 | AQ11: 0 | AR11: 0 | AS11: 0 | AT11: 0 | AU11: 0 | AV11: 0 | AW11: 0 | AZ11: =SUM(AN11:AY11) -> 0 | BM11: =SUM(BA11:BL11) -> 0 | BN11: 0 | BO11: 0 | BP11: 0 | BQ11: 0 | BR11: 0 | BS11: 0 | BT11: 0 | BU11: 0 | BV11: 0 | CC11: =B11-L11-Y11-Z11-AZ11-BM11-SUM(BN11:BP11) -> 0
A12: AUGUST 2019 | B12: ='Summary of CG Purchased '!D38 -> 0 | G12: 0 | H12: 0 | I12: 0 | J12: 0 | K12: 0 | L12: =SUM(C12:K12) -> 0 | M12: 0 | N12: 0 | O12: 0 | P12: 0 | Q12: 0 | R12: 0 | S12: 0 | T12: 0 | U12: 0 | V12: 0 | W12: 0 | X12: 0 | Y12: =SUM(M12:X12) -> 0 | Z12: =SUM(AA12:AL12) -> 0 | AA12: 0 | AB12: 0 | AC12: 0 | AD12: 0 | AE12: 0 | AF12: 0 | AN12: 0 | AO12: 0 | AP12: 0 | AQ12: 0 | AR12: 0 | AS12: 0 | AT12: 0 | AU12: 0 | AV12: 0 | AW12: 0 | AZ12: =SUM(AN12:AY12) -> 0 | BM12: =SUM(BA12:BL12) -> 0 | BN12: 0 | BO12: 0 | BP12: 0 | BQ12: 0 | BR12: 0 | BS12: 0 | BT12: 0 | BU12: 0 | BV12: 0 | CC12: =B12-L12-Y12-Z12-AZ12-BM12-SUM(BN12:BP12) -> 0
A13: SEPTEMBER 2019 | B13: 16275 | H13: =B13 -> 16275 | I13: 0 | J13: 0 | K13: 0 | L13: =SUM(C13:K13) -> 16275 | M13: 0 | N13: 0 | O13: 0 | P13: 0 | Q13: 0 | R13: 0 | S13: 0 | T13: 0 | U13: 0 | V13: 0 | W13: 0 | X13: 0 | Y13: =SUM(M13:X13) -> 0 | Z13: =SUM(AA13:AL13) -> 0 | AA13: 0 | AB13: 0 | AC13: 0 | AD13: 0 | AE13: 0 | AF13: 0 | AG13: 0 | AH13: 0 | AI13: 0 | AJ13: 0 | AK13: 0 | AL13: 0 | AN13: 0 | AO13: 0 | AP13: 0 | AQ13: 0 | AR13: 0 | AS13: 0 | AT13: 0 | AU13: 0 | AV13: 0 | AW13: 0 | AZ13: =SUM(AN13:AY13) -> 0 | BM13: =SUM(BA13:BL13) -> 0 | BN13: 0 | BO13: 0 | BP13: 0 | BQ13: 0 | BR13: 0 | BS13: 0 | BT13: 0 | BU13: 0 | BV13: 0 | CC13: =B13-L13-Y13-Z13-AZ13-BM13-SUM(BN13:BP13) -> 0
A14: OCTOBER 2019 | B14: ='Summary of CG Purchased '!E54 -> 0 | I14: =B14 -> 0 | J14: 0 | K14: 0 | L14: =SUM(C14:K14) -> 0 | M14: 0 | N14: 0 | O14: 0 | P14: 0 | Q14: 0 | R14: 0 | S14: 0 | T14: 0 | U14: 0 | V14: 0 | W14: 0 | X14: 0 | Y14: =SUM(M14:X14) -> 0 | Z14: =SUM(AA14:AL14) -> 0 | AA14: 0 | AB14: 0 | AC14: 0 | AD14: 0 | AE14: 0 | AF14: 0 | AL14: 0 | AN14: 0 | AO14: 0 | AP14: 0 | AQ14: 0 | AR14: 0 | AS14: 0 | AT14: 0 | AU14: 0 | AV14: 0 | AW14: 0 | AZ14: =SUM(AN14:AY14) -> 0 | BM14: =SUM(BA14:BL14) -> 0 | BN14: 0 | BO14: 0 | BP14: 0 | BQ14: 0 | BR14: 0 | BS14: 0 | BT14: 0 | BU14: 0 | BV14: 0 | CC14: =B14-L14-Y14-Z14-AZ14-BM14-SUM(BN14:BP14) -> 0
A15: NOVEMBER 2019 | J15: 0 | K15: 0 | L15: =SUM(C15:K15) -> 0 | M15: 0 | N15: 0 | O15: 0 | P15: 0 | Q15: 0 | R15: 0 | S15: 0 | T15: 0 | U15: 0 | V15: 0 | W15: 0 | X15: 0 | Y15: =SUM(M15:X15) -> 0 | Z15: =SUM(AA15:AL15) -> 0 | AA15: 0 | AB15: 0 | AC15: 0 | AD15: 0 | AE15: 0 | AF15: 0 | AL15: 0 | AN15: 0 | AO15: 0 | AP15: 0 | AQ15: 0 | AR15: 0 | AS15: 0 | AT15: 0 | AU15: 0 | AV15: 0 | AW15: 0 | AZ15: =SUM(AN15:AY15) -> 0 | BM15: =SUM(BA15:BL15) -> 0 | BN15: 0 | BO15: 0 | BP15: 0 | BQ15: 0 | BR15: 0 | BS15: 0 | BT15: 0 | BU15: 0 | BV15: 0 | CC15: =B15-L15-Y15-Z15-AZ15-BM15-SUM(BN15:BP15) -> 0
A16: DECEMBER 2019 | K16: 0 | L16: =SUM(C16:K16) -> 0 | M16: 0 | N16: 0 | O16: 0 | P16: 0 | Q16: 0 | R16: 0 | S16: 0 | T16: 0 | U16: 0 | V16: 0 | W16: 0 | X16: 0 | Y16: =SUM(M16:X16) -> 0 | Z16: =SUM(AA16:AL16) -> 0 | AA16: 0 | AB16: 0 | AC16: 0 | AD16: 0 | AE16: 0 | AF16: 0 | AL16: 0 | AN16: 0 | AO16: 0 | AP16: 0 | AQ16: 0 | AR16: 0 | AS16: 0 | AT16: 0 | AU16: 0 | AV16: 0 | AW16: 0 | AZ16: =SUM(AN16:AY16) -> 0 | BM16: =SUM(BA16:BL16) -> 0 | BN16: 0 | BO16: 0 | BP16: 0 | BQ16: 0 | BR16: 0 | BS16: 0 | BT16: 0 | BU16: 0 | BV16: 0 | CC16: =B16-L16-Y16-Z16-AZ16-BM16-SUM(BN16:BP16) -> 0
A17: JANUARY 2020 | B17: ='Summary of CG Purchased '!E77 -> 2789.946 | L17: =SUM(C17:K17) -> 0 | M17: ='Summary of CG Purchased '!E77 -> 2789.946 | N17: 0 | O17: 0 | P17: 0 | Q17: 0 | R17: 0 | S17: 0 | T17: 0 | U17: 0 | V17: 0 | W17: 0 | X17: 0 | Y17: =SUM(M17:X17) -> 2789.946 | Z17: =SUM(AA17:AL17) -> 0 | AA17: 0 | AB17: 0 | AC17: 0 | AD17: 0 | AE17: 0 | AF17: 0 | AG17: 0 | AH17: 0 | AI17: 0 | AJ17: 0 | AK17: 0 | AL17: 0 | AN17: 0 | AO17: 0 | AP17: 0 | AQ17: 0 | AR17: 0 | AS17: 0 | AT17: 0 | AU17: 0 | AV17: 0 | AW17: 0 | AZ17: =SUM(AN17:AY17) -> 0 | BM17: =SUM(BA17:BL17) -> 0 | BN17: 0 | BO17: 0 | BP17: 0 | BQ17: 0 | BR17: 0 | BS17: 0 | BT17: 0 | BU17: 0 | BV17: 0 | CC17: =B17-L17-Y17-Z17-AZ17-BM17-SUM(BN17:BP17) -> 0
A18: FEBRUARY 2020 | B18: ='Summary of CG Purchased '!E78 -> 0 | L18: =SUM(C18:K18) -> 0 | N18: 0 | O18: 0 | P18: 0 | Q18: 0 | R18: 0 | S18: 0 | T18: 0 | U18: 0 | V18: 0 | W18: 0 | X18: 0 | Y18: =SUM(M18:X18) -> 0 | Z18: =SUM(AA18:AL18) -> 0 | AA18: 0 | AB18: 0 | AC18: 0 | AD18: 0 | AE18: 0 | AF18: 0 | AL18: 0 | AN18: 0 | AO18: 0 | AP18: 0 | AQ18: 0 | AR18: 0 | AS18: 0 | AT18: 0 | AU18: 0 | AV18: 0 | AW18: 0 | AZ18: =SUM(AN18:AY18) -> 0 | BM18: =SUM(BA18:BL18) -> 0 | BN18: 0 | BO18: 0 | BP18: 0 | BQ18: 0 | BR18: 0 | BS18: 0 | BT18: 0 | BU18: 0 | BV18: 0 | CC18: =B18-L18-Y18-Z18-AZ18-BM18-SUM(BN18:BP18) -> 0
A19: MARCH 2020 | B19: ='Summary of CG Purchased '!F91 -> 4499.4648 | L19: =SUM(C19:K19) -> 0 | O19: ='Summary of CG Purchased '!F91 -> 4499.4648 | P19: 0 | Q19: 0 | R19: 0 | S19: 0 | T19: 0 | U19: 0 | V19: 0 | W19: 0 | X19: 0 | Y19: =SUM(M19:X19) -> 4499.4648 | Z19: =SUM(AA19:AL19) -> 0 | AA19: 0 | AB19: 0 | AC19: 0 | AD19: 0 | AE19: 0 | AF19: 0 | AG19: 0 | AH19: 0 | AI19: 0 | AJ19: 0 | AK19: 0 | AL19: 0 | AN19: 0 | AO19: 0 | AP19: 0 | AQ19: 0 | AR19: 0 | AS19: 0 | AT19: 0 | AU19: 0 | AV19: 0 | AW19: 0 | AZ19: =SUM(AN19:AY19) -> 0 | BM19: =SUM(BA19:BL19) -> 0 | BN19: 0 | BO19: 0 | BP19: 0 | BQ19: 0 | BR19: 0 | BS19: 0 | BT19: 0 | BU19: 0 | BV19: 0 | CC19: =B19-L19-Y19-Z19-AZ19-BM19-SUM(BN19:BP19) -> 0
A20: APRIL 2020 | L20: =SUM(C20:K20) -> 0 | P20: 0 | Q20: 0 | R20: 0 | S20: 0 | T20: 0 | U20: 0 | V20: 0 | W20: 0 | X20: 0 | Y20: =SUM(M20:X20) -> 0 | Z20: =SUM(AA20:AL20) -> 0 | AA20: 0 | AB20: 0 | AC20: 0 | AD20: 0 | AE20: 0 | AF20: 0 | AL20: 0 | AN20: 0 | AO20: 0 | AP20: 0 | AQ20: 0 | AR20: 0 | AS20: 0 | AT20: 0 | AU20: 0 | AV20: 0 | AW20: 0 | AZ20: =SUM(AN20:AY20) -> 0 | BM20: =SUM(BA20:BL20) -> 0 | BN20: 0 | BO20: 0 | BP20: 0 | BQ20: 0 | BR20: 0 | BS20: 0 | BT20: 0 | BU20: 0 | BV20: 0 | CC20: =B20-L20-Y20-Z20-AZ20-BM20-SUM(BN20:BP20) -> 0
A21: MAY 2020 | B21: ='Summary of CG Purchased '!E105 -> 2040 | L21: =SUM(C21:K21) -> 0 | Q21: =B21 -> 2040 | R21: 0 | S21: 0 | T21: 0 | U21: 0 | V21: 0 | W21: 0 | X21: 0 | Y21: =SUM(M21:X21) -> 2040 | Z21: =SUM(AA21:AL21) -> 0 | AA21: 0 | AB21: 0 | AC21: 0 | AD21: 0 | AE21: 0 | AF21: 0 | AG21: 0 | AH21: 0 | AI21: 0 | AJ21: 0 | AK21: 0 | AL21: 0 | AN21: 0 | AO21: 0 | AP21: 0 | AQ21: 0 | AR21: 0 | AS21: 0 | AT21: 0 | AU21: 0 | AV21: 0 | AW21: 0 | AZ21: =SUM(AN21:AY21) -> 0 | BM21: =SUM(BA21:BL21) -> 0 | BN21: 0 | BO21: 0 | BP21: 0 | BQ21: 0 | BR21: 0 | BS21: 0 | BT21: 0 | BU21: 0 | BV21: 0 | CC21: =B21-L21-Y21-Z21-AZ21-BM21-SUM(BN21:BP21) -> 0
A22: JUNE 2020 | L22: =SUM(C22:K22) -> 0 | R22: 0 | S22: 0 | T22: 0 | U22: 0 | V22: 0 | W22: 0 | X22: 0 | Y22: =SUM(M22:X22) -> 0 | Z22: =SUM(AA22:AL22) -> 0 | AA22: 0 | AB22: 0 | AC22: 0 | AD22: 0 | AE22: 0 | AF22: 0 | AL22: 0 | AN22: 0 | AO22: 0 | AP22: 0 | AQ22: 0 | AR22: 0 | AS22: 0 | AT22: 0 | AU22: 0 | AV22: 0 | AW22: 0 | AZ22: =SUM(AN22:AY22) -> 0 | BM22: =SUM(BA22:BL22) -> 0 | BN22: 0 | BO22: 0 | BP22: 0 | BQ22: 0 | BR22: 0 | BS22: 0 | BT22: 0 | BU22: 0 | BV22: 0 | CC22: =B22-L22-Y22-Z22-AZ22-BM22-SUM(BN22:BP22) -> 0
A23: JULY 2020 | L23: =SUM(C23:K23) -> 0 | S23: 0 | T23: 0 | U23: 0 | V23: 0 | W23: 0 | X23: 0 | Y23: =SUM(M23:X23) -> 0 | Z23: =SUM(AA23:AL23) -> 0 | AA23: 0 | AB23: 0 | AC23: 0 | AD23: 0 | AE23: 0 | AF23: 0 | AL23: 0 | AN23: 0 | AO23: 0 | AP23: 0 | AQ23: 0 | AR23: 0 | AS23: 0 | AT23: 0 | AU23: 0 | AV23: 0 | AW23: 0 | AZ23: =SUM(AN23:AY23) -> 0 | BM23: =SUM(BA23:BL23) -> 0 | BN23: 0 | BO23: 0 | BP23: 0 | BQ23: 0 | BR23: 0 | BS23: 0 | BT23: 0 | BU23: 0 | BV23: 0 | CC23: =B23-L23-Y23-Z23-AZ23-BM23-SUM(BN23:BP23) -> 0
A24: AUG 2020 | L24: =SUM(C24:K24) -> 0 | T24: 0 | U24: 0 | V24: 0 | W24: 0 | X24: 0 | Y24: =SUM(M24:X24) -> 0 | Z24: =SUM(AA24:AL24) -> 0 | AA24: 0 | AB24: 0 | AC24: 0 | AD24: 0 | AE24: 0 | AF24: 0 | AL24: 0 | AN24: 0 | AO24: 0 | AP24: 0 | AQ24: 0 | AR24: 0 | AS24: 0 | AT24: 0 | AU24: 0 | AV24: 0 | AW24: 0 | AZ24: =SUM(AN24:AY24) -> 0 | BM24: =SUM(BA24:BL24) -> 0 | BN24: 0 | BO24: 0 | BP24: 0 | BQ24: 0 | BR24: 0 | BS24: 0 | BT24: 0 | BU24: 0 | BV24: 0 | CC24: =B24-L24-Y24-Z24-AZ24-BM24-SUM(BN24:BP24) -> 0
A25: SEP 2020 | L25: =SUM(C25:K25) -> 0 | U25: 0 | V25: 0 | W25: 0 | X25: 0 | Y25: =SUM(M25:X25) -> 0 | Z25: =SUM(AA25:AL25) -> 0 | AA25: 0 | AB25: 0 | AC25: 0 | AD25: 0 | AE25: 0 | AF25: 0 | AL25: 0 | AN25: 0 | AO25: 0 | AP25: 0 | AQ25: 0 | AR25: 0 | AS25: 0 | AT25: 0 | AU25: 0 | AV25: 0 | AW25: 0 | AZ25: =SUM(AN25:AY25) -> 0 | BM25: =SUM(BA25:BL25) -> 0 | BN25: 0 | BO25: 0 | BP25: 0 | BQ25: 0 | BR25: 0 | BS25: 0 | BT25: 0 | BU25: 0 | BV25: 0 | CC25: =B25-L25-Y25-Z25-AZ25-BM25-SUM(BN25:BP25) -> 0
A26: OCT 2020 | L26: =SUM(C26:K26) -> 0 | V26: 0 | W26: 0 | X26: 0 | Y26: =SUM(M26:X26) -> 0 | Z26: =SUM(AA26:AL26) -> 0 | AA26: 0 | AB26: 0 | AC26: 0 | AD26: 0 | AE26: 0 | AF26: 0 | AL26: 0 | AN26: 0 | AO26: 0 | AP26: 0 | AQ26: 0 | AR26: 0 | AS26: 0 | AT26: 0 | AU26: 0 | AV26: 0 | AW26: 0 | AZ26: =SUM(AN26:AY26) -> 0 | BM26: =SUM(BA26:BL26) -> 0 | BN26: 0 | BO26: 0 | BP26: 0 | BQ26: 0 | BR26: 0 | BS26: 0 | BT26: 0 | BU26: 0 | BV26: 0 | CC26: =B26-L26-Y26-Z26-AZ26-BM26-SUM(BN26:BP26) -> 0
A27: NOV 2020 | L27: =SUM(C27:K27) -> 0 | W27: 0 | X27: 0 | Y27: =SUM(M27:X27) -> 0 | Z27: =SUM(AA27:AL27) -> 0 | AA27: 0 | AB27: 0 | AC27: 0 | AD27: 0 | AE27: 0 | AF27: 0 | AL27: 0 | AN27: 0 | AO27: 0 | AP27: 0 | AQ27: 0 | AR27: 0 | AS27: 0 | AT27: 0 | AU27: 0 | AV27: 0 | AW27: 0 | AZ27: =SUM(AN27:AY27) -> 0 | BM27: =SUM(BA27:BL27) -> 0 | BN27: 0 | BO27: 0 | BP27: 0 | BQ27: 0 | BR27: 0 | BS27: 0 | BT27: 0 | BU27: 0 | BV27: 0 | CC27: =B27-L27-Y27-Z27-AZ27-BM27-SUM(BN27:BP27) -> 0
A28: DEC 2020 | L28: =SUM(C28:K28) -> 0 | X28: 0 | Y28: =SUM(M28:X28) -> 0 | Z28: =SUM(AA28:AL28) -> 0 | AA28: 0 | AB28: 0 | AC28: 0 | AD28: 0 | AE28: 0 | AF28: 0 | AL28: 0 | AN28: 0 | AO28: 0 | AP28: 0 | AQ28: 0 | AR28: 0 | AS28: 0 | AT28: 0 | AU28: 0 | AV28: 0 | AW28: 0 | AZ28: =SUM(AN28:AY28) -> 0 | BM28: =SUM(BA28:BL28) -> 0 | BN28: 0 | BO28: 0 | BP28: 0 | BQ28: 0 | BR28: 0 | BS28: 0 | BT28: 0 | BU28: 0 | BV28: 0 | CC28: =B28-L28-Y28-Z28-AZ28-BM28-SUM(BN28:BP28) -> 0
A29: JAN 2021 | Z29: =SUM(AA29:AL29) -> 0 | AA29: 0 | AB29: 0 | AC29: 0 | AD29: 0 | AE29: 0 | AF29: 0 | AG29: 0 | AH29: 0 | AI29: 0 | AJ29: 0 | AK29: 0 | AL29: 0 | AN29: 0 | AO29: 0 | AP29: 0 | AQ29: 0 | AR29: 0 | AS29: 0 | AT29: 0 | AU29: 0 | AV29: 0 | AW29: 0 | AZ29: =SUM(AN29:AY29) -> 0 | BM29: =SUM(BA29:BL29) -> 0 | BN29: 0 | BO29: 0 | BP29: 0 | BQ29: 0 | BR29: 0 | BS29: 0 | BT29: 0 | BU29: 0 | BV29: 0 | CC29: =B29-L29-Y29-Z29-AZ29-BM29-SUM(BN29:BP29) -> 0
A30: FEB 2021 | Z30: =SUM(AA30:AL30) -> 0 | AB30: 0 | AC30: 0 | AD30: 0 | AE30: 0 | AF30: 0 | AG30: 0 | AH30: 0 | AI30: 0 | AJ30: 0 | AK30: 0 | AL30: 0 | AN30: 0 | AO30: 0 | AP30: 0 | AQ30: 0 | AR30: 0 | AS30: 0 | AT30: 0 | AU30: 0 | AV30: 0 | AW30: 0 | AZ30: =SUM(AN30:AY30) -> 0 | BM30: =SUM(BA30:BL30) -> 0 | BN30: 0 | BO30: 0 | BP30: 0 | BQ30: 0 | BR30: 0 | BS30: 0 | BT30: 0 | BU30: 0 | BV30: 0 | CC30: =B30-L30-Y30-Z30-AZ30-BM30-SUM(BN30:BP30) -> 0
A31: MAR 2021 | Z31: =SUM(AA31:AL31) -> 0 | AC31: 0 | AD31: 0 | AE31: 0 | AF31: 0 | AG31: 0 | AH31: 0 | AI31: 0 | AJ31: 0 | AK31: 0 | AL31: 0 | AN31: 0 | AO31: 0 | AP31: 0 | AQ31: 0 | AR31: 0 | AS31: 0 | AT31: 0 | AU31: 0 | AV31: 0 | AW31: 0 | AZ31: =SUM(AN31:AY31) -> 0 | BM31: =SUM(BA31:BL31) -> 0 | BN31: 0 | BO31: 0 | BP31: 0 | BQ31: 0 | BR31: 0 | BS31: 0 | BT31: 0 | BU31: 0 | BV31: 0 | CC31: =B31-L31-Y31-Z31-AZ31-BM31-SUM(BN31:BP31) -> 0
A32: APR 2021 | Z32: =SUM(AA32:AL32) -> 0 | AD32: 0 | AE32: 0 | AF32: 0 | AG32: 0 | AH32: 0 | AI32: 0 | AJ32: 0 | AK32: 0 | AL32: 0 | AN32: 0 | AO32: 0 | AP32: 0 | AQ32: 0 | AR32: 0 | AS32: 0 | AT32: 0 | AU32: 0 | AV32: 0 | AW32: 0 | AZ32: =SUM(AN32:AY32) -> 0 | BM32: =SUM(BA32:BL32) -> 0 | BN32: 0 | BO32: 0 | BP32: 0 | BQ32: 0 | BR32: 0 | BS32: 0 | BT32: 0 | BU32: 0 | BV32: 0 | CC32: =B32-L32-Y32-Z32-AZ32-BM32-SUM(BN32:BP32) -> 0
A33: MAY 2021 | Z33: =SUM(AA33:AL33) -> 0 | AE33: 0 | AF33: 0 | AG33: 0 | AH33: 0 | AI33: 0 | AJ33: 0 | AK33: 0 | AL33: 0 | AN33: 0 | AO33: 0 | AP33: 0 | AQ33: 0 | AR33: 0 | AS33: 0 | AT33: 0 | AU33: 0 | AV33: 0 | AW33: 0 | AZ33: =SUM(AN33:AY33) -> 0 | BM33: =SUM(BA33:BL33) -> 0 | BN33: 0 | BO33: 0 | BP33: 0 | BQ33: 0 | BR33: 0 | BS33: 0 | BT33: 0 | BU33: 0 | BV33: 0 | CC33: =B33-L33-Y33-Z33-AZ33-BM33-SUM(BN33:BP33) -> 0
A34: JUNE 2021 | Z34: =SUM(AA34:AL34) -> 0 | AF34: 0 | AG34: 0 | AH34: 0 | AI34: 0 | AJ34: 0 | AK34: 0 | AL34: 0 | AN34: 0 | AO34: 0 | AP34: 0 | AQ34: 0 | AR34: 0 | AS34: 0 | AT34: 0 | AU34: 0 | AV34: 0 | AW34: 0 | AZ34: =SUM(AN34:AY34) -> 0 | BM34: =SUM(BA34:BL34) -> 0 | BN34: 0 | BO34: 0 | BP34: 0 | BQ34: 0 | BR34: 0 | BS34: 0 | BT34: 0 | BU34: 0 | BV34: 0 | CC34: =B34-L34-Y34-Z34-AZ34-BM34-SUM(BN34:BP34) -> 0
A35: JULY 2021 | Z35: =SUM(AA35:AL35) -> 0 | AG35: 0 | AH35: 0 | AI35: 0 | AJ35: 0 | AK35: 0 | AL35: 0 | AN35: 0 | AO35: 0 | AP35: 0 | AQ35: 0 | AR35: 0 | AS35: 0 | AT35: 0 | AU35: 0 | AV35: 0 | AW35: 0 | AZ35: =SUM(AN35:AY35) -> 0 | BM35: =SUM(BA35:BL35) -> 0 | BN35: 0 | BO35: 0 | BP35: 0 | BQ35: 0 | BR35: 0 | BS35: 0 | BT35: 0 | BU35: 0 | BV35: 0 | CC35: =B35-L35-Y35-Z35-AZ35-BM35-SUM(BN35:BP35) -> 0
A36: AUG 2021 | Z36: =SUM(AA36:AL36) -> 0 | AH36: 0 | AI36: 0 | AJ36: 0 | AK36: 0 | AL36: 0 | AN36: 0 | AO36: 0 | AP36: 0 | AQ36: 0 | AR36: 0 | AS36: 0 | AT36: 0 | AU36: 0 | AV36: 0 | AW36: 0 | AZ36: =SUM(AN36:AY36) -> 0 | BM36: =SUM(BA36:BL36) -> 0 | BN36: 0 | BO36: 0 | BP36: 0 | BQ36: 0 | BR36: 0 | BS36: 0 | BT36: 0 | BU36: 0 | BV36: 0 | CC36: =B36-L36-Y36-Z36-AZ36-BM36-SUM(BN36:BP36) -> 0
A37: SEP 2021 | Z37: =SUM(AA37:AL37) -> 0 | AI37: 0 | AJ37: 0 | AK37: 0 | AL37: 0 | AN37: 0 | AO37: 0 | AP37: 0 | AQ37: 0 | AR37: 0 | AS37: 0 | AT37: 0 | AU37: 0 | AV37: 0 | AW37: 0 | AZ37: =SUM(AN37:AY37) -> 0 | BM37: =SUM(BA37:BL37) -> 0 | BN37: 0 | BO37: 0 | BP37: 0 | BQ37: 0 | BR37: 0 | BS37: 0 | BT37: 0 | BU37: 0 | BV37: 0 | CC37: =B37-L37-Y37-Z37-AZ37-BM37-SUM(BN37:BP37) -> 0
A38: OCT 2021 | Z38: =SUM(AA38:AL38) -> 0 | AJ38: 0 | AK38: 0 | AL38: 0 | AN38: 0 | AO38: 0 | AP38: 0 | AQ38: 0 | AR38: 0 | AS38: 0 | AT38: 0 | AU38: 0 | AV38: 0 | AW38: 0 | AZ38: =SUM(AN38:AY38) -> 0 | BM38: =SUM(BA38:BL38) -> 0 | BN38: 0 | BO38: 0 | BP38: 0 | BQ38: 0 | BR38: 0 | BS38: 0 | BT38: 0 | BU38: 0 | BV38: 0 | CC38: =B38-L38-Y38-Z38-AZ38-BM38-SUM(BN38:BP38) -> 0
A39: NOV 2021 | Z39: =SUM(AA39:AL39) -> 0 | AK39: 0 | AL39: 0 | AN39: 0 | AO39: 0 | AP39: 0 | AQ39: 0 | AR39: 0 | AS39: 0 | AT39: 0 | AU39: 0 | AV39: 0 | AW39: 0 | AZ39: =SUM(AN39:AY39) -> 0 | BM39: =SUM(BA39:BL39) -> 0 | BN39: 0 | BO39: 0 | BP39: 0 | BQ39: 0 | BR39: 0 | BS39: 0 | BT39: 0 | BU39: 0 | BV39: 0 | CC39: =B39-L39-Y39-Z39-AZ39-BM39-SUM(BN39:BP39) -> 0
A40: DEC 2021 | Z40: =SUM(AA40:AL40) -> 0 | AL40: 0 | AN40: 0 | AO40: 0 | AP40: 0 | AQ40: 0 | AR40: 0 | AS40: 0 | AT40: 0 | AU40: 0 | AV40: 0 | AW40: 0 | AZ40: =SUM(AN40:AY40) -> 0 | BM40: =SUM(BA40:BL40) -> 0 | BN40: 0 | BO40: 0 | BP40: 0 | BQ40: 0 | BR40: 0 | BS40: 0 | BT40: 0 | BU40: 0 | BV40: 0 | CC40: =B40-L40-Y40-Z40-AZ40-BM40-SUM(BN40:BP40) -> 0
A41: JAN 2022 | AN41: 0 | AO41: 0 | AP41: 0 | AQ41: 0 | AR41: 0 | AS41: 0 | AT41: 0 | AU41: 0 | AV41: 0 | AW41: 0 | AZ41: =SUM(AN41:AY41) -> 0 | BM41: =SUM(BA41:BL41) -> 0 | BN41: 0 | BO41: 0 | BP41: 0 | BQ41: 0 | BR41: 0 | BS41: 0 | BT41: 0 | BU41: 0 | BV41: 0 | CC41: =B41-L41-Y41-Z41-AZ41-BM41-SUM(BN41:BP41) -> 0
A42: FEB 2022 | AO42: 0 | AP42: 0 | AQ42: 0 | AR42: 0 | AS42: 0 | AT42: 0 | AU42: 0 | AV42: 0 | AW42: 0 | AZ42: =SUM(AN42:AY42) -> 0 | BM42: =SUM(BA42:BL42) -> 0 | BN42: 0 | BO42: 0 | BP42: 0 | BQ42: 0 | BR42: 0 | BS42: 0 | BT42: 0 | BU42: 0 | BV42: 0 | CC42: =B42-L42-Y42-Z42-AZ42-BM42-SUM(BN42:BP42) -> 0
A43: MAR 2022 | AP43: 0 | AQ43: 0 | AR43: 0 | AS43: 0 | AT43: 0 | AU43: 0 | AV43: 0 | AW43: 0 | AZ43: =SUM(AN43:AY43) -> 0 | BM43: =SUM(BA43:BL43) -> 0 | BN43: 0 | BO43: 0 | BP43: 0 | BQ43: 0 | BR43: 0 | BS43: 0 | BT43: 0 | BU43: 0 | BV43: 0 | CC43: =B43-L43-Y43-Z43-AZ43-BM43-SUM(BN43:BP43) -> 0
A44: APR 2022 | AQ44: 0 | AR44: 0 | AS44: 0 | AT44: 0 | AU44: 0 | AV44: 0 | AW44: 0 | AZ44: =SUM(AN44:AY44) -> 0 | BM44: =SUM(BA44:BL44) -> 0 | BN44: 0 | BO44: 0 | BP44: 0 | BQ44: 0 | BR44: 0 | BS44: 0 | BT44: 0 | BU44: 0 | BV44: 0 | CC44: =B44-L44-Y44-Z44-AZ44-BM44-SUM(BN44:BP44) -> 0
A45: MAY 2022 | AZ45: =SUM(AN45:AY45) -> 0 | BM45: =SUM(BA45:BL45) -> 0 | BN45: 0 | BO45: 0 | BP45: 0 | BQ45: 0 | BR45: 0 | BS45: 0 | BT45: 0 | BU45: 0 | BV45: 0 | CC45: =B45-L45-Y45-Z45-AZ45-BM45-SUM(BN45:BP45) -> 0
AA46: 0 | AB46: 0 | AN46: 0 | AO46: 0 | AP46: 0 | AQ46: 0 | AR46: 0 | AS46: 0 | AT46: 0 | AU46: 0 | AV46: 0 | AW46: 0 | AZ46: =SUM(AN46:AY46) -> 0 | BM46: =SUM(BA46:BL46) -> 0 | BN46: 0 | BO46: 0 | BP46: 0 | BQ46: 0 | BR46: 0 | BS46: 0 | BT46: 0 | BU46: 0 | BV46: 0 | CC46: =B46-L46-Y46-Z46-AZ46-BM46-SUM(BN46:BP46) -> 0
A47: TOTAL | B47: =SUM(B8:B46) -> 390381.21 | C47: =SUM(C8:C46) -> 9782.6888 | D47: =SUM(D8:D46) -> 9782.6888 | E47: =SUM(E8:E46) -> 22382.689 | F47: =SUM(F8:F46) -> 9782.6888 | G47: =SUM(G8:G46) -> 9782.6888 | H47: =SUM(H8:H46) -> 26057.689 | I47: =SUM(I8:I46) -> 9782.6888 | ... K47: =SUM(K8:K46) -> 9782.6888 | M47: =SUM(M8:M46) -> 12572.635 | N47: =SUM(N8:N46) -> 9782.6888 | O47: =SUM(O8:O46) -> 14282.154 | P47: =SUM(P8:P46) -> 9782.6888 | Q47: =SUM(Q8:Q46) -> 11822.689 | R47: =SUM(R8:R46) -> 9782.6888 | S47: =SUM(S8:S46) -> 9782.6888 | T47: =SUM(T8:T46) -> 9782.6888 | ... AL47: =SUM(AL8:AL46) -> 9782.6888 | AN47: =SUM(AN8:AN46) -> 9782.6888 | AO47: =SUM(AO8:AO46) -> 9782.6888 | AP47: =SUM(AP8:AP46) -> 9782.6888 | AQ47: =SUM(AQ8:AQ46) -> 0 | AR47: =SUM(AR8:AR46) -> 0 | AS47: =SUM(AS8:AS46) -> 0 | AT47: =SUM(AT8:AT46) -> 0 | AU47: =SUM(AU8:AU46) -> 0 | ... BV47: =SUM(BV8:BV46) -> 0 | CC47: =SUM(CC8:CC46) -> 0
I48: =I47/0.12 -> 81522.406 | K48: =K47/0.12 -> 81522.406 | M48: =M47/0.12 -> 104771.96 | N48: =N47/0.12 -> 81522.406 | O48: =O47/0.12 -> 119017.95 | P48: =P47/0.12 -> 81522.406
I49: =I47+I48 -> 91305.095 | K49: =K47+K48 -> 91305.095 | M49: =M47+M48 -> 117344.59 | N49: =N47+N48 -> 91305.095 | O49: =O47+O48 -> 133300.1 | P49: =P47+P48 -> 91305.095
A51: LEASEHOLD IMPROVEMENT
C52: TAX PERIOD
B53: INPUT TAX | C53: =A55 -> APRIL 2019 | D53: =A56 -> MAY 2019 | E53: =A57 -> JUNE 2019 | F53: =A58 -> JULY 2019 | G53: =A59 -> AUGUST 2019 | H53: =A60 -> SEPTEMBER 2019 | I53: =A61 -> OCTOBER 2019 | J53: =A62 -> NOVEMBER 2019 | K53: =A63 -> DECEMBER 2019 | L53: 2019 TOTAL | M53: =M6 -> JANUARY 2020 | N53: =N6 -> FEBRUARY 2020 | O53: =O6 -> MARCH 2020 | P53: APRIL 2020 | Q53: MAY 2020 | R53: JUNE 2020 | S53: JULY 2020 | T53: AUG 2020 | U53: SEP 2020 | V53: OCT 2020 | W53: NOV 2020 | X53: DEC 2020 | Y53: 2020 TOTAL | Z53: 2021 TOTAL | AA53: JAN 2021 | AB53: FEB 2021 | AC53: MAR 2021 | AD53: APR 2021 | AE53: MAY 2021 | AF53: JUNE 2021 | AG53: JULY 2021 | AH53: AUGUST 2021 | AI53: SEPTEMBER 2021 | AJ53: OCTOBER 2021 | AK53: =AK$6 -> NOVEMBER 2021 | AL53: DECEMBER 2021 | AN53: JAN 2022 | AO53: =AO6 -> FEB 2022 | AP53: =AP6 -> MAR 2022 | AQ53: =AQ6 -> ARP 2022 | AR53: =AR6 -> MAY 2022 | AS53: =AS6 -> JUNE 2022 | AT53: JULY 2022 | AU53: AUG 2022 | AV53: =AV6 -> SEP 2022 | AW53: =AW6 -> OCT 2022 | AX53: =AX6 -> NOV. 2022 | AY53: =AY6 -> DEC. 2022 | AZ53: 2022 TOTAL | BA53: =BA6 -> 44927 | BB53: =BB6 -> 44958 | BC53: =BC6 -> 44986 | BD53: =BD6 -> 45017 | BE53: =BE6 -> 45047 | BF53: =BF6 -> 45078 | BG53: =BG6 -> 45108 | BH53: =BH6 -> 45139 | ... BL53: =BL6 -> 45261 | BM53: 2023 TOTAL | BN53: 45292 | BO53: 45323 | BP53: 45352 | BQ53: 45383 | BR53: 45413 | BS53: 45444 | BT53: 45474 | BU53: 45505 | BV53: 45536 | BW53: =BW6 -> 45566 | BX53: =BX6 -> 45597 | BY53: =BY6 -> 45627 | BZ53: =BZ6 -> 45658 | CA53: =CA6 -> 45689 | CB53: =CB6 -> 45717 | CC53: RUNNING BALANCE
A54: MONTH PURCHASED
A55: APRIL 2019 | B55: ='Summary of CG Purchased '!E7 -> 688499.58 | C55: ='Summary of CG Purchased '!F7 -> 11474.993 | D55: =$C$55 -> 11474.993 | E55: =$C$55 -> 11474.993 | F55: =$C$55 -> 11474.993 | G55: =$C$55 -> 11474.993 | H55: =$C$55 -> 11474.993 | I55: =$C$55 -> 11474.993 | J55: =$C$55 -> 11474.993 | K55: =$C$55 -> 11474.993 | L55: =SUM(C55:K55) -> 103274.94 | M55: =$C$55 -> 11474.993 | N55: =$C$55 -> 11474.993 | O55: =$C$55 -> 11474.993 | P55: =$C$55 -> 11474.993 | Q55: =$C$55 -> 11474.993 | R55: =$C$55 -> 11474.993 | S55: =$C$55 -> 11474.993 | T55: =$C$55 -> 11474.993 | ... X55: =$C$55 -> 11474.993 | Y55: =SUM(M55:X55) -> 137699.92 | Z55: =SUM(AA55:AL55) -> 137699.92 | AA55: =$C$55 -> 11474.993 | AB55: =$C$55 -> 11474.993 | AC55: =$C$55 -> 11474.993 | AD55: =$C$55 -> 11474.993 | AE55: =$C$55 -> 11474.993 | AF55: =$C$55 -> 11474.993 | AG55: =$C$55 -> 11474.993 | AH55: =$C$55 -> 11474.993 | ... AL55: =$C$55 -> 11474.993 | AN55: =$C$55 -> 11474.993 | AO55: =$C$55 -> 11474.993 | AP55: =$C$55 -> 11474.993 | AQ55: =$C$55 -> 11474.993 | AR55: =$C$55 -> 11474.993 | AS55: =$C$55 -> 11474.993 | AT55: =$C$55 -> 11474.993 | AU55: =$C$55 -> 11474.993 | ... AY55: =$C$55 -> 11474.993 | AZ55: =SUM(AN55:AY55) -> 137699.92 | BA55: =$C$55 -> 11474.993 | BB55: =$C$55 -> 11474.993 | BC55: =$C$55 -> 11474.993 | BD55: =$C$55 -> 11474.993 | BE55: =$C$55 -> 11474.993 | BF55: =$C$55 -> 11474.993 | BG55: =$C$55 -> 11474.993 | BH55: =$C$55 -> 11474.993 | ... BL55: =$C$55 -> 11474.993 | BM55: =SUM(BA55:BL55) -> 137699.92 | BN55: =$C$55 -> 11474.993 | BO55: =$C$55 -> 11474.993 | BP55: =$C$55 -> 11474.993 | BQ55: 0 | BR55: 0 | BS55: 0 | BT55: 0 | BU55: 0 | BV55: 0 | CC55: =B55-L55-Y55-Z55-AZ55-BM55-SUM(BN55:BP55) -> 0
A56: MAY 2019 | B56: ='Summary of CG Purchased '!E15 -> 71716.084 | D56: ='Summary of CG Purchased '!F15 -> 71716.084 | E56: 0 | F56: 0 | G56: 0 | H56: 0 | I56: 0 | J56: 0 | K56: 0 | L56: =SUM(C56:K56) -> 71716.084 | M56: 0 | N56: 0 | O56: 0 | P56: 0 | Q56: 0 | R56: 0 | S56: 0 | T56: 0 | U56: 0 | V56: 0 | W56: 0 | X56: 0 | Y56: =SUM(M56:X56) -> 0 | Z56: =SUM(AA56:AL56) -> 0 | AA56: 0 | AB56: 0 | AC56: 0 | AD56: 0 | AE56: 0 | AF56: 0 | AG56: 0 | AH56: 0 | AI56: 0 | AJ56: 0 | AK56: 0 | AL56: 0 | AN56: 0 | AO56: 0 | AP56: 0 | AQ56: 0 | AR56: 0 | AS56: 0 | AT56: 0 | AU56: 0 | AV56: 0 | AW56: 0 | AX56: 0 | AY56: 0 | AZ56: =SUM(AN56:AY56) -> 0 | BA56: 0 | BB56: 0 | BC56: 0 | BD56: 0 | BE56: 0 | BF56: 0 | BG56: 0 | BH56: 0 | BI56: 0 | BJ56: 0 | BK56: 0 | BL56: 0 | BM56: =SUM(BA56:BL56) -> 0 | BN56: 0 | BO56: 0 | BP56: 0 | BQ56: 0 | BR56: 0 | BS56: 0 | BT56: 0 | BU56: 0 | BV56: 0 | CC56: =B56-L56-Y56-Z56-AZ56-BM56-SUM(BN56:BP56) -> 0
A57: JUNE 2019 | B57: ='Summary of CG Purchased '!E23 -> 19154.244 | E57: ='Summary of CG Purchased '!F23 -> 19154.244 | F57: 0 | G57: 0 | H57: 0 | I57: 0 | J57: 0 | K57: 0 | L57: =SUM(C57:K57) -> 19154.244 | M57: 0 | N57: 0 | O57: 0 | P57: 0 | Q57: 0 | R57: 0 | S57: 0 | T57: 0 | U57: 0 | V57: 0 | W57: 0 | X57: 0 | Y57: =SUM(M57:X57) -> 0 | Z57: =SUM(AA57:AL57) -> 0 | AA57: 0 | AB57: 0 | AC57: 0 | AD57: 0 | AE57: 0 | AF57: 0 | AG57: 0 | AH57: 0 | AI57: 0 | AJ57: 0 | AK57: 0 | AL57: 0 | AN57: 0 | AO57: 0 | AP57: 0 | AQ57: 0 | AR57: 0 | AS57: 0 | AT57: 0 | AU57: 0 | AV57: 0 | AW57: 0 | AX57: 0 | AY57: 0 | AZ57: =SUM(AN57:AY57) -> 0 | BA57: 0 | BB57: 0 | BC57: 0 | BD57: 0 | BE57: 0 | BF57: 0 | BG57: 0 | BH57: 0 | BI57: 0 | BJ57: 0 | BK57: 0 | BL57: 0 | BM57: =SUM(BA57:BL57) -> 0 | BN57: 0 | BO57: 0 | BP57: 0 | BQ57: 0 | BR57: 0 | BS57: 0 | BT57: 0 | BU57: 0 | BV57: 0 | CC57: =B57-L57-Y57-Z57-AZ57-BM57-SUM(BN57:BP57) -> 0
A58: JULY 2019 | B58: 20977.056 | F58: 20977.056 | G58: 0 | H58: 0 | I58: 0 | J58: 0 | K58: 0 | L58: =SUM(C58:K58) -> 20977.056 | M58: 0 | N58: 0 | O58: 0 | P58: 0 | Q58: 0 | R58: 0 | S58: 0 | T58: 0 | U58: 0 | V58: 0 | W58: 0 | X58: 0 | Y58: =SUM(M58:X58) -> 0 | Z58: =SUM(AA58:AL58) -> 0 | AA58: 0 | AB58: 0 | AC58: 0 | AD58: 0 | AE58: 0 | AF58: 0 | AG58: 0 | AH58: 0 | AI58: 0 | AJ58: 0 | AK58: 0 | AL58: 0 | AN58: 0 | AO58: 0 | AP58: 0 | AQ58: 0 | AR58: 0 | AS58: 0 | AT58: 0 | AU58: 0 | AV58: 0 | AW58: 0 | AX58: 0 | AY58: 0 | AZ58: =SUM(AN58:AY58) -> 0 | BA58: 0 | BB58: 0 | BC58: 0 | BD58: 0 | BE58: 0 | BF58: 0 | BG58: 0 | BH58: 0 | BI58: 0 | BJ58: 0 | BK58: 0 | BL58: 0 | BM58: =SUM(BA58:BL58) -> 0 | BN58: 0 | BO58: 0 | BP58: 0 | BQ58: 0 | BR58: 0 | BS58: 0 | BT58: 0 | BU58: 0 | BV58: 0 | CC58: =B58-L58-Y58-Z58-AZ58-BM58-SUM(BN58:BP58) -> 0
A59: AUGUST 2019 | B59: 0 | G59: 0 | H59: 0 | I59: 0 | J59: 0 | K59: 0 | L59: =SUM(C59:K59) -> 0 | M59: 0 | N59: 0 | O59: 0 | P59: 0 | Q59: 0 | R59: 0 | S59: 0 | T59: 0 | U59: 0 | V59: 0 | W59: 0 | X59: 0 | Y59: =SUM(M59:X59) -> 0 | Z59: =SUM(AA59:AL59) -> 0 | AA59: 0 | AB59: 0 | AC59: 0 | AD59: 0 | AE59: 0 | AF59: 0 | AN59: 0 | AO59: 0 | AP59: 0 | AQ59: 0 | AR59: 0 | AS59: 0 | AT59: 0 | AU59: 0 | AV59: 0 | AW59: 0 | AX59: 0 | AY59: 0 | AZ59: =SUM(AN59:AY59) -> 0 | BA59: 0 | BB59: 0 | BC59: 0 | BD59: 0 | BE59: 0 | BF59: 0 | BG59: 0 | BH59: 0 | BI59: 0 | BJ59: 0 | BK59: 0 | BL59: 0 | BM59: =SUM(BA59:BL59) -> 0 | BN59: 0 | BO59: 0 | BP59: 0 | BQ59: 0 | BR59: 0 | BS59: 0 | BT59: 0 | BU59: 0 | BV59: 0 | CC59: =B59-L59-Y59-Z59-AZ59-BM59-SUM(BN59:BP59) -> 0
A60: SEPTEMBER 2019 | B60: 11276.828 | H60: 11276.828 | I60: 0 | J60: 0 | K60: 0 | L60: =SUM(C60:K60) -> 11276.828 | M60: 0 | N60: 0 | O60: 0 | P60: 0 | Q60: 0 | R60: 0 | S60: 0 | T60: 0 | U60: 0 | V60: 0 | W60: 0 | X60: 0 | Y60: =SUM(M60:X60) -> 0 | Z60: =SUM(AA60:AL60) -> 0 | AA60: 0 | AB60: 0 | AC60: 0 | AD60: 0 | AE60: 0 | AF60: 0 | AG60: 0 | AH60: 0 | AI60: 0 | AJ60: 0 | AK60: 0 | AL60: 0 | AN60: 0 | AO60: 0 | AP60: 0 | AQ60: 0 | AR60: 0 | AS60: 0 | AT60: 0 | AU60: 0 | AV60: 0 | AW60: 0 | AX60: 0 | AY60: 0 | AZ60: =SUM(AN60:AY60) -> 0 | BA60: 0 | BB60: 0 | BC60: 0 | BD60: 0 | BE60: 0 | BF60: 0 | BG60: 0 | BH60: 0 | BI60: 0 | BJ60: 0 | BK60: 0 | BL60: 0 | BM60: =SUM(BA60:BL60) -> 0 | BN60: 0 | BO60: 0 | BP60: 0 | BQ60: 0 | BR60: 0 | BS60: 0 | BT60: 0 | BU60: 0 | BV60: 0 | CC60: =B60-L60-Y60-Z60-AZ60-BM60-SUM(BN60:BP60) -> 0
A61: OCTOBER 2019 | B61: 0 | I61: 0 | J61: 0 | K61: 0 | L61: =SUM(C61:K61) -> 0 | M61: 0 | N61: 0 | O61: 0 | P61: 0 | Q61: 0 | R61: 0 | S61: 0 | T61: 0 | U61: 0 | V61: 0 | W61: 0 | X61: 0 | Y61: =SUM(M61:X61) -> 0 | Z61: =SUM(AA61:AL61) -> 0 | AA61: 0 | AB61: 0 | AC61: 0 | AD61: 0 | AE61: 0 | AF61: 0 | AN61: 0 | AO61: 0 | AP61: 0 | AQ61: 0 | AR61: 0 | AS61: 0 | AT61: 0 | AU61: 0 | AV61: 0 | AW61: 0 | AX61: 0 | AY61: 0 | AZ61: =SUM(AN61:AY61) -> 0 | BA61: 0 | BB61: 0 | BC61: 0 | BD61: 0 | BE61: 0 | BF61: 0 | BG61: 0 | BH61: 0 | BI61: 0 | BJ61: 0 | BK61: 0 | BL61: 0 | BM61: =SUM(BA61:BL61) -> 0 | BN61: 0 | BO61: 0 | BP61: 0 | BQ61: 0 | BR61: 0 | BS61: 0 | BT61: 0 | BU61: 0 | BV61: 0 | CC61: =B61-L61-Y61-Z61-AZ61-BM61-SUM(BN61:BP61) -> 0
A62: NOVEMBER 2019 | B62: 596.8284 | J62: 596.8284 | K62: 0 | L62: =SUM(C62:K62) -> 596.8284 | M62: 0 | N62: 0 | O62: 0 | P62: 0 | Q62: 0 | R62: 0 | S62: 0 | T62: 0 | U62: 0 | V62: 0 | W62: 0 | X62: 0 | Y62: =SUM(M62:X62) -> 0 | Z62: =SUM(AA62:AL62) -> 0 | AA62: 0 | AB62: 0 | AC62: 0 | AD62: 0 | AE62: 0 | AF62: 0 | AG62: 0 | AH62: 0 | AI62: 0 | AJ62: 0 | AK62: 0 | AL62: 0 | AN62: 0 | AO62: 0 | AP62: 0 | AQ62: 0 | AR62: 0 | AS62: 0 | AT62: 0 | AU62: 0 | AV62: 0 | AW62: 0 | AX62: 0 | AY62: 0 | AZ62: =SUM(AN62:AY62) -> 0 | BA62: 0 | BB62: 0 | BC62: 0 | BD62: 0 | BE62: 0 | BF62: 0 | BG62: 0 | BH62: 0 | BI62: 0 | BJ62: 0 | BK62: 0 | BL62: 0 | BM62: =SUM(BA62:BL62) -> 0 | BN62: 0 | BO62: 0 | BP62: 0 | BQ62: 0 | BR62: 0 | BS62: 0 | BT62: 0 | BU62: 0 | BV62: 0 | CC62: =B62-L62-Y62-Z62-AZ62-BM62-SUM(BN62:BP62) -> 0
A63: DECEMBER 2019 | B63: 0 | K63: 0 | L63: =SUM(C63:K63) -> 0 | M63: 0 | N63: 0 | O63: 0 | P63: 0 | Q63: 0 | R63: 0 | S63: 0 | T63: 0 | U63: 0 | V63: 0 | W63: 0 | X63: 0 | Y63: =SUM(M63:X63) -> 0 | Z63: =SUM(AA63:AL63) -> 0 | AA63: 0 | AB63: 0 | AC63: 0 | AD63: 0 | AE63: 0 | AF63: 0 | AN63: 0 | AO63: 0 | AP63: 0 | AQ63: 0 | AR63: 0 | AS63: 0 | AT63: 0 | AU63: 0 | AV63: 0 | AW63: 0 | AX63: 0 | AY63: 0 | AZ63: =SUM(AN63:AY63) -> 0 | BA63: 0 | BB63: 0 | BC63: 0 | BD63: 0 | BE63: 0 | BF63: 0 | BG63: 0 | BH63: 0 | BI63: 0 | BJ63: 0 | BK63: 0 | BL63: 0 | BM63: =SUM(BA63:BL63) -> 0 | BN63: 0 | BO63: 0 | BP63: 0 | BQ63: 0 | BR63: 0 | BS63: 0 | BT63: 0 | BU63: 0 | BV63: 0 | CC63: =B63-L63-Y63-Z63-AZ63-BM63-SUM(BN63:BP63) -> 0
A64: JANUARY 2020 | B64: ='Summary of CG Purchased '!E78 -> 0 | L64: =SUM(C64:K64) -> 0 | M64: ='Summary of CG Purchased '!E78 -> 0 | N64: ='Summary of CG Purchased '!F78 -> 0 | O64: ='Summary of CG Purchased '!G78 -> 0 | P64: ='Summary of CG Purchased '!H78 | Q64: 0 | R64: 0 | S64: 0 | T64: 0 | U64: 0 | V64: 0 | W64: 0 | X64: 0 | Y64: =SUM(M64:X64) -> 0 | Z64: =SUM(AA64:AL64) -> 0 | AA64: 0 | AB64: 0 | AC64: 0 | AD64: 0 | AE64: 0 | AF64: 0 | AN64: 0 | AO64: 0 | AP64: 0 | AQ64: 0 | AR64: 0 | AS64: 0 | AT64: 0 | AU64: 0 | AV64: 0 | AW64: 0 | AX64: 0 | AY64: 0 | AZ64: =SUM(AN64:AY64) -> 0 | BA64: 0 | BB64: 0 | BC64: 0 | BD64: 0 | BE64: 0 | BF64: 0 | BG64: 0 | BH64: 0 | BI64: 0 | BJ64: 0 | BK64: 0 | BL64: 0 | BM64: =SUM(BA64:BL64) -> 0 | BN64: 0 | BO64: 0 | BP64: 0 | BQ64: 0 | BR64: 0 | BS64: 0 | BT64: 0 | BU64: 0 | BV64: 0 | CC64: =B64-L64-Y64-Z64-AZ64-BM64-SUM(BN64:BP64) -> 0
A65: FEBRUARY 2020 | B65: ='Summary of CG Purchased '!F85 -> 5072.2452 | L65: =SUM(C65:K65) -> 0 | N65: ='Summary of CG Purchased '!F85 -> 5072.2452 | O65: 0 | P65: 0 | Q65: 0 | R65: 0 | S65: 0 | T65: 0 | U65: 0 | V65: 0 | W65: 0 | X65: 0 | Y65: =SUM(M65:X65) -> 5072.2452 | Z65: =SUM(AA65:AL65) -> 0 | AA65: 0 | AB65: 0 | AC65: 0 | AD65: 0 | AE65: 0 | AF65: 0 | AG65: 0 | AH65: 0 | AI65: 0 | AJ65: 0 | AK65: 0 | AL65: 0 | AN65: 0 | AO65: 0 | AP65: 0 | AQ65: 0 | AR65: 0 | AS65: 0 | AT65: 0 | AU65: 0 | AV65: 0 | AW65: 0 | AX65: 0 | AY65: 0 | AZ65: =SUM(AN65:AY65) -> 0 | BA65: 0 | BB65: 0 | BC65: 0 | BD65: 0 | BE65: 0 | BF65: 0 | BG65: 0 | BH65: 0 | BI65: 0 | BJ65: 0 | BK65: 0 | BL65: 0 | BM65: =SUM(BA65:BL65) -> 0 | BN65: 0 | BO65: 0 | BP65: 0 | BQ65: 0 | BR65: 0 | BS65: 0 | BT65: 0 | BU65: 0 | BV65: 0 | CC65: =B65-L65-Y65-Z65-AZ65-BM65-SUM(BN65:BP65) -> 0
A66: MARCH 2020 | B66: ='Summary of CG Purchased '!F92 -> 8640 | L66: =SUM(C66:K66) -> 0 | O66: ='Summary of CG Purchased '!F92 -> 8640 | P66: ='Summary of CG Purchased '!G91 -> 0 | Q66: 0 | R66: 0 | S66: 0 | T66: 0 | U66: 0 | V66: 0 | W66: 0 | X66: 0 | Y66: =SUM(M66:X66) -> 8640 | Z66: =SUM(AA66:AL66) -> 0 | AA66: 0 | AB66: 0 | AC66: 0 | AD66: 0 | AE66: 0 | AF66: 0 | AG66: 0 | AH66: 0 | AI66: 0 | AJ66: 0 | AK66: 0 | AL66: 0 | AN66: 0 | AO66: 0 | AP66: 0 | AQ66: 0 | AR66: 0 | AS66: 0 | AT66: 0 | AU66: 0 | AV66: 0 | AW66: 0 | AX66: 0 | AY66: 0 | AZ66: =SUM(AN66:AY66) -> 0 | BA66: 0 | BB66: 0 | BC66: 0 | BD66: 0 | BE66: 0 | BF66: 0 | BG66: 0 | BH66: 0 | BI66: 0 | BJ66: 0 | BK66: 0 | BL66: 0 | BM66: =SUM(BA66:BL66) -> 0 | BN66: 0 | BO66: 0 | BP66: 0 | BQ66: 0 | BR66: 0 | BS66: 0 | BT66: 0 | BU66: 0 | BV66: 0 | CC66: =B66-L66-Y66-Z66-AZ66-BM66-SUM(BN66:BP66) -> 0
A67: APRIL 2020 | L67: =SUM(C67:K67) -> 0 | Q67: 0 | R67: 0 | S67: 0 | T67: 0 | U67: 0 | V67: 0 | W67: 0 | X67: 0 | Y67: =SUM(M67:X67) -> 0 | Z67: =SUM(AA67:AL67) -> 0 | AA67: 0 | AB67: 0 | AC67: 0 | AD67: 0 | AE67: 0 | AF67: 0 | AN67: 0 | AO67: 0 | AP67: 0 | AQ67: 0 | AR67: 0 | AS67: 0 | AT67: 0 | AU67: 0 | AV67: 0 | AW67: 0 | AX67: 0 | AY67: 0 | AZ67: =SUM(AN67:AY67) -> 0 | BA67: 0 | BB67: 0 | BC67: 0 | BD67: 0 | BE67: 0 | BF67: 0 | BG67: 0 | BH67: 0 | BI67: 0 | BJ67: 0 | BK67: 0 | BL67: 0 | BM67: =SUM(BA67:BL67) -> 0 | BN67: 0 | BO67: 0 | BP67: 0 | BQ67: 0 | BR67: 0 | BS67: 0 | BT67: 0 | BU67: 0 | BV67: 0 | CC67: =B67-L67-Y67-Z67-AZ67-BM67-SUM(BN67:BP67) -> 0
A68: MAY 2020 | L68: =SUM(C68:K68) -> 0 | Q68: 0 | R68: 0 | S68: 0 | T68: 0 | U68: 0 | V68: 0 | W68: 0 | X68: 0 | Y68: =SUM(M68:X68) -> 0 | Z68: =SUM(AA68:AL68) -> 0 | AA68: 0 | AB68: 0 | AC68: 0 | AD68: 0 | AE68: 0 | AF68: 0 | AN68: 0 | AO68: 0 | AP68: 0 | AQ68: 0 | AR68: 0 | AS68: 0 | AT68: 0 | AU68: 0 | AV68: 0 | AW68: 0 | AX68: 0 | AY68: 0 | AZ68: =SUM(AN68:AY68) -> 0 | BA68: 0 | BB68: 0 | BC68: 0 | BD68: 0 | BE68: 0 | BF68: 0 | BG68: 0 | BH68: 0 | BI68: 0 | BJ68: 0 | BK68: 0 | BL68: 0 | BM68: =SUM(BA68:BL68) -> 0 | BN68: 0 | BO68: 0 | BP68: 0 | BQ68: 0 | BR68: 0 | BS68: 0 | BT68: 0 | BU68: 0 | BV68: 0 | CC68: =B68-L68-Y68-Z68-AZ68-BM68-SUM(BN68:BP68) -> 0
A69: JUNE 2020 | B69: ='Summary of CG Purchased '!E113 -> 172054.81 | L69: =SUM(C69:K69) -> 0 | R69: ='Summary of CG Purchased '!F113 -> 2867.5801 | S69: =$R$69 -> 2867.5801 | T69: =$R$69 -> 2867.5801 | U69: =$R$69 -> 2867.5801 | V69: =$R$69 -> 2867.5801 | W69: =$R$69 -> 2867.5801 | X69: =$R$69 -> 2867.5801 | Y69: =SUM(M69:X69) -> 20073.061 | Z69: =SUM(AA69:AL69) -> 34410.961 | AA69: =$R$69 -> 2867.5801 | AB69: =$R$69 -> 2867.5801 | AC69: =$R$69 -> 2867.5801 | AD69: =$R$69 -> 2867.5801 | AE69: =$R$69 -> 2867.5801 | AF69: =$R$69 -> 2867.5801 | AG69: =$R$69 -> 2867.5801 | AH69: =$R$69 -> 2867.5801 | ... AL69: =$R$69 -> 2867.5801 | AN69: =$R$69 -> 2867.5801 | AO69: =$R$69 -> 2867.5801 | AP69: =$R$69 -> 2867.5801 | AQ69: =$R$69 -> 2867.5801 | AR69: =$R$69 -> 2867.5801 | AS69: =$R$69 -> 2867.5801 | AT69: =$R$69 -> 2867.5801 | AU69: =$R$69 -> 2867.5801 | ... AY69: =$R$69 -> 2867.5801 | AZ69: =SUM(AN69:AY69) -> 34410.961 | BA69: =$R$69 -> 2867.5801 | BB69: =$R$69 -> 2867.5801 | BC69: =$R$69 -> 2867.5801 | BD69: =$R$69 -> 2867.5801 | BE69: =$R$69 -> 2867.5801 | BF69: =$R$69 -> 2867.5801 | BG69: =$R$69 -> 2867.5801 | BH69: =$R$69 -> 2867.5801 | ... BL69: =$R$69 -> 2867.5801 | BM69: =SUM(BA69:BL69) -> 34410.961 | BN69: =$R$69 -> 2867.5801 | BO69: =$R$69 -> 2867.5801 | BP69: =$R$69 -> 2867.5801 | BQ69: =$R$69 -> 2867.5801 | BR69: =$R$69 -> 2867.5801 | BS69: =$R$69 -> 2867.5801 | BT69: =$R$69 -> 2867.5801 | BU69: =$R$69 -> 2867.5801 | ... CB69: =$R$69 -> 2867.5801 | CC69: =B69-L69-Y69-Z69-AZ69-BM69-SUM(BN69:BP69)-SUM(BQ69:BS69)-SUM(BT69:BV69)-SUM(BW69:CB69) -> 5735.1602 | CD69: =CC69+CB69+CA69+BZ69 -> 14337.9
A70: JULY 2020 | L70: =SUM(C70:K70) -> 0 | S70: =0 -> 0 | T70: =0 -> 0 | U70: 0 | V70: 0 | W70: 0 | X70: 0 | Y70: =SUM(M70:X70) -> 0 | Z70: =SUM(AA70:AL70) -> 0 | AA70: 0 | AB70: 0 | AC70: 0 | AD70: 0 | AE70: 0 | AF70: 0 | AN70: 0 | AO70: 0 | AP70: 0 | AQ70: 0 | AR70: 0 | AS70: 0 | AT70: 0 | AU70: 0 | AV70: 0 | AW70: 0 | AX70: 0 | AY70: 0 | AZ70: =SUM(AN70:AY70) -> 0 | BA70: 0 | BB70: 0 | BC70: 0 | BD70: 0 | BE70: 0 | BF70: 0 | BG70: 0 | BH70: 0 | BI70: 0 | BJ70: 0 | BK70: 0 | BL70: 0 | BM70: =SUM(BA70:BL70) -> 0 | BN70: 0 | BO70: 0 | BP70: 0 | BQ70: 0 | BR70: 0 | BS70: 0 | BT70: 0 | BU70: 0 | BV70: 0 | CC70: =B70-L70-Y70-Z70-AZ70-BM70-SUM(BN70:BP70) -> 0
A71: AUG 2020 | L71: =SUM(C71:K71) -> 0 | T71: 0 | U71: 0 | V71: 0 | W71: 0 | X71: 0 | Y71: =SUM(M71:X71) -> 0 | Z71: =SUM(AA71:AL71) -> 0 | AA71: 0 | AB71: 0 | AC71: 0 | AD71: 0 | AE71: 0 | AF71: 0 | AN71: 0 | AO71: 0 | AP71: 0 | AQ71: 0 | AR71: 0 | AS71: 0 | AT71: 0 | AU71: 0 | AV71: 0 | AW71: 0 | AX71: 0 | AY71: 0 | AZ71: =SUM(AN71:AY71) -> 0 | BA71: 0 | BB71: 0 | BC71: 0 | BD71: 0 | BE71: 0 | BF71: 0 | BG71: 0 | BH71: 0 | BI71: 0 | BJ71: 0 | BK71: 0 | BL71: 0 | BM71: =SUM(BA71:BL71) -> 0 | BN71: 0 | BO71: 0 | BP71: 0 | BQ71: 0 | BR71: 0 | BS71: 0 | BT71: 0 | BU71: 0 | BV71: 0 | CC71: =B71-L71-Y71-Z71-AZ71-BM71-SUM(BN71:BP71) -> 0
A72: SEP 2020 | L72: =SUM(C72:K72) -> 0 | U72: 0 | V72: 0 | W72: 0 | X72: 0 | Y72: =SUM(M72:X72) -> 0 | Z72: =SUM(AA72:AL72) -> 0 | AA72: 0 | AB72: 0 | AC72: 0 | AD72: 0 | AE72: 0 | AF72: 0 | AN72: 0 | AO72: 0 | AP72: 0 | AQ72: 0 | AR72: 0 | AS72: 0 | AT72: 0 | AU72: 0 | AV72: 0 | AW72: 0 | AX72: 0 | AY72: 0 | AZ72: =SUM(AN72:AY72) -> 0 | BA72: 0 | BB72: 0 | BC72: 0 | BD72: 0 | BE72: 0 | BF72: 0 | BG72: 0 | BH72: 0 | BI72: 0 | BJ72: 0 | BK72: 0 | BL72: 0 | BM72: =SUM(BA72:BL72) -> 0 | BN72: 0 | BO72: 0 | BP72: 0 | BQ72: 0 | BR72: 0 | BS72: 0 | BT72: 0 | BU72: 0 | BV72: 0 | CC72: =B72-L72-Y72-Z72-AZ72-BM72-SUM(BN72:BP72) -> 0
A73: OCT 2020 | L73: =SUM(C73:K73) -> 0 | V73: 0 | W73: 0 | X73: 0 | Y73: =SUM(M73:X73) -> 0 | Z73: =SUM(AA73:AL73) -> 0 | AA73: 0 | AB73: 0 | AC73: 0 | AD73: 0 | AE73: 0 | AF73: 0 | AN73: 0 | AO73: 0 | AP73: 0 | AQ73: 0 | AR73: 0 | AS73: 0 | AT73: 0 | AU73: 0 | AV73: 0 | AW73: 0 | AX73: 0 | AY73: 0 | AZ73: =SUM(AN73:AY73) -> 0 | BA73: 0 | BB73: 0 | BC73: 0 | BD73: 0 | BE73: 0 | BF73: 0 | BG73: 0 | BH73: 0 | BI73: 0 | BJ73: 0 | BK73: 0 | BL73: 0 | BM73: =SUM(BA73:BL73) -> 0 | BN73: 0 | BO73: 0 | BP73: 0 | BQ73: 0 | BR73: 0 | BS73: 0 | BT73: 0 | BU73: 0 | BV73: 0 | CC73: =B73-L73-Y73-Z73-AZ73-BM73-SUM(BN73:BP73) -> 0
A74: NOV 2020 | L74: =SUM(C74:K74) -> 0 | W74: 0 | X74: 0 | Y74: =SUM(M74:X74) -> 0 | Z74: =SUM(AA74:AL74) -> 0 | AA74: 0 | AB74: 0 | AC74: 0 | AD74: 0 | AE74: 0 | AF74: 0 | AN74: 0 | AO74: 0 | AP74: 0 | AQ74: 0 | AR74: 0 | AS74: 0 | AT74: 0 | AU74: 0 | AV74: 0 | AW74: 0 | AX74: 0 | AY74: 0 | AZ74: =SUM(AN74:AY74) -> 0 | BA74: 0 | BB74: 0 | BC74: 0 | BD74: 0 | BE74: 0 | BF74: 0 | BG74: 0 | BH74: 0 | BI74: 0 | BJ74: 0 | BK74: 0 | BL74: 0 | BM74: =SUM(BA74:BL74) -> 0 | BN74: 0 | BO74: 0 | BP74: 0 | BQ74: 0 | BR74: 0 | BS74: 0 | BT74: 0 | BU74: 0 | BV74: 0 | CC74: =B74-L74-Y74-Z74-AZ74-BM74-SUM(BN74:BP74) -> 0
A75: DEC 2020 | L75: =SUM(C75:K75) -> 0 | X75: 0 | Y75: =SUM(M75:X75) -> 0 | Z75: =SUM(AA75:AL75) -> 0 | AA75: 0 | AB75: 0 | AC75: 0 | AD75: 0 | AE75: 0 | AF75: 0 | AN75: 0 | AO75: 0 | AP75: 0 | AQ75: 0 | AR75: 0 | AS75: 0 | AT75: 0 | AU75: 0 | AV75: 0 | AW75: 0 | AX75: 0 | AY75: 0 | AZ75: =SUM(AN75:AY75) -> 0 | BA75: 0 | BB75: 0 | BC75: 0 | BD75: 0 | BE75: 0 | BF75: 0 | BG75: 0 | BH75: 0 | BI75: 0 | BJ75: 0 | BK75: 0 | BL75: 0 | BM75: =SUM(BA75:BL75) -> 0 | BN75: 0 | BO75: 0 | BP75: 0 | BQ75: 0 | BR75: 0 | BS75: 0 | BT75: 0 | BU75: 0 | BV75: 0 | CC75: =B75-L75-Y75-Z75-AZ75-BM75-SUM(BN75:BP75) -> 0
A76: JAN 2021 | B76: 0 | Z76: =SUM(AA76:AL76) -> 0 | AA76: 0 | AB76: 0 | AC76: 0 | AD76: 0 | AE76: 0 | AF76: 0 | AG76: 0 | AH76: 0 | AI76: 0 | AJ76: 0 | AK76: 0 | AL76: 0 | AN76: 0 | AO76: 0 | AP76: 0 | AQ76: 0 | AR76: 0 | AS76: 0 | AT76: 0 | AU76: 0 | AV76: 0 | AW76: 0 | AX76: 0 | AY76: 0 | AZ76: =SUM(AN76:AY76) -> 0 | BA76: 0 | BB76: 0 | BC76: 0 | BD76: 0 | BE76: 0 | BF76: 0 | BG76: 0 | BH76: 0 | BI76: 0 | BJ76: 0 | BK76: 0 | BL76: 0 | BM76: =SUM(BA76:BL76) -> 0 | BN76: 0 | BO76: 0 | BP76: 0 | BQ76: 0 | BR76: 0 | BS76: 0 | BT76: 0 | BU76: 0 | BV76: 0 | CC76: =B76-L76-Y76-Z76-AZ76-BM76-SUM(BN76:BP76) -> 0
A77: FEB 2021 | B77: 0 | Z77: =SUM(AA77:AL77) -> 0 | AB77: 0 | AC77: 0 | AD77: 0 | AE77: 0 | AF77: 0 | AG77: 0 | AH77: 0 | AI77: 0 | AJ77: 0 | AK77: 0 | AL77: 0 | AZ77: =SUM(AN77:AY77) -> 0 | BM77: =SUM(BA77:BL77) -> 0 | CC77: =B77-L77-Y77-Z77-AZ77-BM77-SUM(BN77:BP77) -> 0
A78: MAR 2021 | B78: 0 | Z78: =SUM(AA78:AL78) -> 0 | AC78: 0 | AD78: 0 | AE78: 0 | AF78: 0 | AG78: 0 | AH78: 0 | AI78: 0 | AJ78: 0 | AK78: 0 | AL78: 0 | AZ78: =SUM(AN78:AY78) -> 0 | BM78: =SUM(BA78:BL78) -> 0 | CC78: =B78-L78-Y78-Z78-AZ78-BM78-SUM(BN78:BP78) -> 0
A79: APR 2021 | B79: 0 | Z79: =SUM(AA79:AL79) -> 0 | AD79: 0 | AE79: 0 | AF79: 0 | AG79: 0 | AH79: 0 | AI79: 0 | AJ79: 0 | AK79: 0 | AZ79: =SUM(AN79:AY79) -> 0 | BM79: =SUM(BA79:BL79) -> 0 | CC79: =B79-L79-Y79-Z79-AZ79-BM79-SUM(BN79:BP79) -> 0
A80: MAY 2021 | B80: 0 | Z80: =SUM(AA80:AL80) -> 0 | AE80: 0 | AF80: 0 | AG80: 0 | AH80: 0 | AI80: 0 | AJ80: 0 | AK80: 0 | AL80: 0 | AZ80: =SUM(AN80:AY80) -> 0 | BM80: =SUM(BA80:BL80) -> 0 | CC80: =B80-L80-Y80-Z80-AZ80-BM80-SUM(BN80:BP80) -> 0
A81: JUNE 2021 | B81: 0 | Z81: =SUM(AA81:AL81) -> 0 | AF81: 0 | AG81: 0 | AH81: 0 | AI81: 0 | AJ81: 0 | AK81: 0 | AZ81: =SUM(AN81:AY81) -> 0 | BM81: =SUM(BA81:BL81) -> 0 | CC81: =B81-L81-Y81-Z81-AZ81-BM81-SUM(BN81:BP81) -> 0
A82: JULY 2021 | Z82: =SUM(AA82:AL82) -> 0 | AG82: 0 | AH82: 0 | AI82: 0 | AJ82: 0 | AK82: 0 | AL82: 0 | AZ82: =SUM(AN82:AY82) -> 0 | BM82: =SUM(BA82:BL82) -> 0 | CC82: =B82-L82-Y82-Z82-AZ82-BM82-SUM(BN82:BP82) -> 0
A83: AUG 2021 | Z83: =SUM(AA83:AL83) -> 0 | AH83: 0 | AI83: 0 | AJ83: 0 | AK83: 0 | AL83: 0 | AZ83: =SUM(AN83:AY83) -> 0 | BM83: =SUM(BA83:BL83) -> 0 | CC83: =B83-L83-Y83-Z83-AZ83-BM83-SUM(BN83:BP83) -> 0
A84: SEP 2021 | Z84: =SUM(AA84:AL84) -> 0 | AI84: 0 | AJ84: 0 | AK84: 0 | AL84: 0 | AZ84: =SUM(AN84:AY84) -> 0 | BM84: =SUM(BA84:BL84) -> 0 | CC84: =B84-L84-Y84-Z84-AZ84-BM84-SUM(BN84:BP84) -> 0
A85: OCT 2021 | Z85: =SUM(AA85:AL85) -> 0 | AJ85: 0 | AK85: 0 | AL85: 0 | AZ85: =SUM(AN85:AY85) -> 0 | BM85: =SUM(BA85:BL85) -> 0 | CC85: =B85-L85-Y85-Z85-AZ85-BM85-SUM(BN85:BP85) -> 0
A86: NOV 2021 | Z86: =SUM(AA86:AL86) -> 0 | AK86: 0 | AL86: 0 | AZ86: =SUM(AN86:AY86) -> 0 | BM86: =SUM(BA86:BL86) -> 0 | CC86: =B86-L86-Y86-Z86-AZ86-BM86-SUM(BN86:BP86) -> 0
A87: DEC 2021 | Z87: =SUM(AA87:AL87) -> 0 | AL87: 0 | AZ87: =SUM(AN87:AY87) -> 0 | BM87: =SUM(BA87:BL87) -> 0 | CC87: =B87-L87-Y87-Z87-AZ87-BM87-SUM(BN87:BP87) -> 0
A88: JAN 2022 | AA88: 0 | AB88: 0 | AC88: 0 | AD88: 0 | AE88: 0 | AF88: 0 | AG88: 0 | AH88: 0 | AI88: 0 | AJ88: 0 | AK88: 0 | AL88: 0 | AN88: 0 | AO88: 0 | AP88: 0 | AQ88: 0 | AR88: 0 | AS88: 0 | AT88: 0 | AU88: 0 | AV88: 0 | AW88: 0 | AX88: 0 | AY88: 0 | AZ88: =SUM(AN88:AY88) -> 0 | BA88: 0 | BB88: 0 | BC88: 0 | BD88: 0 | BE88: 0 | BF88: 0 | BG88: 0 | BH88: 0 | BI88: 0 | BJ88: 0 | BK88: 0 | BL88: 0 | BM88: =SUM(BA88:BL88) -> 0 | BN88: 0 | BO88: 0 | BP88: 0 | BQ88: 0 | BR88: 0 | BS88: 0 | BT88: 0 | BU88: 0 | BV88: 0 | CC88: =B88-L88-Y88-Z88-AZ88-BM88-SUM(BN88:BP88) -> 0
A89: FEB 2022 | AO89: 0 | AP89: 0 | AQ89: 0 | AR89: 0 | AS89: 0 | AT89: 0 | AU89: 0 | AV89: 0 | AW89: 0 | AX89: 0 | AY89: 0 | AZ89: =SUM(AN89:AY89) -> 0 | BA89: 0 | BB89: 0 | BC89: 0 | BD89: 0 | BE89: 0 | BF89: 0 | BG89: 0 | BH89: 0 | BI89: 0 | BJ89: 0 | BK89: 0 | BL89: 0 | BM89: =SUM(BA89:BL89) -> 0 | BN89: 0 | BO89: 0 | BP89: 0 | BQ89: 0 | BR89: 0 | BS89: 0 | BT89: 0 | BU89: 0 | BV89: 0 | CC89: =B89-L89-Y89-Z89-AZ89-BM89-SUM(BN89:BP89) -> 0
A90: MAR 2022 | AP90: 0 | AQ90: 0 | AR90: 0 | AS90: 0 | AT90: 0 | AU90: 0 | AV90: 0 | AW90: 0 | AX90: 0 | AY90: 0 | AZ90: =SUM(AN90:AY90) -> 0 | BA90: 0 | BB90: 0 | BC90: 0 | BD90: 0 | BE90: 0 | BF90: 0 | BG90: 0 | BH90: 0 | BI90: 0 | BJ90: 0 | BK90: 0 | BL90: 0 | BM90: =SUM(BA90:BL90) -> 0 | BN90: 0 | BO90: 0 | BP90: 0 | BQ90: 0 | BR90: 0 | BS90: 0 | BT90: 0 | BU90: 0 | BV90: 0 | CC90: =B90-L90-Y90-Z90-AZ90-BM90-SUM(BN90:BP90) -> 0
A91: APR 2022 | AQ91: 0 | AR91: 0 | AS91: 0 | AT91: 0 | AU91: 0 | AV91: 0 | AW91: 0 | AX91: 0 | AY91: 0 | AZ91: =SUM(AN91:AY91) -> 0 | BA91: 0 | BB91: 0 | BC91: 0 | BD91: 0 | BE91: 0 | BF91: 0 | BG91: 0 | BH91: 0 | BI91: 0 | BJ91: 0 | BK91: 0 | BL91: 0 | BM91: =SUM(BA91:BL91) -> 0 | BN91: 0 | BO91: 0 | BP91: 0 | BQ91: 0 | BR91: 0 | BS91: 0 | BT91: 0 | BU91: 0 | BV91: 0 | CC91: =B91-L91-Y91-Z91-AZ91-BM91-SUM(BN91:BP91) -> 0
A92: MAY 2022 | AZ92: =SUM(AN92:AY92) -> 0 | BM92: =SUM(BA92:BL92) -> 0 | BN92: 0 | BO92: 0 | BP92: 0 | BQ92: 0 | BR92: 0 | BS92: 0 | BT92: 0 | BU92: 0 | BV92: 0 | CC92: =B92-L92-Y92-Z92-AZ92-BM92-SUM(BN92:BP92) -> 0
AA93: 0 | AB93: 0 | AN93: 0 | AO93: 0 | AP93: 0 | AQ93: 0 | AR93: 0 | AS93: 0 | AT93: 0 | AU93: 0 | AV93: 0 | AW93: 0 | AX93: 0 | AY93: 0 | AZ93: =SUM(AN93:AY93) -> 0 | BA93: 0 | BB93: 0 | BC93: 0 | BD93: 0 | BE93: 0 | BF93: 0 | BG93: 0 | BH93: 0 | BI93: 0 | BJ93: 0 | BK93: 0 | BL93: 0 | BM93: =SUM(BA93:BL93) -> 0 | BN93: 0 | BO93: 0 | BP93: 0 | BQ93: 0 | BR93: 0 | BS93: 0 | BT93: 0 | BU93: 0 | BV93: 0 | CC93: =B93-L93-Y93-Z93-AZ93-BM93-SUM(BN93:BP93) -> 0
A94: TOTAL | B94: =SUM(B55:B93) -> 997987.67 | C94: =SUM(C55:C93) -> 11474.993 | D94: =SUM(D55:D93) -> 83191.077 | E94: =SUM(E55:E93) -> 30629.237 | F94: =SUM(F55:F93) -> 32452.049 | G94: =SUM(G55:G93) -> 11474.993 | H94: =SUM(H55:H93) -> 22751.821 | I94: =SUM(I55:I93) -> 11474.993 | ... AL94: =SUM(AL55:AL93) -> 14342.573 | AN94: =SUM(AN55:AN93) -> 14342.573 | AO94: =SUM(AO55:AO93) -> 14342.573 | AP94: =SUM(AP55:AP93) -> 14342.573 | AQ94: =SUM(AQ55:AQ93) -> 14342.573 | AR94: =SUM(AR55:AR93) -> 14342.573 | AS94: =SUM(AS55:AS93) -> 14342.573 | AT94: =SUM(AT55:AT93) -> 14342.573 | AU94: =SUM(AU55:AU93) -> 14342.573 | ... CC94: =SUM(CC55:CC93) -> 5735.1602
I95: =I94/0.12 -> 95624.941 | J95: =J94/0.12 -> 100598.51 | K95: =K94/0.12 -> 95624.941 | M95: =M94/0.12 -> 95624.941 | N95: =N94/0.12 -> 137893.65 | O95: =O94/0.12 -> 167624.94 | P95: =P94/0.12 -> 95624.941
I96: =I94+I95 -> 107099.93 | J96: =J94+J95 -> 112670.33 | K96: =K94+K95 -> 107099.93 | M96: =M94+M95 -> 107099.93 | N96: =N94+N95 -> 154440.89 | O96: =O94+O95 -> 187739.93 | P96: =P94+P95 -> 107099.93
A98: OFFICE EQUIPMENT
C99: TAX PERIOD
B100: INPUT TAX | C100: =A102 -> APRIL 2019 | D100: =A103 -> MAY 2019 | E100: =A104 -> JUNE 2019 | F100: =A105 -> JULY 2019 | G100: =A106 -> AUGUST 2019 | H100: =A107 -> SEPTEMBER 2019 | I100: =A108 -> OCTOBER 2019 | J100: =A109 -> NOVEMBER 2019 | K100: =A110 -> DECEMBER 2019 | L100: 2019 TOTAL | M100: =M6 -> JANUARY 2020 | N100: =N6 -> FEBRUARY 2020 | O100: =O6 -> MARCH 2020 | P100: =P6 -> APRIL 2020 | Q100: MAY 2020 | R100: JUNE 2020 | S100: JULY 2020 | T100: AUG 2020 | U100: SEP 2020 | V100: OCT 2020 | W100: NOV 2020 | X100: DEC 2020 | Y100: 2020 TOTAL | Z100: 2021 TOTAL | AA100: JAN 2021 | AB100: FEB 2021 | AC100: MAR 2021 | AD100: APR 2021 | AE100: MAY 2021 | AF100: JUNE 2021 | AG100: JULY 2021 | AH100: AUGUST 2021 | AI100: SEPTEMBER 2021 | AJ100: OCTOBER 2021 | AK100: =AK$6 -> NOVEMBER 2021 | AL100: DECEMBER 2021 | AN100: JAN 2022 | AO100: =AO53 -> FEB 2022 | AP100: =AP53 -> MAR 2022 | AQ100: =AQ53 -> ARP 2022 | AR100: =AR53 -> MAY 2022 | AS100: =AS53 -> JUNE 2022 | AT100: JULY 2022 | AU100: AUG 2022 | AV100: =AV53 -> SEP 2022 | AW100: =AW53 -> OCT 2022 | AX100: =AX53 -> NOV. 2022 | AY100: =AY53 -> DEC. 2022 | AZ100: 2022 TOTAL | BA100: =BA53 -> 44927 | BB100: =BB53 -> 44958 | BC100: =BC53 -> 44986 | BD100: =BD53 -> 45017 | BE100: =BE53 -> 45047 | BF100: =BF53 -> 45078 | BG100: =BG53 -> 45108 | BH100: =BH53 -> 45139 | ... CB100: =CB53 -> 45717 | CC100: RUNNING BALANCE
A101: MONTH PURCHASED
A102: APRIL 2019 | B102: ='Summary of CG Purchased '!E8 -> 36211.951 | C102: ='Summary of CG Purchased '!F8 -> 36211.951 | D102: 0 | E102: 0 | F102: 0 | G102: 0 | H102: 0 | I102: 0 | J102: 0 | K102: 0 | L102: =SUM(C102:K102) -> 36211.951 | M102: 0 | N102: 0 | O102: 0 | P102: 0 | Q102: 0 | R102: 0 | S102: 0 | T102: 0 | U102: 0 | V102: 0 | W102: 0 | X102: 0 | Y102: =SUM(M102:X102) -> 0 | Z102: =SUM(AA102:AL102) -> 0 | AA102: 0 | AB102: 0 | AC102: 0 | AD102: 0 | AE102: 0 | AF102: 0 | AG102: 0 | AH102: 0 | AI102: 0 | AJ102: 0 | AK102: 0 | AL102: 0 | AN102: 0 | AO102: 0 | AP102: 0 | AQ102: 0 | AR102: 0 | AS102: 0 | AT102: 0 | AZ102: 0 | BM102: =SUM(BA102:BL102) -> 0 | BN102: 0 | BO102: 0 | BP102: 0 | BQ102: 0 | BR102: 0 | BS102: 0 | BT102: 0 | BU102: 0 | BV102: 0 | CC102: =B102-L102-Y102-Z102-AZ102-BM102-SUM(BN102:BP102) -> 0
A103: MAY 2019 | B103: ='Summary of CG Purchased '!E16 -> 0 | D103: ='Summary of CG Purchased '!F16 -> 0 | E103: 0 | F103: 0 | G103: 0 | H103: 0 | I103: 0 | J103: 0 | K103: 0 | L103: =SUM(C103:K103) -> 0 | M103: 0 | N103: 0 | O103: 0 | P103: 0 | Q103: 0 | R103: 0 | S103: 0 | T103: 0 | U103: 0 | V103: 0 | W103: 0 | X103: 0 | Y103: =SUM(M103:X103) -> 0 | Z103: =SUM(AA103:AL103) -> 0 | AA103: 0 | AB103: 0 | AC103: 0 | AD103: 0 | AE103: 0 | AF103: 0 | AN103: 0 | AO103: 0 | AP103: 0 | AQ103: 0 | AR103: 0 | AS103: 0 | AT103: 0 | BM103: =SUM(BA103:BL103) -> 0 | CC103: =B103-L103-Y103-Z103-AZ103-BM103-SUM(BN103:BP103) -> 0
...

Sheet Xero Sales
A1: Monthly VAT & Non-VAT Sales
A2: Shirefolk Ventures, Inc.
A3: For the period 1 January 2022 to 31 January 2022
A4: Cash Basis
A6: Source contains Adjustment, Bank Transfer, Conversion Balance Journal, Expense Claim, Expense Claim Payment, Manual Journal, Payable Credit Note, Payable Credit Note Allocation, Payable Credit Note Refund, Payable Invoice, Payable Overpayment, Payable Overpayment Allocation, Payable Overpayment Refund, Payable Payment, Payable Prepayment, Payable Prepayment Allocation, Payable Prepayment Refund, Receivable Credit Note, Receivable Credit Note Allocation, Receivable Credit Note Refund, Receivable Invoice, Receivable Overpayment, Receivable Overpayment Allocation, Receivable Overpayment Refund, Receivable Payment, Receivable Prepayment, Receivable Prepayment Refund, Receive Money, Spend Money Tax Rate Name contains VAT on Sales (Services), Zero Rated Sales (Services), Non-Tax, Tax Exempt
A8: Date | B8: Source | C8: Description | D8: Reference | E8: Debit | F8: Credit | G8: Gross | H8: Tax | I8: Tax Rate | J8: Account
A10: Tax Exempt
A11: 44568 | B11: Receivable Payment | C11: Payment: Sophia Ybanez | D11: AR 0162 | E11: 0 | F11: 3114.7 | G11: 3114.7 | H11: 0 | I11: 0 | J11: Other Revenue from Clients
A12: Total Tax Exempt | E12: =E11 -> 0 | F12: =F11 -> 3114.7 | G12: =G11 -> 3114.7 | H12: =H11 -> 0
A14: VAT on Sales (Services)
A15: 44564 | B15: Receivable Payment | C15: Payment: Metals Focus Data Ltd. | D15: OR 0551 | E15: 0 | F15: 8928.57 | G15: 10000 | H15: 1071.43 | I15: 12 | J15: Monthly Membership: Permanent Desk
A16: 44564 | B16: Receivable Payment | C16: Payment: DITO Telecommunity Corporation | D16: OR 0552 | E16: 0 | F16: 66964.29 | G16: 75000 | H16: 8035.71 | I16: 12 | J16: Monthly Membership: Monthly Fly Pass
A17: 44567 | B17: Receivable Payment | C17: Payment: Snapp Ventures Inc. | D17: AR 0161 | E17: 0 | F17: 94.75 | G17: 106.12 | H17: 11.37 | I17: 12 | J17: Walk Ins: 10-Day Fly Pass
A18: 44567 | B18: Receivable Payment | C18: Payment: Snapp Ventures Inc. | D18: AR 0161 | E18: 0 | F18: 94.75 | G18: 106.12 | H18: 11.37 | I18: 12 | J18: Walk Ins: 10-Day Fly Pass
A19: 44567 | B19: Receivable Payment | C19: Payment: Snapp Ventures Inc. | D19: AR 0161 | E19: 0 | F19: 94.75 | G19: 106.12 | H19: 11.37 | I19: 12 | J19: Walk Ins: 10-Day Fly Pass
A20: 44567 | B20: Receivable Payment | C20: Payment: Snapp Ventures Inc. | D20: AR 0161 | E20: 0 | F20: 94.75 | G20: 106.12 | H20: 11.37 | I20: 12 | J20: Walk Ins: 10-Day Fly Pass
A21: 44567 | B21: Receivable Payment | C21: Payment: Snapp Ventures Inc. | D21: AR 0161 | E21: 0 | F21: 94.75 | G21: 106.12 | H21: 11.37 | I21: 12 | J21: Walk Ins: 10-Day Fly Pass
A22: 44567 | B22: Receivable Payment | C22: Payment: Snapp Ventures Inc. | D22: AR 0161 | E22: 0 | F22: 10.33 | G22: 11.57 | H22: 1.24 | I22: 12 | J22: Add Ons: Locker Rental
A23: 44567 | B23: Receivable Payment | C23: Payment: Snapp Ventures Inc. | D23: AR 0161 | E23: 0 | F23: 10.33 | G23: 11.57 | H23: 1.24 | I23: 12 | J23: Add Ons: Locker Rental
A24: 44567 | B24: Receivable Payment | C24: Payment: Snapp Ventures Inc. | D24: AR 0161 | E24: 0 | F24: 10.33 | G24: 11.57 | H24: 1.24 | I24: 12 | J24: Add Ons: Locker Rental
A25: 44568 | B25: Receivable Payment | C25: Payment: Snapp Ventures Inc. | D25: OR 0554 | E25: 0 | F25: 2360.61 | G25: 2643.88 | H25: 283.27 | I25: 12 | J25: Walk Ins: 10-Day Fly Pass
A26: 44568 | B26: Receivable Payment | C26: Payment: Snapp Ventures Inc. | D26: OR 0554 | E26: 0 | F26: 2360.61 | G26: 2643.88 | H26: 283.27 | I26: 12 | J26: Walk Ins: 10-Day Fly Pass
... A37: 44592 | B37: Receivable Payment | C37: Payment: Suzette May Tiu | D37: OR 0560 | E37: 0 | F37: 2455.36 | G37: 2750 | H37: 294.64 | I37: 12 | J37: Walk Ins: 10-Day Fly Pass
A38: Total VAT on Sales (Services) | E38: =SUM(E15:E37) -> 0 | F38: =SUM(F15:F37) -> 136294.67 | G38: =SUM(G15:G37) -> 152650 | H38: =SUM(H15:H37) -> 16355.33
A40: Total | E40: =SUM(E12,E38) -> 0 | F40: =SUM(F12,F38) -> 139409.37 | G40: =SUM(G12,G38) -> 155764.7 | H40: =SUM(H12,H38) -> 16355.33
A44: Monthly VAT & Non-VAT Sales
A45: Shirefolk Ventures, Inc.
